Workbook

Sheet Asset Register
A1: REIT | B1: SPV / Holding entity | C1: Property / Asset | D1: Type | E1: City | F1: Locality / Area | G1: Micro-market (valuer) | H1: Address | I1: Leasable (sq ft) | J1: Leasable (msf) | K1: Completed (msf) | L1: Committed occ. | M1: In-place occ. | N1: Market rent /sqft/mo | O1: In-place rent /sqft/mo | P1: Rent reversion | Q1: WALE (yrs) | R1: Tenants | S1: Cap rate | T1: Discount rate | U1: Market value (INR cr) | V1: Value/sqft (INR) | W1: Mgmt fee (valuation DCF) | X1: Insurance (valuation DCF) | Y1: Notes / source
A2: Embassy | B2: Manyata Promoters Private Limited (MPPL) | C2: Embassy Manyata | D2: Office | E2: Bengaluru | F2: Nagawara / Hebbal | G2: Peripheral North (Outer Ring Road / Hebbal stretch) | H2: Along Outer Ring Road, Nagawara, Bengaluru, Karnataka; land approx. 119.15 acres | I2: 17200000 | J2: 17.2 | K2: 14.6 | M2: 0.94 | N2: 105 | O2: 95 | P2: =IF(OR(N2="",O2="",O2=0),"",N2/O2-1) | Q2: 8.8 | S2: 0.08 | T2: 0.12 | U2: 27868.9 | V2: =IF(OR(U2="",I2="",I2=0),"",U2*10000000/I2) | W2: Property Management Fees = 3% of Total Income (lease rentals, parking, fitout, other operating income) | X2: INR 0.3/sqft/mo; property tax & insurance escalated 3% p.a. | Y2: Mixed-use: completed office 14.6 msf + UC/proposed office 2.6 msf + Hotel (5-star 266 keys, 3-star 353 keys). Value split: completed 242,591 + UC/proposed 17,026 + hotel 19,072. Cap rate 8% office/retail, 7.14% hospitality; discount rate 11.5% operational office, 12.75% UC, 11.90% hospitality (reported field uses office cap 8% / operational discount ~11.5-12.75, rounded to 12). Retail mkt rent 105, anchor 94.5. Blocks M3A/M3B on leasehold land from EPDPL. Source lines ~9433-10476, value summary L4237.
A3: Embassy | B3: Vikas Telecom Private Limited (VTPL) & Sarla Infrastructure Private Limited (SIPL) | C3: Embassy TechVillage | D3: Office | E3: Bengaluru | F3: Bellandur | G3: Outer Ring Road (Sarjapura-Marathahalli), Bellandur-Marathahalli | H3: Devarabeesanahalli Village & Kariyamanna Agrahara Village, Varthur Hobli, Bengaluru East Taluk, Karnataka; land approx. 84.05 acres under purview | I3: 9700000 | J3: 9.7 | K3: 9.2 | M3: 0.95 | N3: 105 | O3: 90 | P3: =IF(OR(N3="",O3="",O3=0),"",N3/O3-1) | Q3: 9.5 | S3: 0.08 | T3: 0.12 | U3: 16624.6 | V3: =IF(OR(U3="",I3="",I3=0),"",U3*10000000/I3) | W3: Property Management Fees = 3% of Total Income | X3: INR 0.21/sqft/mo | Y3: Mixed-use: completed office 9.2 msf + UC office 0.4 msf + 2 UC hotels (5-star 311 keys, 3-star 207 keys). Value split: completed 153,974 + UC/proposed 4,258 + hotel 8,014. Cap 8% office/retail, 7.14% hospitality; discount 11.5% operational, 12.75% UC office, 13.25% UC hotel. Retail mkt rent 90. SIPL portion (1.2 msf, Block 9) BTS to JP Morgan. Source lines ~10477-11428.
A4: Embassy | B4: GolfLinks Software Park Private Limited (GLSP, 50% JV) + Eleanor Realty Holdings India Private Limited (ERHIPL, Pinehurst 100%) | C4: Embassy GolfLinks (incl. Pinehurst) | D4: Office | E4: Bengaluru | F4: Domlur | G4: Suburban East (Intermediate Ring Road, near CBD) | H4: Challaghatta Village, Varthur Hobli, Mahadevapura, Bengaluru East Taluk 560071; land approx. 37.1 acres | I4: 3400000 | J4: 3.4 | K4: 3.4 | M4: 1 | N4: 170 | O4: 160 | P4: =IF(OR(N4="",O4="",O4=0),"",N4/O4-1) | Q4: 10 | S4: 0.08 | T4: 0.12 | U4: 5129.8 | V4: =IF(OR(U4="",I4="",I4=0),"",U4*10000000/I4) | W4: Property Management Fees = 3% of Total Income (both GolfLinks and Pinehurst) | X4: GolfLinks INR 0.3/sqft/mo; Pinehurst INR 0.5/sqft/mo | Y4: 100% property value = GolfLinks 84,937 + Pinehurst 8,829 = 93,766; REIT economic interest = 50% of GolfLinks + 100% Pinehurst = 51,298 (this is the share-of-total value shown in the portfolio summary). Cap 7.75% office/retail; discount 11.5% operational. Pinehurst (0.3 msf) acquired via 100% Eleanor Realty stake Q3 FY2026: mkt rent 180, in-place 167 (192 as of 1-Apr-2026). GolfLinks office mkt rent 170, in-place 160; retail mkt rent 55. cap_rate field records 7.75 rounded to 8. Source lines ~11429-12099; summary L4288.
A5: Embassy | B5: Quadron Business Park Private Limited (QBPL) | C5: Embassy One | D5: Office | E5: Bengaluru | F5: Bellary Road (Mekhri Circle) | G5: Peripheral North (between Hebbal and off-CBD) | H5: Embassy One, Bellary Road, Ganga Nagar, Bengaluru, Karnataka; land approx. 5.6 acres (3.2 acres under valuation scope) | I5: 300000 | J5: 0.3 | K5: 0.3 | M5: 1 | N5: 151 | O5: 151 | P5: =IF(OR(N5="",O5="",O5=0),"",N5/O5-1) | Q5: 7.6 | S5: 0.08 | T5: 0.12 | U5: 1572 | V5: =IF(OR(U5="",I5="",I5=0),"",U5*10000000/I5) | W5: Property Management Fees = 3% of Total Income | X5: INR 0.4/sqft/mo | Y5: Mixed-use: completed office 0.3 msf (Pinnacle tower) + Four Seasons hotel 230 keys (5-star). Value split: office 5,902 + hotel 9,818 = 15,720. Cap 7.75% office, 7.14% hospitality (recorded 8, rounded); discount 11.5% operational, 11.90% hospitality. Office mkt rent = in-place 151 (incl. car park). Residential apartments excluded. Vacancy provision 5%. SPV Quadron Business Park Pvt Ltd (same SPV that owns Embassy Quadron Pune). Source lines ~12100-12800.
A6: Embassy | B6: Embassy Construction Private Limited (ECPL) | C6: Embassy Business Hub | D6: Office | E6: Bengaluru | F6: Yelahanka | G6: Peripheral North / North Bengaluru (Yelahanka-Devanahalli) | H6: Sy. No. 25/2, 25/3 & 26, Venkatala Village, Bellary Road (NH-44), Yelahanka, Bengaluru North, Karnataka; JDA land approx. 13 acres | I6: 1400000 | J6: 1.4 | K6: 0.4 | N6: 69 | O6: 58 | P6: =IF(OR(N6="",O6="",O6=0),"",N6/O6-1) | R6: 1 | S6: 0.08 | T6: 0.12 | U6: 722.4 | V6: =IF(OR(U6="",I6="",I6=0),"",U6*10000000/I6) | W6: Property Management Fees = 3% of Total Income | X6: INR 0.25/sqft/mo | Y6: REIT share (developer share under JDA) approx. 1.4 msf: Phase I completed 0.4 msf (single tenant Philips India, lease to Nov 2038) + Phase II UC 1.0 msf (completion FY2028). Value split: Phase I 4,652 + Phase II UC 2,572 = 7,224. Cap 8%; discount 11.5% Phase I operational, 12.75% Phase II UC. SPV named from consolidated AR/FS (ECPL) - valuation report showed only JDA ownership, no explicit Entity line. Phase II pending dev cost INR 6,569 Mn. Source lines ~12802-13413; AR L1275/7021.
A7: Embassy | B7: Indian Express Newspapers (Mumbai) Private Limited (IENMPL) | C7: Express Towers | D7: Office | E7: Mumbai | F7: Nariman Point | G7: South Mumbai CBD (Nariman Point) | H7: Plot No. 236, Block III of Backbay Reclamation Estate, Barrister Rajni Patel Marg, Nariman Point, Mumbai; land approx. 1.5 acres (freehold) | I7: 500000 | J7: 0.5 | K7: 0.5 | M7: 1 | N7: 350 | O7: 296 | P7: =IF(OR(N7="",O7="",O7=0),"",N7/O7-1) | Q7: 4 | S7: 0.08 | T7: 0.12 | U7: 2449.9 | V7: =IF(OR(U7="",I7="",I7=0),"",U7*10000000/I7) | W7: Property Management Fees = 3% of Total Income | X7: INR 0.4/sqft/mo | Y7: Completed office 0.5 msf (= total). Cap 7.5% (recorded 8, rounded); discount 11.5% operational. Office mkt rent revised 300->350; in-place 296. Age ~56 yrs, LEED Platinum. Acquisition price INR 18,385 Mn (related party). Source lines ~13414-13934.
A8: Embassy | B8: Vikhroli Corporate Park Private Limited (VCPPL) | C8: Embassy 247 | D8: Office | E8: Mumbai | F8: Vikhroli West | G8: Eastern Suburbs (Vikhroli West) | H8: Hariyali Village, Kurla Taluka, Lal Bahadur Shastri (LBS) Road, Gandhi Nagar, Vikhroli West, Mumbai; land approx. 7.3 acres (freehold) | I8: 1200000 | J8: 1.2 | K8: 1.2 | M8: 1 | N8: 135 | O8: 118 | P8: =IF(OR(N8="",O8="",O8=0),"",N8/O8-1) | Q8: 3.1 | S8: 0.08 | T8: 0.12 | U8: 2243.7 | V8: =IF(OR(U8="",I8="",I8=0),"",U8*10000000/I8) | W8: Property Management Fees = 3% of Total Income | X8: INR 0.3/sqft/mo | Y8: Completed office 1.2 msf (3 towers A/B/C). Cap 8%; discount 11.5% operational. Office mkt rent revised 121->135; retail mkt rent 250; in-place 118. LEED Platinum. Acquisition price INR 16,727 Mn (related party). Source lines ~13935-14458.
A9: Embassy | B9: Earnest Towers Private Limited (ETPL) | C9: First International Financial Centre (FIFC) | D9: Office | E9: Mumbai | F9: Bandra Kurla Complex | G9: Bandra Kurla Complex (BKC) / Secondary Business District, G Block | H9: Plot No. C-54 & C-55, G Block, BKC Road, Bandra Kurla Complex, Mumbai 400 051; leasehold land from MMRDA, approx. 2.0 acres | I9: 400000 | J9: 0.4 | K9: 0.4 | M9: 1 | N9: 350 | O9: 325 | P9: =IF(OR(N9="",O9="",O9=0),"",N9/O9-1) | Q9: 3.5 | S9: 0.08 | T9: 0.12 | U9: 1840.6 | V9: =IF(OR(U9="",I9="",I9=0),"",U9*10000000/I9) | W9: Property Management Fees = 3% of Total Income | X9: INR 0.1/sqft/mo | Y9: Leasehold interest in ~226,663 sqft (2 basements, part ground+1st, entire 2nd-7th floors) with 54.2% undivided land share. Cap 7.5% (recorded 8, rounded); discount 11.5% operational. Office mkt rent revised 320->350; retail mkt rent revised 350->425; in-place 325. High property tax INR 12.0/sqft/mo. LEED Platinum. Acquisition price INR 14,614 Mn. Source lines ~14459-15003.
A10: Embassy | B10: Embassy Pune TechZone Private Limited (EPTPL) | C10: Embassy TechZone | D10: Office | E10: Pune | F10: Hinjewadi Phase 2 | G10: PBD West / Hinjewadi Phase 2 | H10: Plot No. 3A, Hinjewadi Phase 2 Road, Hinjewadi Rajiv Gandhi Infotech Park, Hinjewadi, Pune, Maharashtra 411057; land approx. 67.5 acres (leasehold) | I10: 5500000 | J10: 5.5 | K10: 3 | M10: 0.77 | N10: 50 | O10: 54 | P10: =IF(OR(N10="",O10="",O10=0),"",N10/O10-1) | Q10: 5.6 | S10: 0.08 | T10: 0.12 | U10: 2592.4 | V10: =IF(OR(U10="",I10="",I10=0),"",U10*10000000/I10) | W10: Property Management Fees = 3% of Total Income; Asset Mgmt fee booked below NOI | X10: INR 0.2/sqft/mo | Y10: Mixed-use: completed office 3.0 msf + UC/proposed office 2.4 msf + 116-key hotel. Value split: completed 23,235 + UC/proposed 2,450 + hotel 239. Cap 8.25% office (recorded 8, rounded), 7.14% hospitality; discount 11.5% operational, 12.75% UC office, 13.25% UC hotel. Occupancy may fall to 73% if a domestic tech tenant exits 1-Apr-2026. Acquisition price INR 20,720 Mn. Source lines ~15004-15839.
A11: Embassy | B11: Quadron Business Park Private Limited (QBPL) | C11: Embassy Quadron | D11: Office | E11: Pune | F11: Hinjewadi Phase 2 | G11: PBD West / Hinjewadi Phase 2 | H11: Plot No. 28, Hinjewadi Phase 2 Road, Hinjewadi Rajiv Gandhi Infotech Park, Pimpri-Chinchwad, Pune, Maharashtra 411057; land approx. 25.5 acres (leasehold) | I11: 1900000 | J11: 1.9 | K11: 1.9 | M11: 0.24 | N11: 46 | O11: 56 | P11: =IF(OR(N11="",O11="",O11=0),"",N11/O11-1) | Q11: 4.3 | S11: 0.08 | T11: 0.12 | U11: 1003.9 | V11: =IF(OR(U11="",I11="",I11=0),"",U11*10000000/I11) | W11: Property Management Fees = 3% of Total Income; Asset Mgmt fee below NOI | X11: INR 0.2/sqft/mo | Y11: Completed office 1.9 msf (all completed, no UC). Cap 8.25% (recorded 8, rounded); discount 11.5% operational. Very low occupancy 24%. Office mkt rent 46, in-place 56. Same SPV as Embassy One (Bengaluru). Acquisition price INR 13,961 Mn. Source lines ~15840-16388.
A12: Embassy | B12: Qubix Business Park Private Limited (QBPPL) | C12: Embassy Qubix | D12: Office | E12: Pune | F12: Hinjewadi Phase 1 | G12: PBD West / Hinjewadi Phase 1 | H12: Blue Ridge Township, Phase 1, Hinjewadi Rajiv Gandhi Infotech Park, Pimpri-Chinchwad, Pune, Maharashtra 411057; land approx. 25.2 acres (freehold) | I12: 1500000 | J12: 1.5 | K12: 1.5 | M12: 0.78 | N12: 50 | O12: 51 | P12: =IF(OR(N12="",O12="",O12=0),"",N12/O12-1) | Q12: 4.2 | S12: 0.08 | T12: 0.12 | U12: 1048.3 | V12: =IF(OR(U12="",I12="",I12=0),"",U12*10000000/I12) | W12: Property Management Fees = 3% of Total Income; Asset Mgmt fee below NOI | X12: INR 0.3/sqft/mo | Y12: Completed office 1.5 msf (5 SEZ + 1 Non-SEZ block). Cap 8.25% (recorded 8, rounded); discount 11.5% operational. Only freehold Pune asset. Office mkt rent 50, in-place 51. Acquisition price INR 9,868 Mn. Source lines ~16389-16936.
A13: Embassy | B13: Oxygen Business Park Private Limited (OBPPL) | C13: Embassy Oxygen | D13: Office | E13: Noida | F13: Noida-Greater Noida Expressway | G13: Noida-Greater Noida Expressway (Sector 144) | H13: Plot No. 7, Sector-144, Noida, Uttar Pradesh; land approx. 24.8 acres, leasehold from NOIDA Authority | I13: 3300000 | J13: 3.3 | K13: 3.3 | M13: 0.9 | N13: 59 | O13: 57 | P13: =IF(OR(N13="",O13="",O13=0),"",N13/O13-1) | Q13: 9.1 | S13: 0.08 | T13: 0.12 | U13: 2951.8 | V13: =IF(OR(U13="",I13="",I13=0),"",U13*10000000/I13) | W13: Property Management Fees = 3% of Total Income (booked below NOI) | X13: INR 0.22/sqft/mo; plus Land Lease Payment INR 0.38/sqft/mo (in lieu of property tax) | Y13: Completed office 3.3 msf (10 buildings incl food court). Cap 8%; discount 11.5% operational. Office mkt rent 59 (incl parking), in-place 57; retail mkt rent 85. Seismic Zone IV. Acquisition price INR 18,258 Mn. Source lines ~16937-17515.
A14: Embassy | B14: Galaxy Square Private Limited (GSPL) | C14: Embassy Galaxy | D14: Office | E14: Noida | F14: Noida Sector 62 | G14: Noida Sector 62 | H14: A-44 & 45, Sector-62, Noida, Uttar Pradesh; land approx. 9.9 acres, leasehold from NOIDA Authority | I14: 1400000 | J14: 1.4 | K14: 1.4 | M14: 1 | N14: 51 | O14: 46 | P14: =IF(OR(N14="",O14="",O14=0),"",N14/O14-1) | Q14: 9.5 | S14: 0.08 | T14: 0.12 | U14: 1131.1 | V14: =IF(OR(U14="",I14="",I14=0),"",U14*10000000/I14) | W14: Property Management Fees = 3% of Total Income (below NOI) | X14: INR 0.27/sqft/mo; Land Lease Payment INR 0.34/sqft/mo | Y14: Completed office 1.4 msf (5 Non-SEZ blocks). Rent roll ~99.6% occupied. Cap 8%; discount 11.5% operational. Office mkt rent 51 (incl parking), in-place 46; retail mkt rent 85. LEED Platinum. Acquisition price INR 8,122 Mn. Source lines ~17516-18059.
A15: Embassy | B15: Umbel Properties Private Limited (UPPL) | C15: Hilton at Embassy GolfLinks | D15: Hotel | E15: Bengaluru | F15: Domlur | G15: Suburban East (inside Embassy GolfLinks Business Park, Intermediate Ring Road) | H15: Challaghatta Village, Varthur Hobli, Bengaluru East Taluk 560071; land approx. 3.6 acres (freehold) | I15: 500000 | J15: 0.5 | K15: 0.5 | M15: 0.72 | P15: =IF(OR(N15="",O15="",O15=0),"",N15/O15-1) | S15: 0.07 | T15: 0.12 | U15: 887.6 | V15: =IF(OR(U15="",I15="",I15=0),"",U15*10000000/I15) | W15: Base Management Fee 2% of Total Revenue; Management Incentive Fee 5.5% of Gross Operating Profit; FF&E reserve 2% | Y15: 247-key 5-star hotel (developed area ~0.5 msf). Stabilized occupancy 72% (FY2026); ADR INR 15,000/room/night +5% YoY from Oct 2026; F&B revenue 40% of rooms revenue. Cap rate 7.14% derived via EV/EBITDA 14x (recorded 7, rounded); discount rate 11.90% (recorded 12, rounded). No psf rent (hotel). Acquisition price INR 4,766 Mn. Source lines ~18060-18516.
A16: Embassy | B16: ESNP Property Builders and Developers Private Limited (ESNP) | C16: Embassy Splendid Techzone | D16: Office | E16: Chennai | F16: Pallavaram | G16: Suburban South (Pallavaram-Thoraipakkam Road) | H16: Pallavaram-Thoraipakkam (PTR) Road, Pallavaram, Chennai, Tamil Nadu; land approx. 25.37 acres (leasehold from SNP) | I16: 5100000 | J16: 5.1 | K16: 2.5 | M16: 0.84 | N16: 75 | O16: 73 | P16: =IF(OR(N16="",O16="",O16=0),"",N16/O16-1) | Q16: 11.5 | S16: 0.08 | T16: 0.12 | U16: 2058.7 | V16: =IF(OR(U16="",I16="",I16=0),"",U16*10000000/I16) | W16: Property Management Fees = 3% of Total Income (below NOI) | X16: INR 0.13/sqft/mo | Y16: Mixed-use (IT/ITeS SEZ/Non-SEZ): completed 2.5 msf + UC/proposed 2.6 msf. Value split: completed 15,556 + UC 5,031 = 20,587. Cap 8% office/retail; discount 11.5% operational office. Office mkt rent 75 (incl parking), in-place 73; retail mkt rent 25. Land freehold of SNP granting leasehold to ESNP (30 yrs from 9-Nov-2016, renewable). Pending dev cost ~INR 8,083 Mn. Acquisition price INR 11,853 Mn. Source lines ~18517-19186.
A17: Embassy | B17: Embassy Energy Private Limited (EEPL) | C17: Embassy Energy (Solar Park) | D17: Other | E17: Bellary District, Karnataka | F17: Villages Ittigi & Mooregeri and Nellukudure | G17: Villages Ittigi & Mooregeri (Huvinhadagali Taluka) and Nellukudure (Hagribommanhalli Taluka) | H17: Bellary District, Karnataka; primary access SH-45; land approx. 465.8 acres | P17: =IF(OR(N17="",O17="",O17=0),"",N17/O17-1) | T17: 0.12 | U17: 414.3 | V17: =IF(OR(U17="",I17="",I17=0),"",U17*10000000/I17) | Y17: Solar Park: installed capacity 130 MW DC / 100 MW AC; commissioned Feb 2018; ~215 MU/yr; CUF 17.35%. No leasable area or psf rent. Discount rate 11.5% (recorded 12, rounded); no cap rate (25-yr DCF over CERC useful life, no terminal cap). PPA tariff FY2027 INR 6.83/unit, escalation 2.5%/yr; 25-yr PPAs with Embassy office parks/hotels (Manyata, GolfLinks, Hilton GolfLinks, TechVillage) plus C&I offtakers. O&M INR 18.3 Mn/qtr. No property mgmt fee (admin/O&M/employee costs instead). SPV labelled 'Power Limited' in one value table (likely typo for Private Limited). Acquisition price INR 10,690 Mn. Source lines ~19187-19981.
A18: Mindspace | B18: Sundew Properties Limited | C18: Mindspace Madhapur (Sundew) | D18: Office | E18: Hyderabad | F18: Madhapur | G18: Madhapur | H18: Mindspace Madhapur, Titus Towers, TSIIC software layout, Madhapur, Hyderabad, Telangana 500081 | I18: 5870000 | J18: 5.87 | K18: 5.87 | L18: 0.99 | M18: 0.96 | N18: 105 | O18: 75.58 | P18: =IF(OR(N18="",O18="",O18=0),"",N18/O18-1) | Q18: 7.84 | R18: 51 | S18: 0.08 | T18: 0.12 | U18: 7963.812 | V18: =IF(OR(U18="",I18="",I18=0),"",U18*10000000/I18) | Y18: Grade A IT Park, 8 buildings (Non-SEZ 11,22; SEZ rest); Bldg 22 hotel. MREIT 89% interest (100% value INR89,481.03mn). Exit cap 7.75%, WACC 11.75%. Occ 96.3%/committed 98.7%. Land 40.25 ac freehold. p.1-52 (chunk a)
A19: Mindspace | B19: K Raheja IT Park (Hyderabad) Limited | C19: Mindspace Madhapur (KRIT) | D19: Office | E19: Hyderabad | F19: Madhapur | G19: Madhapur | H19: Mindspace Madhapur (KRIT), Madhapur, Hyderabad, Telangana 500081 | I19: 5940000 | J19: 5.94 | K19: 2.18 | L19: 0.99 | M19: 0.97 | N19: 105 | O19: 79.96 | P19: =IF(OR(N19="",O19="",O19=0),"",N19/O19-1) | Q19: 7.24 | R19: 29 | S19: 0.08 | T19: 0.12 | U19: 5982.4 | V19: =IF(OR(U19="",I19="",I19=0),"",U19*10000000/I19) | Y19: IT Park Non-SEZ (incl retail). Exit cap 7.75%, WACC 11.75%. Occ 96.5%/committed 99.2%. Land 48.43 ac freehold. chunk a
A20: Mindspace | B20: Intime Properties Limited | C20: Mindspace Madhapur (Intime) | D20: Office | E20: Hyderabad | F20: Madhapur | G20: Madhapur | H20: Mindspace Madhapur (Intime), Madhapur, Hyderabad, Telangana 500081 | I20: 2030000 | J20: 2.03 | K20: 2.03 | L20: 1 | M20: 1 | N20: 105 | O20: 79.06 | P20: =IF(OR(N20="",O20="",O20=0),"",N20/O20-1) | Q20: 7.08 | R20: 35 | S20: 0.08 | T20: 0.12 | U20: 2855.721 | V20: =IF(OR(U20="",I20="",I20=0),"",U20*10000000/I20) | Y20: IT Park Non-SEZ. Exit cap 7.75%, WACC 11.75%. Occ 99.8%/committed 99.8%. Land 8.52 ac freehold. chunk a
A21: Mindspace | B21: Mindspace Business Parks Private Limited | C21: Mindspace Pocharam | D21: Other | E21: Hyderabad | F21: Pocharam | G21: Pocharam (PBD East / Suburbs Other) | H21: Mindspace Pocharam, Hyderabad – Non-SEZ IT Park | I21: 570000 | J21: 0.57 | K21: 0.57 | L21: 0 | M21: 0 | P21: =IF(OR(N21="",O21="",O21=0),"",N21/O21-1) | R21: 0 | U21: 100.435 | V21: =IF(OR(U21="",I21="",I21=0),"",U21*10000000/I21) | Y21: Non-SEZ IT Park; built component 0.57 msf currently VACANT (NIL occupancy/tenants) + undeveloped land held at land value. Valued via Land & Building/DCF hybrid; land ~INR30.49mn/acre. Land 26.464 ac freehold. chunk a
A22: Mindspace | B22: Sustain Properties Private Limited | C22: Commerzone Raidurg (Sustain) | D22: Office | E22: Hyderabad | F22: Madhapur | G22: Madhapur (Raidurg) | H22: Commerzone Raidurg (Sustain), Madhapur, Hyderabad, Telangana 500081 | I22: 1820000 | J22: 1.82 | K22: 1.82 | L22: 1 | M22: 1 | O22: 69.1 | P22: =IF(OR(N22="",O22="",O22=0),"",N22/O22-1) | Q22: 10.5 | R22: 2 | S22: 0.08 | T22: 0.12 | U22: 2585.322 | V22: =IF(OR(U22="",I22="",I22=0),"",U22*10000000/I22) | Y22: SEZ IT/ITeS. Exit cap 7.75%, WACC 11.75%. Occ 100%/committed 100%. Sustain entitled 65.5% undivided share of 9.07 ac land. Market rent per JLL (not a single psf figure in exec summary). chunk a
A23: Mindspace | B23: Mack Soft Tech Private Limited | C23: The Square, Financial District (Hyderabad) | D23: Office | E23: Hyderabad | F23: Gachibowli | G23: Gachibowli / Nanakramguda (Financial District) | H23: The Square, 110 Financial District, Nanakramguda, Hyderabad, Telangana 500032 | I23: 820000 | J23: 0.82 | K23: 0.82 | L23: 0.72 | M23: 0.62 | N23: 60 | O23: 60 | P23: =IF(OR(N23="",O23="",O23=0),"",N23/O23-1) | Q23: 3.4 | R23: 25 | S23: 0.08 | T23: 0.12 | U23: 707.727 | V23: =IF(OR(U23="",I23="",I23=0),"",U23*10000000/I23) | Y23: Non-SEZ office. Exit cap 8.00%, WACC 11.75%. Occ 61.5%/committed 72.3%. Market/marginal office rent INR60/psf/mo. Land ~6 ac freehold. chunk b
A24: Mindspace | B24: Mindspace Business Parks Private Limited | C24: Mindspace Airoli East | D24: Office | E24: Navi Mumbai | F24: Thane-Belapur Road | G24: Thane-Belapur Road (Airoli) | H24: Plot No.3, Kalwa Trans Thane Creek Ind. Area, Mindspace, Opp. Airoli Station, Airoli, Navi Mumbai 400708 | I24: 7400000 | J24: 7.4 | K24: 4.98 | L24: 0.83 | M24: 0.73 | N24: 69 | O24: 68.3 | P24: =IF(OR(N24="",O24="",O24=0),"",N24/O24-1) | Q24: 4.9 | R24: 48 | S24: 0.08 | T24: 0.12 | U24: 5802.395 | V24: =IF(OR(U24="",I24="",I24=0),"",U24*10000000/I24) | Y24: Grade A IT SEZ. Total 7.4 msf = 4.98 completed (occ/tenants shown) + 2.41 under-constr/future (B17 hotel+office, Bldg15; NIL occupancy). Exit cap 8.00%; WACC 11.75% completed, 13% UC. Completed occ 73.2%/committed 83.1%, 48 tenants. Land ~50.1 ac leasehold (MIDC 99yr). Also power distribution (see Energispace). chunk b
A25: Mindspace | B25: Gigaplex Estate Private Limited | C25: Mindspace Airoli West | D25: Office | E25: Navi Mumbai | F25: Thane-Belapur Road | G25: Thane-Belapur Road (Airoli) | H25: Mindspace Airoli West, Navi Mumbai, Maharashtra | I25: 6460000 | J25: 6.46 | K25: 5.41 | L25: 0.99 | M25: 0.97 | N25: 71 | O25: 67.2 | P25: =IF(OR(N25="",O25="",O25=0),"",N25/O25-1) | Q25: 9 | R25: 62 | S25: 0.08 | T25: 0.12 | U25: 6577 | V25: =IF(OR(U25="",I25="",I25=0),"",U25*10000000/I25) | Y25: IT SEZ w/ data-centre buildings. Total 6.46 msf incl UC data centres (B7,B9A,B11). Completed 5.41 msf occ 96.6%/committed 98.7%, 62 tenants. Exit cap 8.00% (completed; 8.25% terminal on some); WACC 11.75% completed/13% UC. Market office rent INR71/psf/mo. Land ~50 ac leasehold (MIDC 95yr). chunk b
A26: Mindspace | B26: Avocado Properties and Trading (India) Private Limited | C26: Paradigm Mindspace Malad | D26: Office | E26: Mumbai | F26: Malad | G26: Western Suburbs (Malad) | H26: Paradigm Mindspace Malad, Mumbai, Maharashtra | I26: 760000 | J26: 0.76 | K26: 0.76 | L26: 0.99 | M26: 0.99 | N26: 116 | O26: 108.5 | P26: =IF(OR(N26="",O26="",O26=0),"",N26/O26-1) | Q26: 3.1 | R26: 9 | S26: 0.08 | T26: 0.12 | U26: 1371.121 | V26: =IF(OR(U26="",I26="",I26=0),"",U26*10000000/I26) | Y26: Office. Exit cap 8.00%, WACC 11.75%. Occ 98.6%/committed 98.6%, 9 tenants. Market/marginal rent INR116/psf/mo, in-place INR108.5. WALE 3.1 yrs. Land ~4.2 ac freehold. chunk b
A27: Mindspace | B27: Avacado Properties and Trading (India) Private Limited | C27: The Square, BKC (Mumbai) | D27: Office | E27: Mumbai | F27: BKC | G27: BKC (SBD BKC) | H27: The Square, BKC, Mumbai, Maharashtra | I27: 150000 | J27: 0.15 | K27: 0.15 | L27: 1 | M27: 1 | N27: 318 | O27: 240 | P27: =IF(OR(N27="",O27="",O27=0),"",N27/O27-1) | R27: 1 | S27: 0.08 | T27: 0.12 | U27: 533.868 | V27: =IF(OR(U27="",I27="",I27=0),"",U27*10000000/I27) | Y27: BKC office, fully operational single-tenant. Exit cap ~7.5-7.75%, WACC 11.75%. Occ 100%/committed 100%, 1 office tenant. Market/marginal rent INR318, in-place INR240 psf/mo. MV INR5,338.68mn. Land ~0.9 ac. SPV Avacado Properties. chunk b
A28: Mindspace | B28: KRC (Ascent SPV) | C28: The Square / Ascent, Worli | D28: Office | E28: Mumbai | F28: Worli | G28: Worli (SBD Central) | H28: Ascent, Worli, Mumbai, Maharashtra | I28: 450000 | J28: 0.45 | K28: 0.45 | L28: 0.97 | M28: 0.96 | N28: 340 | O28: 306.3 | P28: =IF(OR(N28="",O28="",O28=0),"",N28/O28-1) | Q28: 7.9 | R28: 8 | S28: 0.08 | T28: 0.12 | U28: 2314.206 | V28: =IF(OR(U28="",I28="",I28=0),"",U28*10000000/I28) | Y28: Commercial Non-SEZ + 36 residential units to rent. Exit cap 7.50%, WACC 11.75%. Occ 95.5%/committed 96.7%, 8 office tenants. Market rent INR340, in-place INR306.3 psf/mo. Leasehold (perpetual). ~4.61 ac (22.45% undivided). chunk c
A29: Mindspace | B29: Mindspace Business Parks Private Limited | C29: Commerzone Yerwada (Pune) | D29: Office | E29: Pune | F29: Yerwada | G29: Yerwada (SBD East) | H29: Commerzone IT Park, Yerwada, Pune, Maharashtra | I29: 1790000 | J29: 1.79 | K29: 1.79 | L29: 0.96 | M29: 0.92 | N29: 82 | O29: 87.3 | P29: =IF(OR(N29="",O29="",O29=0),"",N29/O29-1) | Q29: 5.3 | R29: 19 | S29: 0.08 | T29: 0.12 | U29: 2235.438 | V29: =IF(OR(U29="",I29="",I29=0),"",U29*10000000/I29) | Y29: Office. Exit cap 8.00%, WACC 11.75%. Occ 91.8%/committed 96.3%, 19 tenants. Market/marginal office rent INR82, in-place INR87.3 psf/mo. Land ~25.7 ac freehold. chunk c
A30: Mindspace | B30: KRC Infrastructure and Projects Private Limited | C30: Gera Commerzone SEZ & IT Park (Kharadi, Pune) | D30: Office | E30: Pune | F30: Kharadi | G30: Kharadi (SBD East) | H30: Gera Commerzone SEZ and IT Park, Kharadi, Pune, Maharashtra | I30: 3000000 | J30: 3 | K30: 3 | L30: 1 | M30: 1 | N30: 90 | O30: 85.4 | P30: =IF(OR(N30="",O30="",O30=0),"",N30/O30-1) | Q30: 7.2 | R30: 28 | S30: 0.08 | T30: 0.12 | U30: 5311.9 | V30: =IF(OR(U30="",I30="",I30=0),"",U30*10000000/I30) | Y30: SEZ IT. Exit cap 7.75%, WACC 11.75% completed/13% UC. Occ 100%/100%, 28 tenants. Market office rent INR90, in-place INR85.4 psf/mo. Land ~26 ac freehold. chunk c
A31: Mindspace | B31: Mindspace Business Parks Private Limited | C31: The Square, Nagar Road (Pune) | D31: Office | E31: Pune | F31: Nagar Road | G31: Nagar Road (SBD East) | H31: The Square, Nagar Road, Pune, Maharashtra | I31: 780000 | J31: 0.78 | K31: 0.78 | L31: 1 | M31: 1 | N31: 85 | O31: 85.3 | P31: =IF(OR(N31="",O31="",O31=0),"",N31/O31-1) | Q31: 2.4 | R31: 4 | S31: 0.08 | T31: 0.12 | U31: 1055.141 | V31: =IF(OR(U31="",I31="",I31=0),"",U31*10000000/I31) | Y31: Office. Exit cap 8.00%, WACC 11.75%. Occ 100%/100%, 4 tenants. Market office rent INR85, in-place INR85.3 psf/mo. Land ~10.1 ac freehold. chunk c
A32: Mindspace | B32: Pramaan Properties Private Limited | C32: Pune IT Building, Kalyani Nagar | D32: Office | E32: Pune | F32: Kalyani Nagar | G32: Kalyani Nagar (SBD East) | H32: Pune IT Building (B8), Kalyani Nagar, Pune, Maharashtra | I32: 110000 | J32: 0.11 | K32: 0.11 | L32: 0.94 | M32: 0.88 | N32: 84 | O32: 86.2 | P32: =IF(OR(N32="",O32="",O32=0),"",N32/O32-1) | Q32: 6.34 | R32: 1 | S32: 0.08 | T32: 0.12 | U32: 148.151 | V32: =IF(OR(U32="",I32="",I32=0),"",U32*10000000/I32) | Y32: Single office building B8. Exit cap office 8.00%, WACC 11.75%. Occ 88.1%/committed 94.2%, 1 tenant. Market office rent INR84 (amenity INR65), in-place INR86.2 psf/mo. Land ~0.67 ac (39.96% undivided share) freehold. chunk d
A33: Mindspace | B33: Horizonview Properties Private Limited | C33: Commerzone Porur (Chennai) | D33: Office | E33: Chennai | F33: Porur | G33: Porur (SBD Southwest) | H33: Commerzone, Porur, Chennai, Tamil Nadu | I33: 1150000 | J33: 1.15 | K33: 1.15 | L33: 1 | M33: 1 | N33: 72 | O33: 65.7 | P33: =IF(OR(N33="",O33="",O33=0),"",N33/O33-1) | R33: 16 | S33: 0.08 | T33: 0.12 | U33: 1333.474 | V33: =IF(OR(U33="",I33="",I33=0),"",U33*10000000/I33) | Y33: Office. Exit cap 7.75%, WACC 11.75%. Occ 99.5%/committed 100%, 16 tenants. Market/marginal office rent INR72, in-place INR65.7 psf/mo. Land ~6.13 ac freehold. WALE not cleanly captured. chunk d
A34: Mindspace | B34: Sundew Real Estate Private Limited | C34: The Square, Avenue 98 (BKC Annex) | D34: Office | E34: Mumbai | F34: BKC-Annex | G34: BKC-Annex (SBD BKC) | H34: The Square, Avenue 98 (BKC Annex), Mumbai, Maharashtra | I34: 220000 | J34: 0.22 | K34: 0.16 | L34: 1 | M34: 1 | N34: 250 | O34: 197.1 | P34: =IF(OR(N34="",O34="",O34=0),"",N34/O34-1) | R34: 1 | S34: 0.08 | T34: 0.12 | U34: 756.9 | V34: =IF(OR(U34="",I34="",I34=0),"",U34*10000000/I34) | Y34: Commercial Non-SEZ. Leasable 0.22 msf, completed ~0.16 msf. Exit cap 7.50%, WACC 11.75%. Occ 100%/100%, 1 office tenant. Market rent INR250, in-place INR197.1 psf/mo. Land ~1.08 ac freehold. chunk d
A35: Brookfield | B35: Candor Kolkata One Hi-Tech Structures Private Limited | C35: Candor Techspace G2 | D35: Office | E35: Gurugram | F35: Dundahera | G35: Old Delhi-Gurugram Road, Dundahera (Gurugram, established office/residential/retail micro-market; near DLF Cyber City) | H35: Candor Techspace, Dundahera, Gurugram, Haryana | I35: 4183449 | J35: 4.18 | K35: 4.08 | L35: 0.83 | N35: 90 | O35: 88 | P35: =IF(OR(N35="",O35="",O35=0),"",N35/O35-1) | Q35: 8.1 | S35: 0.08 | T35: 0.12 | U35: 4811.2 | V35: =IF(OR(U35="",I35="",I35=0),"",U35*10000000/I35) | Y35: Completed leasable 4,083,525 sqft (13 bldgs, 83.34% committed occ) + future dev 99,924 sqft. WACC operational 11.50%, WACC under-construction/future dev 12.75% (discount_rate shown=12 rounded from 12.75 UC; operational WACC 11.5). REIT share 100% via Candor SPV; SPV entitled to 72% of gross revenue via JDA with Gurgaon Infospace Ltd (GIL owns land, gets 28%); economic interest in asset 72% (deck). Gross acq price K1+G2 = Rs 62.3 Bn. Completed MV 47,575mn + future dev 537mn = 48,112mn. Source val report pp.19-22; deck p.14 (Investor Pres FY26).
A36: Brookfield | B36: Seaview Developers Private Limited | C36: Candor Techspace N1 | D36: Office | E36: Noida | F36: Sector 62 (Noida) | G36: Sector 62, Noida (institutional sector, NCR) | H36: Plot no. B2, Sector 62, Noida, Uttar Pradesh | J36: 2.88 | K36: 2.02 | L36: 0.98 | N36: 72 | O36: 64 | P36: =IF(OR(N36="",O36="",O36=0),"",N36/O36-1) | Q36: 7.8 | S36: 0.08 | T36: 0.12 | U36: 2948.5 | V36: =IF(OR(U36="",I36="",I36=0),"",U36*10000000/I36) | Y36: Completed 20,23,237 sqft (7 bldgs, 97.96% committed occ) + future dev 0.86 msf. REIT share 100%. WACC operational 11.50%, UC 12.75%. Completed MV 26,026mn + future dev 3,459mn = 29,485mn. Source val report pp.23-26; deck p.14.
A37: Brookfield | B37: Festus Properties Private Limited | C37: Candor Techspace N2 | D37: Office | E37: Noida | F37: Sector 135 (Noida) | G37: Sector 135, Noida-Greater Noida Expressway micro-market | H37: Plot No. 20, 21, Sector 135, Noida, Uttar Pradesh | J37: 4.69 | K37: 3.92 | L37: 0.94 | N37: 70 | O37: 64 | P37: =IF(OR(N37="",O37="",O37=0),"",N37/O37-1) | Q37: 6.9 | S37: 0.08 | T37: 0.12 | U37: 4941 | V37: =IF(OR(U37="",I37="",I37=0),"",U37*10000000/I37) | Y37: Completed 39,15,881 sqft (14 bldgs, 93.52% committed occ) + future dev 0.77 msf. REIT share 100%. Achievable mkt rent: 70 SEZ office / 57 non-SEZ / 60 mixed-use retail; inplace(current effective) 64. WACC operational 11.50%, UC 12.75%. Completed MV 47,064mn + future dev 2,346mn = 49,410mn. Source val report pp.27-30; deck p.14.
A38: Brookfield | B38: Shantiniketan Properties Private Limited | C38: Candor Techspace K1 | D38: Office | E38: Kolkata | F38: New Town (Rajarhat) | G38: New Town, Rajarhat, Kolkata (established office micro-market; ~1.5km from CBD metro) | H38: Plot No. 1, DH Block, New Town, Rajarhat, Kolkata, West Bengal | J38: 5.89 | K38: 3.2 | L38: 0.99 | N38: 55 | O38: 49 | P38: =IF(OR(N38="",O38="",O38=0),"",N38/O38-1) | Q38: 8.9 | S38: 0.085 | T38: 0.12 | U38: 3621 | V38: =IF(OR(U38="",I38="",I38=0),"",U38*10000000/I38) | Y38: Completed 32,01,857 sqft (12 bldgs, 98.82% committed occ) + under construction 0.58 msf + future dev 2.11 msf. REIT share 100%. Achievable mkt rent 55 SEZ office /57 non-SEZ /60 mixed-use retail; inplace 49. Cap rate 8.50%. WACC operational 11.50%, UC 12.75%. MV: completed 29,479mn + UC 2,430mn + future dev 4,301mn = 36,210mn. Gross acq price K1+G2=Rs62.3Bn. Source val report pp.31-35; deck p.14.
A39: Brookfield | B39: Festus Properties Private Limited | C39: Kensington (A & B) | D39: Office | E39: Mumbai | F39: Powai / Andheri | G39: Andheri & Powai micro-market, MMR (only private IT/ITeS SEZ in Mumbai excl. Thane/Navi Mumbai) | H39: Hiranandani Business Park, CTS No. 28A, Powai, Mumbai 400076, Maharashtra | I39: 1619079 | J39: 1.61 | K39: 1.61 | L39: 0.96 | N39: 160 | O39: 136 | P39: =IF(OR(N39="",O39="",O39=0),"",N39/O39-1) | Q39: 9.1 | S39: 0.08 | T39: 0.12 | U39: 3198.1 | V39: =IF(OR(U39="",I39="",I39=0),"",U39*10000000/I39) | Y39: Single bldg two wings, 1,619,079 sqft, 95.61% committed occ (val rpt) / 96% (deck). REIT share 100%. Deck groups Kensington under 'Downtown Powai - SEZ' (100% economic interest). Property tax entity: Festus Properties Pvt Ltd (val rpt). Achievable mkt rent 160 IT SEZ /175 IT; inplace(current effective) 136. Cap rate 8.00%, WACC operational 11.50%. Major tenants: TCS, L&T, GE Oil & Gas, Ergo Technology, Nomura, Aptia, RXO. Gross acq price Rs22.9Bn. MV 31,981mn. Source val report pp.36-39; deck p.14.
A40: Brookfield | B40: Candor Gurgaon One Realty Projects Private Limited | C40: Candor Techspace G1 | D40: Office | E40: Gurugram | F40: Sector 48 (Gurugram) | G40: Sector 48, Gurugram (Village Tikri), Haryana | H40: Village Tikri, Sector 48, Gurugram, Haryana | J40: 3.89 | K40: 3.79 | L40: 0.89 | N40: 88 | O40: 83 | P40: =IF(OR(N40="",O40="",O40=0),"",N40/O40-1) | Q40: 6.3 | S40: 0.08 | T40: 0.12 | U40: 6048.9 | V40: =IF(OR(U40="",I40="",I40=0),"",U40*10000000/I40) | Y40: JV / North Commercial Portfolio - equity-accounted; REIT economic interest 50% (deck). Val report MV of financial interest is 100% asset value 60,489mn (completed 59,924mn + future dev 565mn); 12 completed bldgs, 88.67% committed occ (val rpt)/89% (deck). Held via North Commercial Portfolio Holding Entity (BIRET 50% / GIC 50%). WACC operational 11.50%, UC 12.75%. Source val report pp.40-43; deck p.14, p.38.
A41: Brookfield | B41: Kairos Properties Private Limited | C41: Downtown Powai (Kairos) | D41: Office | E41: Mumbai | F41: Powai | G41: Andheri & Powai micro-market, MMR | H41: Hiranandani Business Park, Powai, Mumbai 400076, Maharashtra | J41: 2.86 | K41: 2.86 | L41: 0.95 | N41: 195 | O41: 186 | P41: =IF(OR(N41="",O41="",O41=0),"",N41/O41-1) | Q41: 3.9 | T41: 0.12 | U41: 8575 | V41: =IF(OR(U41="",I41="",I41=0),"",U41*10000000/I41) | Y41: JV / North Commercial Portfolio - equity-accounted; REIT interest 50% Equity + 50% CCDs (val rpt sec 4.7.3); deck 'Downtown Powai - IT/Commercial' 50% economic interest. Val report MV of financial interest 85,750mn (appears to be 100% asset basis). Cap rate stated NA (multiple use types); WACC operational 11.50%. Achievable mkt rent: office 195 commercial + separate IT Central/South, retail multiple (Delphi/Ventura Rs450-543); inplace(current effective) 186. Held via North portfolio (BIRET/GIC). Source val report pp.44-47; deck p.14, p.38.
A42: Brookfield | B42: Aspen Buildtech Private Limited | C42: Worldmark Tower 1 (Worldmark New Delhi) | D42: Retail | E42: New Delhi | F42: Aerocity | G42: Aerocity / Airport District, Delhi International Airport (established office & retail micro-market, Delhi NCR) | H42: Aerocity, Delhi International Airport, New Delhi | I42: 607892 | J42: 0.61 | K42: 0.61 | L42: 0.99 | N42: 235 | O42: 214 | P42: =IF(OR(N42="",O42="",O42=0),"",N42/O42-1) | U42: 1885.6 | V42: =IF(OR(U42="",I42="",I42=0),"",U42*10000000/I42) | Y42: JV / North Commercial Portfolio - equity-accounted; part of 'Worldmark, New Delhi' (deck 50% economic interest, WALE 5.1yr, inplace rent ~230 combined WM ND). Tower 1: 607,892 sqft, 99.4% committed occ. Cap rate NA in val rpt; WACC operational 11.50%. Achievable mkt rent office 235 / retail 190; current effective 214. Val report MV 18,856mn (100% asset basis). Held via Aspen Buildtech, North portfolio (BIRET/GIC 50/50). Source val report pp.48-51; deck p.14.
A43: Brookfield | B43: Aspen Buildtech Private Limited | C43: Worldmark Tower 2 & 3 (Worldmark New Delhi) | D43: Retail | E43: New Delhi | F43: Aerocity | G43: Aerocity / Airport District, Delhi International Airport (Delhi NCR) | H43: Aerocity, Delhi International Airport, New Delhi | I43: 847326 | J43: 0.85 | K43: 0.85 | L43: 0.93 | N43: 235 | O43: 249 | P43: =IF(OR(N43="",O43="",O43=0),"",N43/O43-1) | U43: 2806.3 | V43: =IF(OR(U43="",I43="",I43=0),"",U43*10000000/I43) | Y43: JV / North Commercial Portfolio - equity-accounted; part of 'Worldmark, New Delhi' (deck 50% economic interest). Tower 2&3: 847,326 sqft, 92.90% committed occ. Cap rate NA; WACC operational 11.50%. Achievable mkt rent office 235 / retail 190 / Atelier 410; current effective rents 249 (T?) & 232 (T?). Val report MV 28,063mn (100% asset basis). Held via Aspen Buildtech, North portfolio (BIRET/GIC 50/50). Source val report pp.52-57; deck p.14.
A44: Brookfield | B44: Rostrum Realty Private Limited | C44: Bharti Airtel Centre | D44: Office | E44: Gurugram | F44: Sector 18 (Gurugram) | G44: Sector 18, Phase IV, Gurugram North micro-market (near DLF Cyber City) | H44: Phase IV, Sector 18, Gurugram, Haryana | I44: 692585 | J44: 0.69 | K44: 0.69 | L44: 1 | M44: 1 | O44: 131 | P44: =IF(OR(N44="",O44="",O44=0),"",N44/O44-1) | Q44: 2 | R44: 1 | S44: 0.08 | T44: 0.12 | U44: 1428.4 | V44: =IF(OR(U44="",I44="",I44=0),"",U44*10000000/I44) | Y44: JV / North Commercial Portfolio - equity-accounted; REIT 50% economic interest (deck). Held by Rostrum Realty Pvt Ltd (also holds Pavilion Mall). Single bldg 692,585 sqft, 100% committed occ, single tenant (Bharti Airtel). Current effective rent 131 (deck in-place rent at expiry Rs131). Cap rate 8.00%, WACC operational 11.50%. Val report MV 14,284mn (100% asset basis). Source val report pp.58-61; deck p.14, p.30.
A45: Brookfield | B45: Oak Infrastructure Developers Private Limited | C45: Worldmark Gurugram | D45: Retail | E45: Gurugram | F45: Golf Course Ext (Sector 65) | G45: Sector 65, Gurugram (Golf Course Extension Road area) | H45: Sector 65, Gurugram, Haryana | I45: 751397 | J45: 0.75 | K45: 0.75 | L45: 0.92 | M45: 0.92 | O45: 94 | P45: =IF(OR(N45="",O45="",O45=0),"",N45/O45-1) | Q45: 5.8 | S45: 0.08 | T45: 0.12 | U45: 1091.2 | V45: =IF(OR(U45="",I45="",I45=0),"",U45*10000000/I45) | Y45: JV / North Commercial Portfolio - equity-accounted; REIT 50% economic interest (deck). Held by Oak Infrastructure Developers. 5 towers (Tower 1-5), 751,397 sqft, 92.2% committed occ (val rpt)/92% (deck). Current effective rent 94 (deck inplace Rs94). Cap rate 8.00%, WACC operational 11.50%. Val report MV 10,912mn (100% asset basis). Source val report pp.62-65; deck p.14.
A46: Brookfield | B46: Rostrum Realty Private Limited | C46: Pavilion Mall | D46: Retail | E46: Ludhiana | F46: Civil Lines | G46: Civil Lines, Ludhiana, Punjab | H46: Civil Lines, Ludhiana, Punjab | I46: 389845 | J46: 0.39 | K46: 0.39 | L46: 0.79 | M46: 0.79 | O46: 61 | P46: =IF(OR(N46="",O46="",O46=0),"",N46/O46-1) | Q46: 5.2 | S46: 0.0875 | T46: 0.12 | U46: 345 | V46: =IF(OR(U46="",I46="",I46=0),"",U46*10000000/I46) | Y46: JV / North Commercial Portfolio - equity-accounted; REIT 50% economic interest (deck). Held by Rostrum Realty Pvt Ltd (with Airtel Centre). Retail mall, 1 tower 389,845 sqft, 79.15% committed occ. Current effective rent 61. Cap rate 8.75%, WACC operational 11.50%. Val report MV 3,450mn (100% asset basis). Source val report pp.66-70; deck p.14.
A47: Brookfield | B47: Arliga Ecoworld Business Parks Private Limited | C47: Ecoworld | D47: Office | E47: Bengaluru | F47: Bellandur | G47: Outer Ring Road (ORR), Bellandur-Marathahalli (Competitive REIT micro-market) | H47: Outer Ring Road, Bellandur-Marathahalli, Bengaluru, Karnataka | I47: 7732309 | J47: 7.73 | K47: 7.65 | L47: 0.94 | M47: 0.94 | N47: 114 | O47: 100 | P47: =IF(OR(N47="",O47="",O47=0),"",N47/O47-1) | Q47: 6.1 | S47: 0.08 | T47: 0.12 | U47: 14827.9 | V47: =IF(OR(U47="",I47="",I47=0),"",U47*10000000/I47) | Y47: Acquired Q3 FY2026 (large-scale Bengaluru entry). 15 completed bldgs, 7,652,675 sqft, 94.3% effective committed occ (excl campus 3A/B/C; 94.7% incl) + future dev 79,634 sqft. REIT share 100% at val date; NOTE post-val (Apr 20 2026 / Q1 FY27) Ecoworld SPV raised Rs1,125 cr from 360One -> 360One 13%, BIRET retains 87%. Achievable mkt rent office 114 / retail 90; current effective 100 (96 incl campus 3). Cap rate 7.75% (shown 8 rounded); WACC operational 11.50%, UC 12.75%. Major tenants Honeywell, KPMG, Standard Chartered, Morgan Stanley, Shell, State Street. Completed MV 147,583mn + future dev 696mn = 148,279mn. Source val report pp.71-74; deck p.14.
A48: Nexus | B48: Select Infrastructure Private Limited (SIPL) | C48: Nexus Select Citywalk | D48: Retail | E48: New Delhi | F48: Saket | G48: Saket, South Delhi | H48: Plot No. P-1B, District Centre, Saket, Delhi, India | I48: 550908 | J48: 0.55 | K48: 0.55 | L48: 0.99 | M48: 0.97 | N48: 534.7 | O48: 470.1 | P48: =IF(OR(N48="",O48="",O48=0),"",N48/O48-1) | Q48: 4.7 | R48: 212 | S48: 0.075 | T48: 0.1138 | U48: 5004 | V48: =IF(OR(U48="",I48="",I48=0),"",U48*10000000/I48) | Y48: Freehold. Committed occ 98.8% (cert p68); leased 531,773/550,908 sf. Market/marginal rent 534.7 psf/mo, in-place (warm shell) 470.1 psf/mo (p125). WALE 4.7yr by area / 3.7yr by rental (p120). Cap rate 7.50% (premium asset, p61). 212+ brands. Value INR 50,040mn (p69). Source pages 68-69, 120, 125; cap rate p61; WACC p65.
A49: Nexus | B49: CSJ Infrastructure Private Limited (CSJIPL) | C49: Nexus Elante Complex | D49: Retail | E49: Chandigarh | F49: Industrial Area Phase I | G49: Industrial Area Phase I | H49: Plot No. 178-178A, Industrial Area Phase I, Chandigarh, India | I49: 1410000 | J49: 1.41 | K49: 1.33 | L49: 0.94 | M49: 0.91 | N49: 208.9 | O49: 197 | P49: =IF(OR(N49="",O49="",O49=0),"",N49/O49-1) | Q49: 4.3 | R49: 277 | S49: 0.075 | T49: 0.1138 | U49: 5983.4 | V49: =IF(OR(U49="",I49="",I49=0),"",U49*10000000/I49) | Y49: Freehold. RETAIL component only in this row (mall). Committed occ mall 94.4%; leased 1,210,824/1,326,512 sf. Mall market rent 208.9 psf/mo, in-place 197.0 psf/mo. Mall WALE 4.3yr area/3.9yr rental. Mall cap 7.50%. Mall value INR 52,095mn. Complex also has Elante Office (0.08msf/84,691 sf, occ 88.4%, in-place 120.1/marginal 109.0 psf/mo, WALE 2.7yr, cap 8.25%, WACC 11.78%, value INR 1,342mn) and Hyatt Regency Chandigarh 211-key hotel (cap 7.14%/14x EV-EBITDA, WACC 11.88%, value INR 6,397mn). Total complex value INR 59,834mn. Mall leasable incl recent 58,537 sf acquisition by CSJIPL. Pages 70-71, cap p61/62/63, WACC p65-67.
A50: Nexus | B50: Select Infrastructure Private Limited (SIPL) | C50: Nexus Seawoods | D50: Retail | E50: Navi Mumbai | F50: Nerul | G50: Nerul / Seawoods, Sector 40 | H50: Plot No. R1, Sector 40, Nerul Node, Navi Mumbai, District Thane, Maharashtra, India | I50: 979577 | J50: 0.98 | K50: 0.98 | L50: 0.98 | M50: 0.98 | N50: 160.2 | O50: 152.6 | P50: =IF(OR(N50="",O50="",O50=0),"",N50/O50-1) | Q50: 5.8 | R50: 290 | S50: 0.0775 | T50: 0.1138 | U50: 2805.1 | V50: =IF(OR(U50="",I50="",I50=0),"",U50*10000000/I50) | Y50: Leasehold (CIDCO, 60yr from 2008; ~42yr remaining, perpetuity assumed). Committed occ 98.1%; leased 954,988/979,577 sf. Market rent 160.2, in-place 152.6 psf/mo. WALE 5.8yr area/4.8yr rental. Cap 7.75%. Includes 0.2msf AIRSPACE F&B/entertainment zone. Value INR 28,051mn. Pages 72-73, cap p61, WACC p65.
A51: Nexus | B51: Euthoria Developers Private Limited (EDPL) | C51: Nexus Ahmedabad One | D51: Retail | E51: Ahmedabad | F51: Vastrapur | G51: Vastrapur / Memnagar | H51: Final Plot No. 216, Moje Vastrapur, Taluka Vejalpur, District Ahmedabad, India | I51: 888276 | J51: 0.89 | K51: 0.89 | L51: 0.96 | M51: 0.95 | N51: 145.7 | O51: 131.6 | P51: =IF(OR(N51="",O51="",O51=0),"",N51/O51-1) | Q51: 8.1 | R51: 213 | S51: 0.08 | T51: 0.1138 | U51: 2050 | V51: =IF(OR(U51="",I51="",I51=0),"",U51*10000000/I51) | Y51: Leasehold (AUDA, 99yr from 2006; perpetuity assumed). Two phases (P-I 2011, P-II Aug 2021). Committed occ 96.0%; leased 845,775/888,276 sf. Market rent 145.7, in-place 131.6 psf/mo. WALE 8.1yr area/4.9yr rental. Cap 8.00%. Largest Grade A mall in Gujarat. Value INR 20,500mn. Pages 74-75, cap p61, WACC p65.
A52: Nexus | B52: Nexus Hyderabad Retail Private Limited (NHRPL) | C52: Nexus Hyderabad | D52: Retail | E52: Hyderabad | F52: Kukatpally | G52: Kukatpally | H52: Sy. No.1009, Kukatpally Village, Kukatpally Mandal, Medchal Malkajgiri District, Hyderabad, India | I52: 831841 | J52: 0.83 | K52: 0.83 | L52: 0.99 | M52: 0.98 | N52: 132.3 | O52: 118.9 | P52: =IF(OR(N52="",O52="",O52=0),"",N52/O52-1) | Q52: 3.1 | R52: 175 | S52: 0.08 | T52: 0.1138 | U52: 1978.3 | V52: =IF(OR(U52="",I52="",I52=0),"",U52*10000000/I52) | Y52: Freehold. Committed occ 98.8%; leased 815,382/831,841 sf. Market rent 132.3, in-place 118.9 psf/mo. WALE 3.1yr area/2.9yr rental. Cap 8.00%. Value INR 19,783mn. Pages 76-77, cap p61, WACC p65.
A53: Nexus | B53: Nexus Hyderabad Retail Private Limited (NHRPL) | C53: Nexus Koramangala | D53: Retail | E53: Bengaluru | F53: Koramangala | G53: Koramangala | H53: Municipal No. 21, Hosur Road, Lakkasandra Ward No. 63, Bengaluru, India | I53: 307374 | J53: 0.31 | K53: 0.31 | L53: 0.97 | M53: 0.94 | N53: 211.1 | O53: 191 | P53: =IF(OR(N53="",O53="",O53=0),"",N53/O53-1) | Q53: 5.5 | R53: 99 | S53: 0.075 | T53: 0.1138 | U53: 1138.2 | V53: =IF(OR(U53="",I53="",I53=0),"",U53*10000000/I53) | Y53: Freehold. Value/area reflect NHRPL economic interest of 307,374 sf = ownership 254,960 sf + short-term leasehold 21,877 sf + revenue-share 30,537 sf (both valid to 31 Mar 2028). Committed occ 96.9%; leased 288,599/307,374 sf. Market rent 211.1, in-place 191.0 psf/mo. WALE 5.5yr area/5.0yr rental. Cap 7.50%. Value INR 11,382mn. Pages 78-79, cap p61, WACC p65.
A54: Nexus | B54: Vijaya Productions Private Limited (VPPL) | C54: Nexus Vijaya Complex | D54: Retail | E54: Chennai | F54: Vadapalani | G54: Vadapalani / Arcot Road | H54: Survey Nos. 5/1, 5/3, 5/7, 5/5, Arcot Road, Chennai, India | I54: 840000 | J54: 0.84 | K54: 0.65 | L54: 0.99 | M54: 0.98 | N54: 117.1 | O54: 109.8 | P54: =IF(OR(N54="",O54="",O54=0),"",N54/O54-1) | Q54: 4.5 | R54: 131 | S54: 0.08 | T54: 0.1138 | U54: 1781.2 | V54: =IF(OR(U54="",I54="",I54=0),"",U54*10000000/I54) | Y54: Freehold. RETAIL row (mall). Committed occ mall 99.4%; leased 637,489/653,765 sf. Mall market rent 117.1, in-place 109.8 psf/mo. Mall WALE 4.5yr area/3.9yr rental. Mall cap 8.00%. Mall value INR 15,665mn. Complex also has Vijaya Office 0.19msf (190,061 sf, occ 100%, in-place 58.5/marginal 64.0 psf/mo, WALE 4.6yr, cap 8.25%, WACC 11.78%, value INR 2,147mn). Total complex value INR 17,812mn. Pages 80-81, cap p61/62, WACC p65-66.
A55: Nexus | B55: Chitrali Properties Private Limited (CPPL) / Daksha Infrastructure Private Limited (DIPL) | C55: Nexus Westend Complex | D55: Retail | E55: Pune | F55: Aundh | G55: Aundh | H55: Survey No. 169/1 (CTS No. 2495), Village Aundh, Taluka Haveli, District Pune, Maharashtra, India | I55: 1410000 | J55: 1.41 | K55: 0.43 | L55: 0.94 | M55: 0.93 | N55: 142 | O55: 124.7 | P55: =IF(OR(N55="",O55="",O55=0),"",N55/O55-1) | Q55: 8.1 | R55: 129 | S55: 0.0825 | T55: 0.1138 | U55: 2307.2 | V55: =IF(OR(U55="",I55="",I55=0),"",U55*10000000/I55) | Y55: Freehold. RETAIL row (mall). Committed occ mall 94.1%; leased 401,882/433,090 sf. Mall market rent 142.0, in-place 124.7 psf/mo. Mall WALE 8.1yr area/5.5yr rental. Mall cap 8.25% (high competition submarket). Mall value INR 9,576mn. Complex also has Westend Icon Offices 0.98msf (977,967 sf, occ 93.0%, leased 861,802 sf, in-place 96.6/marginal 96.4 psf/mo, cap 8.25%, WACC 11.78%, value INR 13,496mn). Total complex value INR 23,072mn. Pages 82-83, cap p61/62, WACC p65-66.
A56: Nexus | B56: Safari Retreats Private Limited (SRPL) | C56: Nexus Esplanade | D56: Retail | E56: Bhubaneswar | F56: Rasulgarh | G56: Rasulgarh | H56: Various plots, Mouza Govind Prasad & Bomikhal, Tehsil Bhubaneswar, District Khurda, Odisha, India | I56: 428391 | J56: 0.43 | K56: 0.43 | L56: 0.99 | M56: 0.99 | N56: 161.7 | O56: 154.1 | P56: =IF(OR(N56="",O56="",O56=0),"",N56/O56-1) | Q56: 6.5 | R56: 125 | S56: 0.08 | T56: 0.1138 | U56: 1165.5 | V56: =IF(OR(U56="",I56="",I56=0),"",U56*10000000/I56) | Y56: Part Freehold / Part Leasehold (~44yr remaining leasehold, perpetuity assumed). Committed occ 98.9%; leased 423,650/428,391 sf. Market rent 161.7, in-place 154.1 psf/mo. WALE 6.5yr area/5.4yr rental. Cap 8.00%. Value INR 11,655mn. Pages 84-85, cap p61, WACC p65.
A57: Nexus | B57: Euthoria Developers Private Limited (EDPL) | C57: Nexus Amritsar | D57: Retail | E57: Amritsar | F57: Rajinder Nagar | G57: Rajinder Nagar, G.T. Road | H57: Khasra nos. 605 etc., Sultanwind Suburban, G.T. Road, Amritsar, Punjab, India | I57: 539181 | J57: 0.54 | K57: 0.54 | L57: 0.97 | M57: 0.95 | N57: 99.1 | O57: 89.5 | P57: =IF(OR(N57="",O57="",O57=0),"",N57/O57-1) | Q57: 7.7 | R57: 156 | S57: 0.08 | T57: 0.1138 | U57: 885.1 | V57: =IF(OR(U57="",I57="",I57=0),"",U57*10000000/I57) | Y57: Freehold. Committed occ 97.4%; leased 509,841/539,181 sf. Market rent 99.1, in-place 89.5 psf/mo. WALE 7.7yr area/5.2yr rental. Cap 8.00%. Value INR 8,851mn. Pages 86-87, cap p61, WACC p65.
A58: Nexus | B58: Nexus Shantiniketan Retail Private Limited (NSRPL) | C58: Nexus Shantiniketan | D58: Retail | E58: Bengaluru | F58: Whitefield | G58: Whitefield / Hoodi | H58: Municipal No. 13/288, Hoodi-Sadaramangala, Whitefield Sub-Division, Bengaluru, Karnataka, India | I58: 407492 | J58: 0.41 | K58: 0.41 | L58: 0.98 | M58: 0.97 | N58: 116 | O58: 109.8 | P58: =IF(OR(N58="",O58="",O58=0),"",N58/O58-1) | Q58: 6.4 | R58: 122 | S58: 0.08 | T58: 0.1138 | U58: 925.9 | V58: =IF(OR(U58="",I58="",I58=0),"",U58*10000000/I58) | Y58: Freehold. Area & value ADJUSTED for 64.90% economic interest. Total mall leasable 627,877 sf (0.63msf), NSRPL share 407,492 sf (0.41msf). Total asset value 100%=INR 14,267mn; adjusted-for-stake value INR 9,259mn. Committed occ 98.3%; leased 611,139/627,877 sf (full asset). Market rent 116.0, in-place 109.8 psf/mo. WALE 6.4yr area/5.2yr rental. Cap 8.00%. Pages 88-89, value-summary p108, cap p61, WACC p65.
A59: Nexus | B59: Nexusmalls Whitefield Private Limited (NWPL) | C59: Nexus Whitefield Complex | D59: Retail | E59: Bengaluru | F59: Whitefield | G59: Whitefield | H59: Survey No. 62, Whitefield Main Road, Whitefield, Bengaluru, Karnataka 560066, India | I59: 321367 | J59: 0.32 | K59: 0.32 | L59: 0.98 | N59: 102.6 | O59: 92 | P59: =IF(OR(N59="",O59="",O59=0),"",N59/O59-1) | Q59: 3.7 | R59: 91 | S59: 0.08 | T59: 0.1138 | U59: 831.9 | V59: =IF(OR(U59="",I59="",I59=0),"",U59*10000000/I59) | Y59: Freehold. RETAIL row (mall). Committed occ mall 98.1%. Mall market rent 102.6, in-place 92.0 psf/mo. Mall WALE 3.7yr area/3.4yr rental. Mall cap 8.00%. Mall value INR 5,824mn. Complex also has 143-key Oakwood Residence Whitefield Bangalore hotel (cap 7.14%/14x, WACC 11.88%, value INR 2,495mn). Total complex value INR 8,319mn. Pages 90-91, cap p61/63, WACC p65-67.
A60: Nexus | B60: Nexus Udaipur Retail Private Limited (NURPL) | C60: Nexus Celebration | D60: Retail | E60: Udaipur | F60: Bhuwana | G60: Bhuwana / NH8 | H60: Bhuwana (Phase-II), NH 8, Udaipur, Rajasthan, India | I60: 402926 | J60: 0.4 | K60: 0.4 | L60: 0.9 | N60: 86.5 | O60: 82.4 | P60: =IF(OR(N60="",O60="",O60=0),"",N60/O60-1) | Q60: 3.5 | R60: 107 | S60: 0.0825 | T60: 0.1138 | U60: 531.3 | V60: =IF(OR(U60="",I60="",I60=0),"",U60*10000000/I60) | Y60: Leasehold (99yr from 2004; ~77yr remaining, perpetuity assumed). Committed occ 90.4%. Market rent 86.5, in-place 82.4 psf/mo. WALE 3.5yr area/3.4yr rental. Cap 8.25% (tier-2 city, only retail development in city). Value INR 5,313mn. Pages 92-93, cap p61, WACC p65.
A61: Nexus | B61: Nexus Mangaluru Retail Private Limited (NMRPL Mangaluru) | C61: Fiza by Nexus | D61: Retail | E61: Mangaluru | F61: Pandeshwar | G61: Pandeshwar | H61: Plot No. TS 210 (R.S. No. 335), Attavara village, Pandeshwar Road, Mangalore, India | I61: 486030 | J61: 0.49 | K61: 0.49 | L61: 0.97 | N61: 86.5 | O61: 82.4 | P61: =IF(OR(N61="",O61="",O61=0),"",N61/O61-1) | Q61: 5.6 | R61: 119 | S61: 0.0825 | T61: 0.1138 | U61: 505.7 | V61: =IF(OR(U61="",I61="",I61=0),"",U61*10000000/I61) | Y61: Freehold. Area & value ADJUSTED for 68% economic interest. Total mall leasable 714,750 sf (0.71msf), NMRPL share 486,030 sf (0.49msf). Total asset value 100%=INR 7,436mn; adjusted value INR 5,057mn. Committed occ 97.3%. Market rent 86.5, in-place 82.4 psf/mo (rent-table value taken from Fiza chapter region pp94-95; layout ambiguous vs Celebration - spot-verify if precision critical). WALE 5.6yr area/5.0yr rental. Cap 8.25% (tier-2 city). Pages 94-95, value-summary p108, cap p61, WACC p65.
A62: Nexus | B62: Nexus Mysore Retail Private Limited (NMRPL Mysore) | C62: Nexus Centre City | D62: Retail | E62: Mysuru | F62: Nazarbad | G62: Nazarbad, Hyder Ali Road | H62: Survey No. 9 & Khata No. 33, Eranagare Village, Hyderali Road, Nazarbad Mohalla, Mysuru, Karnataka 570010, India | I62: 326002 | J62: 0.33 | K62: 0.33 | L62: 1 | M62: 0.99 | N62: 79.3 | O62: 71.5 | P62: =IF(OR(N62="",O62="",O62=0),"",N62/O62-1) | Q62: 6.1 | R62: 94 | S62: 0.0825 | T62: 0.1138 | U62: 424.1 | V62: =IF(OR(U62="",I62="",I62=0),"",U62*10000000/I62) | Y62: Freehold. Committed occ 99.7%; occupied 323,207/326,002 sf. Market rent 79.3, in-place 71.5 psf/mo. WALE 6.1yr area/4.8yr rental. Cap 8.25% (tier-2 city). Value INR 4,241mn. Pages 96-97, cap p61, WACC p65.
A63: Nexus | B63: Naman Mall Management Company Private Limited (NMMCPL) | C63: Nexus Indore Central | D63: Retail | E63: Indore | F63: South Tukoganj | G63: South Tukoganj, RNT Marg | H63: Plot No. 170, Rabindranath Tagore Marg, Indore, Madhya Pradesh, India | I63: 246864 | J63: 0.25 | K63: 0.25 | L63: 0.87 | M63: 0.87 | N63: 67.2 | O63: 63.4 | P63: =IF(OR(N63="",O63="",O63=0),"",N63/O63-1) | Q63: 10.8 | S63: 0.085 | T63: 0.1138 | U63: 212 | V63: =IF(OR(U63="",I63="",I63=0),"",U63*10000000/I63) | Y63: Freehold. Committed occ 87.3%; leased 214,464/246,864 sf. Market rent 67.2, in-place 63.4 psf/mo. WALE 10.8yr area/11.7yr rental. Cap 8.50% (tier-2 city, high competition; highest cap in portfolio). Value INR 2,120mn. Number of brands not stated numerically in cert. Pages 98-99, cap p61, WACC p65.
A64: Nexus | B64: Mamadapur Solar Private Limited (MSPL) | C64: Karnataka Solar Park | D64: Solar | E64: Vijayapura | F64: Kodabagi Village | G64: Kodabagi Village, Babaleshwar Taluk | H64: Kodabagi Village, Mamadapura Hobli, Babaleshwar Taluk, Bijapura District, Vijayapura, Karnataka 586113, India | P64: =IF(OR(N64="",O64="",O64=0),"",N64/O64-1) | T64: 0.115 | U64: 75.9 | V64: =IF(OR(U64="",I64="",I64=0),"",U64*10000000/I64) | Y64: Leasehold (67.925 acres, ~20yr remaining). NOT a mall: 15 MW (AC) captive solar PV plant with PPA supplying Nexus Koramangala, Shantiniketan, Whitefield, Centre City and Fiza. Valued via DCF. WACC 11.50% (cost of debt 8.5%, equity 14.5%). Value INR 759mn. Pages 100-101, WACC p66-67.
A65: Nexus | B65: Vijaya Productions Private Limited (VPPL) | C65: Nexus Vega City | D65: Retail | E65: Bengaluru | F65: Bannerghatta Road | G65: Bannerghatta Road, Bilekahalli | H65: Municipal No.1335/172/1 & 75, Bilekahalli Village, Bannerghatta Road, Bengaluru, Karnataka, India | I65: 439687 | J65: 0.44 | K65: 0.44 | L65: 0.99 | N65: 124.4 | O65: 121 | P65: =IF(OR(N65="",O65="",O65=0),"",N65/O65-1) | Q65: 10.7 | R65: 127 | S65: 0.08 | T65: 0.1138 | U65: 1071.9 | V65: =IF(OR(U65="",I65="",I65=0),"",U65*10000000/I65) | Y65: Freehold. Acquired Feb 2025 (post-IPO) at purchase price INR 8,697.5mn; not a related-party transaction. UDS in land for mall = 12,748 sqm. Committed occ 99.0%. Market rent 124.4, in-place 121.0 psf/mo. WALE 10.7yr area/8.6yr rental. Cap 8.00%. Value INR 10,719mn. Pages 102-103, cap p62, WACC p65.
A66: Nexus | B66: Select Infrastructure Private Limited (SIPL) | C66: Nexus MBD Complex | D66: Retail | E66: Ludhiana | F66: Ferozepur Road | G66: Ferozepur Road, Sunder Nagar | H66: Village Barewal Awana (Ferozepur Road), Tehsil & District Ludhiana, Punjab, India | I66: 257400 | J66: 0.26 | K66: 0.26 | L66: 0.99 | N66: 125.5 | O66: 110 | P66: =IF(OR(N66="",O66="",O66=0),"",N66/O66-1) | Q66: 6.2 | R66: 86 | S66: 0.0825 | T66: 0.1138 | U66: 603.3 | V66: =IF(OR(U66="",I66="",I66=0),"",U66*10000000/I66) | Y66: Freehold. RETAIL row (mall). Acquired May 2025 (post-IPO) at purchase price INR 4,900mn; not related-party. Committed occ mall 99.3%. Mall market rent 125.5, in-place 110.0 psf/mo. Mall WALE 6.2yr area/5.6yr rental. Mall cap 8.25% (tier-2 city). Mall value INR 4,521mn. Complex also has 96-key Radisson Blu Hotel Ludhiana (cap 7.14%/14x, WACC 11.88%, value INR 1,512mn). Total complex value INR 6,033mn. Pages 104-105, cap p61/63, WACC p65-67.
A67: Nexus | B67: Indore Treasure Island Private Limited (ITIPL) | C67: Treasure Island | D67: Retail | E67: Indore | F67: South Tukoganj | G67: South Tukoganj, MG Road | H67: Plot No. 11, MG Road, Tukoganj, Indore, Madhya Pradesh, India | I67: 220425 | J67: 0.22 | K67: 0.22 | L67: 0.87 | M67: 0.84 | N67: 72.4 | O67: 69.4 | P67: =IF(OR(N67="",O67="",O67=0),"",N67/O67-1) | Q67: 5.1 | R67: 86 | S67: 0.085 | T67: 0.1138 | U67: 278.3 | V67: =IF(OR(U67="",I67="",I67=0),"",U67*10000000/I67) | Y67: Leasehold (renewable 4yr 11mo). Nexus Select Trust owns 50% economic interest. Area & value ADJUSTED for 50% stake: total leasable 440,850 sf (0.43msf), share 220,425 sf (0.22msf); total value 100%=INR 5,566mn, adjusted INR 2,783mn. Committed occ 86.8%; leased 368,943/440,850 sf (full asset). Market rent 72.4, in-place 69.4 psf/mo. WALE 5.1yr area/3.7yr rental. Cap 8.50% (tier-2, high competition). Pages 106-107, value-summary p109, cap p61, WACC p65.
A68: KRT | B68: M/S Devbhumi Realtors Pvt Ltd | C68: Sattva Knowledge City | D68: Office | E68: Hyderabad | F68: HITEC City | G68: IT Corridor–HITEC City | H68: Plot No.2, Survey No. 83/1, Raidurg Panmaktha Village, Serilingampally Mandal, Ranga Reddy District, Telangana. | I68: 7295223 | J68: 7.3 | L68: 0.997 | N68: 120 | O68: 80.4 | P68: =IF(OR(N68="",O68="",O68=0),"",N68/O68-1) | Q68: 10 | S68: 0.075 | T68: 0.1146 | U68: 12292 | V68: =IF(OR(U68="",I68="",I68=0),"",U68*10000000/I68) | W68: 3.0% of the Facility Rentals | X68: INR 15.7 Mn from Apr'26 to Mar'27 (Mgmt input; 5% p.a. escalation from Apr'27) | Y68: Detailed sec 7 (pdf p.157); Valuation Certificate sec 6; Value Summary sec 4 (pdf p.55-56)
A69: KRT | B69: M/S Worldwide Realcon Pvt Ltd | C69: Sattva Knowledge Park | D69: Office | E69: Hyderabad | F69: HITEC City | G69: IT Corridor–HITEC City | H69: Plot No. 16, Survey No. 83/1, Raidurg Panmaktha Village, Serilingampally Mandal, Ranga Reddy District, Telangana. | I69: 3300963 | J69: 3.3 | L69: 0.968 | N69: 120 | O69: 79 | P69: =IF(OR(N69="",O69="",O69=0),"",N69/O69-1) | Q69: 10 | S69: 0.075 | T69: 0.1146 | U69: 5675.5 | V69: =IF(OR(U69="",I69="",I69=0),"",U69*10000000/I69) | W69: 3.0% of the Facility Rentals | X69: INR 4.1 Mn from Apr'26 to Mar'27 (Mgmt input; 5% p.a. escalation from Apr'27) | Y69: Detailed sec 8 (pdf p.176); Valuation Certificate sec 6; Value Summary sec 4 (pdf p.55-56)
A70: KRT | B70: M/S Sattva Knowledge Centre Pvt Ltd | C70: Sattva Knowledge Capital | D70: Office | E70: Hyderabad | F70: Nanakramguda | G70: Extended IT Corridor | H70: Plot No. 8 (Part), Survey No. 115, Nanakramguda Village, Serilingampally Mandal, Ranga Reddy District, Telangana. | I70: 2295894 | J70: 2.3 | N70: 68 | O70: 66.4 | P70: =IF(OR(N70="",O70="",O70=0),"",N70/O70-1) | S70: 0.0775 | T70: 0.1146 | U70: 2942.5 | V70: =IF(OR(U70="",I70="",I70=0),"",U70*10000000/I70) | W70: 3.0% of the Facility Rentals | X70: INR 2.1 Mn from Apr'26 to Mar'27 (Mgmt input; 5% p.a. escalation from Apr'27) | Y70: Detailed sec 9 (pdf p.191); Valuation Certificate sec 6; Value Summary sec 4 (pdf p.55-56)
A71: KRT | B71: One Bkc Realtors Private Limited | C71: One BKC | D71: Office | E71: Mumbai | F71: BKC & BKC-O | G71: BKC & BKC-O | H71: Plot No. C-66, C.T.S. No. 4207 (part), Village Kole-Kalyan, Mumbai Suburban District, G Block, Bandra- Kurla Complex, Bandra East, Mumbai | I71: 750044 | J71: 0.8 | L71: 0.872 | N71: 420 | O71: 366.7 | P71: =IF(OR(N71="",O71="",O71=0),"",N71/O71-1) | Q71: 3.8 | S71: 0.075 | T71: 0.1146 | U71: 4666.7 | V71: =IF(OR(U71="",I71="",I71=0),"",U71*10000000/I71) | W71: 3.0% of the Facility Rentals | X71: INR 3.2 Mn from Apr'26 to Mar'27 (Mgmt input; 5% p.a. escalation from Apr'27) | Y71: Detailed sec 10 (pdf p.206); Valuation Certificate sec 6; Value Summary sec 4 (pdf p.55-56)
A72: KRT | B72: One World Center Private Limited | C72: One World Center | D72: Office | E72: Mumbai | F72: Prabhadevi | G72: EXT - CBD | H72: Survey No. 841, Senapati Bapat Marg, Elphinstone Road, Lower Parel, Mumbai | I72: 1752214 | J72: 1.8 | L72: 0.925 | N72: 255 | O72: 211.7 | P72: =IF(OR(N72="",O72="",O72=0),"",N72/O72-1) | Q72: 3.5 | S72: 0.0775 | T72: 0.1146 | U72: 6276.7 | V72: =IF(OR(U72="",I72="",I72=0),"",U72*10000000/I72) | W72: 3.0% of the Facility Rentals | X72: INR 4.1 Mn from Apr'26 to Mar'27 (Mgmt input; 5% p.a. escalation from Apr'27) | Y72: Detailed sec 11 (pdf p.222); Valuation Certificate sec 6; Value Summary sec 4 (pdf p.55-56)
A73: KRT | B73: One International Center Pvt Ltd | C73: One International Center | D73: Office | E73: Mumbai | F73: Prabhadevi | G73: EXT - CBD | H73: Part of Plot 612 & 613, Senapati Bapat Marg, Prabhadevi, Dadar (W), Mumbai | I73: 1778186 | J73: 1.8 | L73: 0.891 | N73: 220 | O73: 186.9 | P73: =IF(OR(N73="",O73="",O73=0),"",N73/O73-1) | Q73: 2.6 | S73: 0.0775 | T73: 0.1146 | U73: 5534.3 | V73: =IF(OR(U73="",I73="",I73=0),"",U73*10000000/I73) | W73: 3.0% of the Facility Rentals | X73: INR 4.4 Mn from Apr'26 to Mar'27 (Mgmt input; 5% p.a. escalation from Apr'27) | Y73: Detailed sec 12 (pdf p.238); Valuation Certificate sec 6; Value Summary sec 4 (pdf p.55-56)
A74: KRT | B74: One International Center Private Limited | C74: One Unity Center | D74: Office | E74: Mumbai | F74: Prabhadevi | G74: EXT - CBD | H74: Part of Plot 612 & 613, Senapati Bapat Marg, Prabhadevi, Dadar (W), Mumbai. | I74: 1002111 | J74: 1 | L74: 0.844 | N74: 245 | O74: 198.8 | P74: =IF(OR(N74="",O74="",O74=0),"",N74/O74-1) | Q74: 5.7 | S74: 0.0775 | T74: 0.1146 | U74: 3364.2 | V74: =IF(OR(U74="",I74="",I74=0),"",U74*10000000/I74) | W74: 3.0% of the Facility Rentals | X74: INR 2.5 Mn from Apr'26 to Mar'27 (Mgmt input; 5% p.a. escalation from Apr'27) | Y74: Detailed sec 13 (pdf p.254); Valuation Certificate sec 6; Value Summary sec 4 (pdf p.55-56)
A75: KRT | B75: Prima Bay Private Limited | C75: Prima Bay | D75: Office | E75: Mumbai | F75: Powai | G75: PBD East | H75: C.T.S. No. 117A/1D (Part), Village Tungwa, Powai, Mumbai | I75: 806228 | J75: 0.8 | L75: 0.88 | N75: 165 | O75: 165.6 | P75: =IF(OR(N75="",O75="",O75=0),"",N75/O75-1) | Q75: 4.2 | S75: 0.08 | T75: 0.1146 | U75: 1879.4 | V75: =IF(OR(U75="",I75="",I75=0),"",U75*10000000/I75) | W75: 3.0% of the Facility Rentals | X75: INR 1.6 Mn from Apr'26 to Mar'27 (Mgmt input; 5% p.a. escalation from Apr'27) | Y75: Detailed sec 14 (pdf p.270); Valuation Certificate sec 6; Value Summary sec 4 (pdf p.55-56)
A76: KRT | B76: Cessna Garden Developers Private Limited | C76: Cessna Business Park | D76: Office | E76: Bengaluru | F76: Kadubeesanahalli | G76: Outer Ring-Road (ORR) | H76: Kadubeesanahalli Village, Varthur Hobli, Bengaluru South Taluk, Bengaluru. | I76: 4222478 | J76: 4.2 | L76: 0.944 | N76: 95 | O76: 70.9 | P76: =IF(OR(N76="",O76="",O76=0),"",N76/O76-1) | Q76: 16.1 | S76: 0.0766 | T76: 0.1146 | U76: 4906.1 | V76: =IF(OR(U76="",I76="",I76=0),"",U76*10000000/I76) | W76: 3.0% of the Facility Rentals | X76: INR 7.5 Mn from Apr'26 to Mar'27 (Mgmt input; 5% p.a. escalation from Apr'27) | Y76: Detailed sec 15 (pdf p.286); Valuation Certificate sec 6; Value Summary sec 4 (pdf p.55-56)
A77: KRT | B77: Exora Business Park Private Limited | C77: Exora Business Park | D77: Office | E77: Bengaluru | F77: Marathahalli | G77: Outer Ring-Road (ORR) | H77: Amani Bellandur Khane Village, Bengaluru East Taluk, Bengaluru. | I77: 2221078 | J77: 2.2 | L77: 0.777 | N77: 100 | O77: 89.8 | P77: =IF(OR(N77="",O77="",O77=0),"",N77/O77-1) | Q77: 6.6 | S77: 0.08 | T77: 0.1146 | U77: 3451.7 | V77: =IF(OR(U77="",I77="",I77=0),"",U77*10000000/I77) | W77: 3.0% of the Facility Rentals | X77: INR 3.3 Mn from Apr'26 to Mar'27 (Mgmt input; 5% p.a. escalation from Apr'27) | Y77: Detailed sec 16 (pdf p.305); Valuation Certificate sec 6; Value Summary sec 4 (pdf p.55-56)
A78: KRT | B78: M/S Gv Techparks Pvt Ltd | C78: Sattva Global City | D78: Office | E78: Bengaluru | F78: Tumkur Road | G78: Peripheral Business District - Others (along Mysore Road) | H78: Pattanagere and Mylasandra Villages, Kengeri hobli, Bengaluru | L78: 0.811 | O78: 58.5 | P78: =IF(OR(N78="",O78="",O78=0),"",N78/O78-1) | Q78: 8.7 | S78: 0.085 | T78: 0.1146 | U78: 4414.8 | V78: =IF(OR(U78="",I78="",I78=0),"",U78*10000000/I78) | W78: 3.0% of the Facility Rentals | X78: INR 6.12 Mn from Apr'26 to Mar'27 (Mgmt input; 5% p.a. escalation from Apr'27) | Y78: Operational block MV 34223 (4.2 msf) + Future Development MV 9925 (8.0 msf) | Detailed sec 17 (pdf p.321); Valuation Certificate sec 6; Value Summary sec 4 (pdf p.55-56)
A79: KRT | B79: Softzone Techpark Limited | C79: Sattva Softzone | D79: Office | E79: Bengaluru | F79: Bellandur | G79: Outer Ring-Road (ORR) | H79: Khata No.799/80/1/81/1/81/2, Ward No.150-Bellandur, Bengaluru | I79: 1003221 | J79: 1 | L79: 0.905 | N79: 107 | O79: 57.6 | P79: =IF(OR(N79="",O79="",O79=0),"",N79/O79-1) | Q79: 5.9 | S79: 0.08 | T79: 0.1146 | U79: 1818.4 | V79: =IF(OR(U79="",I79="",I79=0),"",U79*10000000/I79) | W79: 3.0% of the Facility Rentals | X79: INR 1.3 Mn from Apr'26 to Mar'27 (Mgmt input; 5% p.a. escalation from Apr'27) | Y79: Detailed sec 18 (pdf p.340); Valuation Certificate sec 6; Value Summary sec 4 (pdf p.55-56)
A80: KRT | B80: Darshita Hi-rise Pvt Ltd. | C80: Sattva Knowledge Court | D80: Office | E80: Bengaluru | F80: Whitefield | G80: Peripheral Business District - Whitefield (PBD-W) | H80: Survey No.77, bearing Khatha No-299, Doddanekkundi Village, K.R Puram Hobli, Bengaluru East Taluk, Bengaluru | I80: 879373 | J80: 0.9 | L80: 0.918 | N80: 80 | O80: 72.1 | P80: =IF(OR(N80="",O80="",O80=0),"",N80/O80-1) | Q80: 11.3 | S80: 0.08 | T80: 0.1146 | U80: 1258.6 | V80: =IF(OR(U80="",I80="",I80=0),"",U80*10000000/I80) | W80: 3.0% of the Facility Rentals | X80: INR 1.2 Mn from Apr'26 to Mar'27 (Mgmt input; 5% p.a. escalation from Apr'27) | Y80: Detailed sec 19 (pdf p.357); Valuation Certificate sec 6; Value Summary sec 4 (pdf p.55-56)
A81: KRT | B81: Salarpuria Griha Nirman Pvt Ltd | C81: Sattva Techpoint | D81: Office | E81: Bengaluru | F81: Whitefield / KR Puram | G81: EBD (Eastern Business District) | H81: Municipal No 30, 100 Feet Road, Srinivagilu, Ward No. 68, Bengaluru. | I81: 334593 | J81: 0.3 | N81: 135 | O81: 129.8 | P81: =IF(OR(N81="",O81="",O81=0),"",N81/O81-1) | Q81: 10.9 | S81: 0.08 | T81: 0.1146 | U81: 746.4 | V81: =IF(OR(U81="",I81="",I81=0),"",U81*10000000/I81) | W81: Property Management Fee 3.0% of Facility Rentals (below NOI line) | X81: INR 0.5 Mn from Apr'26 to Mar'27 (Mgmt input; 5% p.a. escalation from Apr'27) | Y81: Detailed sec 20 (pdf p.373); Valuation Certificate sec 6; Value Summary sec 4 (pdf p.55-56)
A82: KRT | B82: Pluto Business Parks Private Limited | C82: One Trade Tower | D82: Office | E82: Bengaluru | F82: Palace Road | G82: CBD (Central Business District) | H82: Municipal No. 46, Situated At Palace Road, Municipal Ward No.77, Sampangiramnagar, Bengaluru. | I82: 175336 | J82: 0.2 | N82: 210 | O82: 187.8 | P82: =IF(OR(N82="",O82="",O82=0),"",N82/O82-1) | Q82: 3.2 | S82: 0.0775 | T82: 0.1146 | U82: 611.2 | V82: =IF(OR(U82="",I82="",I82=0),"",U82*10000000/I82) | W82: 3.0% of the Facility Rentals | X82: INR 1.0 Mn from Apr'26 to Mar'27 (Mgmt input; 5% p.a. escalation from Apr'27) | Y82: Detailed sec 21 (pdf p.389); Valuation Certificate sec 6; Value Summary sec 4 (pdf p.55-56)
A83: KRT | B83: Siddeshwari Grihanirman Pvt. Ltd. | C83: Sattva Horizon | D83: Office | E83: Bengaluru | F83: Bellary Road | G83: NBD -Bellary Road (Beyond Kogilu cross) | H83: Khata No.1303/6/1 & 7/1, Venkatala, Ward No.01-Kempegowda Ward, Yelahanka, Bengaluru. | I83: 615560 | J83: 0.6 | N83: 66 | O83: 62 | P83: =IF(OR(N83="",O83="",O83=0),"",N83/O83-1) | Q83: 18.5 | S83: 0.08 | T83: 0.1146 | U83: 655.6 | V83: =IF(OR(U83="",I83="",I83=0),"",U83*10000000/I83) | W83: 3.0% of the Facility Rentals | X83: INR 0.7 Mn from Apr'26 to Mar'27 (Mgmt input; 5% p.a. escalation from Apr'27) | Y83: Detailed sec 22 (pdf p.403); Valuation Certificate sec 6; Value Summary sec 4 (pdf p.55-56)
A84: KRT | B84: Salarpuria Properties Pvt Ltd | C84: Sattva Touchstone | D84: Office | E84: Bengaluru | F84: Kadubeesanahalli | G84: Outer Ring-Road (ORR) | H84: Sy. No. 15/1A & 14-P7, Kadubeesanahalli Village, Varthur Hobli, Mahadevapura Zone, Ward No. 150- Bellandur, Bengaluru. | I84: 321440 | J84: 0.3 | L84: 0.432 | N84: 78 | O84: 78.3 | P84: =IF(OR(N84="",O84="",O84=0),"",N84/O84-1) | Q84: 2.3 | S84: 0.0825 | T84: 0.1146 | U84: 398.1 | V84: =IF(OR(U84="",I84="",I84=0),"",U84*10000000/I84) | W84: 3.0% of the Facility Rentals | X84: INR 0.6 Mn from Apr'26 to Mar'27 (Mgmt input; 5% p.a. escalation from Apr'27) | Y84: Detailed sec 23 (pdf p.416); Valuation Certificate sec 6; Value Summary sec 4 (pdf p.55-56)
A85: KRT | B85: Quadro Info technologies Pvt Ltd | C85: Sattva Infozone | D85: Office | E85: Bengaluru | F85: Peripheral (PBD) | G85: Peripheral Business District (PBD-O) | H85: Sy Nos. 39(P), 41(P) & 42(P), Electronic City, Doddathogur Village, Begur, Hobli, Bengaluru South Taluk, Bengaluru. | I85: 444591 | J85: 0.4 | L85: 0.822 | N85: 61 | O85: 54.4 | P85: =IF(OR(N85="",O85="",O85=0),"",N85/O85-1) | Q85: 3.7 | S85: 0.0825 | T85: 0.1146 | U85: 417.8 | V85: =IF(OR(U85="",I85="",I85=0),"",U85*10000000/I85) | W85: 3.0% of the Facility Rentals | X85: INR 0.5 Mn from Apr'26 to Mar'27 (Mgmt input; 5% p.a. escalation from Apr'27) | Y85: Detailed sec 24 (pdf p.432); Valuation Certificate sec 6; Value Summary sec 4 (pdf p.55-56)
A86: KRT | B86: 2. Softzone Techpark Limited | C86: Sattva Magnificia (I & II) | D86: Office | E86: Bengaluru | F86: KR Puram | G86: Extended Business District - EBD (KR Puram) | H86: Khata No:23/23/57/18/78/23 Beniganahalli and Vijinapura Village, K.R Puram Hobli, HAL Sub-division, Mahadevapura Zone, Bengaluru. | I86: 191976 | J86: 0.2 | N86: 107 | O86: 101.8 | P86: =IF(OR(N86="",O86="",O86=0),"",N86/O86-1) | Q86: 8.6 | S86: 0.08 | T86: 0.1146 | U86: 326.2 | V86: =IF(OR(U86="",I86="",I86=0),"",U86*10000000/I86) | W86: 3.0% of the Facility Rentals | X86: INR 0.1 Mn from Apr'26 to Mar'27 (Mgmt input; 5% p.a. escalation from Apr'27) | Y86: Magnificia I (MV 1357) + II (MV 1905) combined | Detailed sec 25 (pdf p.448); Valuation Certificate sec 6; Value Summary sec 4 (pdf p.55-56)
A87: KRT | B87: Jaganmayi Real Estate | C87: Sattva South Avenue | D87: Office | E87: Bengaluru | F87: Peripheral (PBD) | G87: Peripheral Business District (PBD-O) | H87: Plot No. 33, 33A & 33B, Sy. No.20, 22 & 23, Veerasandra Industrial Area, Veerasandra Village, Attibele Hobli, Anekal Taluk, Bengaluru | I87: 341553 | J87: 0.3 | L87: 0.598 | N87: 68 | O87: 69.2 | P87: =IF(OR(N87="",O87="",O87=0),"",N87/O87-1) | Q87: 9.6 | S87: 0.0825 | T87: 0.1146 | U87: 406.2 | V87: =IF(OR(U87="",I87="",I87=0),"",U87*10000000/I87) | W87: 3.0% of the Facility Rentals | X87: INR 0.4 Mn from Apr'26 to Mar'27 (Mgmt input; 5% p.a. escalation from Apr'27) | Y87: Detailed sec 26 (pdf p.467); Valuation Certificate sec 6; Value Summary sec 4 (pdf p.55-56)
A88: KRT | B88: Debonair Realtors Pvt Ltd | C88: Sattva Eminence | D88: Office | E88: Bengaluru | F88: Outer Ring Road | G88: Outer Ring-Road (ORR) | H88: Sy No. 174/175/176, Khata No: 239/240, Amani Bellandur Khane Village, Varthur Hobli, Bengaluru East Taluk, Bengaluru | I88: 164198 | J88: 0.2 | L88: 0.999 | N88: 86 | O88: 65.7 | P88: =IF(OR(N88="",O88="",O88=0),"",N88/O88-1) | Q88: 13.5 | S88: 0.08 | T88: 0.1146 | U88: 237 | V88: =IF(OR(U88="",I88="",I88=0),"",U88*10000000/I88) | W88: 3.0% of the Facility Rentals | X88: INR 0.2 Mn from Apr'26 to Mar'27 (Mgmt input; 5% p.a. escalation from Apr'27) | Y88: Detailed sec 27 (pdf p.482); Valuation Certificate sec 6; Value Summary sec 4 (pdf p.55-56)
A89: KRT | B89: Harkeshwar Realtors Private Limited | C89: Sattva Cosmo Lavelle | D89: Office | E89: Bengaluru | F89: Lavelle Road | G89: CBD (Central Business District) | H89: Municipal No. 9 (Old Nos. 9, 9/3, & 9/4), Residency Road, Richmond Circle, Bengaluru | I89: 77022 | J89: 0.1 | N89: 235 | O89: 235 | P89: =IF(OR(N89="",O89="",O89=0),"",N89/O89-1) | Q89: 14.8 | S89: 0.0775 | T89: 0.1146 | U89: 297.8 | V89: =IF(OR(U89="",I89="",I89=0),"",U89*10000000/I89) | W89: 3.0% of the Facility Rentals | X89: INR 0.2 Mn from Apr'26 to Mar'27 (Mgmt input; 5% p.a. escalation from Apr'27) | Y89: Detailed sec 28 (pdf p.497); Valuation Certificate sec 6; Value Summary sec 4 (pdf p.55-56)
A90: KRT | B90: Salarpuria Developers Pvt Ltd | C90: Sattva Premia | D90: Office | E90: Bengaluru | F90: Kadubeesanahalli | G90: ORR | H90: Sy No. 16, Khata No.316/1 to 316/5, Outer Ring Road Kadubeesanahalli Village, Mahadevapura Zone, Bengaluru East Taluk, Bengaluru. | I90: 113172 | J90: 0.1 | L90: 1 | N90: 80 | O90: 80 | P90: =IF(OR(N90="",O90="",O90=0),"",N90/O90-1) | Q90: 14.5 | S90: 0.0825 | T90: 0.1146 | U90: 133.8 | V90: =IF(OR(U90="",I90="",I90=0),"",U90*10000000/I90) | W90: 3.0% of the Facility Rentals | X90: INR 0.1 Mn from Apr'26 to Mar'27 (Mgmt input; 5% p.a. escalation from Apr'27) | Y90: Detailed sec 29 (pdf p.512); Valuation Certificate sec 6; Value Summary sec 4 (pdf p.55-56)
A91: KRT | B91: Sattva Developers Pvt Ltd | C91: Sattva Supreme | D91: Office | E91: Bengaluru | F91: Munnekolala | G91: Outer Ring-Road (ORR) | H91: Sy. No. 92/5 of Munnekolala Village, Varthur Hobli, Bengaluru East Taluk, Bengaluru | I91: 63929 | J91: 0.1 | L91: 0.322 | N91: 80 | O91: 91.1 | P91: =IF(OR(N91="",O91="",O91=0),"",N91/O91-1) | Q91: 3.7 | S91: 0.085 | T91: 0.1146 | U91: 72.5 | V91: =IF(OR(U91="",I91="",I91=0),"",U91*10000000/I91) | W91: Property Management Fee 3.0% of Facility Rentals (below NOI line) | X91: INR 0.2 Mn from Apr'26 to Mar'27 (Mgmt input; 5% p.a. escalation from Apr'27) | Y91: Detailed sec 30 (pdf p.526); Valuation Certificate sec 6; Value Summary sec 4 (pdf p.55-56)
A92: KRT | B92: Darshita Housing Pvt. Ltd. | C92: Sattva Endeavour | D92: Office | E92: Bengaluru | F92: Peripheral (PBD) | G92: Peripheral Business District (PBD – O) | H92: Sy No 44(P), 44/1A1, 46(P) and 47(P), Electronic City 2nd Phase, Begur (Konnappana Agrahara Village), Bengaluru South Taluk, Bengaluru. | I92: 739671 | J92: 0.7 | N92: 66 | P92: =IF(OR(N92="",O92="",O92=0),"",N92/O92-1) | S92: 0.0825 | T92: 0.124 | U92: 644.3 | V92: =IF(OR(U92="",I92="",I92=0),"",U92*10000000/I92) | W92: 3.0% of the Facility Rentals | X92: INR 1.4 Mn from Apr'26 to Mar'27 (Mgmt input; 5% p.a. escalation from Apr'27) | Y92: Detailed sec 31 (pdf p.541); Valuation Certificate sec 6; Value Summary sec 4 (pdf p.55-56)
A93: KRT | B93: Salarpuria Builders Private Limited | C93: Sattva Spectrum | D93: Office | E93: Bengaluru | F93: Peripheral (PBD) | G93: Peripheral Business District (PBD-O) | H93: Municipal No. 2355 / 78/6,5, 3, 8B, 9(P), Marathahalli Division, Doddakanelli, Marathahalli, Bengaluru | I93: 480962 | J93: 0.5 | N93: 75 | P93: =IF(OR(N93="",O93="",O93=0),"",N93/O93-1) | S93: 0.0825 | T93: 0.124 | U93: 494.2 | V93: =IF(OR(U93="",I93="",I93=0),"",U93*10000000/I93) | W93: 3.0% of the Facility Rentals | X93: INR 0.9 Mn from Apr'26 to Mar'27 (Mgmt input; 5% p.a. escalation from Apr'27) | Y93: Detailed sec 32 (pdf p.554); Valuation Certificate sec 6; Value Summary sec 4 (pdf p.55-56)
A94: KRT | B94: Kosmo One Business Park Private Limited | C94: Kosmo One | D94: Office | E94: Chennai | F94: Ambattur | G94: Ambattur | H94: Survey Nos. 195 Part, 196 Part, 197 Part, 198 Part, 199 Part And 200 Part, Mannurpet Village, And Survey Nos. 6 Part, 7 Part, 8 Part And 10 Part, Athipet Village, No. 14, 3Rd Main Road, Ambattur Industrial Estate, Ambattur, Chennai. | I94: 1911704 | J94: 1.9 | L94: 0.971 | N94: 57 | O94: 44.3 | P94: =IF(OR(N94="",O94="",O94=0),"",N94/O94-1) | Q94: 4.8 | S94: 0.08 | T94: 0.1146 | U94: 1623.7 | V94: =IF(OR(U94="",I94="",I94=0),"",U94*10000000/I94) | W94: 3.0% of the Facility Rentals | X94: INR 2.8 Mn from Apr'26 to Mar'27 (Mgmt input; 5% p.a. escalation from Apr'27) | Y94: Detailed sec 33 (pdf p.567); Valuation Certificate sec 6; Value Summary sec 4 (pdf p.55-56)
A95: KRT | B95: One Qube Realtors Private Limited | C95: One Qube | D95: Office | E95: Gurugram | F95: NH-8 (Gurugram) | G95: NH-8 (Before Rajiv Chowk) | H95: Plot No. 20, Sector-18, Urban Estate, Gurugram, Haryana. | I95: 555964 | J95: 0.6 | L95: 0.916 | N95: 125 | O95: 107.5 | P95: =IF(OR(N95="",O95="",O95=0),"",N95/O95-1) | Q95: 7.2 | S95: 0.08 | T95: 0.1146 | U95: 1029.5 | V95: =IF(OR(U95="",I95="",I95=0),"",U95*10000000/I95) | W95: 3.0% of the Facility Rentals | X95: INR 1.2 Mn from Apr'26 to Mar'27 (Mgmt input; 5% p.a. escalation from Apr'27) | Y95: Detailed sec 34 (pdf p.582); Valuation Certificate sec 6; Value Summary sec 4 (pdf p.55-56)
A96: KRT | B96: Pluto Atriza Business Parks Private Limited | C96: Fintech One | D96: Office | E96: GIFT City, Ahmedabad | F96: GIFT City | G96: GIFT City, Ahmedabad | H96: Survey No. 500, Village Ratanpur, Taluka And District: Gandhinagar, Gujarat. | I96: 452528 | J96: 0.5 | L96: 0.98 | N96: 63 | O96: 52 | P96: =IF(OR(N96="",O96="",O96=0),"",N96/O96-1) | Q96: 7.8 | S96: 0.08 | T96: 0.1146 | U96: 439.1 | V96: =IF(OR(U96="",I96="",I96=0),"",U96*10000000/I96) | W96: 3.0% of the Facility Rentals | X96: INR 0.9 Mn from Apr'26 to Mar'27 (Mgmt input; 5% p.a. escalation from Apr'27) | Y96: Detailed sec 35 (pdf p.597); Valuation Certificate sec 6; Value Summary sec 4 (pdf p.55-56)
A97: KRT | B97: One BKC Solar Energy Private Limited | C97: One BKC Solar | D97: Solar | E97: Dhule, Maharashtra | F97: Bhadgaon | H97: Bhadgaon, Dhule, Maharashtra | P97: =IF(OR(N97="",O97="",O97=0),"",N97/O97-1) | T97: 0.1146 | U97: 31.6 | V97: =IF(OR(U97="",I97="",I97=0),"",U97*10000000/I97) | W97: Property Management Fee 3.0% of Facility Rentals (below NOI line) | Y97: Detailed sec 36 (pdf p.612); Valuation Certificate sec 6; Value Summary sec 4 (pdf p.55-56)
A98: KRT | B98: Prima Bay Solar Energy Private Limited | C98: Prima Bay Solar | D98: Solar | E98: Dhule, Maharashtra | F98: Bhadgaon (Dhule) | H98: Bhadgaon, Dhule, Maharashtra | P98: =IF(OR(N98="",O98="",O98=0),"",N98/O98-1) | T98: 0.1146 | U98: 27.6 | V98: =IF(OR(U98="",I98="",I98=0),"",U98*10000000/I98) | W98: Property Management Fee 3.0% of Facility Rentals (below NOI line) | Y98: Detailed sec 37 (pdf p.619); Valuation Certificate sec 6; Value Summary sec 4 (pdf p.55-56)
A99: KRT | B99: Shirasa Regency Park Private Limited | C99: Karnataka Solar I | D99: Solar | E99: Chitradurga, Karnataka | F99: Nanivala Challakare | H99: Taluk Nanivala Challakare, District: Chitradurga, Karnataka | P99: =IF(OR(N99="",O99="",O99=0),"",N99/O99-1) | T99: 0.1146 | U99: 228.2 | V99: =IF(OR(U99="",I99="",I99=0),"",U99*10000000/I99) | W99: Property Management Fee 3.0% of Facility Rentals (below NOI line) | Y99: Detailed sec 38 (pdf p.626); Valuation Certificate sec 6; Value Summary sec 4 (pdf p.55-56)
A100: KRT | B100: NABS Datazone Private Limited (the ‘NABS’) | C100: Karnataka Solar - II | D100: Solar | E100: Chitradurga, Karnataka | F100: Nanivala Challakare | H100: Taluk Nanivala Challakare, District: Chitradurga, Karnataka | P100: =IF(OR(N100="",O100="",O100=0),"",N100/O100-1) | T100: 0.1225 | U100: 109.3 | V100: =IF(OR(U100="",I100="",I100=0),"",U100*10000000/I100) | W100: Property Management Fee 3.0% of Facility Rentals (below NOI line) | Y100: Detailed sec 39 (pdf p.634); Valuation Certificate sec 6; Value Summary sec 4 (pdf p.55-56)
...

Sheet Pricing by Area
A1: City | B1: Type | C1: # Assets | D1: Leasable (msf) | E1: Market value (INR cr) | F1: Avg value/sqft (INR) | G1: Avg market rent | H1: Avg in-place rent | I1: Avg reversion | J1: Avg cap rate
A2: Ahmedabad | B2: Retail | C2: =COUNTIFS('Asset Register'!$E$2:$E$109,$A2,'Asset Register'!$D$2:$D$109,$B2) | D2: =SUMIFS('Asset Register'!$J$2:$J$109,'Asset Register'!$E$2:$E$109,$A2,'Asset Register'!$D$2:$D$109,$B2) | E2: =SUMIFS('Asset Register'!$U$2:$U$109,'Asset Register'!$E$2:$E$109,$A2,'Asset Register'!$D$2:$D$109,$B2) | F2: =IFERROR(SUMIFS('Asset Register'!$U$2:$U$109,'Asset Register'!$E$2:$E$109,$A2,'Asset Register'!$D$2:$D$109,$B2)*10000000/SUMIFS('Asset Register'!$I$2:$I$109,'Asset Register'!$E$2:$E$109,$A2,'Asset Register'!$D$2:$D$109,$B2),"") | G2: =IFERROR(AVERAGEIFS('Asset Register'!$N$2:$N$109,'Asset Register'!$E$2:$E$109,$A2,'Asset Register'!$D$2:$D$109,$B2),"") | H2: =IFERROR(AVERAGEIFS('Asset Register'!$O$2:$O$109,'Asset Register'!$E$2:$E$109,$A2,'Asset Register'!$D$2:$D$109,$B2),"") | I2: =IFERROR(AVERAGEIFS('Asset Register'!$P$2:$P$109,'Asset Register'!$E$2:$E$109,$A2,'Asset Register'!$D$2:$D$109,$B2),"") | J2: =IFERROR(AVERAGEIFS('Asset Register'!$S$2:$S$109,'Asset Register'!$E$2:$E$109,$A2,'Asset Register'!$D$2:$D$109,$B2),"")
A3: Amritsar | B3: Retail | C3: =COUNTIFS('Asset Register'!$E$2:$E$109,$A3,'Asset Register'!$D$2:$D$109,$B3) | D3: =SUMIFS('Asset Register'!$J$2:$J$109,'Asset Register'!$E$2:$E$109,$A3,'Asset Register'!$D$2:$D$109,$B3) | E3: =SUMIFS('Asset Register'!$U$2:$U$109,'Asset Register'!$E$2:$E$109,$A3,'Asset Register'!$D$2:$D$109,$B3) | F3: =IFERROR(SUMIFS('Asset Register'!$U$2:$U$109,'Asset Register'!$E$2:$E$109,$A3,'Asset Register'!$D$2:$D$109,$B3)*10000000/SUMIFS('Asset Register'!$I$2:$I$109,'Asset Register'!$E$2:$E$109,$A3,'Asset Register'!$D$2:$D$109,$B3),"") | G3: =IFERROR(AVERAGEIFS('Asset Register'!$N$2:$N$109,'Asset Register'!$E$2:$E$109,$A3,'Asset Register'!$D$2:$D$109,$B3),"") | H3: =IFERROR(AVERAGEIFS('Asset Register'!$O$2:$O$109,'Asset Register'!$E$2:$E$109,$A3,'Asset Register'!$D$2:$D$109,$B3),"") | I3: =IFERROR(AVERAGEIFS('Asset Register'!$P$2:$P$109,'Asset Register'!$E$2:$E$109,$A3,'Asset Register'!$D$2:$D$109,$B3),"") | J3: =IFERROR(AVERAGEIFS('Asset Register'!$S$2:$S$109,'Asset Register'!$E$2:$E$109,$A3,'Asset Register'!$D$2:$D$109,$B3),"")
A4: Bellary District, Karnataka | B4: Other | C4: =COUNTIFS('Asset Register'!$E$2:$E$109,$A4,'Asset Register'!$D$2:$D$109,$B4) | D4: =SUMIFS('Asset Register'!$J$2:$J$109,'Asset Register'!$E$2:$E$109,$A4,'Asset Register'!$D$2:$D$109,$B4) | E4: =SUMIFS('Asset Register'!$U$2:$U$109,'Asset Register'!$E$2:$E$109,$A4,'Asset Register'!$D$2:$D$109,$B4) | F4: =IFERROR(SUMIFS('Asset Register'!$U$2:$U$109,'Asset Register'!$E$2:$E$109,$A4,'Asset Register'!$D$2:$D$109,$B4)*10000000/SUMIFS('Asset Register'!$I$2:$I$109,'Asset Register'!$E$2:$E$109,$A4,'Asset Register'!$D$2:$D$109,$B4),"") | G4: =IFERROR(AVERAGEIFS('Asset Register'!$N$2:$N$109,'Asset Register'!$E$2:$E$109,$A4,'Asset Register'!$D$2:$D$109,$B4),"") | H4: =IFERROR(AVERAGEIFS('Asset Register'!$O$2:$O$109,'Asset Register'!$E$2:$E$109,$A4,'Asset Register'!$D$2:$D$109,$B4),"") | I4: =IFERROR(AVERAGEIFS('Asset Register'!$P$2:$P$109,'Asset Register'!$E$2:$E$109,$A4,'Asset Register'!$D$2:$D$109,$B4),"") | J4: =IFERROR(AVERAGEIFS('Asset Register'!$S$2:$S$109,'Asset Register'!$E$2:$E$109,$A4,'Asset Register'!$D$2:$D$109,$B4),"")
A5: Bengaluru | B5: Hotel | C5: =COUNTIFS('Asset Register'!$E$2:$E$109,$A5,'Asset Register'!$D$2:$D$109,$B5) | D5: =SUMIFS('Asset Register'!$J$2:$J$109,'Asset Register'!$E$2:$E$109,$A5,'Asset Register'!$D$2:$D$109,$B5) | E5: =SUMIFS('Asset Register'!$U$2:$U$109,'Asset Register'!$E$2:$E$109,$A5,'Asset Register'!$D$2:$D$109,$B5) | F5: =IFERROR(SUMIFS('Asset Register'!$U$2:$U$109,'Asset Register'!$E$2:$E$109,$A5,'Asset Register'!$D$2:$D$109,$B5)*10000000/SUMIFS('Asset Register'!$I$2:$I$109,'Asset Register'!$E$2:$E$109,$A5,'Asset Register'!$D$2:$D$109,$B5),"") | G5: =IFERROR(AVERAGEIFS('Asset Register'!$N$2:$N$109,'Asset Register'!$E$2:$E$109,$A5,'Asset Register'!$D$2:$D$109,$B5),"") | H5: =IFERROR(AVERAGEIFS('Asset Register'!$O$2:$O$109,'Asset Register'!$E$2:$E$109,$A5,'Asset Register'!$D$2:$D$109,$B5),"") | I5: =IFERROR(AVERAGEIFS('Asset Register'!$P$2:$P$109,'Asset Register'!$E$2:$E$109,$A5,'Asset Register'!$D$2:$D$109,$B5),"") | J5: =IFERROR(AVERAGEIFS('Asset Register'!$S$2:$S$109,'Asset Register'!$E$2:$E$109,$A5,'Asset Register'!$D$2:$D$109,$B5),"")
A6: Bengaluru | B6: Office | C6: =COUNTIFS('Asset Register'!$E$2:$E$109,$A6,'Asset Register'!$D$2:$D$109,$B6) | D6: =SUMIFS('Asset Register'!$J$2:$J$109,'Asset Register'!$E$2:$E$109,$A6,'Asset Register'!$D$2:$D$109,$B6) | E6: =SUMIFS('Asset Register'!$U$2:$U$109,'Asset Register'!$E$2:$E$109,$A6,'Asset Register'!$D$2:$D$109,$B6) | F6: =IFERROR(SUMIFS('Asset Register'!$U$2:$U$109,'Asset Register'!$E$2:$E$109,$A6,'Asset Register'!$D$2:$D$109,$B6)*10000000/SUMIFS('Asset Register'!$I$2:$I$109,'Asset Register'!$E$2:$E$109,$A6,'Asset Register'!$D$2:$D$109,$B6),"") | G6: =IFERROR(AVERAGEIFS('Asset Register'!$N$2:$N$109,'Asset Register'!$E$2:$E$109,$A6,'Asset Register'!$D$2:$D$109,$B6),"") | H6: =IFERROR(AVERAGEIFS('Asset Register'!$O$2:$O$109,'Asset Register'!$E$2:$E$109,$A6,'Asset Register'!$D$2:$D$109,$B6),"") | I6: =IFERROR(AVERAGEIFS('Asset Register'!$P$2:$P$109,'Asset Register'!$E$2:$E$109,$A6,'Asset Register'!$D$2:$D$109,$B6),"") | J6: =IFERROR(AVERAGEIFS('Asset Register'!$S$2:$S$109,'Asset Register'!$E$2:$E$109,$A6,'Asset Register'!$D$2:$D$109,$B6),"")
A7: Bengaluru | B7: Retail | C7: =COUNTIFS('Asset Register'!$E$2:$E$109,$A7,'Asset Register'!$D$2:$D$109,$B7) | D7: =SUMIFS('Asset Register'!$J$2:$J$109,'Asset Register'!$E$2:$E$109,$A7,'Asset Register'!$D$2:$D$109,$B7) | E7: =SUMIFS('Asset Register'!$U$2:$U$109,'Asset Register'!$E$2:$E$109,$A7,'Asset Register'!$D$2:$D$109,$B7) | F7: =IFERROR(SUMIFS('Asset Register'!$U$2:$U$109,'Asset Register'!$E$2:$E$109,$A7,'Asset Register'!$D$2:$D$109,$B7)*10000000/SUMIFS('Asset Register'!$I$2:$I$109,'Asset Register'!$E$2:$E$109,$A7,'Asset Register'!$D$2:$D$109,$B7),"") | G7: =IFERROR(AVERAGEIFS('Asset Register'!$N$2:$N$109,'Asset Register'!$E$2:$E$109,$A7,'Asset Register'!$D$2:$D$109,$B7),"") | H7: =IFERROR(AVERAGEIFS('Asset Register'!$O$2:$O$109,'Asset Register'!$E$2:$E$109,$A7,'Asset Register'!$D$2:$D$109,$B7),"") | I7: =IFERROR(AVERAGEIFS('Asset Register'!$P$2:$P$109,'Asset Register'!$E$2:$E$109,$A7,'Asset Register'!$D$2:$D$109,$B7),"") | J7: =IFERROR(AVERAGEIFS('Asset Register'!$S$2:$S$109,'Asset Register'!$E$2:$E$109,$A7,'Asset Register'!$D$2:$D$109,$B7),"")
A8: Bhubaneswar | B8: Retail | C8: =COUNTIFS('Asset Register'!$E$2:$E$109,$A8,'Asset Register'!$D$2:$D$109,$B8) | D8: =SUMIFS('Asset Register'!$J$2:$J$109,'Asset Register'!$E$2:$E$109,$A8,'Asset Register'!$D$2:$D$109,$B8) | E8: =SUMIFS('Asset Register'!$U$2:$U$109,'Asset Register'!$E$2:$E$109,$A8,'Asset Register'!$D$2:$D$109,$B8) | F8: =IFERROR(SUMIFS('Asset Register'!$U$2:$U$109,'Asset Register'!$E$2:$E$109,$A8,'Asset Register'!$D$2:$D$109,$B8)*10000000/SUMIFS('Asset Register'!$I$2:$I$109,'Asset Register'!$E$2:$E$109,$A8,'Asset Register'!$D$2:$D$109,$B8),"") | G8: =IFERROR(AVERAGEIFS('Asset Register'!$N$2:$N$109,'Asset Register'!$E$2:$E$109,$A8,'Asset Register'!$D$2:$D$109,$B8),"") | H8: =IFERROR(AVERAGEIFS('Asset Register'!$O$2:$O$109,'Asset Register'!$E$2:$E$109,$A8,'Asset Register'!$D$2:$D$109,$B8),"") | I8: =IFERROR(AVERAGEIFS('Asset Register'!$P$2:$P$109,'Asset Register'!$E$2:$E$109,$A8,'Asset Register'!$D$2:$D$109,$B8),"") | J8: =IFERROR(AVERAGEIFS('Asset Register'!$S$2:$S$109,'Asset Register'!$E$2:$E$109,$A8,'Asset Register'!$D$2:$D$109,$B8),"")
A9: Chandigarh | B9: Retail | C9: =COUNTIFS('Asset Register'!$E$2:$E$109,$A9,'Asset Register'!$D$2:$D$109,$B9) | D9: =SUMIFS('Asset Register'!$J$2:$J$109,'Asset Register'!$E$2:$E$109,$A9,'Asset Register'!$D$2:$D$109,$B9) | E9: =SUMIFS('Asset Register'!$U$2:$U$109,'Asset Register'!$E$2:$E$109,$A9,'Asset Register'!$D$2:$D$109,$B9) | F9: =IFERROR(SUMIFS('Asset Register'!$U$2:$U$109,'Asset Register'!$E$2:$E$109,$A9,'Asset Register'!$D$2:$D$109,$B9)*10000000/SUMIFS('Asset Register'!$I$2:$I$109,'Asset Register'!$E$2:$E$109,$A9,'Asset Register'!$D$2:$D$109,$B9),"") | G9: =IFERROR(AVERAGEIFS('Asset Register'!$N$2:$N$109,'Asset Register'!$E$2:$E$109,$A9,'Asset Register'!$D$2:$D$109,$B9),"") | H9: =IFERROR(AVERAGEIFS('Asset Register'!$O$2:$O$109,'Asset Register'!$E$2:$E$109,$A9,'Asset Register'!$D$2:$D$109,$B9),"") | I9: =IFERROR(AVERAGEIFS('Asset Register'!$P$2:$P$109,'Asset Register'!$E$2:$E$109,$A9,'Asset Register'!$D$2:$D$109,$B9),"") | J9: =IFERROR(AVERAGEIFS('Asset Register'!$S$2:$S$109,'Asset Register'!$E$2:$E$109,$A9,'Asset Register'!$D$2:$D$109,$B9),"")
A10: Chennai | B10: Office | C10: =COUNTIFS('Asset Register'!$E$2:$E$109,$A10,'Asset Register'!$D$2:$D$109,$B10) | D10: =SUMIFS('Asset Register'!$J$2:$J$109,'Asset Register'!$E$2:$E$109,$A10,'Asset Register'!$D$2:$D$109,$B10) | E10: =SUMIFS('Asset Register'!$U$2:$U$109,'Asset Register'!$E$2:$E$109,$A10,'Asset Register'!$D$2:$D$109,$B10) | F10: =IFERROR(SUMIFS('Asset Register'!$U$2:$U$109,'Asset Register'!$E$2:$E$109,$A10,'Asset Register'!$D$2:$D$109,$B10)*10000000/SUMIFS('Asset Register'!$I$2:$I$109,'Asset Register'!$E$2:$E$109,$A10,'Asset Register'!$D$2:$D$109,$B10),"") | G10: =IFERROR(AVERAGEIFS('Asset Register'!$N$2:$N$109,'Asset Register'!$E$2:$E$109,$A10,'Asset Register'!$D$2:$D$109,$B10),"") | H10: =IFERROR(AVERAGEIFS('Asset Register'!$O$2:$O$109,'Asset Register'!$E$2:$E$109,$A10,'Asset Register'!$D$2:$D$109,$B10),"") | I10: =IFERROR(AVERAGEIFS('Asset Register'!$P$2:$P$109,'Asset Register'!$E$2:$E$109,$A10,'Asset Register'!$D$2:$D$109,$B10),"") | J10: =IFERROR(AVERAGEIFS('Asset Register'!$S$2:$S$109,'Asset Register'!$E$2:$E$109,$A10,'Asset Register'!$D$2:$D$109,$B10),"")
A11: Chennai | B11: Retail | C11: =COUNTIFS('Asset Register'!$E$2:$E$109,$A11,'Asset Register'!$D$2:$D$109,$B11) | D11: =SUMIFS('Asset Register'!$J$2:$J$109,'Asset Register'!$E$2:$E$109,$A11,'Asset Register'!$D$2:$D$109,$B11) | E11: =SUMIFS('Asset Register'!$U$2:$U$109,'Asset Register'!$E$2:$E$109,$A11,'Asset Register'!$D$2:$D$109,$B11) | F11: =IFERROR(SUMIFS('Asset Register'!$U$2:$U$109,'Asset Register'!$E$2:$E$109,$A11,'Asset Register'!$D$2:$D$109,$B11)*10000000/SUMIFS('Asset Register'!$I$2:$I$109,'Asset Register'!$E$2:$E$109,$A11,'Asset Register'!$D$2:$D$109,$B11),"") | G11: =IFERROR(AVERAGEIFS('Asset Register'!$N$2:$N$109,'Asset Register'!$E$2:$E$109,$A11,'Asset Register'!$D$2:$D$109,$B11),"") | H11: =IFERROR(AVERAGEIFS('Asset Register'!$O$2:$O$109,'Asset Register'!$E$2:$E$109,$A11,'Asset Register'!$D$2:$D$109,$B11),"") | I11: =IFERROR(AVERAGEIFS('Asset Register'!$P$2:$P$109,'Asset Register'!$E$2:$E$109,$A11,'Asset Register'!$D$2:$D$109,$B11),"") | J11: =IFERROR(AVERAGEIFS('Asset Register'!$S$2:$S$109,'Asset Register'!$E$2:$E$109,$A11,'Asset Register'!$D$2:$D$109,$B11),"")
A12: Chitradurga, Karnataka | B12: Solar | C12: =COUNTIFS('Asset Register'!$E$2:$E$109,$A12,'Asset Register'!$D$2:$D$109,$B12) | D12: =SUMIFS('Asset Register'!$J$2:$J$109,'Asset Register'!$E$2:$E$109,$A12,'Asset Register'!$D$2:$D$109,$B12) | E12: =SUMIFS('Asset Register'!$U$2:$U$109,'Asset Register'!$E$2:$E$109,$A12,'Asset Register'!$D$2:$D$109,$B12) | F12: =IFERROR(SUMIFS('Asset Register'!$U$2:$U$109,'Asset Register'!$E$2:$E$109,$A12,'Asset Register'!$D$2:$D$109,$B12)*10000000/SUMIFS('Asset Register'!$I$2:$I$109,'Asset Register'!$E$2:$E$109,$A12,'Asset Register'!$D$2:$D$109,$B12),"") | G12: =IFERROR(AVERAGEIFS('Asset Register'!$N$2:$N$109,'Asset Register'!$E$2:$E$109,$A12,'Asset Register'!$D$2:$D$109,$B12),"") | H12: =IFERROR(AVERAGEIFS('Asset Register'!$O$2:$O$109,'Asset Register'!$E$2:$E$109,$A12,'Asset Register'!$D$2:$D$109,$B12),"") | I12: =IFERROR(AVERAGEIFS('Asset Register'!$P$2:$P$109,'Asset Register'!$E$2:$E$109,$A12,'Asset Register'!$D$2:$D$109,$B12),"") | J12: =IFERROR(AVERAGEIFS('Asset Register'!$S$2:$S$109,'Asset Register'!$E$2:$E$109,$A12,'Asset Register'!$D$2:$D$109,$B12),"")
A13: Dhule, Maharashtra | B13: Solar | C13: =COUNTIFS('Asset Register'!$E$2:$E$109,$A13,'Asset Register'!$D$2:$D$109,$B13) | D13: =SUMIFS('Asset Register'!$J$2:$J$109,'Asset Register'!$E$2:$E$109,$A13,'Asset Register'!$D$2:$D$109,$B13) | E13: =SUMIFS('Asset Register'!$U$2:$U$109,'Asset Register'!$E$2:$E$109,$A13,'Asset Register'!$D$2:$D$109,$B13) | F13: =IFERROR(SUMIFS('Asset Register'!$U$2:$U$109,'Asset Register'!$E$2:$E$109,$A13,'Asset Register'!$D$2:$D$109,$B13)*10000000/SUMIFS('Asset Register'!$I$2:$I$109,'Asset Register'!$E$2:$E$109,$A13,'Asset Register'!$D$2:$D$109,$B13),"") | G13: =IFERROR(AVERAGEIFS('Asset Register'!$N$2:$N$109,'Asset Register'!$E$2:$E$109,$A13,'Asset Register'!$D$2:$D$109,$B13),"") | H13: =IFERROR(AVERAGEIFS('Asset Register'!$O$2:$O$109,'Asset Register'!$E$2:$E$109,$A13,'Asset Register'!$D$2:$D$109,$B13),"") | I13: =IFERROR(AVERAGEIFS('Asset Register'!$P$2:$P$109,'Asset Register'!$E$2:$E$109,$A13,'Asset Register'!$D$2:$D$109,$B13),"") | J13: =IFERROR(AVERAGEIFS('Asset Register'!$S$2:$S$109,'Asset Register'!$E$2:$E$109,$A13,'Asset Register'!$D$2:$D$109,$B13),"")
... A34: Vijayapura | B34: Solar | C34: =COUNTIFS('Asset Register'!$E$2:$E$109,$A34,'Asset Register'!$D$2:$D$109,$B34) | D34: =SUMIFS('Asset Register'!$J$2:$J$109,'Asset Register'!$E$2:$E$109,$A34,'Asset Register'!$D$2:$D$109,$B34) | E34: =SUMIFS('Asset Register'!$U$2:$U$109,'Asset Register'!$E$2:$E$109,$A34,'Asset Register'!$D$2:$D$109,$B34) | F34: =IFERROR(SUMIFS('Asset Register'!$U$2:$U$109,'Asset Register'!$E$2:$E$109,$A34,'Asset Register'!$D$2:$D$109,$B34)*10000000/SUMIFS('Asset Register'!$I$2:$I$109,'Asset Register'!$E$2:$E$109,$A34,'Asset Register'!$D$2:$D$109,$B34),"") | G34: =IFERROR(AVERAGEIFS('Asset Register'!$N$2:$N$109,'Asset Register'!$E$2:$E$109,$A34,'Asset Register'!$D$2:$D$109,$B34),"") | H34: =IFERROR(AVERAGEIFS('Asset Register'!$O$2:$O$109,'Asset Register'!$E$2:$E$109,$A34,'Asset Register'!$D$2:$D$109,$B34),"") | I34: =IFERROR(AVERAGEIFS('Asset Register'!$P$2:$P$109,'Asset Register'!$E$2:$E$109,$A34,'Asset Register'!$D$2:$D$109,$B34),"") | J34: =IFERROR(AVERAGEIFS('Asset Register'!$S$2:$S$109,'Asset Register'!$E$2:$E$109,$A34,'Asset Register'!$D$2:$D$109,$B34),"")

Sheet By REIT
A1: REIT | B1: # Assets | C1: Leasable (msf) | D1: Portfolio value (INR cr) | E1: Avg value/sqft (INR) | F1: Avg market rent | G1: Avg in-place rent | H1: Avg cap rate
A2: Embassy | B2: =COUNTIFS('Asset Register'!$A$2:$A$109,$A2) | C2: =SUMIFS('Asset Register'!$J$2:$J$109,'Asset Register'!$A$2:$A$109,$A2) | D2: =SUMIFS('Asset Register'!$U$2:$U$109,'Asset Register'!$A$2:$A$109,$A2) | E2: =IFERROR(SUMIFS('Asset Register'!$U$2:$U$109,'Asset Register'!$A$2:$A$109,$A2)*10000000/SUMIFS('Asset Register'!$I$2:$I$109,'Asset Register'!$A$2:$A$109,$A2),"") | F2: =IFERROR(AVERAGEIFS('Asset Register'!$N$2:$N$109,'Asset Register'!$A$2:$A$109,$A2),"") | G2: =IFERROR(AVERAGEIFS('Asset Register'!$O$2:$O$109,'Asset Register'!$A$2:$A$109,$A2),"") | H2: =IFERROR(AVERAGEIFS('Asset Register'!$S$2:$S$109,'Asset Register'!$A$2:$A$109,$A2),"")
A3: Mindspace | B3: =COUNTIFS('Asset Register'!$A$2:$A$109,$A3) | C3: =SUMIFS('Asset Register'!$J$2:$J$109,'Asset Register'!$A$2:$A$109,$A3) | D3: =SUMIFS('Asset Register'!$U$2:$U$109,'Asset Register'!$A$2:$A$109,$A3) | E3: =IFERROR(SUMIFS('Asset Register'!$U$2:$U$109,'Asset Register'!$A$2:$A$109,$A3)*10000000/SUMIFS('Asset Register'!$I$2:$I$109,'Asset Register'!$A$2:$A$109,$A3),"") | F3: =IFERROR(AVERAGEIFS('Asset Register'!$N$2:$N$109,'Asset Register'!$A$2:$A$109,$A3),"") | G3: =IFERROR(AVERAGEIFS('Asset Register'!$O$2:$O$109,'Asset Register'!$A$2:$A$109,$A3),"") | H3: =IFERROR(AVERAGEIFS('Asset Register'!$S$2:$S$109,'Asset Register'!$A$2:$A$109,$A3),"")
A4: Brookfield | B4: =COUNTIFS('Asset Register'!$A$2:$A$109,$A4) | C4: =SUMIFS('Asset Register'!$J$2:$J$109,'Asset Register'!$A$2:$A$109,$A4) | D4: =SUMIFS('Asset Register'!$U$2:$U$109,'Asset Register'!$A$2:$A$109,$A4) | E4: =IFERROR(SUMIFS('Asset Register'!$U$2:$U$109,'Asset Register'!$A$2:$A$109,$A4)*10000000/SUMIFS('Asset Register'!$I$2:$I$109,'Asset Register'!$A$2:$A$109,$A4),"") | F4: =IFERROR(AVERAGEIFS('Asset Register'!$N$2:$N$109,'Asset Register'!$A$2:$A$109,$A4),"") | G4: =IFERROR(AVERAGEIFS('Asset Register'!$O$2:$O$109,'Asset Register'!$A$2:$A$109,$A4),"") | H4: =IFERROR(AVERAGEIFS('Asset Register'!$S$2:$S$109,'Asset Register'!$A$2:$A$109,$A4),"")
A5: Nexus | B5: =COUNTIFS('Asset Register'!$A$2:$A$109,$A5) | C5: =SUMIFS('Asset Register'!$J$2:$J$109,'Asset Register'!$A$2:$A$109,$A5) | D5: =SUMIFS('Asset Register'!$U$2:$U$109,'Asset Register'!$A$2:$A$109,$A5) | E5: =IFERROR(SUMIFS('Asset Register'!$U$2:$U$109,'Asset Register'!$A$2:$A$109,$A5)*10000000/SUMIFS('Asset Register'!$I$2:$I$109,'Asset Register'!$A$2:$A$109,$A5),"") | F5: =IFERROR(AVERAGEIFS('Asset Register'!$N$2:$N$109,'Asset Register'!$A$2:$A$109,$A5),"") | G5: =IFERROR(AVERAGEIFS('Asset Register'!$O$2:$O$109,'Asset Register'!$A$2:$A$109,$A5),"") | H5: =IFERROR(AVERAGEIFS('Asset Register'!$S$2:$S$109,'Asset Register'!$A$2:$A$109,$A5),"")
A6: KRT | B6: =COUNTIFS('Asset Register'!$A$2:$A$109,$A6) | C6: =SUMIFS('Asset Register'!$J$2:$J$109,'Asset Register'!$A$2:$A$109,$A6) | D6: =SUMIFS('Asset Register'!$U$2:$U$109,'Asset Register'!$A$2:$A$109,$A6) | E6: =IFERROR(SUMIFS('Asset Register'!$U$2:$U$109,'Asset Register'!$A$2:$A$109,$A6)*10000000/SUMIFS('Asset Register'!$I$2:$I$109,'Asset Register'!$A$2:$A$109,$A6),"") | F6: =IFERROR(AVERAGEIFS('Asset Register'!$N$2:$N$109,'Asset Register'!$A$2:$A$109,$A6),"") | G6: =IFERROR(AVERAGEIFS('Asset Register'!$O$2:$O$109,'Asset Register'!$A$2:$A$109,$A6),"") | H6: =IFERROR(AVERAGEIFS('Asset Register'!$S$2:$S$109,'Asset Register'!$A$2:$A$109,$A6),"")
A7: Bagmane | B7: =COUNTIFS('Asset Register'!$A$2:$A$109,$A7) | C7: =SUMIFS('Asset Register'!$J$2:$J$109,'Asset Register'!$A$2:$A$109,$A7) | D7: =SUMIFS('Asset Register'!$U$2:$U$109,'Asset Register'!$A$2:$A$109,$A7) | E7: =IFERROR(SUMIFS('Asset Register'!$U$2:$U$109,'Asset Register'!$A$2:$A$109,$A7)*10000000/SUMIFS('Asset Register'!$I$2:$I$109,'Asset Register'!$A$2:$A$109,$A7),"") | F7: =IFERROR(AVERAGEIFS('Asset Register'!$N$2:$N$109,'Asset Register'!$A$2:$A$109,$A7),"") | G7: =IFERROR(AVERAGEIFS('Asset Register'!$O$2:$O$109,'Asset Register'!$A$2:$A$109,$A7),"") | H7: =IFERROR(AVERAGEIFS('Asset Register'!$S$2:$S$109,'Asset Register'!$A$2:$A$109,$A7),"")
A8: TOTAL | B8: =SUM(B2:B7) | C8: =SUM(C2:C7) | D8: =SUM(D2:D7)

Sheet Embassy
A1: Embassy - Asset-level detail (valuation 31 Mar 2026; 16 assets)
A3: SPV / Holding entity | B3: Property / Asset | C3: Type | D3: City | E3: Locality / Area | F3: Micro-market (valuer) | G3: Address | H3: Leasable (sq ft) | I3: Leasable (msf) | J3: Completed (msf) | K3: Committed occ. | L3: In-place occ. | M3: Market rent /sqft/mo | N3: In-place rent /sqft/mo | O3: Rent reversion | P3: WALE (yrs) | Q3: Tenants | R3: Cap rate | S3: Discount rate | T3: Market value (INR cr) | U3: Value/sqft (INR) | V3: Mgmt fee (valuation DCF) | W3: Insurance (valuation DCF) | X3: Notes / source
A4: Manyata Promoters Private Limited (MPPL) | B4: Embassy Manyata | C4: Office | D4: Bengaluru | E4: Nagawara / Hebbal | F4: Peripheral North (Outer Ring Road / Hebbal stretch) | G4: Along Outer Ring Road, Nagawara, Bengaluru, Karnataka; land approx. 119.15 acres | H4: 17200000 | I4: 17.2 | J4: 14.6 | L4: 0.94 | M4: 105 | N4: 95 | O4: =IF(OR(M4="",N4="",N4=0),"",M4/N4-1) | P4: 8.8 | R4: 0.08 | S4: 0.12 | T4: 27868.9 | U4: =IF(OR(T4="",H4="",H4=0),"",T4*10000000/H4) | V4: Property Management Fees = 3% of Total Income (lease rentals, parking, fitout, other operating income) | W4: INR 0.3/sqft/mo; property tax & insurance escalated 3% p.a. | X4: Mixed-use: completed office 14.6 msf + UC/proposed office 2.6 msf + Hotel (5-star 266 keys, 3-star 353 keys). Value split: completed 242,591 + UC/proposed 17,026 + hotel 19,072. Cap rate 8% office/retail, 7.14% hospitality; discount rate 11.5% operational office, 12.75% UC, 11.90% hospitality (reported field uses office cap 8% / operational discount ~11.5-12.75, rounded to 12). Retail mkt rent 105, anchor 94.5. Blocks M3A/M3B on leasehold land from EPDPL. Source lines ~9433-10476, value summary L4237.
A5: Vikas Telecom Private Limited (VTPL) & Sarla Infrastructure Private Limited (SIPL) | B5: Embassy TechVillage | C5: Office | D5: Bengaluru | E5: Bellandur | F5: Outer Ring Road (Sarjapura-Marathahalli), Bellandur-Marathahalli | G5: Devarabeesanahalli Village & Kariyamanna Agrahara Village, Varthur Hobli, Bengaluru East Taluk, Karnataka; land approx. 84.05 acres under purview | H5: 9700000 | I5: 9.7 | J5: 9.2 | L5: 0.95 | M5: 105 | N5: 90 | O5: =IF(OR(M5="",N5="",N5=0),"",M5/N5-1) | P5: 9.5 | R5: 0.08 | S5: 0.12 | T5: 16624.6 | U5: =IF(OR(T5="",H5="",H5=0),"",T5*10000000/H5) | V5: Property Management Fees = 3% of Total Income | W5: INR 0.21/sqft/mo | X5: Mixed-use: completed office 9.2 msf + UC office 0.4 msf + 2 UC hotels (5-star 311 keys, 3-star 207 keys). Value split: completed 153,974 + UC/proposed 4,258 + hotel 8,014. Cap 8% office/retail, 7.14% hospitality; discount 11.5% operational, 12.75% UC office, 13.25% UC hotel. Retail mkt rent 90. SIPL portion (1.2 msf, Block 9) BTS to JP Morgan. Source lines ~10477-11428.
A6: GolfLinks Software Park Private Limited (GLSP, 50% JV) + Eleanor Realty Holdings India Private Limited (ERHIPL, Pinehurst 100%) | B6: Embassy GolfLinks (incl. Pinehurst) | C6: Office | D6: Bengaluru | E6: Domlur | F6: Suburban East (Intermediate Ring Road, near CBD) | G6: Challaghatta Village, Varthur Hobli, Mahadevapura, Bengaluru East Taluk 560071; land approx. 37.1 acres | H6: 3400000 | I6: 3.4 | J6: 3.4 | L6: 1 | M6: 170 | N6: 160 | O6: =IF(OR(M6="",N6="",N6=0),"",M6/N6-1) | P6: 10 | R6: 0.08 | S6: 0.12 | T6: 5129.8 | U6: =IF(OR(T6="",H6="",H6=0),"",T6*10000000/H6) | V6: Property Management Fees = 3% of Total Income (both GolfLinks and Pinehurst) | W6: GolfLinks INR 0.3/sqft/mo; Pinehurst INR 0.5/sqft/mo | X6: 100% property value = GolfLinks 84,937 + Pinehurst 8,829 = 93,766; REIT economic interest = 50% of GolfLinks + 100% Pinehurst = 51,298 (this is the share-of-total value shown in the portfolio summary). Cap 7.75% office/retail; discount 11.5% operational. Pinehurst (0.3 msf) acquired via 100% Eleanor Realty stake Q3 FY2026: mkt rent 180, in-place 167 (192 as of 1-Apr-2026). GolfLinks office mkt rent 170, in-place 160; retail mkt rent 55. cap_rate field records 7.75 rounded to 8. Source lines ~11429-12099; summary L4288.
A7: Quadron Business Park Private Limited (QBPL) | B7: Embassy One | C7: Office | D7: Bengaluru | E7: Bellary Road (Mekhri Circle) | F7: Peripheral North (between Hebbal and off-CBD) | G7: Embassy One, Bellary Road, Ganga Nagar, Bengaluru, Karnataka; land approx. 5.6 acres (3.2 acres under valuation scope) | H7: 300000 | I7: 0.3 | J7: 0.3 | L7: 1 | M7: 151 | N7: 151 | O7: =IF(OR(M7="",N7="",N7=0),"",M7/N7-1) | P7: 7.6 | R7: 0.08 | S7: 0.12 | T7: 1572 | U7: =IF(OR(T7="",H7="",H7=0),"",T7*10000000/H7) | V7: Property Management Fees = 3% of Total Income | W7: INR 0.4/sqft/mo | X7: Mixed-use: completed office 0.3 msf (Pinnacle tower) + Four Seasons hotel 230 keys (5-star). Value split: office 5,902 + hotel 9,818 = 15,720. Cap 7.75% office, 7.14% hospitality (recorded 8, rounded); discount 11.5% operational, 11.90% hospitality. Office mkt rent = in-place 151 (incl. car park). Residential apartments excluded. Vacancy provision 5%. SPV Quadron Business Park Pvt Ltd (same SPV that owns Embassy Quadron Pune). Source lines ~12100-12800.
A8: Embassy Construction Private Limited (ECPL) | B8: Embassy Business Hub | C8: Office | D8: Bengaluru | E8: Yelahanka | F8: Peripheral North / North Bengaluru (Yelahanka-Devanahalli) | G8: Sy. No. 25/2, 25/3 & 26, Venkatala Village, Bellary Road (NH-44), Yelahanka, Bengaluru North, Karnataka; JDA land approx. 13 acres | H8: 1400000 | I8: 1.4 | J8: 0.4 | M8: 69 | N8: 58 | O8: =IF(OR(M8="",N8="",N8=0),"",M8/N8-1) | Q8: 1 | R8: 0.08 | S8: 0.12 | T8: 722.4 | U8: =IF(OR(T8="",H8="",H8=0),"",T8*10000000/H8) | V8: Property Management Fees = 3% of Total Income | W8: INR 0.25/sqft/mo | X8: REIT share (developer share under JDA) approx. 1.4 msf: Phase I completed 0.4 msf (single tenant Philips India, lease to Nov 2038) + Phase II UC 1.0 msf (completion FY2028). Value split: Phase I 4,652 + Phase II UC 2,572 = 7,224. Cap 8%; discount 11.5% Phase I operational, 12.75% Phase II UC. SPV named from consolidated AR/FS (ECPL) - valuation report showed only JDA ownership, no explicit Entity line. Phase II pending dev cost INR 6,569 Mn. Source lines ~12802-13413; AR L1275/7021.
A9: Indian Express Newspapers (Mumbai) Private Limited (IENMPL) | B9: Express Towers | C9: Office | D9: Mumbai | E9: Nariman Point | F9: South Mumbai CBD (Nariman Point) | G9: Plot No. 236, Block III of Backbay Reclamation Estate, Barrister Rajni Patel Marg, Nariman Point, Mumbai; land approx. 1.5 acres (freehold) | H9: 500000 | I9: 0.5 | J9: 0.5 | L9: 1 | M9: 350 | N9: 296 | O9: =IF(OR(M9="",N9="",N9=0),"",M9/N9-1) | P9: 4 | R9: 0.08 | S9: 0.12 | T9: 2449.9 | U9: =IF(OR(T9="",H9="",H9=0),"",T9*10000000/H9) | V9: Property Management Fees = 3% of Total Income | W9: INR 0.4/sqft/mo | X9: Completed office 0.5 msf (= total). Cap 7.5% (recorded 8, rounded); discount 11.5% operational. Office mkt rent revised 300->350; in-place 296. Age ~56 yrs, LEED Platinum. Acquisition price INR 18,385 Mn (related party). Source lines ~13414-13934.
A10: Vikhroli Corporate Park Private Limited (VCPPL) | B10: Embassy 247 | C10: Office | D10: Mumbai | E10: Vikhroli West | F10: Eastern Suburbs (Vikhroli West) | G10: Hariyali Village, Kurla Taluka, Lal Bahadur Shastri (LBS) Road, Gandhi Nagar, Vikhroli West, Mumbai; land approx. 7.3 acres (freehold) | H10: 1200000 | I10: 1.2 | J10: 1.2 | L10: 1 | M10: 135 | N10: 118 | O10: =IF(OR(M10="",N10="",N10=0),"",M10/N10-1) | P10: 3.1 | R10: 0.08 | S10: 0.12 | T10: 2243.7 | U10: =IF(OR(T10="",H10="",H10=0),"",T10*10000000/H10) | V10: Property Management Fees = 3% of Total Income | W10: INR 0.3/sqft/mo | X10: Completed office 1.2 msf (3 towers A/B/C). Cap 8%; discount 11.5% operational. Office mkt rent revised 121->135; retail mkt rent 250; in-place 118. LEED Platinum. Acquisition price INR 16,727 Mn (related party). Source lines ~13935-14458.
A11: Earnest Towers Private Limited (ETPL) | B11: First International Financial Centre (FIFC) | C11: Office | D11: Mumbai | E11: Bandra Kurla Complex | F11: Bandra Kurla Complex (BKC) / Secondary Business District, G Block | G11: Plot No. C-54 & C-55, G Block, BKC Road, Bandra Kurla Complex, Mumbai 400 051; leasehold land from MMRDA, approx. 2.0 acres | H11: 400000 | I11: 0.4 | J11: 0.4 | L11: 1 | M11: 350 | N11: 325 | O11: =IF(OR(M11="",N11="",N11=0),"",M11/N11-1) | P11: 3.5 | R11: 0.08 | S11: 0.12 | T11: 1840.6 | U11: =IF(OR(T11="",H11="",H11=0),"",T11*10000000/H11) | V11: Property Management Fees = 3% of Total Income | W11: INR 0.1/sqft/mo | X11: Leasehold interest in ~226,663 sqft (2 basements, part ground+1st, entire 2nd-7th floors) with 54.2% undivided land share. Cap 7.5% (recorded 8, rounded); discount 11.5% operational. Office mkt rent revised 320->350; retail mkt rent revised 350->425; in-place 325. High property tax INR 12.0/sqft/mo. LEED Platinum. Acquisition price INR 14,614 Mn. Source lines ~14459-15003.
A12: Embassy Pune TechZone Private Limited (EPTPL) | B12: Embassy TechZone | C12: Office | D12: Pune | E12: Hinjewadi Phase 2 | F12: PBD West / Hinjewadi Phase 2 | G12: Plot No. 3A, Hinjewadi Phase 2 Road, Hinjewadi Rajiv Gandhi Infotech Park, Hinjewadi, Pune, Maharashtra 411057; land approx. 67.5 acres (leasehold) | H12: 5500000 | I12: 5.5 | J12: 3 | L12: 0.77 | M12: 50 | N12: 54 | O12: =IF(OR(M12="",N12="",N12=0),"",M12/N12-1) | P12: 5.6 | R12: 0.08 | S12: 0.12 | T12: 2592.4 | U12: =IF(OR(T12="",H12="",H12=0),"",T12*10000000/H12) | V12: Property Management Fees = 3% of Total Income; Asset Mgmt fee booked below NOI | W12: INR 0.2/sqft/mo | X12: Mixed-use: completed office 3.0 msf + UC/proposed office 2.4 msf + 116-key hotel. Value split: completed 23,235 + UC/proposed 2,450 + hotel 239. Cap 8.25% office (recorded 8, rounded), 7.14% hospitality; discount 11.5% operational, 12.75% UC office, 13.25% UC hotel. Occupancy may fall to 73% if a domestic tech tenant exits 1-Apr-2026. Acquisition price INR 20,720 Mn. Source lines ~15004-15839.
A13: Quadron Business Park Private Limited (QBPL) | B13: Embassy Quadron | C13: Office | D13: Pune | E13: Hinjewadi Phase 2 | F13: PBD West / Hinjewadi Phase 2 | G13: Plot No. 28, Hinjewadi Phase 2 Road, Hinjewadi Rajiv Gandhi Infotech Park, Pimpri-Chinchwad, Pune, Maharashtra 411057; land approx. 25.5 acres (leasehold) | H13: 1900000 | I13: 1.9 | J13: 1.9 | L13: 0.24 | M13: 46 | N13: 56 | O13: =IF(OR(M13="",N13="",N13=0),"",M13/N13-1) | P13: 4.3 | R13: 0.08 | S13: 0.12 | T13: 1003.9 | U13: =IF(OR(T13="",H13="",H13=0),"",T13*10000000/H13) | V13: Property Management Fees = 3% of Total Income; Asset Mgmt fee below NOI | W13: INR 0.2/sqft/mo | X13: Completed office 1.9 msf (all completed, no UC). Cap 8.25% (recorded 8, rounded); discount 11.5% operational. Very low occupancy 24%. Office mkt rent 46, in-place 56. Same SPV as Embassy One (Bengaluru). Acquisition price INR 13,961 Mn. Source lines ~15840-16388.
A14: Qubix Business Park Private Limited (QBPPL) | B14: Embassy Qubix | C14: Office | D14: Pune | E14: Hinjewadi Phase 1 | F14: PBD West / Hinjewadi Phase 1 | G14: Blue Ridge Township, Phase 1, Hinjewadi Rajiv Gandhi Infotech Park, Pimpri-Chinchwad, Pune, Maharashtra 411057; land approx. 25.2 acres (freehold) | H14: 1500000 | I14: 1.5 | J14: 1.5 | L14: 0.78 | M14: 50 | N14: 51 | O14: =IF(OR(M14="",N14="",N14=0),"",M14/N14-1) | P14: 4.2 | R14: 0.08 | S14: 0.12 | T14: 1048.3 | U14: =IF(OR(T14="",H14="",H14=0),"",T14*10000000/H14) | V14: Property Management Fees = 3% of Total Income; Asset Mgmt fee below NOI | W14: INR 0.3/sqft/mo | X14: Completed office 1.5 msf (5 SEZ + 1 Non-SEZ block). Cap 8.25% (recorded 8, rounded); discount 11.5% operational. Only freehold Pune asset. Office mkt rent 50, in-place 51. Acquisition price INR 9,868 Mn. Source lines ~16389-16936.
A15: Oxygen Business Park Private Limited (OBPPL) | B15: Embassy Oxygen | C15: Office | D15: Noida | E15: Noida-Greater Noida Expressway | F15: Noida-Greater Noida Expressway (Sector 144) | G15: Plot No. 7, Sector-144, Noida, Uttar Pradesh; land approx. 24.8 acres, leasehold from NOIDA Authority | H15: 3300000 | I15: 3.3 | J15: 3.3 | L15: 0.9 | M15: 59 | N15: 57 | O15: =IF(OR(M15="",N15="",N15=0),"",M15/N15-1) | P15: 9.1 | R15: 0.08 | S15: 0.12 | T15: 2951.8 | U15: =IF(OR(T15="",H15="",H15=0),"",T15*10000000/H15) | V15: Property Management Fees = 3% of Total Income (booked below NOI) | W15: INR 0.22/sqft/mo; plus Land Lease Payment INR 0.38/sqft/mo (in lieu of property tax) | X15: Completed office 3.3 msf (10 buildings incl food court). Cap 8%; discount 11.5% operational. Office mkt rent 59 (incl parking), in-place 57; retail mkt rent 85. Seismic Zone IV. Acquisition price INR 18,258 Mn. Source lines ~16937-17515.
A16: Galaxy Square Private Limited (GSPL) | B16: Embassy Galaxy | C16: Office | D16: Noida | E16: Noida Sector 62 | F16: Noida Sector 62 | G16: A-44 & 45, Sector-62, Noida, Uttar Pradesh; land approx. 9.9 acres, leasehold from NOIDA Authority | H16: 1400000 | I16: 1.4 | J16: 1.4 | L16: 1 | M16: 51 | N16: 46 | O16: =IF(OR(M16="",N16="",N16=0),"",M16/N16-1) | P16: 9.5 | R16: 0.08 | S16: 0.12 | T16: 1131.1 | U16: =IF(OR(T16="",H16="",H16=0),"",T16*10000000/H16) | V16: Property Management Fees = 3% of Total Income (below NOI) | W16: INR 0.27/sqft/mo; Land Lease Payment INR 0.34/sqft/mo | X16: Completed office 1.4 msf (5 Non-SEZ blocks). Rent roll ~99.6% occupied. Cap 8%; discount 11.5% operational. Office mkt rent 51 (incl parking), in-place 46; retail mkt rent 85. LEED Platinum. Acquisition price INR 8,122 Mn. Source lines ~17516-18059.
A17: Umbel Properties Private Limited (UPPL) | B17: Hilton at Embassy GolfLinks | C17: Hotel | D17: Bengaluru | E17: Domlur | F17: Suburban East (inside Embassy GolfLinks Business Park, Intermediate Ring Road) | G17: Challaghatta Village, Varthur Hobli, Bengaluru East Taluk 560071; land approx. 3.6 acres (freehold) | H17: 500000 | I17: 0.5 | J17: 0.5 | L17: 0.72 | O17: =IF(OR(M17="",N17="",N17=0),"",M17/N17-1) | R17: 0.07 | S17: 0.12 | T17: 887.6 | U17: =IF(OR(T17="",H17="",H17=0),"",T17*10000000/H17) | V17: Base Management Fee 2% of Total Revenue; Management Incentive Fee 5.5% of Gross Operating Profit; FF&E reserve 2% | X17: 247-key 5-star hotel (developed area ~0.5 msf). Stabilized occupancy 72% (FY2026); ADR INR 15,000/room/night +5% YoY from Oct 2026; F&B revenue 40% of rooms revenue. Cap rate 7.14% derived via EV/EBITDA 14x (recorded 7, rounded); discount rate 11.90% (recorded 12, rounded). No psf rent (hotel). Acquisition price INR 4,766 Mn. Source lines ~18060-18516.
A18: ESNP Property Builders and Developers Private Limited (ESNP) | B18: Embassy Splendid Techzone | C18: Office | D18: Chennai | E18: Pallavaram | F18: Suburban South (Pallavaram-Thoraipakkam Road) | G18: Pallavaram-Thoraipakkam (PTR) Road, Pallavaram, Chennai, Tamil Nadu; land approx. 25.37 acres (leasehold from SNP) | H18: 5100000 | I18: 5.1 | J18: 2.5 | L18: 0.84 | M18: 75 | N18: 73 | O18: =IF(OR(M18="",N18="",N18=0),"",M18/N18-1) | P18: 11.5 | R18: 0.08 | S18: 0.12 | T18: 2058.7 | U18: =IF(OR(T18="",H18="",H18=0),"",T18*10000000/H18) | V18: Property Management Fees = 3% of Total Income (below NOI) | W18: INR 0.13/sqft/mo | X18: Mixed-use (IT/ITeS SEZ/Non-SEZ): completed 2.5 msf + UC/proposed 2.6 msf. Value split: completed 15,556 + UC 5,031 = 20,587. Cap 8% office/retail; discount 11.5% operational office. Office mkt rent 75 (incl parking), in-place 73; retail mkt rent 25. Land freehold of SNP granting leasehold to ESNP (30 yrs from 9-Nov-2016, renewable). Pending dev cost ~INR 8,083 Mn. Acquisition price INR 11,853 Mn. Source lines ~18517-19186.
A19: Embassy Energy Private Limited (EEPL) | B19: Embassy Energy (Solar Park) | C19: Other | D19: Bellary District, Karnataka | E19: Villages Ittigi & Mooregeri and Nellukudure | F19: Villages Ittigi & Mooregeri (Huvinhadagali Taluka) and Nellukudure (Hagribommanhalli Taluka) | G19: Bellary District, Karnataka; primary access SH-45; land approx. 465.8 acres | O19: =IF(OR(M19="",N19="",N19=0),"",M19/N19-1) | S19: 0.12 | T19: 414.3 | U19: =IF(OR(T19="",H19="",H19=0),"",T19*10000000/H19) | X19: Solar Park: installed capacity 130 MW DC / 100 MW AC; commissioned Feb 2018; ~215 MU/yr; CUF 17.35%. No leasable area or psf rent. Discount rate 11.5% (recorded 12, rounded); no cap rate (25-yr DCF over CERC useful life, no terminal cap). PPA tariff FY2027 INR 6.83/unit, escalation 2.5%/yr; 25-yr PPAs with Embassy office parks/hotels (Manyata, GolfLinks, Hilton GolfLinks, TechVillage) plus C&I offtakers. O&M INR 18.3 Mn/qtr. No property mgmt fee (admin/O&M/employee costs instead). SPV labelled 'Power Limited' in one value table (likely typo for Private Limited). Acquisition price INR 10,690 Mn. Source lines ~19187-19981.
A20: TOTAL / weighted | H20: =SUM(H4:H19) | I20: =SUM(I4:I19) | M20: =IFERROR(AVERAGE(M4:M19),"") | N20: =IFERROR(AVERAGE(N4:N19),"") | T20: =SUM(T4:T19) | U20: =IFERROR(T20*10000000/H20,"")

Sheet Mindspace
A1: Mindspace - Asset-level detail (valuation 31 Mar 2026; 17 assets)
A3: SPV / Holding entity | B3: Property / Asset | C3: Type | D3: City | E3: Locality / Area | F3: Micro-market (valuer) | G3: Address | H3: Leasable (sq ft) | I3: Leasable (msf) | J3: Completed (msf) | K3: Committed occ. | L3: In-place occ. | M3: Market rent /sqft/mo | N3: In-place rent /sqft/mo | O3: Rent reversion | P3: WALE (yrs) | Q3: Tenants | R3: Cap rate | S3: Discount rate | T3: Market value (INR cr) | U3: Value/sqft (INR) | V3: Mgmt fee (valuation DCF) | W3: Insurance (valuation DCF) | X3: Notes / source
A4: Sundew Properties Limited | B4: Mindspace Madhapur (Sundew) | C4: Office | D4: Hyderabad | E4: Madhapur | F4: Madhapur | G4: Mindspace Madhapur, Titus Towers, TSIIC software layout, Madhapur, Hyderabad, Telangana 500081 | H4: 5870000 | I4: 5.87 | J4: 5.87 | K4: 0.99 | L4: 0.96 | M4: 105 | N4: 75.58 | O4: =IF(OR(M4="",N4="",N4=0),"",M4/N4-1) | P4: 7.84 | Q4: 51 | R4: 0.08 | S4: 0.12 | T4: 7963.812 | U4: =IF(OR(T4="",H4="",H4=0),"",T4*10000000/H4) | X4: Grade A IT Park, 8 buildings (Non-SEZ 11,22; SEZ rest); Bldg 22 hotel. MREIT 89% interest (100% value INR89,481.03mn). Exit cap 7.75%, WACC 11.75%. Occ 96.3%/committed 98.7%. Land 40.25 ac freehold. p.1-52 (chunk a)
A5: K Raheja IT Park (Hyderabad) Limited | B5: Mindspace Madhapur (KRIT) | C5: Office | D5: Hyderabad | E5: Madhapur | F5: Madhapur | G5: Mindspace Madhapur (KRIT), Madhapur, Hyderabad, Telangana 500081 | H5: 5940000 | I5: 5.94 | J5: 2.18 | K5: 0.99 | L5: 0.97 | M5: 105 | N5: 79.96 | O5: =IF(OR(M5="",N5="",N5=0),"",M5/N5-1) | P5: 7.24 | Q5: 29 | R5: 0.08 | S5: 0.12 | T5: 5982.4 | U5: =IF(OR(T5="",H5="",H5=0),"",T5*10000000/H5) | X5: IT Park Non-SEZ (incl retail). Exit cap 7.75%, WACC 11.75%. Occ 96.5%/committed 99.2%. Land 48.43 ac freehold. chunk a
A6: Intime Properties Limited | B6: Mindspace Madhapur (Intime) | C6: Office | D6: Hyderabad | E6: Madhapur | F6: Madhapur | G6: Mindspace Madhapur (Intime), Madhapur, Hyderabad, Telangana 500081 | H6: 2030000 | I6: 2.03 | J6: 2.03 | K6: 1 | L6: 1 | M6: 105 | N6: 79.06 | O6: =IF(OR(M6="",N6="",N6=0),"",M6/N6-1) | P6: 7.08 | Q6: 35 | R6: 0.08 | S6: 0.12 | T6: 2855.721 | U6: =IF(OR(T6="",H6="",H6=0),"",T6*10000000/H6) | X6: IT Park Non-SEZ. Exit cap 7.75%, WACC 11.75%. Occ 99.8%/committed 99.8%. Land 8.52 ac freehold. chunk a
A7: Mindspace Business Parks Private Limited | B7: Mindspace Pocharam | C7: Other | D7: Hyderabad | E7: Pocharam | F7: Pocharam (PBD East / Suburbs Other) | G7: Mindspace Pocharam, Hyderabad – Non-SEZ IT Park | H7: 570000 | I7: 0.57 | J7: 0.57 | K7: 0 | L7: 0 | O7: =IF(OR(M7="",N7="",N7=0),"",M7/N7-1) | Q7: 0 | T7: 100.435 | U7: =IF(OR(T7="",H7="",H7=0),"",T7*10000000/H7) | X7: Non-SEZ IT Park; built component 0.57 msf currently VACANT (NIL occupancy/tenants) + undeveloped land held at land value. Valued via Land & Building/DCF hybrid; land ~INR30.49mn/acre. Land 26.464 ac freehold. chunk a
A8: Sustain Properties Private Limited | B8: Commerzone Raidurg (Sustain) | C8: Office | D8: Hyderabad | E8: Madhapur | F8: Madhapur (Raidurg) | G8: Commerzone Raidurg (Sustain), Madhapur, Hyderabad, Telangana 500081 | H8: 1820000 | I8: 1.82 | J8: 1.82 | K8: 1 | L8: 1 | N8: 69.1 | O8: =IF(OR(M8="",N8="",N8=0),"",M8/N8-1) | P8: 10.5 | Q8: 2 | R8: 0.08 | S8: 0.12 | T8: 2585.322 | U8: =IF(OR(T8="",H8="",H8=0),"",T8*10000000/H8) | X8: SEZ IT/ITeS. Exit cap 7.75%, WACC 11.75%. Occ 100%/committed 100%. Sustain entitled 65.5% undivided share of 9.07 ac land. Market rent per JLL (not a single psf figure in exec summary). chunk a
A9: Mack Soft Tech Private Limited | B9: The Square, Financial District (Hyderabad) | C9: Office | D9: Hyderabad | E9: Gachibowli | F9: Gachibowli / Nanakramguda (Financial District) | G9: The Square, 110 Financial District, Nanakramguda, Hyderabad, Telangana 500032 | H9: 820000 | I9: 0.82 | J9: 0.82 | K9: 0.72 | L9: 0.62 | M9: 60 | N9: 60 | O9: =IF(OR(M9="",N9="",N9=0),"",M9/N9-1) | P9: 3.4 | Q9: 25 | R9: 0.08 | S9: 0.12 | T9: 707.727 | U9: =IF(OR(T9="",H9="",H9=0),"",T9*10000000/H9) | X9: Non-SEZ office. Exit cap 8.00%, WACC 11.75%. Occ 61.5%/committed 72.3%. Market/marginal office rent INR60/psf/mo. Land ~6 ac freehold. chunk b
A10: Mindspace Business Parks Private Limited | B10: Mindspace Airoli East | C10: Office | D10: Navi Mumbai | E10: Thane-Belapur Road | F10: Thane-Belapur Road (Airoli) | G10: Plot No.3, Kalwa Trans Thane Creek Ind. Area, Mindspace, Opp. Airoli Station, Airoli, Navi Mumbai 400708 | H10: 7400000 | I10: 7.4 | J10: 4.98 | K10: 0.83 | L10: 0.73 | M10: 69 | N10: 68.3 | O10: =IF(OR(M10="",N10="",N10=0),"",M10/N10-1) | P10: 4.9 | Q10: 48 | R10: 0.08 | S10: 0.12 | T10: 5802.395 | U10: =IF(OR(T10="",H10="",H10=0),"",T10*10000000/H10) | X10: Grade A IT SEZ. Total 7.4 msf = 4.98 completed (occ/tenants shown) + 2.41 under-constr/future (B17 hotel+office, Bldg15; NIL occupancy). Exit cap 8.00%; WACC 11.75% completed, 13% UC. Completed occ 73.2%/committed 83.1%, 48 tenants. Land ~50.1 ac leasehold (MIDC 99yr). Also power distribution (see Energispace). chunk b
A11: Gigaplex Estate Private Limited | B11: Mindspace Airoli West | C11: Office | D11: Navi Mumbai | E11: Thane-Belapur Road | F11: Thane-Belapur Road (Airoli) | G11: Mindspace Airoli West, Navi Mumbai, Maharashtra | H11: 6460000 | I11: 6.46 | J11: 5.41 | K11: 0.99 | L11: 0.97 | M11: 71 | N11: 67.2 | O11: =IF(OR(M11="",N11="",N11=0),"",M11/N11-1) | P11: 9 | Q11: 62 | R11: 0.08 | S11: 0.12 | T11: 6577 | U11: =IF(OR(T11="",H11="",H11=0),"",T11*10000000/H11) | X11: IT SEZ w/ data-centre buildings. Total 6.46 msf incl UC data centres (B7,B9A,B11). Completed 5.41 msf occ 96.6%/committed 98.7%, 62 tenants. Exit cap 8.00% (completed; 8.25% terminal on some); WACC 11.75% completed/13% UC. Market office rent INR71/psf/mo. Land ~50 ac leasehold (MIDC 95yr). chunk b
A12: Avocado Properties and Trading (India) Private Limited | B12: Paradigm Mindspace Malad | C12: Office | D12: Mumbai | E12: Malad | F12: Western Suburbs (Malad) | G12: Paradigm Mindspace Malad, Mumbai, Maharashtra | H12: 760000 | I12: 0.76 | J12: 0.76 | K12: 0.99 | L12: 0.99 | M12: 116 | N12: 108.5 | O12: =IF(OR(M12="",N12="",N12=0),"",M12/N12-1) | P12: 3.1 | Q12: 9 | R12: 0.08 | S12: 0.12 | T12: 1371.121 | U12: =IF(OR(T12="",H12="",H12=0),"",T12*10000000/H12) | X12: Office. Exit cap 8.00%, WACC 11.75%. Occ 98.6%/committed 98.6%, 9 tenants. Market/marginal rent INR116/psf/mo, in-place INR108.5. WALE 3.1 yrs. Land ~4.2 ac freehold. chunk b
A13: Avacado Properties and Trading (India) Private Limited | B13: The Square, BKC (Mumbai) | C13: Office | D13: Mumbai | E13: BKC | F13: BKC (SBD BKC) | G13: The Square, BKC, Mumbai, Maharashtra | H13: 150000 | I13: 0.15 | J13: 0.15 | K13: 1 | L13: 1 | M13: 318 | N13: 240 | O13: =IF(OR(M13="",N13="",N13=0),"",M13/N13-1) | Q13: 1 | R13: 0.08 | S13: 0.12 | T13: 533.868 | U13: =IF(OR(T13="",H13="",H13=0),"",T13*10000000/H13) | X13: BKC office, fully operational single-tenant. Exit cap ~7.5-7.75%, WACC 11.75%. Occ 100%/committed 100%, 1 office tenant. Market/marginal rent INR318, in-place INR240 psf/mo. MV INR5,338.68mn. Land ~0.9 ac. SPV Avacado Properties. chunk b
A14: KRC (Ascent SPV) | B14: The Square / Ascent, Worli | C14: Office | D14: Mumbai | E14: Worli | F14: Worli (SBD Central) | G14: Ascent, Worli, Mumbai, Maharashtra | H14: 450000 | I14: 0.45 | J14: 0.45 | K14: 0.97 | L14: 0.96 | M14: 340 | N14: 306.3 | O14: =IF(OR(M14="",N14="",N14=0),"",M14/N14-1) | P14: 7.9 | Q14: 8 | R14: 0.08 | S14: 0.12 | T14: 2314.206 | U14: =IF(OR(T14="",H14="",H14=0),"",T14*10000000/H14) | X14: Commercial Non-SEZ + 36 residential units to rent. Exit cap 7.50%, WACC 11.75%. Occ 95.5%/committed 96.7%, 8 office tenants. Market rent INR340, in-place INR306.3 psf/mo. Leasehold (perpetual). ~4.61 ac (22.45% undivided). chunk c
A15: Mindspace Business Parks Private Limited | B15: Commerzone Yerwada (Pune) | C15: Office | D15: Pune | E15: Yerwada | F15: Yerwada (SBD East) | G15: Commerzone IT Park, Yerwada, Pune, Maharashtra | H15: 1790000 | I15: 1.79 | J15: 1.79 | K15: 0.96 | L15: 0.92 | M15: 82 | N15: 87.3 | O15: =IF(OR(M15="",N15="",N15=0),"",M15/N15-1) | P15: 5.3 | Q15: 19 | R15: 0.08 | S15: 0.12 | T15: 2235.438 | U15: =IF(OR(T15="",H15="",H15=0),"",T15*10000000/H15) | X15: Office. Exit cap 8.00%, WACC 11.75%. Occ 91.8%/committed 96.3%, 19 tenants. Market/marginal office rent INR82, in-place INR87.3 psf/mo. Land ~25.7 ac freehold. chunk c
A16: KRC Infrastructure and Projects Private Limited | B16: Gera Commerzone SEZ & IT Park (Kharadi, Pune) | C16: Office | D16: Pune | E16: Kharadi | F16: Kharadi (SBD East) | G16: Gera Commerzone SEZ and IT Park, Kharadi, Pune, Maharashtra | H16: 3000000 | I16: 3 | J16: 3 | K16: 1 | L16: 1 | M16: 90 | N16: 85.4 | O16: =IF(OR(M16="",N16="",N16=0),"",M16/N16-1) | P16: 7.2 | Q16: 28 | R16: 0.08 | S16: 0.12 | T16: 5311.9 | U16: =IF(OR(T16="",H16="",H16=0),"",T16*10000000/H16) | X16: SEZ IT. Exit cap 7.75%, WACC 11.75% completed/13% UC. Occ 100%/100%, 28 tenants. Market office rent INR90, in-place INR85.4 psf/mo. Land ~26 ac freehold. chunk c
A17: Mindspace Business Parks Private Limited | B17: The Square, Nagar Road (Pune) | C17: Office | D17: Pune | E17: Nagar Road | F17: Nagar Road (SBD East) | G17: The Square, Nagar Road, Pune, Maharashtra | H17: 780000 | I17: 0.78 | J17: 0.78 | K17: 1 | L17: 1 | M17: 85 | N17: 85.3 | O17: =IF(OR(M17="",N17="",N17=0),"",M17/N17-1) | P17: 2.4 | Q17: 4 | R17: 0.08 | S17: 0.12 | T17: 1055.141 | U17: =IF(OR(T17="",H17="",H17=0),"",T17*10000000/H17) | X17: Office. Exit cap 8.00%, WACC 11.75%. Occ 100%/100%, 4 tenants. Market office rent INR85, in-place INR85.3 psf/mo. Land ~10.1 ac freehold. chunk c
A18: Pramaan Properties Private Limited | B18: Pune IT Building, Kalyani Nagar | C18: Office | D18: Pune | E18: Kalyani Nagar | F18: Kalyani Nagar (SBD East) | G18: Pune IT Building (B8), Kalyani Nagar, Pune, Maharashtra | H18: 110000 | I18: 0.11 | J18: 0.11 | K18: 0.94 | L18: 0.88 | M18: 84 | N18: 86.2 | O18: =IF(OR(M18="",N18="",N18=0),"",M18/N18-1) | P18: 6.34 | Q18: 1 | R18: 0.08 | S18: 0.12 | T18: 148.151 | U18: =IF(OR(T18="",H18="",H18=0),"",T18*10000000/H18) | X18: Single office building B8. Exit cap office 8.00%, WACC 11.75%. Occ 88.1%/committed 94.2%, 1 tenant. Market office rent INR84 (amenity INR65), in-place INR86.2 psf/mo. Land ~0.67 ac (39.96% undivided share) freehold. chunk d
A19: Horizonview Properties Private Limited | B19: Commerzone Porur (Chennai) | C19: Office | D19: Chennai | E19: Porur | F19: Porur (SBD Southwest) | G19: Commerzone, Porur, Chennai, Tamil Nadu | H19: 1150000 | I19: 1.15 | J19: 1.15 | K19: 1 | L19: 1 | M19: 72 | N19: 65.7 | O19: =IF(OR(M19="",N19="",N19=0),"",M19/N19-1) | Q19: 16 | R19: 0.08 | S19: 0.12 | T19: 1333.474 | U19: =IF(OR(T19="",H19="",H19=0),"",T19*10000000/H19) | X19: Office. Exit cap 7.75%, WACC 11.75%. Occ 99.5%/committed 100%, 16 tenants. Market/marginal office rent INR72, in-place INR65.7 psf/mo. Land ~6.13 ac freehold. WALE not cleanly captured. chunk d
A20: Sundew Real Estate Private Limited | B20: The Square, Avenue 98 (BKC Annex) | C20: Office | D20: Mumbai | E20: BKC-Annex | F20: BKC-Annex (SBD BKC) | G20: The Square, Avenue 98 (BKC Annex), Mumbai, Maharashtra | H20: 220000 | I20: 0.22 | J20: 0.16 | K20: 1 | L20: 1 | M20: 250 | N20: 197.1 | O20: =IF(OR(M20="",N20="",N20=0),"",M20/N20-1) | Q20: 1 | R20: 0.08 | S20: 0.12 | T20: 756.9 | U20: =IF(OR(T20="",H20="",H20=0),"",T20*10000000/H20) | X20: Commercial Non-SEZ. Leasable 0.22 msf, completed ~0.16 msf. Exit cap 7.50%, WACC 11.75%. Occ 100%/100%, 1 office tenant. Market rent INR250, in-place INR197.1 psf/mo. Land ~1.08 ac freehold. chunk d
A21: TOTAL / weighted | H21: =SUM(H4:H20) | I21: =SUM(I4:I20) | M21: =IFERROR(AVERAGE(M4:M20),"") | N21: =IFERROR(AVERAGE(N4:N20),"") | T21: =SUM(T4:T20) | U21: =IFERROR(T21*10000000/H21,"")

Sheet Brookfield
A1: Brookfield - Asset-level detail (valuation 31 Mar 2026; 13 assets)
A3: SPV / Holding entity | B3: Property / Asset | C3: Type | D3: City | E3: Locality / Area | F3: Micro-market (valuer) | G3: Address | H3: Leasable (sq ft) | I3: Leasable (msf) | J3: Completed (msf) | K3: Committed occ. | L3: In-place occ. | M3: Market rent /sqft/mo | N3: In-place rent /sqft/mo | O3: Rent reversion | P3: WALE (yrs) | Q3: Tenants | R3: Cap rate | S3: Discount rate | T3: Market value (INR cr) | U3: Value/sqft (INR) | V3: Mgmt fee (valuation DCF) | W3: Insurance (valuation DCF) | X3: Notes / source
A4: Candor Kolkata One Hi-Tech Structures Private Limited | B4: Candor Techspace G2 | C4: Office | D4: Gurugram | E4: Dundahera | F4: Old Delhi-Gurugram Road, Dundahera (Gurugram, established office/residential/retail micro-market; near DLF Cyber City) | G4: Candor Techspace, Dundahera, Gurugram, Haryana | H4: 4183449 | I4: 4.18 | J4: 4.08 | K4: 0.83 | M4: 90 | N4: 88 | O4: =IF(OR(M4="",N4="",N4=0),"",M4/N4-1) | P4: 8.1 | R4: 0.08 | S4: 0.12 | T4: 4811.2 | U4: =IF(OR(T4="",H4="",H4=0),"",T4*10000000/H4) | X4: Completed leasable 4,083,525 sqft (13 bldgs, 83.34% committed occ) + future dev 99,924 sqft. WACC operational 11.50%, WACC under-construction/future dev 12.75% (discount_rate shown=12 rounded from 12.75 UC; operational WACC 11.5). REIT share 100% via Candor SPV; SPV entitled to 72% of gross revenue via JDA with Gurgaon Infospace Ltd (GIL owns land, gets 28%); economic interest in asset 72% (deck). Gross acq price K1+G2 = Rs 62.3 Bn. Completed MV 47,575mn + future dev 537mn = 48,112mn. Source val report pp.19-22; deck p.14 (Investor Pres FY26).
A5: Seaview Developers Private Limited | B5: Candor Techspace N1 | C5: Office | D5: Noida | E5: Sector 62 (Noida) | F5: Sector 62, Noida (institutional sector, NCR) | G5: Plot no. B2, Sector 62, Noida, Uttar Pradesh | I5: 2.88 | J5: 2.02 | K5: 0.98 | M5: 72 | N5: 64 | O5: =IF(OR(M5="",N5="",N5=0),"",M5/N5-1) | P5: 7.8 | R5: 0.08 | S5: 0.12 | T5: 2948.5 | U5: =IF(OR(T5="",H5="",H5=0),"",T5*10000000/H5) | X5: Completed 20,23,237 sqft (7 bldgs, 97.96% committed occ) + future dev 0.86 msf. REIT share 100%. WACC operational 11.50%, UC 12.75%. Completed MV 26,026mn + future dev 3,459mn = 29,485mn. Source val report pp.23-26; deck p.14.
A6: Festus Properties Private Limited | B6: Candor Techspace N2 | C6: Office | D6: Noida | E6: Sector 135 (Noida) | F6: Sector 135, Noida-Greater Noida Expressway micro-market | G6: Plot No. 20, 21, Sector 135, Noida, Uttar Pradesh | I6: 4.69 | J6: 3.92 | K6: 0.94 | M6: 70 | N6: 64 | O6: =IF(OR(M6="",N6="",N6=0),"",M6/N6-1) | P6: 6.9 | R6: 0.08 | S6: 0.12 | T6: 4941 | U6: =IF(OR(T6="",H6="",H6=0),"",T6*10000000/H6) | X6: Completed 39,15,881 sqft (14 bldgs, 93.52% committed occ) + future dev 0.77 msf. REIT share 100%. Achievable mkt rent: 70 SEZ office / 57 non-SEZ / 60 mixed-use retail; inplace(current effective) 64. WACC operational 11.50%, UC 12.75%. Completed MV 47,064mn + future dev 2,346mn = 49,410mn. Source val report pp.27-30; deck p.14.
A7: Shantiniketan Properties Private Limited | B7: Candor Techspace K1 | C7: Office | D7: Kolkata | E7: New Town (Rajarhat) | F7: New Town, Rajarhat, Kolkata (established office micro-market; ~1.5km from CBD metro) | G7: Plot No. 1, DH Block, New Town, Rajarhat, Kolkata, West Bengal | I7: 5.89 | J7: 3.2 | K7: 0.99 | M7: 55 | N7: 49 | O7: =IF(OR(M7="",N7="",N7=0),"",M7/N7-1) | P7: 8.9 | R7: 0.085 | S7: 0.12 | T7: 3621 | U7: =IF(OR(T7="",H7="",H7=0),"",T7*10000000/H7) | X7: Completed 32,01,857 sqft (12 bldgs, 98.82% committed occ) + under construction 0.58 msf + future dev 2.11 msf. REIT share 100%. Achievable mkt rent 55 SEZ office /57 non-SEZ /60 mixed-use retail; inplace 49. Cap rate 8.50%. WACC operational 11.50%, UC 12.75%. MV: completed 29,479mn + UC 2,430mn + future dev 4,301mn = 36,210mn. Gross acq price K1+G2=Rs62.3Bn. Source val report pp.31-35; deck p.14.
A8: Festus Properties Private Limited | B8: Kensington (A & B) | C8: Office | D8: Mumbai | E8: Powai / Andheri | F8: Andheri & Powai micro-market, MMR (only private IT/ITeS SEZ in Mumbai excl. Thane/Navi Mumbai) | G8: Hiranandani Business Park, CTS No. 28A, Powai, Mumbai 400076, Maharashtra | H8: 1619079 | I8: 1.61 | J8: 1.61 | K8: 0.96 | M8: 160 | N8: 136 | O8: =IF(OR(M8="",N8="",N8=0),"",M8/N8-1) | P8: 9.1 | R8: 0.08 | S8: 0.12 | T8: 3198.1 | U8: =IF(OR(T8="",H8="",H8=0),"",T8*10000000/H8) | X8: Single bldg two wings, 1,619,079 sqft, 95.61% committed occ (val rpt) / 96% (deck). REIT share 100%. Deck groups Kensington under 'Downtown Powai - SEZ' (100% economic interest). Property tax entity: Festus Properties Pvt Ltd (val rpt). Achievable mkt rent 160 IT SEZ /175 IT; inplace(current effective) 136. Cap rate 8.00%, WACC operational 11.50%. Major tenants: TCS, L&T, GE Oil & Gas, Ergo Technology, Nomura, Aptia, RXO. Gross acq price Rs22.9Bn. MV 31,981mn. Source val report pp.36-39; deck p.14.
A9: Candor Gurgaon One Realty Projects Private Limited | B9: Candor Techspace G1 | C9: Office | D9: Gurugram | E9: Sector 48 (Gurugram) | F9: Sector 48, Gurugram (Village Tikri), Haryana | G9: Village Tikri, Sector 48, Gurugram, Haryana | I9: 3.89 | J9: 3.79 | K9: 0.89 | M9: 88 | N9: 83 | O9: =IF(OR(M9="",N9="",N9=0),"",M9/N9-1) | P9: 6.3 | R9: 0.08 | S9: 0.12 | T9: 6048.9 | U9: =IF(OR(T9="",H9="",H9=0),"",T9*10000000/H9) | X9: JV / North Commercial Portfolio - equity-accounted; REIT economic interest 50% (deck). Val report MV of financial interest is 100% asset value 60,489mn (completed 59,924mn + future dev 565mn); 12 completed bldgs, 88.67% committed occ (val rpt)/89% (deck). Held via North Commercial Portfolio Holding Entity (BIRET 50% / GIC 50%). WACC operational 11.50%, UC 12.75%. Source val report pp.40-43; deck p.14, p.38.
A10: Kairos Properties Private Limited | B10: Downtown Powai (Kairos) | C10: Office | D10: Mumbai | E10: Powai | F10: Andheri & Powai micro-market, MMR | G10: Hiranandani Business Park, Powai, Mumbai 400076, Maharashtra | I10: 2.86 | J10: 2.86 | K10: 0.95 | M10: 195 | N10: 186 | O10: =IF(OR(M10="",N10="",N10=0),"",M10/N10-1) | P10: 3.9 | S10: 0.12 | T10: 8575 | U10: =IF(OR(T10="",H10="",H10=0),"",T10*10000000/H10) | X10: JV / North Commercial Portfolio - equity-accounted; REIT interest 50% Equity + 50% CCDs (val rpt sec 4.7.3); deck 'Downtown Powai - IT/Commercial' 50% economic interest. Val report MV of financial interest 85,750mn (appears to be 100% asset basis). Cap rate stated NA (multiple use types); WACC operational 11.50%. Achievable mkt rent: office 195 commercial + separate IT Central/South, retail multiple (Delphi/Ventura Rs450-543); inplace(current effective) 186. Held via North portfolio (BIRET/GIC). Source val report pp.44-47; deck p.14, p.38.
A11: Aspen Buildtech Private Limited | B11: Worldmark Tower 1 (Worldmark New Delhi) | C11: Retail | D11: New Delhi | E11: Aerocity | F11: Aerocity / Airport District, Delhi International Airport (established office & retail micro-market, Delhi NCR) | G11: Aerocity, Delhi International Airport, New Delhi | H11: 607892 | I11: 0.61 | J11: 0.61 | K11: 0.99 | M11: 235 | N11: 214 | O11: =IF(OR(M11="",N11="",N11=0),"",M11/N11-1) | T11: 1885.6 | U11: =IF(OR(T11="",H11="",H11=0),"",T11*10000000/H11) | X11: JV / North Commercial Portfolio - equity-accounted; part of 'Worldmark, New Delhi' (deck 50% economic interest, WALE 5.1yr, inplace rent ~230 combined WM ND). Tower 1: 607,892 sqft, 99.4% committed occ. Cap rate NA in val rpt; WACC operational 11.50%. Achievable mkt rent office 235 / retail 190; current effective 214. Val report MV 18,856mn (100% asset basis). Held via Aspen Buildtech, North portfolio (BIRET/GIC 50/50). Source val report pp.48-51; deck p.14.
A12: Aspen Buildtech Private Limited | B12: Worldmark Tower 2 & 3 (Worldmark New Delhi) | C12: Retail | D12: New Delhi | E12: Aerocity | F12: Aerocity / Airport District, Delhi International Airport (Delhi NCR) | G12: Aerocity, Delhi International Airport, New Delhi | H12: 847326 | I12: 0.85 | J12: 0.85 | K12: 0.93 | M12: 235 | N12: 249 | O12: =IF(OR(M12="",N12="",N12=0),"",M12/N12-1) | T12: 2806.3 | U12: =IF(OR(T12="",H12="",H12=0),"",T12*10000000/H12) | X12: JV / North Commercial Portfolio - equity-accounted; part of 'Worldmark, New Delhi' (deck 50% economic interest). Tower 2&3: 847,326 sqft, 92.90% committed occ. Cap rate NA; WACC operational 11.50%. Achievable mkt rent office 235 / retail 190 / Atelier 410; current effective rents 249 (T?) & 232 (T?). Val report MV 28,063mn (100% asset basis). Held via Aspen Buildtech, North portfolio (BIRET/GIC 50/50). Source val report pp.52-57; deck p.14.
A13: Rostrum Realty Private Limited | B13: Bharti Airtel Centre | C13: Office | D13: Gurugram | E13: Sector 18 (Gurugram) | F13: Sector 18, Phase IV, Gurugram North micro-market (near DLF Cyber City) | G13: Phase IV, Sector 18, Gurugram, Haryana | H13: 692585 | I13: 0.69 | J13: 0.69 | K13: 1 | L13: 1 | N13: 131 | O13: =IF(OR(M13="",N13="",N13=0),"",M13/N13-1) | P13: 2 | Q13: 1 | R13: 0.08 | S13: 0.12 | T13: 1428.4 | U13: =IF(OR(T13="",H13="",H13=0),"",T13*10000000/H13) | X13: JV / North Commercial Portfolio - equity-accounted; REIT 50% economic interest (deck). Held by Rostrum Realty Pvt Ltd (also holds Pavilion Mall). Single bldg 692,585 sqft, 100% committed occ, single tenant (Bharti Airtel). Current effective rent 131 (deck in-place rent at expiry Rs131). Cap rate 8.00%, WACC operational 11.50%. Val report MV 14,284mn (100% asset basis). Source val report pp.58-61; deck p.14, p.30.
A14: Oak Infrastructure Developers Private Limited | B14: Worldmark Gurugram | C14: Retail | D14: Gurugram | E14: Golf Course Ext (Sector 65) | F14: Sector 65, Gurugram (Golf Course Extension Road area) | G14: Sector 65, Gurugram, Haryana | H14: 751397 | I14: 0.75 | J14: 0.75 | K14: 0.92 | L14: 0.92 | N14: 94 | O14: =IF(OR(M14="",N14="",N14=0),"",M14/N14-1) | P14: 5.8 | R14: 0.08 | S14: 0.12 | T14: 1091.2 | U14: =IF(OR(T14="",H14="",H14=0),"",T14*10000000/H14) | X14: JV / North Commercial Portfolio - equity-accounted; REIT 50% economic interest (deck). Held by Oak Infrastructure Developers. 5 towers (Tower 1-5), 751,397 sqft, 92.2% committed occ (val rpt)/92% (deck). Current effective rent 94 (deck inplace Rs94). Cap rate 8.00%, WACC operational 11.50%. Val report MV 10,912mn (100% asset basis). Source val report pp.62-65; deck p.14.
A15: Rostrum Realty Private Limited | B15: Pavilion Mall | C15: Retail | D15: Ludhiana | E15: Civil Lines | F15: Civil Lines, Ludhiana, Punjab | G15: Civil Lines, Ludhiana, Punjab | H15: 389845 | I15: 0.39 | J15: 0.39 | K15: 0.79 | L15: 0.79 | N15: 61 | O15: =IF(OR(M15="",N15="",N15=0),"",M15/N15-1) | P15: 5.2 | R15: 0.0875 | S15: 0.12 | T15: 345 | U15: =IF(OR(T15="",H15="",H15=0),"",T15*10000000/H15) | X15: JV / North Commercial Portfolio - equity-accounted; REIT 50% economic interest (deck). Held by Rostrum Realty Pvt Ltd (with Airtel Centre). Retail mall, 1 tower 389,845 sqft, 79.15% committed occ. Current effective rent 61. Cap rate 8.75%, WACC operational 11.50%. Val report MV 3,450mn (100% asset basis). Source val report pp.66-70; deck p.14.
A16: Arliga Ecoworld Business Parks Private Limited | B16: Ecoworld | C16: Office | D16: Bengaluru | E16: Bellandur | F16: Outer Ring Road (ORR), Bellandur-Marathahalli (Competitive REIT micro-market) | G16: Outer Ring Road, Bellandur-Marathahalli, Bengaluru, Karnataka | H16: 7732309 | I16: 7.73 | J16: 7.65 | K16: 0.94 | L16: 0.94 | M16: 114 | N16: 100 | O16: =IF(OR(M16="",N16="",N16=0),"",M16/N16-1) | P16: 6.1 | R16: 0.08 | S16: 0.12 | T16: 14827.9 | U16: =IF(OR(T16="",H16="",H16=0),"",T16*10000000/H16) | X16: Acquired Q3 FY2026 (large-scale Bengaluru entry). 15 completed bldgs, 7,652,675 sqft, 94.3% effective committed occ (excl campus 3A/B/C; 94.7% incl) + future dev 79,634 sqft. REIT share 100% at val date; NOTE post-val (Apr 20 2026 / Q1 FY27) Ecoworld SPV raised Rs1,125 cr from 360One -> 360One 13%, BIRET retains 87%. Achievable mkt rent office 114 / retail 90; current effective 100 (96 incl campus 3). Cap rate 7.75% (shown 8 rounded); WACC operational 11.50%, UC 12.75%. Major tenants Honeywell, KPMG, Standard Chartered, Morgan Stanley, Shell, State Street. Completed MV 147,583mn + future dev 696mn = 148,279mn. Source val report pp.71-74; deck p.14.
A17: TOTAL / weighted | H17: =SUM(H4:H16) | I17: =SUM(I4:I16) | M17: =IFERROR(AVERAGE(M4:M16),"") | N17: =IFERROR(AVERAGE(N4:N16),"") | T17: =SUM(T4:T16) | U17: =IFERROR(T17*10000000/H17,"")

Sheet Nexus
A1: Nexus - Asset-level detail (valuation 31 Mar 2026; 20 assets)
A3: SPV / Holding entity | B3: Property / Asset | C3: Type | D3: City | E3: Locality / Area | F3: Micro-market (valuer) | G3: Address | H3: Leasable (sq ft) | I3: Leasable (msf) | J3: Completed (msf) | K3: Committed occ. | L3: In-place occ. | M3: Market rent /sqft/mo | N3: In-place rent /sqft/mo | O3: Rent reversion | P3: WALE (yrs) | Q3: Tenants | R3: Cap rate | S3: Discount rate | T3: Market value (INR cr) | U3: Value/sqft (INR) | V3: Mgmt fee (valuation DCF) | W3: Insurance (valuation DCF) | X3: Notes / source
A4: Select Infrastructure Private Limited (SIPL) | B4: Nexus Select Citywalk | C4: Retail | D4: New Delhi | E4: Saket | F4: Saket, South Delhi | G4: Plot No. P-1B, District Centre, Saket, Delhi, India | H4: 550908 | I4: 0.55 | J4: 0.55 | K4: 0.99 | L4: 0.97 | M4: 534.7 | N4: 470.1 | O4: =IF(OR(M4="",N4="",N4=0),"",M4/N4-1) | P4: 4.7 | Q4: 212 | R4: 0.075 | S4: 0.1138 | T4: 5004 | U4: =IF(OR(T4="",H4="",H4=0),"",T4*10000000/H4) | X4: Freehold. Committed occ 98.8% (cert p68); leased 531,773/550,908 sf. Market/marginal rent 534.7 psf/mo, in-place (warm shell) 470.1 psf/mo (p125). WALE 4.7yr by area / 3.7yr by rental (p120). Cap rate 7.50% (premium asset, p61). 212+ brands. Value INR 50,040mn (p69). Source pages 68-69, 120, 125; cap rate p61; WACC p65.
A5: CSJ Infrastructure Private Limited (CSJIPL) | B5: Nexus Elante Complex | C5: Retail | D5: Chandigarh | E5: Industrial Area Phase I | F5: Industrial Area Phase I | G5: Plot No. 178-178A, Industrial Area Phase I, Chandigarh, India | H5: 1410000 | I5: 1.41 | J5: 1.33 | K5: 0.94 | L5: 0.91 | M5: 208.9 | N5: 197 | O5: =IF(OR(M5="",N5="",N5=0),"",M5/N5-1) | P5: 4.3 | Q5: 277 | R5: 0.075 | S5: 0.1138 | T5: 5983.4 | U5: =IF(OR(T5="",H5="",H5=0),"",T5*10000000/H5) | X5: Freehold. RETAIL component only in this row (mall). Committed occ mall 94.4%; leased 1,210,824/1,326,512 sf. Mall market rent 208.9 psf/mo, in-place 197.0 psf/mo. Mall WALE 4.3yr area/3.9yr rental. Mall cap 7.50%. Mall value INR 52,095mn. Complex also has Elante Office (0.08msf/84,691 sf, occ 88.4%, in-place 120.1/marginal 109.0 psf/mo, WALE 2.7yr, cap 8.25%, WACC 11.78%, value INR 1,342mn) and Hyatt Regency Chandigarh 211-key hotel (cap 7.14%/14x EV-EBITDA, WACC 11.88%, value INR 6,397mn). Total complex value INR 59,834mn. Mall leasable incl recent 58,537 sf acquisition by CSJIPL. Pages 70-71, cap p61/62/63, WACC p65-67.
A6: Select Infrastructure Private Limited (SIPL) | B6: Nexus Seawoods | C6: Retail | D6: Navi Mumbai | E6: Nerul | F6: Nerul / Seawoods, Sector 40 | G6: Plot No. R1, Sector 40, Nerul Node, Navi Mumbai, District Thane, Maharashtra, India | H6: 979577 | I6: 0.98 | J6: 0.98 | K6: 0.98 | L6: 0.98 | M6: 160.2 | N6: 152.6 | O6: =IF(OR(M6="",N6="",N6=0),"",M6/N6-1) | P6: 5.8 | Q6: 290 | R6: 0.0775 | S6: 0.1138 | T6: 2805.1 | U6: =IF(OR(T6="",H6="",H6=0),"",T6*10000000/H6) | X6: Leasehold (CIDCO, 60yr from 2008; ~42yr remaining, perpetuity assumed). Committed occ 98.1%; leased 954,988/979,577 sf. Market rent 160.2, in-place 152.6 psf/mo. WALE 5.8yr area/4.8yr rental. Cap 7.75%. Includes 0.2msf AIRSPACE F&B/entertainment zone. Value INR 28,051mn. Pages 72-73, cap p61, WACC p65.
A7: Euthoria Developers Private Limited (EDPL) | B7: Nexus Ahmedabad One | C7: Retail | D7: Ahmedabad | E7: Vastrapur | F7: Vastrapur / Memnagar | G7: Final Plot No. 216, Moje Vastrapur, Taluka Vejalpur, District Ahmedabad, India | H7: 888276 | I7: 0.89 | J7: 0.89 | K7: 0.96 | L7: 0.95 | M7: 145.7 | N7: 131.6 | O7: =IF(OR(M7="",N7="",N7=0),"",M7/N7-1) | P7: 8.1 | Q7: 213 | R7: 0.08 | S7: 0.1138 | T7: 2050 | U7: =IF(OR(T7="",H7="",H7=0),"",T7*10000000/H7) | X7: Leasehold (AUDA, 99yr from 2006; perpetuity assumed). Two phases (P-I 2011, P-II Aug 2021). Committed occ 96.0%; leased 845,775/888,276 sf. Market rent 145.7, in-place 131.6 psf/mo. WALE 8.1yr area/4.9yr rental. Cap 8.00%. Largest Grade A mall in Gujarat. Value INR 20,500mn. Pages 74-75, cap p61, WACC p65.
A8: Nexus Hyderabad Retail Private Limited (NHRPL) | B8: Nexus Hyderabad | C8: Retail | D8: Hyderabad | E8: Kukatpally | F8: Kukatpally | G8: Sy. No.1009, Kukatpally Village, Kukatpally Mandal, Medchal Malkajgiri District, Hyderabad, India | H8: 831841 | I8: 0.83 | J8: 0.83 | K8: 0.99 | L8: 0.98 | M8: 132.3 | N8: 118.9 | O8: =IF(OR(M8="",N8="",N8=0),"",M8/N8-1) | P8: 3.1 | Q8: 175 | R8: 0.08 | S8: 0.1138 | T8: 1978.3 | U8: =IF(OR(T8="",H8="",H8=0),"",T8*10000000/H8) | X8: Freehold. Committed occ 98.8%; leased 815,382/831,841 sf. Market rent 132.3, in-place 118.9 psf/mo. WALE 3.1yr area/2.9yr rental. Cap 8.00%. Value INR 19,783mn. Pages 76-77, cap p61, WACC p65.
A9: Nexus Hyderabad Retail Private Limited (NHRPL) | B9: Nexus Koramangala | C9: Retail | D9: Bengaluru | E9: Koramangala | F9: Koramangala | G9: Municipal No. 21, Hosur Road, Lakkasandra Ward No. 63, Bengaluru, India | H9: 307374 | I9: 0.31 | J9: 0.31 | K9: 0.97 | L9: 0.94 | M9: 211.1 | N9: 191 | O9: =IF(OR(M9="",N9="",N9=0),"",M9/N9-1) | P9: 5.5 | Q9: 99 | R9: 0.075 | S9: 0.1138 | T9: 1138.2 | U9: =IF(OR(T9="",H9="",H9=0),"",T9*10000000/H9) | X9: Freehold. Value/area reflect NHRPL economic interest of 307,374 sf = ownership 254,960 sf + short-term leasehold 21,877 sf + revenue-share 30,537 sf (both valid to 31 Mar 2028). Committed occ 96.9%; leased 288,599/307,374 sf. Market rent 211.1, in-place 191.0 psf/mo. WALE 5.5yr area/5.0yr rental. Cap 7.50%. Value INR 11,382mn. Pages 78-79, cap p61, WACC p65.
A10: Vijaya Productions Private Limited (VPPL) | B10: Nexus Vijaya Complex | C10: Retail | D10: Chennai | E10: Vadapalani | F10: Vadapalani / Arcot Road | G10: Survey Nos. 5/1, 5/3, 5/7, 5/5, Arcot Road, Chennai, India | H10: 840000 | I10: 0.84 | J10: 0.65 | K10: 0.99 | L10: 0.98 | M10: 117.1 | N10: 109.8 | O10: =IF(OR(M10="",N10="",N10=0),"",M10/N10-1) | P10: 4.5 | Q10: 131 | R10: 0.08 | S10: 0.1138 | T10: 1781.2 | U10: =IF(OR(T10="",H10="",H10=0),"",T10*10000000/H10) | X10: Freehold. RETAIL row (mall). Committed occ mall 99.4%; leased 637,489/653,765 sf. Mall market rent 117.1, in-place 109.8 psf/mo. Mall WALE 4.5yr area/3.9yr rental. Mall cap 8.00%. Mall value INR 15,665mn. Complex also has Vijaya Office 0.19msf (190,061 sf, occ 100%, in-place 58.5/marginal 64.0 psf/mo, WALE 4.6yr, cap 8.25%, WACC 11.78%, value INR 2,147mn). Total complex value INR 17,812mn. Pages 80-81, cap p61/62, WACC p65-66.
A11: Chitrali Properties Private Limited (CPPL) / Daksha Infrastructure Private Limited (DIPL) | B11: Nexus Westend Complex | C11: Retail | D11: Pune | E11: Aundh | F11: Aundh | G11: Survey No. 169/1 (CTS No. 2495), Village Aundh, Taluka Haveli, District Pune, Maharashtra, India | H11: 1410000 | I11: 1.41 | J11: 0.43 | K11: 0.94 | L11: 0.93 | M11: 142 | N11: 124.7 | O11: =IF(OR(M11="",N11="",N11=0),"",M11/N11-1) | P11: 8.1 | Q11: 129 | R11: 0.0825 | S11: 0.1138 | T11: 2307.2 | U11: =IF(OR(T11="",H11="",H11=0),"",T11*10000000/H11) | X11: Freehold. RETAIL row (mall). Committed occ mall 94.1%; leased 401,882/433,090 sf. Mall market rent 142.0, in-place 124.7 psf/mo. Mall WALE 8.1yr area/5.5yr rental. Mall cap 8.25% (high competition submarket). Mall value INR 9,576mn. Complex also has Westend Icon Offices 0.98msf (977,967 sf, occ 93.0%, leased 861,802 sf, in-place 96.6/marginal 96.4 psf/mo, cap 8.25%, WACC 11.78%, value INR 13,496mn). Total complex value INR 23,072mn. Pages 82-83, cap p61/62, WACC p65-66.
A12: Safari Retreats Private Limited (SRPL) | B12: Nexus Esplanade | C12: Retail | D12: Bhubaneswar | E12: Rasulgarh | F12: Rasulgarh | G12: Various plots, Mouza Govind Prasad & Bomikhal, Tehsil Bhubaneswar, District Khurda, Odisha, India | H12: 428391 | I12: 0.43 | J12: 0.43 | K12: 0.99 | L12: 0.99 | M12: 161.7 | N12: 154.1 | O12: =IF(OR(M12="",N12="",N12=0),"",M12/N12-1) | P12: 6.5 | Q12: 125 | R12: 0.08 | S12: 0.1138 | T12: 1165.5 | U12: =IF(OR(T12="",H12="",H12=0),"",T12*10000000/H12) | X12: Part Freehold / Part Leasehold (~44yr remaining leasehold, perpetuity assumed). Committed occ 98.9%; leased 423,650/428,391 sf. Market rent 161.7, in-place 154.1 psf/mo. WALE 6.5yr area/5.4yr rental. Cap 8.00%. Value INR 11,655mn. Pages 84-85, cap p61, WACC p65.
A13: Euthoria Developers Private Limited (EDPL) | B13: Nexus Amritsar | C13: Retail | D13: Amritsar | E13: Rajinder Nagar | F13: Rajinder Nagar, G.T. Road | G13: Khasra nos. 605 etc., Sultanwind Suburban, G.T. Road, Amritsar, Punjab, India | H13: 539181 | I13: 0.54 | J13: 0.54 | K13: 0.97 | L13: 0.95 | M13: 99.1 | N13: 89.5 | O13: =IF(OR(M13="",N13="",N13=0),"",M13/N13-1) | P13: 7.7 | Q13: 156 | R13: 0.08 | S13: 0.1138 | T13: 885.1 | U13: =IF(OR(T13="",H13="",H13=0),"",T13*10000000/H13) | X13: Freehold. Committed occ 97.4%; leased 509,841/539,181 sf. Market rent 99.1, in-place 89.5 psf/mo. WALE 7.7yr area/5.2yr rental. Cap 8.00%. Value INR 8,851mn. Pages 86-87, cap p61, WACC p65.
A14: Nexus Shantiniketan Retail Private Limited (NSRPL) | B14: Nexus Shantiniketan | C14: Retail | D14: Bengaluru | E14: Whitefield | F14: Whitefield / Hoodi | G14: Municipal No. 13/288, Hoodi-Sadaramangala, Whitefield Sub-Division, Bengaluru, Karnataka, India | H14: 407492 | I14: 0.41 | J14: 0.41 | K14: 0.98 | L14: 0.97 | M14: 116 | N14: 109.8 | O14: =IF(OR(M14="",N14="",N14=0),"",M14/N14-1) | P14: 6.4 | Q14: 122 | R14: 0.08 | S14: 0.1138 | T14: 925.9 | U14: =IF(OR(T14="",H14="",H14=0),"",T14*10000000/H14) | X14: Freehold. Area & value ADJUSTED for 64.90% economic interest. Total mall leasable 627,877 sf (0.63msf), NSRPL share 407,492 sf (0.41msf). Total asset value 100%=INR 14,267mn; adjusted-for-stake value INR 9,259mn. Committed occ 98.3%; leased 611,139/627,877 sf (full asset). Market rent 116.0, in-place 109.8 psf/mo. WALE 6.4yr area/5.2yr rental. Cap 8.00%. Pages 88-89, value-summary p108, cap p61, WACC p65.
A15: Nexusmalls Whitefield Private Limited (NWPL) | B15: Nexus Whitefield Complex | C15: Retail | D15: Bengaluru | E15: Whitefield | F15: Whitefield | G15: Survey No. 62, Whitefield Main Road, Whitefield, Bengaluru, Karnataka 560066, India | H15: 321367 | I15: 0.32 | J15: 0.32 | K15: 0.98 | M15: 102.6 | N15: 92 | O15: =IF(OR(M15="",N15="",N15=0),"",M15/N15-1) | P15: 3.7 | Q15: 91 | R15: 0.08 | S15: 0.1138 | T15: 831.9 | U15: =IF(OR(T15="",H15="",H15=0),"",T15*10000000/H15) | X15: Freehold. RETAIL row (mall). Committed occ mall 98.1%. Mall market rent 102.6, in-place 92.0 psf/mo. Mall WALE 3.7yr area/3.4yr rental. Mall cap 8.00%. Mall value INR 5,824mn. Complex also has 143-key Oakwood Residence Whitefield Bangalore hotel (cap 7.14%/14x, WACC 11.88%, value INR 2,495mn). Total complex value INR 8,319mn. Pages 90-91, cap p61/63, WACC p65-67.
A16: Nexus Udaipur Retail Private Limited (NURPL) | B16: Nexus Celebration | C16: Retail | D16: Udaipur | E16: Bhuwana | F16: Bhuwana / NH8 | G16: Bhuwana (Phase-II), NH 8, Udaipur, Rajasthan, India | H16: 402926 | I16: 0.4 | J16: 0.4 | K16: 0.9 | M16: 86.5 | N16: 82.4 | O16: =IF(OR(M16="",N16="",N16=0),"",M16/N16-1) | P16: 3.5 | Q16: 107 | R16: 0.0825 | S16: 0.1138 | T16: 531.3 | U16: =IF(OR(T16="",H16="",H16=0),"",T16*10000000/H16) | X16: Leasehold (99yr from 2004; ~77yr remaining, perpetuity assumed). Committed occ 90.4%. Market rent 86.5, in-place 82.4 psf/mo. WALE 3.5yr area/3.4yr rental. Cap 8.25% (tier-2 city, only retail development in city). Value INR 5,313mn. Pages 92-93, cap p61, WACC p65.
A17: Nexus Mangaluru Retail Private Limited (NMRPL Mangaluru) | B17: Fiza by Nexus | C17: Retail | D17: Mangaluru | E17: Pandeshwar | F17: Pandeshwar | G17: Plot No. TS 210 (R.S. No. 335), Attavara village, Pandeshwar Road, Mangalore, India | H17: 486030 | I17: 0.49 | J17: 0.49 | K17: 0.97 | M17: 86.5 | N17: 82.4 | O17: =IF(OR(M17="",N17="",N17=0),"",M17/N17-1) | P17: 5.6 | Q17: 119 | R17: 0.0825 | S17: 0.1138 | T17: 505.7 | U17: =IF(OR(T17="",H17="",H17=0),"",T17*10000000/H17) | X17: Freehold. Area & value ADJUSTED for 68% economic interest. Total mall leasable 714,750 sf (0.71msf), NMRPL share 486,030 sf (0.49msf). Total asset value 100%=INR 7,436mn; adjusted value INR 5,057mn. Committed occ 97.3%. Market rent 86.5, in-place 82.4 psf/mo (rent-table value taken from Fiza chapter region pp94-95; layout ambiguous vs Celebration - spot-verify if precision critical). WALE 5.6yr area/5.0yr rental. Cap 8.25% (tier-2 city). Pages 94-95, value-summary p108, cap p61, WACC p65.
A18: Nexus Mysore Retail Private Limited (NMRPL Mysore) | B18: Nexus Centre City | C18: Retail | D18: Mysuru | E18: Nazarbad | F18: Nazarbad, Hyder Ali Road | G18: Survey No. 9 & Khata No. 33, Eranagare Village, Hyderali Road, Nazarbad Mohalla, Mysuru, Karnataka 570010, India | H18: 326002 | I18: 0.33 | J18: 0.33 | K18: 1 | L18: 0.99 | M18: 79.3 | N18: 71.5 | O18: =IF(OR(M18="",N18="",N18=0),"",M18/N18-1) | P18: 6.1 | Q18: 94 | R18: 0.0825 | S18: 0.1138 | T18: 424.1 | U18: =IF(OR(T18="",H18="",H18=0),"",T18*10000000/H18) | X18: Freehold. Committed occ 99.7%; occupied 323,207/326,002 sf. Market rent 79.3, in-place 71.5 psf/mo. WALE 6.1yr area/4.8yr rental. Cap 8.25% (tier-2 city). Value INR 4,241mn. Pages 96-97, cap p61, WACC p65.
A19: Naman Mall Management Company Private Limited (NMMCPL) | B19: Nexus Indore Central | C19: Retail | D19: Indore | E19: South Tukoganj | F19: South Tukoganj, RNT Marg | G19: Plot No. 170, Rabindranath Tagore Marg, Indore, Madhya Pradesh, India | H19: 246864 | I19: 0.25 | J19: 0.25 | K19: 0.87 | L19: 0.87 | M19: 67.2 | N19: 63.4 | O19: =IF(OR(M19="",N19="",N19=0),"",M19/N19-1) | P19: 10.8 | R19: 0.085 | S19: 0.1138 | T19: 212 | U19: =IF(OR(T19="",H19="",H19=0),"",T19*10000000/H19) | X19: Freehold. Committed occ 87.3%; leased 214,464/246,864 sf. Market rent 67.2, in-place 63.4 psf/mo. WALE 10.8yr area/11.7yr rental. Cap 8.50% (tier-2 city, high competition; highest cap in portfolio). Value INR 2,120mn. Number of brands not stated numerically in cert. Pages 98-99, cap p61, WACC p65.
A20: Mamadapur Solar Private Limited (MSPL) | B20: Karnataka Solar Park | C20: Solar | D20: Vijayapura | E20: Kodabagi Village | F20: Kodabagi Village, Babaleshwar Taluk | G20: Kodabagi Village, Mamadapura Hobli, Babaleshwar Taluk, Bijapura District, Vijayapura, Karnataka 586113, India | O20: =IF(OR(M20="",N20="",N20=0),"",M20/N20-1) | S20: 0.115 | T20: 75.9 | U20: =IF(OR(T20="",H20="",H20=0),"",T20*10000000/H20) | X20: Leasehold (67.925 acres, ~20yr remaining). NOT a mall: 15 MW (AC) captive solar PV plant with PPA supplying Nexus Koramangala, Shantiniketan, Whitefield, Centre City and Fiza. Valued via DCF. WACC 11.50% (cost of debt 8.5%, equity 14.5%). Value INR 759mn. Pages 100-101, WACC p66-67.
A21: Vijaya Productions Private Limited (VPPL) | B21: Nexus Vega City | C21: Retail | D21: Bengaluru | E21: Bannerghatta Road | F21: Bannerghatta Road, Bilekahalli | G21: Municipal No.1335/172/1 & 75, Bilekahalli Village, Bannerghatta Road, Bengaluru, Karnataka, India | H21: 439687 | I21: 0.44 | J21: 0.44 | K21: 0.99 | M21: 124.4 | N21: 121 | O21: =IF(OR(M21="",N21="",N21=0),"",M21/N21-1) | P21: 10.7 | Q21: 127 | R21: 0.08 | S21: 0.1138 | T21: 1071.9 | U21: =IF(OR(T21="",H21="",H21=0),"",T21*10000000/H21) | X21: Freehold. Acquired Feb 2025 (post-IPO) at purchase price INR 8,697.5mn; not a related-party transaction. UDS in land for mall = 12,748 sqm. Committed occ 99.0%. Market rent 124.4, in-place 121.0 psf/mo. WALE 10.7yr area/8.6yr rental. Cap 8.00%. Value INR 10,719mn. Pages 102-103, cap p62, WACC p65.
A22: Select Infrastructure Private Limited (SIPL) | B22: Nexus MBD Complex | C22: Retail | D22: Ludhiana | E22: Ferozepur Road | F22: Ferozepur Road, Sunder Nagar | G22: Village Barewal Awana (Ferozepur Road), Tehsil & District Ludhiana, Punjab, India | H22: 257400 | I22: 0.26 | J22: 0.26 | K22: 0.99 | M22: 125.5 | N22: 110 | O22: =IF(OR(M22="",N22="",N22=0),"",M22/N22-1) | P22: 6.2 | Q22: 86 | R22: 0.0825 | S22: 0.1138 | T22: 603.3 | U22: =IF(OR(T22="",H22="",H22=0),"",T22*10000000/H22) | X22: Freehold. RETAIL row (mall). Acquired May 2025 (post-IPO) at purchase price INR 4,900mn; not related-party. Committed occ mall 99.3%. Mall market rent 125.5, in-place 110.0 psf/mo. Mall WALE 6.2yr area/5.6yr rental. Mall cap 8.25% (tier-2 city). Mall value INR 4,521mn. Complex also has 96-key Radisson Blu Hotel Ludhiana (cap 7.14%/14x, WACC 11.88%, value INR 1,512mn). Total complex value INR 6,033mn. Pages 104-105, cap p61/63, WACC p65-67.
A23: Indore Treasure Island Private Limited (ITIPL) | B23: Treasure Island | C23: Retail | D23: Indore | E23: South Tukoganj | F23: South Tukoganj, MG Road | G23: Plot No. 11, MG Road, Tukoganj, Indore, Madhya Pradesh, India | H23: 220425 | I23: 0.22 | J23: 0.22 | K23: 0.87 | L23: 0.84 | M23: 72.4 | N23: 69.4 | O23: =IF(OR(M23="",N23="",N23=0),"",M23/N23-1) | P23: 5.1 | Q23: 86 | R23: 0.085 | S23: 0.1138 | T23: 278.3 | U23: =IF(OR(T23="",H23="",H23=0),"",T23*10000000/H23) | X23: Leasehold (renewable 4yr 11mo). Nexus Select Trust owns 50% economic interest. Area & value ADJUSTED for 50% stake: total leasable 440,850 sf (0.43msf), share 220,425 sf (0.22msf); total value 100%=INR 5,566mn, adjusted INR 2,783mn. Committed occ 86.8%; leased 368,943/440,850 sf (full asset). Market rent 72.4, in-place 69.4 psf/mo. WALE 5.1yr area/3.7yr rental. Cap 8.50% (tier-2, high competition). Pages 106-107, value-summary p109, cap p61, WACC p65.
A24: TOTAL / weighted | H24: =SUM(H4:H23) | I24: =SUM(I4:I23) | M24: =IFERROR(AVERAGE(M4:M23),"") | N24: =IFERROR(AVERAGE(N4:N23),"") | T24: =SUM(T4:T23) | U24: =IFERROR(T24*10000000/H24,"")

Sheet KRT
A1: KRT - Asset-level detail (valuation 31 Mar 2026; 33 assets)
A3: SPV / Holding entity | B3: Property / Asset | C3: Type | D3: City | E3: Locality / Area | F3: Micro-market (valuer) | G3: Address | H3: Leasable (sq ft) | I3: Leasable (msf) | J3: Completed (msf) | K3: Committed occ. | L3: In-place occ. | M3: Market rent /sqft/mo | N3: In-place rent /sqft/mo | O3: Rent reversion | P3: WALE (yrs) | Q3: Tenants | R3: Cap rate | S3: Discount rate | T3: Market value (INR cr) | U3: Value/sqft (INR) | V3: Mgmt fee (valuation DCF) | W3: Insurance (valuation DCF) | X3: Notes / source
A4: M/S Devbhumi Realtors Pvt Ltd | B4: Sattva Knowledge City | C4: Office | D4: Hyderabad | E4: HITEC City | F4: IT Corridor–HITEC City | G4: Plot No.2, Survey No. 83/1, Raidurg Panmaktha Village, Serilingampally Mandal, Ranga Reddy District, Telangana. | H4: 7295223 | I4: 7.3 | K4: 0.997 | M4: 120 | N4: 80.4 | O4: =IF(OR(M4="",N4="",N4=0),"",M4/N4-1) | P4: 10 | R4: 0.075 | S4: 0.1146 | T4: 12292 | U4: =IF(OR(T4="",H4="",H4=0),"",T4*10000000/H4) | V4: 3.0% of the Facility Rentals | W4: INR 15.7 Mn from Apr'26 to Mar'27 (Mgmt input; 5% p.a. escalation from Apr'27) | X4: Detailed sec 7 (pdf p.157); Valuation Certificate sec 6; Value Summary sec 4 (pdf p.55-56)
A5: M/S Worldwide Realcon Pvt Ltd | B5: Sattva Knowledge Park | C5: Office | D5: Hyderabad | E5: HITEC City | F5: IT Corridor–HITEC City | G5: Plot No. 16, Survey No. 83/1, Raidurg Panmaktha Village, Serilingampally Mandal, Ranga Reddy District, Telangana. | H5: 3300963 | I5: 3.3 | K5: 0.968 | M5: 120 | N5: 79 | O5: =IF(OR(M5="",N5="",N5=0),"",M5/N5-1) | P5: 10 | R5: 0.075 | S5: 0.1146 | T5: 5675.5 | U5: =IF(OR(T5="",H5="",H5=0),"",T5*10000000/H5) | V5: 3.0% of the Facility Rentals | W5: INR 4.1 Mn from Apr'26 to Mar'27 (Mgmt input; 5% p.a. escalation from Apr'27) | X5: Detailed sec 8 (pdf p.176); Valuation Certificate sec 6; Value Summary sec 4 (pdf p.55-56)
A6: M/S Sattva Knowledge Centre Pvt Ltd | B6: Sattva Knowledge Capital | C6: Office | D6: Hyderabad | E6: Nanakramguda | F6: Extended IT Corridor | G6: Plot No. 8 (Part), Survey No. 115, Nanakramguda Village, Serilingampally Mandal, Ranga Reddy District, Telangana. | H6: 2295894 | I6: 2.3 | M6: 68 | N6: 66.4 | O6: =IF(OR(M6="",N6="",N6=0),"",M6/N6-1) | R6: 0.0775 | S6: 0.1146 | T6: 2942.5 | U6: =IF(OR(T6="",H6="",H6=0),"",T6*10000000/H6) | V6: 3.0% of the Facility Rentals | W6: INR 2.1 Mn from Apr'26 to Mar'27 (Mgmt input; 5% p.a. escalation from Apr'27) | X6: Detailed sec 9 (pdf p.191); Valuation Certificate sec 6; Value Summary sec 4 (pdf p.55-56)
A7: One Bkc Realtors Private Limited | B7: One BKC | C7: Office | D7: Mumbai | E7: BKC & BKC-O | F7: BKC & BKC-O | G7: Plot No. C-66, C.T.S. No. 4207 (part), Village Kole-Kalyan, Mumbai Suburban District, G Block, Bandra- Kurla Complex, Bandra East, Mumbai | H7: 750044 | I7: 0.8 | K7: 0.872 | M7: 420 | N7: 366.7 | O7: =IF(OR(M7="",N7="",N7=0),"",M7/N7-1) | P7: 3.8 | R7: 0.075 | S7: 0.1146 | T7: 4666.7 | U7: =IF(OR(T7="",H7="",H7=0),"",T7*10000000/H7) | V7: 3.0% of the Facility Rentals | W7: INR 3.2 Mn from Apr'26 to Mar'27 (Mgmt input; 5% p.a. escalation from Apr'27) | X7: Detailed sec 10 (pdf p.206); Valuation Certificate sec 6; Value Summary sec 4 (pdf p.55-56)
A8: One World Center Private Limited | B8: One World Center | C8: Office | D8: Mumbai | E8: Prabhadevi | F8: EXT - CBD | G8: Survey No. 841, Senapati Bapat Marg, Elphinstone Road, Lower Parel, Mumbai | H8: 1752214 | I8: 1.8 | K8: 0.925 | M8: 255 | N8: 211.7 | O8: =IF(OR(M8="",N8="",N8=0),"",M8/N8-1) | P8: 3.5 | R8: 0.0775 | S8: 0.1146 | T8: 6276.7 | U8: =IF(OR(T8="",H8="",H8=0),"",T8*10000000/H8) | V8: 3.0% of the Facility Rentals | W8: INR 4.1 Mn from Apr'26 to Mar'27 (Mgmt input; 5% p.a. escalation from Apr'27) | X8: Detailed sec 11 (pdf p.222); Valuation Certificate sec 6; Value Summary sec 4 (pdf p.55-56)
A9: One International Center Pvt Ltd | B9: One International Center | C9: Office | D9: Mumbai | E9: Prabhadevi | F9: EXT - CBD | G9: Part of Plot 612 & 613, Senapati Bapat Marg, Prabhadevi, Dadar (W), Mumbai | H9: 1778186 | I9: 1.8 | K9: 0.891 | M9: 220 | N9: 186.9 | O9: =IF(OR(M9="",N9="",N9=0),"",M9/N9-1) | P9: 2.6 | R9: 0.0775 | S9: 0.1146 | T9: 5534.3 | U9: =IF(OR(T9="",H9="",H9=0),"",T9*10000000/H9) | V9: 3.0% of the Facility Rentals | W9: INR 4.4 Mn from Apr'26 to Mar'27 (Mgmt input; 5% p.a. escalation from Apr'27) | X9: Detailed sec 12 (pdf p.238); Valuation Certificate sec 6; Value Summary sec 4 (pdf p.55-56)
A10: One International Center Private Limited | B10: One Unity Center | C10: Office | D10: Mumbai | E10: Prabhadevi | F10: EXT - CBD | G10: Part of Plot 612 & 613, Senapati Bapat Marg, Prabhadevi, Dadar (W), Mumbai. | H10: 1002111 | I10: 1 | K10: 0.844 | M10: 245 | N10: 198.8 | O10: =IF(OR(M10="",N10="",N10=0),"",M10/N10-1) | P10: 5.7 | R10: 0.0775 | S10: 0.1146 | T10: 3364.2 | U10: =IF(OR(T10="",H10="",H10=0),"",T10*10000000/H10) | V10: 3.0% of the Facility Rentals | W10: INR 2.5 Mn from Apr'26 to Mar'27 (Mgmt input; 5% p.a. escalation from Apr'27) | X10: Detailed sec 13 (pdf p.254); Valuation Certificate sec 6; Value Summary sec 4 (pdf p.55-56)
A11: Prima Bay Private Limited | B11: Prima Bay | C11: Office | D11: Mumbai | E11: Powai | F11: PBD East | G11: C.T.S. No. 117A/1D (Part), Village Tungwa, Powai, Mumbai | H11: 806228 | I11: 0.8 | K11: 0.88 | M11: 165 | N11: 165.6 | O11: =IF(OR(M11="",N11="",N11=0),"",M11/N11-1) | P11: 4.2 | R11: 0.08 | S11: 0.1146 | T11: 1879.4 | U11: =IF(OR(T11="",H11="",H11=0),"",T11*10000000/H11) | V11: 3.0% of the Facility Rentals | W11: INR 1.6 Mn from Apr'26 to Mar'27 (Mgmt input; 5% p.a. escalation from Apr'27) | X11: Detailed sec 14 (pdf p.270); Valuation Certificate sec 6; Value Summary sec 4 (pdf p.55-56)
A12: Cessna Garden Developers Private Limited | B12: Cessna Business Park | C12: Office | D12: Bengaluru | E12: Kadubeesanahalli | F12: Outer Ring-Road (ORR) | G12: Kadubeesanahalli Village, Varthur Hobli, Bengaluru South Taluk, Bengaluru. | H12: 4222478 | I12: 4.2 | K12: 0.944 | M12: 95 | N12: 70.9 | O12: =IF(OR(M12="",N12="",N12=0),"",M12/N12-1) | P12: 16.1 | R12: 0.0766 | S12: 0.1146 | T12: 4906.1 | U12: =IF(OR(T12="",H12="",H12=0),"",T12*10000000/H12) | V12: 3.0% of the Facility Rentals | W12: INR 7.5 Mn from Apr'26 to Mar'27 (Mgmt input; 5% p.a. escalation from Apr'27) | X12: Detailed sec 15 (pdf p.286); Valuation Certificate sec 6; Value Summary sec 4 (pdf p.55-56)
A13: Exora Business Park Private Limited | B13: Exora Business Park | C13: Office | D13: Bengaluru | E13: Marathahalli | F13: Outer Ring-Road (ORR) | G13: Amani Bellandur Khane Village, Bengaluru East Taluk, Bengaluru. | H13: 2221078 | I13: 2.2 | K13: 0.777 | M13: 100 | N13: 89.8 | O13: =IF(OR(M13="",N13="",N13=0),"",M13/N13-1) | P13: 6.6 | R13: 0.08 | S13: 0.1146 | T13: 3451.7 | U13: =IF(OR(T13="",H13="",H13=0),"",T13*10000000/H13) | V13: 3.0% of the Facility Rentals | W13: INR 3.3 Mn from Apr'26 to Mar'27 (Mgmt input; 5% p.a. escalation from Apr'27) | X13: Detailed sec 16 (pdf p.305); Valuation Certificate sec 6; Value Summary sec 4 (pdf p.55-56)
A14: M/S Gv Techparks Pvt Ltd | B14: Sattva Global City | C14: Office | D14: Bengaluru | E14: Tumkur Road | F14: Peripheral Business District - Others (along Mysore Road) | G14: Pattanagere and Mylasandra Villages, Kengeri hobli, Bengaluru | K14: 0.811 | N14: 58.5 | O14: =IF(OR(M14="",N14="",N14=0),"",M14/N14-1) | P14: 8.7 | R14: 0.085 | S14: 0.1146 | T14: 4414.8 | U14: =IF(OR(T14="",H14="",H14=0),"",T14*10000000/H14) | V14: 3.0% of the Facility Rentals | W14: INR 6.12 Mn from Apr'26 to Mar'27 (Mgmt input; 5% p.a. escalation from Apr'27) | X14: Operational block MV 34223 (4.2 msf) + Future Development MV 9925 (8.0 msf) | Detailed sec 17 (pdf p.321); Valuation Certificate sec 6; Value Summary sec 4 (pdf p.55-56)
A15: Softzone Techpark Limited | B15: Sattva Softzone | C15: Office | D15: Bengaluru | E15: Bellandur | F15: Outer Ring-Road (ORR) | G15: Khata No.799/80/1/81/1/81/2, Ward No.150-Bellandur, Bengaluru | H15: 1003221 | I15: 1 | K15: 0.905 | M15: 107 | N15: 57.6 | O15: =IF(OR(M15="",N15="",N15=0),"",M15/N15-1) | P15: 5.9 | R15: 0.08 | S15: 0.1146 | T15: 1818.4 | U15: =IF(OR(T15="",H15="",H15=0),"",T15*10000000/H15) | V15: 3.0% of the Facility Rentals | W15: INR 1.3 Mn from Apr'26 to Mar'27 (Mgmt input; 5% p.a. escalation from Apr'27) | X15: Detailed sec 18 (pdf p.340); Valuation Certificate sec 6; Value Summary sec 4 (pdf p.55-56)
A16: Darshita Hi-rise Pvt Ltd. | B16: Sattva Knowledge Court | C16: Office | D16: Bengaluru | E16: Whitefield | F16: Peripheral Business District - Whitefield (PBD-W) | G16: Survey No.77, bearing Khatha No-299, Doddanekkundi Village, K.R Puram Hobli, Bengaluru East Taluk, Bengaluru | H16: 879373 | I16: 0.9 | K16: 0.918 | M16: 80 | N16: 72.1 | O16: =IF(OR(M16="",N16="",N16=0),"",M16/N16-1) | P16: 11.3 | R16: 0.08 | S16: 0.1146 | T16: 1258.6 | U16: =IF(OR(T16="",H16="",H16=0),"",T16*10000000/H16) | V16: 3.0% of the Facility Rentals | W16: INR 1.2 Mn from Apr'26 to Mar'27 (Mgmt input; 5% p.a. escalation from Apr'27) | X16: Detailed sec 19 (pdf p.357); Valuation Certificate sec 6; Value Summary sec 4 (pdf p.55-56)
A17: Salarpuria Griha Nirman Pvt Ltd | B17: Sattva Techpoint | C17: Office | D17: Bengaluru | E17: Whitefield / KR Puram | F17: EBD (Eastern Business District) | G17: Municipal No 30, 100 Feet Road, Srinivagilu, Ward No. 68, Bengaluru. | H17: 334593 | I17: 0.3 | M17: 135 | N17: 129.8 | O17: =IF(OR(M17="",N17="",N17=0),"",M17/N17-1) | P17: 10.9 | R17: 0.08 | S17: 0.1146 | T17: 746.4 | U17: =IF(OR(T17="",H17="",H17=0),"",T17*10000000/H17) | V17: Property Management Fee 3.0% of Facility Rentals (below NOI line) | W17: INR 0.5 Mn from Apr'26 to Mar'27 (Mgmt input; 5% p.a. escalation from Apr'27) | X17: Detailed sec 20 (pdf p.373); Valuation Certificate sec 6; Value Summary sec 4 (pdf p.55-56)
A18: Pluto Business Parks Private Limited | B18: One Trade Tower | C18: Office | D18: Bengaluru | E18: Palace Road | F18: CBD (Central Business District) | G18: Municipal No. 46, Situated At Palace Road, Municipal Ward No.77, Sampangiramnagar, Bengaluru. | H18: 175336 | I18: 0.2 | M18: 210 | N18: 187.8 | O18: =IF(OR(M18="",N18="",N18=0),"",M18/N18-1) | P18: 3.2 | R18: 0.0775 | S18: 0.1146 | T18: 611.2 | U18: =IF(OR(T18="",H18="",H18=0),"",T18*10000000/H18) | V18: 3.0% of the Facility Rentals | W18: INR 1.0 Mn from Apr'26 to Mar'27 (Mgmt input; 5% p.a. escalation from Apr'27) | X18: Detailed sec 21 (pdf p.389); Valuation Certificate sec 6; Value Summary sec 4 (pdf p.55-56)
A19: Siddeshwari Grihanirman Pvt. Ltd. | B19: Sattva Horizon | C19: Office | D19: Bengaluru | E19: Bellary Road | F19: NBD -Bellary Road (Beyond Kogilu cross) | G19: Khata No.1303/6/1 & 7/1, Venkatala, Ward No.01-Kempegowda Ward, Yelahanka, Bengaluru. | H19: 615560 | I19: 0.6 | M19: 66 | N19: 62 | O19: =IF(OR(M19="",N19="",N19=0),"",M19/N19-1) | P19: 18.5 | R19: 0.08 | S19: 0.1146 | T19: 655.6 | U19: =IF(OR(T19="",H19="",H19=0),"",T19*10000000/H19) | V19: 3.0% of the Facility Rentals | W19: INR 0.7 Mn from Apr'26 to Mar'27 (Mgmt input; 5% p.a. escalation from Apr'27) | X19: Detailed sec 22 (pdf p.403); Valuation Certificate sec 6; Value Summary sec 4 (pdf p.55-56)
A20: Salarpuria Properties Pvt Ltd | B20: Sattva Touchstone | C20: Office | D20: Bengaluru | E20: Kadubeesanahalli | F20: Outer Ring-Road (ORR) | G20: Sy. No. 15/1A & 14-P7, Kadubeesanahalli Village, Varthur Hobli, Mahadevapura Zone, Ward No. 150- Bellandur, Bengaluru. | H20: 321440 | I20: 0.3 | K20: 0.432 | M20: 78 | N20: 78.3 | O20: =IF(OR(M20="",N20="",N20=0),"",M20/N20-1) | P20: 2.3 | R20: 0.0825 | S20: 0.1146 | T20: 398.1 | U20: =IF(OR(T20="",H20="",H20=0),"",T20*10000000/H20) | V20: 3.0% of the Facility Rentals | W20: INR 0.6 Mn from Apr'26 to Mar'27 (Mgmt input; 5% p.a. escalation from Apr'27) | X20: Detailed sec 23 (pdf p.416); Valuation Certificate sec 6; Value Summary sec 4 (pdf p.55-56)
A21: Quadro Info technologies Pvt Ltd | B21: Sattva Infozone | C21: Office | D21: Bengaluru | E21: Peripheral (PBD) | F21: Peripheral Business District (PBD-O) | G21: Sy Nos. 39(P), 41(P) & 42(P), Electronic City, Doddathogur Village, Begur, Hobli, Bengaluru South Taluk, Bengaluru. | H21: 444591 | I21: 0.4 | K21: 0.822 | M21: 61 | N21: 54.4 | O21: =IF(OR(M21="",N21="",N21=0),"",M21/N21-1) | P21: 3.7 | R21: 0.0825 | S21: 0.1146 | T21: 417.8 | U21: =IF(OR(T21="",H21="",H21=0),"",T21*10000000/H21) | V21: 3.0% of the Facility Rentals | W21: INR 0.5 Mn from Apr'26 to Mar'27 (Mgmt input; 5% p.a. escalation from Apr'27) | X21: Detailed sec 24 (pdf p.432); Valuation Certificate sec 6; Value Summary sec 4 (pdf p.55-56)
A22: 2. Softzone Techpark Limited | B22: Sattva Magnificia (I & II) | C22: Office | D22: Bengaluru | E22: KR Puram | F22: Extended Business District - EBD (KR Puram) | G22: Khata No:23/23/57/18/78/23 Beniganahalli and Vijinapura Village, K.R Puram Hobli, HAL Sub-division, Mahadevapura Zone, Bengaluru. | H22: 191976 | I22: 0.2 | M22: 107 | N22: 101.8 | O22: =IF(OR(M22="",N22="",N22=0),"",M22/N22-1) | P22: 8.6 | R22: 0.08 | S22: 0.1146 | T22: 326.2 | U22: =IF(OR(T22="",H22="",H22=0),"",T22*10000000/H22) | V22: 3.0% of the Facility Rentals | W22: INR 0.1 Mn from Apr'26 to Mar'27 (Mgmt input; 5% p.a. escalation from Apr'27) | X22: Magnificia I (MV 1357) + II (MV 1905) combined | Detailed sec 25 (pdf p.448); Valuation Certificate sec 6; Value Summary sec 4 (pdf p.55-56)
A23: Jaganmayi Real Estate | B23: Sattva South Avenue | C23: Office | D23: Bengaluru | E23: Peripheral (PBD) | F23: Peripheral Business District (PBD-O) | G23: Plot No. 33, 33A & 33B, Sy. No.20, 22 & 23, Veerasandra Industrial Area, Veerasandra Village, Attibele Hobli, Anekal Taluk, Bengaluru | H23: 341553 | I23: 0.3 | K23: 0.598 | M23: 68 | N23: 69.2 | O23: =IF(OR(M23="",N23="",N23=0),"",M23/N23-1) | P23: 9.6 | R23: 0.0825 | S23: 0.1146 | T23: 406.2 | U23: =IF(OR(T23="",H23="",H23=0),"",T23*10000000/H23) | V23: 3.0% of the Facility Rentals | W23: INR 0.4 Mn from Apr'26 to Mar'27 (Mgmt input; 5% p.a. escalation from Apr'27) | X23: Detailed sec 26 (pdf p.467); Valuation Certificate sec 6; Value Summary sec 4 (pdf p.55-56)
A24: Debonair Realtors Pvt Ltd | B24: Sattva Eminence | C24: Office | D24: Bengaluru | E24: Outer Ring Road | F24: Outer Ring-Road (ORR) | G24: Sy No. 174/175/176, Khata No: 239/240, Amani Bellandur Khane Village, Varthur Hobli, Bengaluru East Taluk, Bengaluru | H24: 164198 | I24: 0.2 | K24: 0.999 | M24: 86 | N24: 65.7 | O24: =IF(OR(M24="",N24="",N24=0),"",M24/N24-1) | P24: 13.5 | R24: 0.08 | S24: 0.1146 | T24: 237 | U24: =IF(OR(T24="",H24="",H24=0),"",T24*10000000/H24) | V24: 3.0% of the Facility Rentals | W24: INR 0.2 Mn from Apr'26 to Mar'27 (Mgmt input; 5% p.a. escalation from Apr'27) | X24: Detailed sec 27 (pdf p.482); Valuation Certificate sec 6; Value Summary sec 4 (pdf p.55-56)
A25: Harkeshwar Realtors Private Limited | B25: Sattva Cosmo Lavelle | C25: Office | D25: Bengaluru | E25: Lavelle Road | F25: CBD (Central Business District) | G25: Municipal No. 9 (Old Nos. 9, 9/3, & 9/4), Residency Road, Richmond Circle, Bengaluru | H25: 77022 | I25: 0.1 | M25: 235 | N25: 235 | O25: =IF(OR(M25="",N25="",N25=0),"",M25/N25-1) | P25: 14.8 | R25: 0.0775 | S25: 0.1146 | T25: 297.8 | U25: =IF(OR(T25="",H25="",H25=0),"",T25*10000000/H25) | V25: 3.0% of the Facility Rentals | W25: INR 0.2 Mn from Apr'26 to Mar'27 (Mgmt input; 5% p.a. escalation from Apr'27) | X25: Detailed sec 28 (pdf p.497); Valuation Certificate sec 6; Value Summary sec 4 (pdf p.55-56)
A26: Salarpuria Developers Pvt Ltd | B26: Sattva Premia | C26: Office | D26: Bengaluru | E26: Kadubeesanahalli | F26: ORR | G26: Sy No. 16, Khata No.316/1 to 316/5, Outer Ring Road Kadubeesanahalli Village, Mahadevapura Zone, Bengaluru East Taluk, Bengaluru. | H26: 113172 | I26: 0.1 | K26: 1 | M26: 80 | N26: 80 | O26: =IF(OR(M26="",N26="",N26=0),"",M26/N26-1) | P26: 14.5 | R26: 0.0825 | S26: 0.1146 | T26: 133.8 | U26: =IF(OR(T26="",H26="",H26=0),"",T26*10000000/H26) | V26: 3.0% of the Facility Rentals | W26: INR 0.1 Mn from Apr'26 to Mar'27 (Mgmt input; 5% p.a. escalation from Apr'27) | X26: Detailed sec 29 (pdf p.512); Valuation Certificate sec 6; Value Summary sec 4 (pdf p.55-56)
A27: Sattva Developers Pvt Ltd | B27: Sattva Supreme | C27: Office | D27: Bengaluru | E27: Munnekolala | F27: Outer Ring-Road (ORR) | G27: Sy. No. 92/5 of Munnekolala Village, Varthur Hobli, Bengaluru East Taluk, Bengaluru | H27: 63929 | I27: 0.1 | K27: 0.322 | M27: 80 | N27: 91.1 | O27: =IF(OR(M27="",N27="",N27=0),"",M27/N27-1) | P27: 3.7 | R27: 0.085 | S27: 0.1146 | T27: 72.5 | U27: =IF(OR(T27="",H27="",H27=0),"",T27*10000000/H27) | V27: Property Management Fee 3.0% of Facility Rentals (below NOI line) | W27: INR 0.2 Mn from Apr'26 to Mar'27 (Mgmt input; 5% p.a. escalation from Apr'27) | X27: Detailed sec 30 (pdf p.526); Valuation Certificate sec 6; Value Summary sec 4 (pdf p.55-56)
A28: Darshita Housing Pvt. Ltd. | B28: Sattva Endeavour | C28: Office | D28: Bengaluru | E28: Peripheral (PBD) | F28: Peripheral Business District (PBD – O) | G28: Sy No 44(P), 44/1A1, 46(P) and 47(P), Electronic City 2nd Phase, Begur (Konnappana Agrahara Village), Bengaluru South Taluk, Bengaluru. | H28: 739671 | I28: 0.7 | M28: 66 | O28: =IF(OR(M28="",N28="",N28=0),"",M28/N28-1) | R28: 0.0825 | S28: 0.124 | T28: 644.3 | U28: =IF(OR(T28="",H28="",H28=0),"",T28*10000000/H28) | V28: 3.0% of the Facility Rentals | W28: INR 1.4 Mn from Apr'26 to Mar'27 (Mgmt input; 5% p.a. escalation from Apr'27) | X28: Detailed sec 31 (pdf p.541); Valuation Certificate sec 6; Value Summary sec 4 (pdf p.55-56)
A29: Salarpuria Builders Private Limited | B29: Sattva Spectrum | C29: Office | D29: Bengaluru | E29: Peripheral (PBD) | F29: Peripheral Business District (PBD-O) | G29: Municipal No. 2355 / 78/6,5, 3, 8B, 9(P), Marathahalli Division, Doddakanelli, Marathahalli, Bengaluru | H29: 480962 | I29: 0.5 | M29: 75 | O29: =IF(OR(M29="",N29="",N29=0),"",M29/N29-1) | R29: 0.0825 | S29: 0.124 | T29: 494.2 | U29: =IF(OR(T29="",H29="",H29=0),"",T29*10000000/H29) | V29: 3.0% of the Facility Rentals | W29: INR 0.9 Mn from Apr'26 to Mar'27 (Mgmt input; 5% p.a. escalation from Apr'27) | X29: Detailed sec 32 (pdf p.554); Valuation Certificate sec 6; Value Summary sec 4 (pdf p.55-56)
A30: Kosmo One Business Park Private Limited | B30: Kosmo One | C30: Office | D30: Chennai | E30: Ambattur | F30: Ambattur | G30: Survey Nos. 195 Part, 196 Part, 197 Part, 198 Part, 199 Part And 200 Part, Mannurpet Village, And Survey Nos. 6 Part, 7 Part, 8 Part And 10 Part, Athipet Village, No. 14, 3Rd Main Road, Ambattur Industrial Estate, Ambattur, Chennai. | H30: 1911704 | I30: 1.9 | K30: 0.971 | M30: 57 | N30: 44.3 | O30: =IF(OR(M30="",N30="",N30=0),"",M30/N30-1) | P30: 4.8 | R30: 0.08 | S30: 0.1146 | T30: 1623.7 | U30: =IF(OR(T30="",H30="",H30=0),"",T30*10000000/H30) | V30: 3.0% of the Facility Rentals | W30: INR 2.8 Mn from Apr'26 to Mar'27 (Mgmt input; 5% p.a. escalation from Apr'27) | X30: Detailed sec 33 (pdf p.567); Valuation Certificate sec 6; Value Summary sec 4 (pdf p.55-56)
A31: One Qube Realtors Private Limited | B31: One Qube | C31: Office | D31: Gurugram | E31: NH-8 (Gurugram) | F31: NH-8 (Before Rajiv Chowk) | G31: Plot No. 20, Sector-18, Urban Estate, Gurugram, Haryana. | H31: 555964 | I31: 0.6 | K31: 0.916 | M31: 125 | N31: 107.5 | O31: =IF(OR(M31="",N31="",N31=0),"",M31/N31-1) | P31: 7.2 | R31: 0.08 | S31: 0.1146 | T31: 1029.5 | U31: =IF(OR(T31="",H31="",H31=0),"",T31*10000000/H31) | V31: 3.0% of the Facility Rentals | W31: INR 1.2 Mn from Apr'26 to Mar'27 (Mgmt input; 5% p.a. escalation from Apr'27) | X31: Detailed sec 34 (pdf p.582); Valuation Certificate sec 6; Value Summary sec 4 (pdf p.55-56)
A32: Pluto Atriza Business Parks Private Limited | B32: Fintech One | C32: Office | D32: GIFT City, Ahmedabad | E32: GIFT City | F32: GIFT City, Ahmedabad | G32: Survey No. 500, Village Ratanpur, Taluka And District: Gandhinagar, Gujarat. | H32: 452528 | I32: 0.5 | K32: 0.98 | M32: 63 | N32: 52 | O32: =IF(OR(M32="",N32="",N32=0),"",M32/N32-1) | P32: 7.8 | R32: 0.08 | S32: 0.1146 | T32: 439.1 | U32: =IF(OR(T32="",H32="",H32=0),"",T32*10000000/H32) | V32: 3.0% of the Facility Rentals | W32: INR 0.9 Mn from Apr'26 to Mar'27 (Mgmt input; 5% p.a. escalation from Apr'27) | X32: Detailed sec 35 (pdf p.597); Valuation Certificate sec 6; Value Summary sec 4 (pdf p.55-56)
A33: One BKC Solar Energy Private Limited | B33: One BKC Solar | C33: Solar | D33: Dhule, Maharashtra | E33: Bhadgaon | G33: Bhadgaon, Dhule, Maharashtra | O33: =IF(OR(M33="",N33="",N33=0),"",M33/N33-1) | S33: 0.1146 | T33: 31.6 | U33: =IF(OR(T33="",H33="",H33=0),"",T33*10000000/H33) | V33: Property Management Fee 3.0% of Facility Rentals (below NOI line) | X33: Detailed sec 36 (pdf p.612); Valuation Certificate sec 6; Value Summary sec 4 (pdf p.55-56)
A34: Prima Bay Solar Energy Private Limited | B34: Prima Bay Solar | C34: Solar | D34: Dhule, Maharashtra | E34: Bhadgaon (Dhule) | G34: Bhadgaon, Dhule, Maharashtra | O34: =IF(OR(M34="",N34="",N34=0),"",M34/N34-1) | S34: 0.1146 | T34: 27.6 | U34: =IF(OR(T34="",H34="",H34=0),"",T34*10000000/H34) | V34: Property Management Fee 3.0% of Facility Rentals (below NOI line) | X34: Detailed sec 37 (pdf p.619); Valuation Certificate sec 6; Value Summary sec 4 (pdf p.55-56)
A35: Shirasa Regency Park Private Limited | B35: Karnataka Solar I | C35: Solar | D35: Chitradurga, Karnataka | E35: Nanivala Challakare | G35: Taluk Nanivala Challakare, District: Chitradurga, Karnataka | O35: =IF(OR(M35="",N35="",N35=0),"",M35/N35-1) | S35: 0.1146 | T35: 228.2 | U35: =IF(OR(T35="",H35="",H35=0),"",T35*10000000/H35) | V35: Property Management Fee 3.0% of Facility Rentals (below NOI line) | X35: Detailed sec 38 (pdf p.626); Valuation Certificate sec 6; Value Summary sec 4 (pdf p.55-56)
A36: NABS Datazone Private Limited (the ‘NABS’) | B36: Karnataka Solar - II | C36: Solar | D36: Chitradurga, Karnataka | E36: Nanivala Challakare | G36: Taluk Nanivala Challakare, District: Chitradurga, Karnataka | O36: =IF(OR(M36="",N36="",N36=0),"",M36/N36-1) | S36: 0.1225 | T36: 109.3 | U36: =IF(OR(T36="",H36="",H36=0),"",T36*10000000/H36) | V36: Property Management Fee 3.0% of Facility Rentals (below NOI line) | X36: Detailed sec 39 (pdf p.634); Valuation Certificate sec 6; Value Summary sec 4 (pdf p.55-56)
A37: TOTAL / weighted | H37: =SUM(H4:H36) | I37: =SUM(I4:I36) | M37: =IFERROR(AVERAGE(M4:M36),"") | N37: =IFERROR(AVERAGE(N4:N36),"") | T37: =SUM(T4:T36) | U37: =IFERROR(T37*10000000/H37,"")

Sheet Bagmane
A1: Bagmane - Asset-level detail (valuation 31 Mar 2026 - proforma per RHP; 9 assets)
A3: SPV / Holding entity | B3: Property / Asset | C3: Type | D3: City | E3: Locality / Area | F3: Micro-market (valuer) | G3: Address | H3: Leasable (sq ft) | I3: Leasable (msf) | J3: Completed (msf) | K3: Committed occ. | L3: In-place occ. | M3: Market rent /sqft/mo | N3: In-place rent /sqft/mo | O3: Rent reversion | P3: WALE (yrs) | Q3: Tenants | R3: Cap rate | S3: Discount rate | T3: Market value (INR cr) | U3: Value/sqft (INR) | V3: Mgmt fee (valuation DCF) | W3: Insurance (valuation DCF) | X3: Notes / source
A4: Bagmane Developers Private Limited (HoldCo/BDPL) | B4: Bagmane World Technology Centre (BWTC) | C4: Office | D4: Bengaluru | E4: Outer Ring Road (Mahadevapura) | F4: Outer Ring Road (ORR Southeast) | G4: Ferns City, Mahadevapura Village, Bengaluru, Karnataka, India | H4: 4545298.8 | I4: 4.5 | J4: 4.5 | K4: 0.98 | L4: 0.95 | M4: 103 | N4: 91.7 | O4: =IF(OR(M4="",N4="",N4=0),"",M4/N4-1) | P4: 8.4 | Q4: 19 | R4: 0.08 | S4: 0.12 | T4: 8568.08 | U4: =IF(OR(T4="",H4="",H4=0),"",T4*10000000/H4) | X4: WACC (operational) 11.5%; cap rate 8.0% (terminal). Valuation report occupancy: committed 98.2%, in-place 94.9%. Includes 2 under-construction hotels (607 keys) valued separately. Remaining capex INR 278.1mn; expected completion Q1 FY29. Land 39.3 acres. RHP master table WALE 8.4y. Valuation report pp.628-631.
A5: Bagmane Developers Private Limited (HoldCo/BDPL) | B5: Bagmane Constellation Business Park (BCBP) | C5: Office | D5: Bengaluru | E5: Outer Ring Road (Mahadevapura) | F5: Outer Ring Road (ORR Southeast) | G5: Doddanekundi Village, K.R. Puram Hobli, Bengaluru East Taluk, Bengaluru Urban District, Karnataka 560 048 | H5: 4950438.9 | I5: 4.9 | J5: 5 | K5: 1 | L5: 1 | M5: 105 | N5: 91.5 | O5: =IF(OR(M5="",N5="",N5=0),"",M5/N5-1) | P5: 6 | Q5: 14 | R5: 0.08 | S5: 0.12 | T5: 8924.14 | U5: =IF(OR(T5="",H5="",H5=0),"",T5*10000000/H5) | X5: WACC 11.5%; cap rate 8.0%. Valuation report occupancy: committed 100%, in-place 99.5%. RHP master table leasable 5.0 msf (valuation 4.9 msf / 4,950,438.9 sqft). Amazon key tenant (~2.2 msf). Remaining capex INR 107.4mn. Land 36.4 acres. Valuation report pp.632-636.
A6: Bagmane Rio Private Limited (BRPL) | B6: Bagmane Rio Business Park | C6: Office | D6: Bengaluru | E6: Outer Ring Road (Mahadevapura) | F6: Outer Ring Road (ORR Southeast) | G6: Doddanekundi Village, K.R. Puram Hobli, Bengaluru East Taluk, Bengaluru Urban District, Karnataka | H6: 1105898.6 | I6: 1.1 | J6: 1.1 | K6: 1 | L6: 1 | M6: 115 | N6: 97.8 | O6: =IF(OR(M6="",N6="",N6=0),"",M6/N6-1) | P6: 11 | Q6: 1 | R6: 0.08 | S6: 0.12 | T6: 1773.01 | U6: =IF(OR(T6="",H6="",H6=0),"",T6*10000000/H6) | X6: REIT holds 93% interest; MV of 93% = INR 17,730.1mn, 100% = INR 19,064.7mn. Cap rate 7.75% (single-tenant premium). WACC 11.5%. Single tenant (Google - largest standalone building outside USA). No remaining capex. Land 9.0 acres. Valuation report pp.637-640.
A7: Bagmane Constructions Private Limited (BCPL) - carve-in asset | B7: Luxor @ Bagmane Capital Tech Park | C7: Office | D7: Bengaluru | E7: Outer Ring Road (Mahadevapura) | F7: Outer Ring Road (ORR Southeast) | G7: Doddanekundi Village, Marathahalli Hobli, Bengaluru East Taluk, Bengaluru Urban District, Karnataka 560 048 | H7: 1044731.7 | I7: 1 | J7: 1 | K7: 1 | L7: 0.94 | M7: 110 | N7: 100.3 | O7: =IF(OR(M7="",N7="",N7=0),"",M7/N7-1) | P7: 8.8 | Q7: 6 | R7: 0.08 | S7: 0.12 | T7: 2016.47 | U7: =IF(OR(T7="",H7="",H7=0),"",T7*10000000/H7) | X7: Carve-in asset, 100% owned by BCPL w.e.f. 1 Dec 2025 (previously JD 83.39% BCPL / 16.61% third parties). Cap rate 8.0%; WACC 11.5%. Valuation occupancy: committed 100%, in-place 93.7%. Part of larger 9.0 msf Bagmane Capital Tech Park. Land 50.1 acres. Valuation report pp.641-644.
A8: Bagmane Developers Private Limited (HoldCo/BDPL) | B8: Bagmane Tech Park (BTP) | C8: Office | D8: Bengaluru | E8: Byrasandra (CV Raman Nagar) | F8: SBD City | G8: Byrasandra Village, Krishnarajapuram Hobli, Bengaluru East Taluk, Bengaluru Urban District, Karnataka 560 093 | H8: 4377174.7 | I8: 4.4 | J8: 3.9 | K8: 0.99 | L8: 0.99 | M8: 152 | N8: 143.9 | O8: =IF(OR(M8="",N8="",N8=0),"",M8/N8-1) | P8: 5.7 | Q8: 32 | R8: 0.08 | S8: 0.12 | T8: 11123.9 | U8: =IF(OR(T8="",H8="",H8=0),"",T8*10000000/H8) | X8: Cap rate 7.75% (SBD City premium); WACC operational 11.5%, UC/future 12.75%. Committed & in-place occupancy 98.7% (completed area). Includes 0.5 msf future dev. MV split: completed INR 105,725.5mn + UC/future INR 5,513.5mn = 111,239.0mn. Volvo key tenant. Land 40.6 acres. Valuation report pp.645-648.
A9: Bagmane Developers Private Limited (HoldCo/BDPL) | B9: Bagmane Cosmos Business Park | C9: Office | D9: Bengaluru | E9: Byrasandra (CV Raman Nagar) | F9: SBD City | G9: Bairasandra Village, Marathahalli Hobli, Bengaluru East Taluk, Bengaluru Urban District, Karnataka 560 093 | I9: 3.6 | J9: 1 | K9: 0.94 | L9: 0.68 | M9: 156 | N9: 142.5 | O9: =IF(OR(M9="",N9="",N9=0),"",M9/N9-1) | P9: 12 | Q9: 3 | R9: 0.08 | S9: 0.12 | T9: 6560.84 | U9: =IF(OR(T9="",H9="",H9=0),"",T9*10000000/H9) | X9: Cap rate 7.75% (SBD City premium); WACC operational 11.5%, UC/future 12.75%. Occupancy on completed 1.0 msf: committed 94.2%, in-place 67.8%. 1.0 msf under-construction + 1.5 msf future. MV split: completed INR 26,053.3mn + UC/future INR 39,555.0mn = 65,608.4mn. Texas Instruments key tenant upon completion. Remaining capex incl land INR 514.6mn. Land 22.4 acres. Valuation report pp.649-658.
A10: Bagmane Developers Private Limited (HoldCo/BDPL) | B10: Under Construction Luxury Hotel at Bagmane World Technology Centre | C10: Hotel | D10: Bengaluru | E10: Outer Ring Road (Mahadevapura) | F10: Outer Ring Road (ORR Southeast) | G10: Mahadevapura Village, K.R. Puram Hobli, Bengaluru East Taluk, Bengaluru Urban District, Karnataka 560 048 | O10: =IF(OR(M10="",N10="",N10=0),"",M10/N10-1) | R10: 0.07 | S10: 0.13 | T10: 192.85 | U10: =IF(OR(T10="",H10="",H10=0),"",T10*10000000/H10) | X10: 207 keys, under construction within BWTC. Cap rate 7.14%; WACC (UC/future) 13.00%. Part of 607-key hotel program. Valuation report pp.659-660 (Section 4.7).
A11: Bagmane Developers Private Limited (HoldCo/BDPL) | B11: Under Construction Upscale Hotel at Bagmane World Technology Centre | C11: Hotel | D11: Bengaluru | E11: Outer Ring Road (Mahadevapura) | F11: Outer Ring Road (ORR Southeast) | G11: Mahadevapura Village, K.R. Puram Hobli, Bengaluru East Taluk, Bengaluru Urban District, Karnataka 560 048 | O11: =IF(OR(M11="",N11="",N11=0),"",M11/N11-1) | R11: 0.07 | S11: 0.13 | T11: 342.42 | U11: =IF(OR(T11="",H11="",H11=0),"",T11*10000000/H11) | X11: 400 keys, under construction within BWTC. Cap rate 7.14%; WACC (UC/future) 13.00%. Part of 607-key hotel program. Valuation report pp.660-662 (Section 4.8).
A12: Bagmane Green Power LLP (BGP) | B12: Solar Assets (Chikkodi, Sedam, Yadgir operational; Chitradurga under construction) | C12: Solar | D12: Karnataka (Chikkodi, Sedam, Yadgir, Chitradurga) | E12: Chikkodi | G12: Chikkodi, Sedam, Yadgir and Chitradurga, Karnataka, India | O12: =IF(OR(M12="",N12="",N12=0),"",M12/N12-1) | T12: 761.79 | U12: =IF(OR(T12="",H12="",H12=0),"",T12*10000000/H12) | X12: Held by SPV Bagmane Green Power LLP. WACC operational 11.5%, UC/future 12.75%. Components: Chikkodi 28.0 MW DC = INR 1,613.5mn; Sedam 46.4 MW DC = INR 2,695.0mn; Yadgir 17.5 MW DC = INR 880.2mn (all operational); Chitradurga 72.5 MW DC = INR 2,429.2mn (under construction). Total 164.4 MW DC = INR 7,617.9mn. Supplies renewable power to portfolio. Valuation report pp.663-667 (Section 4.9).
A13: TOTAL / weighted | H13: =SUM(H4:H12) | I13: =SUM(I4:I12) | M13: =IFERROR(AVERAGE(M4:M12),"") | N13: =IFERROR(AVERAGE(N4:N12),"") | T13: =SUM(T4:T12) | U13: =IFERROR(T13*10000000/H13,"")

Sheet Notes & Definitions
A1: Indian REITs - SPV / Asset Register
A3: Purpose | B3: Track every SPV and the property it holds across the six listed Indian REITs, to compare how areas are priced (market vs in-place rent, value per sq ft, cap rate).
A4: Valuation date | B4: 31 March 2026 (independent valuer reports). Bagmane is proforma/combined per its RHP (Trust listed May 2026).
A5: Coverage | B5: 108 assets: Embassy 16, Mindspace 17, Brookfield 13, Nexus 20 (retail), KRT 33, Bagmane 9.
A7: Column | B7: Definition
A8: Locality / Area | B8: Specific neighbourhood (e.g. Saket, Nariman Point, Madhapur, Powai). Where the valuer only gave a broad submarket, the submarket is shown.
A9: Micro-market (valuer) | B9: The independent valuer's submarket designation, verbatim.
A10: Market rent | B10: Valuer's assessed market/marginal rent (warm-shell), INR per sq ft per month.
A11: In-place rent | B11: Current contracted / in-place rent on leased area, INR per sq ft per month. For retail (Nexus) = minimum-guarantee rent.
A12: Rent reversion | B12: Market rent / In-place rent - 1. Positive = under-rented (renewal upside); negative = over-rented.
A13: Value per sq ft | B13: Asset market value / leasable sq ft - the core 'how is this area priced' metric.
A14: Cap rate / Discount rate | B14: Capitalisation rate & WACC adopted by the valuer.
A15: Mgmt fee / Insurance | B15: Assumptions in the valuation DCF. Embassy & KRT disclose per asset; Mindspace, Brookfield, Nexus, Bagmane do not (blank).
A17: Caveats
A18: Tenants | B18: Office valuers usually give only a top-10 tenant table, so counts are blank for Embassy/Brookfield/KRT; Mindspace & Nexus disclose counts.
A19: JV / stake | B19: Values are on a 100% asset basis unless a row's Notes says otherwise (Embassy GolfLinks, Brookfield North portfolio, several Nexus malls held at economic share).
A20: Source | B20: Every figure is from the REIT's independent valuation report (or Bagmane RHP); each row's Notes cites the page(s), and the Property name links to the PDF.
