Workbook

Sheet Comparison
A1: Indian Listed REITs - Comparison Dashboard
A2: Year: | B2: FY2026 | C2: Pick any year (FY2019-FY2026). Consolidated basis. Figures pull live from each REIT sheet (INR crore).
A4: Metric | B4: Unit | C4: Embassy | D4: Mindspace | E4: Brookfield | F4: Nexus (Retail) | G4: Knowledge / KRT | H4: Bagmane*
A5: Revenue from Operations | B5: INR cr | C5: =IFERROR(INDEX(Embassy!$C:$J,9,MATCH($B$2,Embassy!$C$7:$J$7,0)),"") | D5: =IFERROR(INDEX(Mindspace!$C:$J,9,MATCH($B$2,Mindspace!$C$7:$J$7,0)),"") | E5: =IFERROR(INDEX(Brookfield!$C:$J,9,MATCH($B$2,Brookfield!$C$7:$J$7,0)),"") | F5: =IFERROR(INDEX(Nexus!$C:$J,9,MATCH($B$2,Nexus!$C$7:$J$7,0)),"") | G5: =IFERROR(INDEX('Knowledge (KRT)'!$C:$J,9,MATCH($B$2,'Knowledge (KRT)'!$C$7:$J$7,0)),"") | H5: =IFERROR(INDEX(Bagmane!$C:$J,9,MATCH($B$2,Bagmane!$C$7:$J$7,0)),"")
A6: Net Operating Income (NOI) | B6: INR cr | C6: =IFERROR(INDEX(Embassy!$C:$J,13,MATCH($B$2,Embassy!$C$7:$J$7,0)),"") | D6: =IFERROR(INDEX(Mindspace!$C:$J,13,MATCH($B$2,Mindspace!$C$7:$J$7,0)),"") | E6: =IFERROR(INDEX(Brookfield!$C:$J,13,MATCH($B$2,Brookfield!$C$7:$J$7,0)),"") | F6: =IFERROR(INDEX(Nexus!$C:$J,13,MATCH($B$2,Nexus!$C$7:$J$7,0)),"") | G6: =IFERROR(INDEX('Knowledge (KRT)'!$C:$J,13,MATCH($B$2,'Knowledge (KRT)'!$C$7:$J$7,0)),"") | H6: =IFERROR(INDEX(Bagmane!$C:$J,13,MATCH($B$2,Bagmane!$C$7:$J$7,0)),"")
A7: NOI Margin | B7: % | C7: =IFERROR(INDEX(Embassy!$C:$J,14,MATCH($B$2,Embassy!$C$7:$J$7,0)),"") | D7: =IFERROR(INDEX(Mindspace!$C:$J,14,MATCH($B$2,Mindspace!$C$7:$J$7,0)),"") | E7: =IFERROR(INDEX(Brookfield!$C:$J,14,MATCH($B$2,Brookfield!$C$7:$J$7,0)),"") | F7: =IFERROR(INDEX(Nexus!$C:$J,14,MATCH($B$2,Nexus!$C$7:$J$7,0)),"") | G7: =IFERROR(INDEX('Knowledge (KRT)'!$C:$J,14,MATCH($B$2,'Knowledge (KRT)'!$C$7:$J$7,0)),"") | H7: =IFERROR(INDEX(Bagmane!$C:$J,14,MATCH($B$2,Bagmane!$C$7:$J$7,0)),"")
A8: EBITDA | B8: INR cr | C8: =IFERROR(INDEX(Embassy!$C:$J,15,MATCH($B$2,Embassy!$C$7:$J$7,0)),"") | D8: =IFERROR(INDEX(Mindspace!$C:$J,15,MATCH($B$2,Mindspace!$C$7:$J$7,0)),"") | E8: =IFERROR(INDEX(Brookfield!$C:$J,15,MATCH($B$2,Brookfield!$C$7:$J$7,0)),"") | F8: =IFERROR(INDEX(Nexus!$C:$J,15,MATCH($B$2,Nexus!$C$7:$J$7,0)),"") | G8: =IFERROR(INDEX('Knowledge (KRT)'!$C:$J,15,MATCH($B$2,'Knowledge (KRT)'!$C$7:$J$7,0)),"") | H8: =IFERROR(INDEX(Bagmane!$C:$J,15,MATCH($B$2,Bagmane!$C$7:$J$7,0)),"")
A9: NDCF | B9: INR cr | C9: =IFERROR(INDEX(Embassy!$C:$J,23,MATCH($B$2,Embassy!$C$7:$J$7,0)),"") | D9: =IFERROR(INDEX(Mindspace!$C:$J,23,MATCH($B$2,Mindspace!$C$7:$J$7,0)),"") | E9: =IFERROR(INDEX(Brookfield!$C:$J,23,MATCH($B$2,Brookfield!$C$7:$J$7,0)),"") | F9: =IFERROR(INDEX(Nexus!$C:$J,23,MATCH($B$2,Nexus!$C$7:$J$7,0)),"") | G9: =IFERROR(INDEX('Knowledge (KRT)'!$C:$J,23,MATCH($B$2,'Knowledge (KRT)'!$C$7:$J$7,0)),"") | H9: =IFERROR(INDEX(Bagmane!$C:$J,23,MATCH($B$2,Bagmane!$C$7:$J$7,0)),"")
A10: Total Distribution | B10: INR cr | C10: =IFERROR(INDEX(Embassy!$C:$J,24,MATCH($B$2,Embassy!$C$7:$J$7,0)),"") | D10: =IFERROR(INDEX(Mindspace!$C:$J,24,MATCH($B$2,Mindspace!$C$7:$J$7,0)),"") | E10: =IFERROR(INDEX(Brookfield!$C:$J,24,MATCH($B$2,Brookfield!$C$7:$J$7,0)),"") | F10: =IFERROR(INDEX(Nexus!$C:$J,24,MATCH($B$2,Nexus!$C$7:$J$7,0)),"") | G10: =IFERROR(INDEX('Knowledge (KRT)'!$C:$J,24,MATCH($B$2,'Knowledge (KRT)'!$C$7:$J$7,0)),"") | H10: =IFERROR(INDEX(Bagmane!$C:$J,24,MATCH($B$2,Bagmane!$C$7:$J$7,0)),"")
A11: Distribution per Unit (DPU) | B11: INR/unit | C11: =IFERROR(INDEX(Embassy!$C:$J,25,MATCH($B$2,Embassy!$C$7:$J$7,0)),"") | D11: =IFERROR(INDEX(Mindspace!$C:$J,25,MATCH($B$2,Mindspace!$C$7:$J$7,0)),"") | E11: =IFERROR(INDEX(Brookfield!$C:$J,25,MATCH($B$2,Brookfield!$C$7:$J$7,0)),"") | F11: =IFERROR(INDEX(Nexus!$C:$J,25,MATCH($B$2,Nexus!$C$7:$J$7,0)),"") | G11: =IFERROR(INDEX('Knowledge (KRT)'!$C:$J,25,MATCH($B$2,'Knowledge (KRT)'!$C$7:$J$7,0)),"") | H11: =IFERROR(INDEX(Bagmane!$C:$J,25,MATCH($B$2,Bagmane!$C$7:$J$7,0)),"")
A12: Annual Distribution Yield | B12: % | C12: =IFERROR(INDEX(Embassy!$C:$J,39,MATCH($B$2,Embassy!$C$7:$J$7,0)),"") | D12: =IFERROR(INDEX(Mindspace!$C:$J,39,MATCH($B$2,Mindspace!$C$7:$J$7,0)),"") | E12: =IFERROR(INDEX(Brookfield!$C:$J,39,MATCH($B$2,Brookfield!$C$7:$J$7,0)),"") | F12: =IFERROR(INDEX(Nexus!$C:$J,39,MATCH($B$2,Nexus!$C$7:$J$7,0)),"") | G12: =IFERROR(INDEX('Knowledge (KRT)'!$C:$J,39,MATCH($B$2,'Knowledge (KRT)'!$C$7:$J$7,0)),"") | H12: =IFERROR(INDEX(Bagmane!$C:$J,39,MATCH($B$2,Bagmane!$C$7:$J$7,0)),"")
A13: Market Capitalisation | B13: INR cr | C13: =IFERROR(INDEX(Embassy!$C:$J,38,MATCH($B$2,Embassy!$C$7:$J$7,0)),"") | D13: =IFERROR(INDEX(Mindspace!$C:$J,38,MATCH($B$2,Mindspace!$C$7:$J$7,0)),"") | E13: =IFERROR(INDEX(Brookfield!$C:$J,38,MATCH($B$2,Brookfield!$C$7:$J$7,0)),"") | F13: =IFERROR(INDEX(Nexus!$C:$J,38,MATCH($B$2,Nexus!$C$7:$J$7,0)),"") | G13: =IFERROR(INDEX('Knowledge (KRT)'!$C:$J,38,MATCH($B$2,'Knowledge (KRT)'!$C$7:$J$7,0)),"") | H13: =IFERROR(INDEX(Bagmane!$C:$J,38,MATCH($B$2,Bagmane!$C$7:$J$7,0)),"")
A14: GAV / AUM | B14: INR cr | C14: =IFERROR(INDEX(Embassy!$C:$J,28,MATCH($B$2,Embassy!$C$7:$J$7,0)),"") | D14: =IFERROR(INDEX(Mindspace!$C:$J,28,MATCH($B$2,Mindspace!$C$7:$J$7,0)),"") | E14: =IFERROR(INDEX(Brookfield!$C:$J,28,MATCH($B$2,Brookfield!$C$7:$J$7,0)),"") | F14: =IFERROR(INDEX(Nexus!$C:$J,28,MATCH($B$2,Nexus!$C$7:$J$7,0)),"") | G14: =IFERROR(INDEX('Knowledge (KRT)'!$C:$J,28,MATCH($B$2,'Knowledge (KRT)'!$C$7:$J$7,0)),"") | H14: =IFERROR(INDEX(Bagmane!$C:$J,28,MATCH($B$2,Bagmane!$C$7:$J$7,0)),"")
A15: Net Debt | B15: INR cr | C15: =IFERROR(INDEX(Embassy!$C:$J,31,MATCH($B$2,Embassy!$C$7:$J$7,0)),"") | D15: =IFERROR(INDEX(Mindspace!$C:$J,31,MATCH($B$2,Mindspace!$C$7:$J$7,0)),"") | E15: =IFERROR(INDEX(Brookfield!$C:$J,31,MATCH($B$2,Brookfield!$C$7:$J$7,0)),"") | F15: =IFERROR(INDEX(Nexus!$C:$J,31,MATCH($B$2,Nexus!$C$7:$J$7,0)),"") | G15: =IFERROR(INDEX('Knowledge (KRT)'!$C:$J,31,MATCH($B$2,'Knowledge (KRT)'!$C$7:$J$7,0)),"") | H15: =IFERROR(INDEX(Bagmane!$C:$J,31,MATCH($B$2,Bagmane!$C$7:$J$7,0)),"")
A16: Loan-to-Value (LTV) | B16: % | C16: =IFERROR(INDEX(Embassy!$C:$J,33,MATCH($B$2,Embassy!$C$7:$J$7,0)),"") | D16: =IFERROR(INDEX(Mindspace!$C:$J,33,MATCH($B$2,Mindspace!$C$7:$J$7,0)),"") | E16: =IFERROR(INDEX(Brookfield!$C:$J,33,MATCH($B$2,Brookfield!$C$7:$J$7,0)),"") | F16: =IFERROR(INDEX(Nexus!$C:$J,33,MATCH($B$2,Nexus!$C$7:$J$7,0)),"") | G16: =IFERROR(INDEX('Knowledge (KRT)'!$C:$J,33,MATCH($B$2,'Knowledge (KRT)'!$C$7:$J$7,0)),"") | H16: =IFERROR(INDEX(Bagmane!$C:$J,33,MATCH($B$2,Bagmane!$C$7:$J$7,0)),"")
A17: GLA | B17: Msf | C17: =IFERROR(INDEX(Embassy!$C:$J,42,MATCH($B$2,Embassy!$C$7:$J$7,0)),"") | D17: =IFERROR(INDEX(Mindspace!$C:$J,42,MATCH($B$2,Mindspace!$C$7:$J$7,0)),"") | E17: =IFERROR(INDEX(Brookfield!$C:$J,42,MATCH($B$2,Brookfield!$C$7:$J$7,0)),"") | F17: =IFERROR(INDEX(Nexus!$C:$J,42,MATCH($B$2,Nexus!$C$7:$J$7,0)),"") | G17: =IFERROR(INDEX('Knowledge (KRT)'!$C:$J,42,MATCH($B$2,'Knowledge (KRT)'!$C$7:$J$7,0)),"") | H17: =IFERROR(INDEX(Bagmane!$C:$J,42,MATCH($B$2,Bagmane!$C$7:$J$7,0)),"")
A18: Committed Occupancy | B18: % | C18: =IFERROR(INDEX(Embassy!$C:$J,45,MATCH($B$2,Embassy!$C$7:$J$7,0)),"") | D18: =IFERROR(INDEX(Mindspace!$C:$J,45,MATCH($B$2,Mindspace!$C$7:$J$7,0)),"") | E18: =IFERROR(INDEX(Brookfield!$C:$J,45,MATCH($B$2,Brookfield!$C$7:$J$7,0)),"") | F18: =IFERROR(INDEX(Nexus!$C:$J,45,MATCH($B$2,Nexus!$C$7:$J$7,0)),"") | G18: =IFERROR(INDEX('Knowledge (KRT)'!$C:$J,45,MATCH($B$2,'Knowledge (KRT)'!$C$7:$J$7,0)),"") | H18: =IFERROR(INDEX(Bagmane!$C:$J,45,MATCH($B$2,Bagmane!$C$7:$J$7,0)),"")
A19: WALE | B19: years | C19: =IFERROR(INDEX(Embassy!$C:$J,47,MATCH($B$2,Embassy!$C$7:$J$7,0)),"") | D19: =IFERROR(INDEX(Mindspace!$C:$J,47,MATCH($B$2,Mindspace!$C$7:$J$7,0)),"") | E19: =IFERROR(INDEX(Brookfield!$C:$J,47,MATCH($B$2,Brookfield!$C$7:$J$7,0)),"") | F19: =IFERROR(INDEX(Nexus!$C:$J,47,MATCH($B$2,Nexus!$C$7:$J$7,0)),"") | G19: =IFERROR(INDEX('Knowledge (KRT)'!$C:$J,47,MATCH($B$2,'Knowledge (KRT)'!$C$7:$J$7,0)),"") | H19: =IFERROR(INDEX(Bagmane!$C:$J,47,MATCH($B$2,Bagmane!$C$7:$J$7,0)),"")
A21: * Bagmane figures are proforma/combined from its RHP (Trust listed May 2026; pre-operational at FY2026 year-end).
A22: Green/grey figures pull live from the individual REIT sheets - edit data there, not here.

Sheet Embassy
A1: Embassy REIT - Key Financials & Operating Metrics
A2: Sponsor: Embassy Group / Blackstone. All INR figures in INR crore (cr) unless stated. 1 crore = 10 million. FY ends 31 March.
A3: Hover a cell for its Source (report + page + original figure). Grey italic = auto-calculated. YoY% = FY2026 vs FY2025.
C6: CONSOLIDATED | L6: STANDALONE
A7: Metric | B7: Unit | C7: FY2019 | D7: FY2020 | E7: FY2021 | F7: FY2022 | G7: FY2023 | H7: FY2024 | I7: FY2025 | J7: FY2026 | K7: YoY% | L7: FY2019 | M7: FY2020 | N7: FY2021 | O7: FY2022 | P7: FY2023 | Q7: FY2024 | R7: FY2025 | S7: FY2026 | T7: YoY%
A8: INCOME STATEMENT
A9: Revenue from Operations | B9: INR cr | C9: 1877.081 | D9: 2144.922 | E9: 2360.32 | F9: 2962.605 | G9: 3419.543 | H9: 3685.182 | I9: 4038.932 | J9: 4582.356 | K9: =IFERROR((J9-I9)/I9,"") | T9: =IFERROR((S9-R9)/R9,"")
A10: Other Income | B10: INR cr | C10: 153.927 | D10: 99.035 | E10: 118.526 | F10: 126.927 | G10: 144.124 | H10: 203.084 | I10: 142.367 | J10: 93.488 | K10: =IFERROR((J10-I10)/I10,"") | N10: 947.475 | O10: 2113.605 | P10: 2061.986 | Q10: 1905.453 | R10: 1633.517 | S10: 2173.532 | T10: =IFERROR((S10-R10)/R10,"")
A11: Total Income | B11: INR cr | C11: =IF(AND(C9="",C10=""),"",N(C9)+N(C10)) | D11: =IF(AND(D9="",D10=""),"",N(D9)+N(D10)) | E11: =IF(AND(E9="",E10=""),"",N(E9)+N(E10)) | F11: =IF(AND(F9="",F10=""),"",N(F9)+N(F10)) | G11: =IF(AND(G9="",G10=""),"",N(G9)+N(G10)) | H11: =IF(AND(H9="",H10=""),"",N(H9)+N(H10)) | I11: =IF(AND(I9="",I10=""),"",N(I9)+N(I10)) | J11: =IF(AND(J9="",J10=""),"",N(J9)+N(J10)) | K11: =IFERROR((J11-I11)/I11,"") | L11: =IF(AND(L9="",L10=""),"",N(L9)+N(L10)) | M11: =IF(AND(M9="",M10=""),"",N(M9)+N(M10)) | N11: =IF(AND(N9="",N10=""),"",N(N9)+N(N10)) | O11: =IF(AND(O9="",O10=""),"",N(O9)+N(O10)) | P11: =IF(AND(P9="",P10=""),"",N(P9)+N(P10)) | Q11: =IF(AND(Q9="",Q10=""),"",N(Q9)+N(Q10)) | R11: =IF(AND(R9="",R10=""),"",N(R9)+N(R10)) | S11: =IF(AND(S9="",S10=""),"",N(S9)+N(S10)) | T11: =IFERROR((S11-R11)/R11,"")
A12: Property / Operating Expenses | B12: INR cr | C12: 237.656 | D12: 184.284 | E12: 220.801 | F12: 324.331 | G12: 399.633 | H12: 524.895 | I12: 561.366 | J12: 585.526 | K12: =IFERROR((J12-I12)/I12,"") | T12: =IFERROR((S12-R12)/R12,"")
A13: Net Operating Income (NOI) | B13: INR cr | C13: 1574.1 | D13: 1817 | F13: 2491.1 | G13: 2766.28 | H13: 2981.9 | I13: 3283.5 | J13: 3760 | K13: =IFERROR((J13-I13)/I13,"") | T13: =IFERROR((S13-R13)/R13,"")
A14: NOI Margin | B14: % | C14: =IF(OR(C13="",C9="",N(C9)=0),"",C13/C9) | D14: =IF(OR(D13="",D9="",N(D9)=0),"",D13/D9) | E14: =IF(OR(E13="",E9="",N(E9)=0),"",E13/E9) | F14: =IF(OR(F13="",F9="",N(F9)=0),"",F13/F9) | G14: =IF(OR(G13="",G9="",N(G9)=0),"",G13/G9) | H14: =IF(OR(H13="",H9="",N(H9)=0),"",H13/H9) | I14: =IF(OR(I13="",I9="",N(I9)=0),"",I13/I9) | J14: =IF(OR(J13="",J9="",N(J9)=0),"",J13/J9) | L14: =IF(OR(L13="",L9="",N(L9)=0),"",L13/L9) | M14: =IF(OR(M13="",M9="",N(M9)=0),"",M13/M9) | N14: =IF(OR(N13="",N9="",N(N9)=0),"",N13/N9) | O14: =IF(OR(O13="",O9="",N(O9)=0),"",O13/O9) | P14: =IF(OR(P13="",P9="",N(P9)=0),"",P13/P9) | Q14: =IF(OR(Q13="",Q9="",N(Q9)=0),"",Q13/Q9) | R14: =IF(OR(R13="",R9="",N(R9)=0),"",R13/R9) | S14: =IF(OR(S13="",S9="",N(S9)=0),"",S13/S9)
A15: EBITDA | B15: INR cr | C15: 1513.656 | D15: 1764.677 | E15: 1969.321 | F15: 2425.017 | G15: 2688.499 | H15: 2972.411 | I15: 3188.75 | J15: 3602.234 | K15: =IFERROR((J15-I15)/I15,"") | L15: -9.447 | N15: 1189.896 | O15: 2076.255 | P15: 2013.282 | T15: =IFERROR((S15-R15)/R15,"")
A16: EBITDA Margin | B16: % | C16: =IF(OR(C15="",C9="",N(C9)=0),"",C15/C9) | D16: =IF(OR(D15="",D9="",N(D9)=0),"",D15/D9) | E16: =IF(OR(E15="",E9="",N(E9)=0),"",E15/E9) | F16: =IF(OR(F15="",F9="",N(F9)=0),"",F15/F9) | G16: =IF(OR(G15="",G9="",N(G9)=0),"",G15/G9) | H16: =IF(OR(H15="",H9="",N(H9)=0),"",H15/H9) | I16: =IF(OR(I15="",I9="",N(I9)=0),"",I15/I9) | J16: =IF(OR(J15="",J9="",N(J9)=0),"",J15/J9) | L16: =IF(OR(L15="",L9="",N(L9)=0),"",L15/L9) | M16: =IF(OR(M15="",M9="",N(M9)=0),"",M15/M9) | N16: =IF(OR(N15="",N9="",N(N9)=0),"",N15/N9) | O16: =IF(OR(O15="",O9="",N(O9)=0),"",O15/O9) | P16: =IF(OR(P15="",P9="",N(P9)=0),"",P15/P9) | Q16: =IF(OR(Q15="",Q9="",N(Q9)=0),"",Q15/Q9) | R16: =IF(OR(R15="",R9="",N(R9)=0),"",R15/R9) | S16: =IF(OR(S15="",S9="",N(S9)=0),"",S15/S9)
A17: Finance Costs | B17: INR cr | C17: 705.981 | D17: 380.354 | E17: 645.289 | F17: 828.528 | G17: 976.063 | H17: 1087.235 | I17: 1328.625 | J17: 1495.042 | K17: =IFERROR((J17-I17)/I17,"") | L17: 0 | N17: 469.865 | O17: 646.23 | P17: 601.763 | Q17: 720.717 | R17: 652.053 | S17: 810.413 | T17: =IFERROR((S17-R17)/R17,"")
A18: Depreciation & Amortisation | B18: INR cr | C18: 356.319 | D18: 528.124 | E18: 570.697 | F18: 796.463 | G18: 1128.416 | H18: 968.989 | I18: 1141.515 | J18: 1265.785 | K18: =IFERROR((J18-I18)/I18,"") | T18: =IFERROR((S18-R18)/R18,"")
A19: Profit Before Tax (PBT) | B19: INR cr | C19: 566.509 | D19: 795.534 | E19: 753.887 | F19: 896.24 | G19: 661.77 | H19: 1089.073 | I19: 193.042 | J19: 1133.571 | K19: =IFERROR((J19-I19)/I19,"") | L19: -9.447 | N19: 451.22 | O19: 1344.277 | P19: 1282.007 | Q19: 1208.576 | R19: 631.4 | S19: 1314.927 | T19: =IFERROR((S19-R19)/R19,"")
A20: Profit After Tax (PAT) | B20: INR cr | C20: 365.329 | D20: 765.534 | E20: 698.353 | F20: 888.385 | G20: 505.958 | H20: 964.028 | I20: 1624.436 | J20: 338.545 | K20: =IFERROR((J20-I20)/I20,"") | L20: -9.447 | N20: 447.442 | O20: 1339.742 | P20: 1279.148 | Q20: 1206.824 | R20: 631.152 | S20: 1313.495 | T20: =IFERROR((S20-R20)/R20,"")
A21: PAT Margin | B21: % | C21: =IF(OR(C20="",C9="",N(C9)=0),"",C20/C9) | D21: =IF(OR(D20="",D9="",N(D9)=0),"",D20/D9) | E21: =IF(OR(E20="",E9="",N(E9)=0),"",E20/E9) | F21: =IF(OR(F20="",F9="",N(F9)=0),"",F20/F9) | G21: =IF(OR(G20="",G9="",N(G9)=0),"",G20/G9) | H21: =IF(OR(H20="",H9="",N(H9)=0),"",H20/H9) | I21: =IF(OR(I20="",I9="",N(I9)=0),"",I20/I9) | J21: =IF(OR(J20="",J9="",N(J9)=0),"",J20/J9) | L21: =IF(OR(L20="",L9="",N(L9)=0),"",L20/L9) | M21: =IF(OR(M20="",M9="",N(M9)=0),"",M20/M9) | N21: =IF(OR(N20="",N9="",N(N9)=0),"",N20/N9) | O21: =IF(OR(O20="",O9="",N(O9)=0),"",O20/O9) | P21: =IF(OR(P20="",P9="",N(P9)=0),"",P20/P9) | Q21: =IF(OR(Q20="",Q9="",N(Q9)=0),"",Q20/Q9) | R21: =IF(OR(R20="",R9="",N(R9)=0),"",R20/R9) | S21: =IF(OR(S20="",S9="",N(S9)=0),"",S20/S9)
A22: DISTRIBUTIONS & CASH FLOW
A23: Net Distributable Cash Flow (NDCF) | B23: INR cr | D23: 1886.592 | E23: 1835.62 | F23: 2063.819 | G23: 2060.819 | H23: 2024.665 | I23: 2184.553 | J23: 2400.831 | K23: =IFERROR((J23-I23)/I23,"") | L23: n/a | M23: n/a | N23: n/a | O23: n/a | P23: n/a | Q23: n/a | R23: n/a | S23: n/a | T23: n/a
A24: Total Distribution | B24: INR cr | D24: 1882.092 | E24: 1836.409 | F24: 2062.617 | G24: 2057.877 | H24: 2021.858 | I24: 2181.103 | J24: 2396.275 | K24: =IFERROR((J24-I24)/I24,"") | L24: n/a | M24: n/a | N24: n/a | O24: n/a | P24: n/a | Q24: n/a | R24: n/a | S24: n/a | T24: n/a
A25: Distribution per Unit (DPU) | B25: INR/unit | D25: 24.39 | E25: 21.48 | F25: 21.76 | G25: 21.71 | H25: 21.33 | I25: 23.01 | J25: 25.28 | K25: =IFERROR((J25-I25)/I25,"") | L25: n/a | M25: n/a | N25: n/a | O25: n/a | P25: n/a | Q25: n/a | R25: n/a | S25: n/a | T25: n/a
A26: NDCF Payout Ratio | B26: % | C26: =IF(OR(C24="",C23="",N(C23)=0),"",C24/C23) | D26: =IF(OR(D24="",D23="",N(D23)=0),"",D24/D23) | E26: =IF(OR(E24="",E23="",N(E23)=0),"",E24/E23) | F26: =IF(OR(F24="",F23="",N(F23)=0),"",F24/F23) | G26: =IF(OR(G24="",G23="",N(G23)=0),"",G24/G23) | H26: =IF(OR(H24="",H23="",N(H23)=0),"",H24/H23) | I26: =IF(OR(I24="",I23="",N(I23)=0),"",I24/I23) | J26: =IF(OR(J24="",J23="",N(J23)=0),"",J24/J23) | L26: n/a | M26: n/a | N26: n/a | O26: n/a | P26: n/a | Q26: n/a | R26: n/a | S26: n/a | T26: n/a
A27: BALANCE SHEET & LEVERAGE
A28: Gross Asset Value (GAV) / AUM | B28: INR cr | C28: 31612.4 | D28: 32974.625 | E28: 46605.125 | F28: 49007.8 | G28: 51414.114 | H28: 54911.478 | I28: 60567.286 | J28: 69943.737 | K28: =IFERROR((J28-I28)/I28,"") | L28: n/a | M28: n/a | N28: n/a | O28: n/a | P28: n/a | Q28: n/a | R28: n/a | S28: n/a | T28: n/a
A29: Gross Debt | B29: INR cr | C29: 7124.565 | D29: 5617.051 | E29: 10622.3 | F29: 12101.352 | G29: 14805.496 | H29: 16807.953 | I29: 19807.304 | J29: 22384.789 | K29: =IFERROR((J29-I29)/I29,"") | L29: 0 | N29: 8331.91 | O29: 7449.133 | P29: 9465.781 | Q29: 9144.66 | R29: 8064.714 | S29: 12114.256 | T29: =IFERROR((S29-R29)/R29,"")
A30: Cash & Cash Equivalents | B30: INR cr | C30: 4961.271 | D30: 324.916 | E30: 917.478 | F30: 588.449 | G30: 817.348 | H30: 1026.847 | I30: 676.586 | J30: 980.376 | K30: =IFERROR((J30-I30)/I30,"") | L30: 4281.853 | N30: 717.126 | O30: 520.047 | P30: 528.015 | Q30: 518.712 | R30: 0.966 | S30: 153.643 | T30: =IFERROR((S30-R30)/R30,"")
A31: Net Debt | B31: INR cr | C31: =IF(C29="","",C29-N(C30)) | D31: =IF(D29="","",D29-N(D30)) | E31: =IF(E29="","",E29-N(E30)) | F31: =IF(F29="","",F29-N(F30)) | G31: =IF(G29="","",G29-N(G30)) | H31: =IF(H29="","",H29-N(H30)) | I31: =IF(I29="","",I29-N(I30)) | J31: =IF(J29="","",J29-N(J30)) | K31: =IFERROR((J31-I31)/I31,"") | L31: =IF(L29="","",L29-N(L30)) | M31: =IF(M29="","",M29-N(M30)) | N31: =IF(N29="","",N29-N(N30)) | O31: =IF(O29="","",O29-N(O30)) | P31: =IF(P29="","",P29-N(P30)) | Q31: =IF(Q29="","",Q29-N(Q30)) | R31: =IF(R29="","",R29-N(R30)) | S31: =IF(S29="","",S29-N(S30)) | T31: =IFERROR((S31-R31)/R31,"")
A32: Net Worth / Unitholders Equity | B32: INR cr | C32: 22894.479 | D32: 22317.784 | E32: 27093.067 | F32: 25886.69 | G32: 24368.298 | H32: 23274.175 | I32: 22761.16 | J32: 20780.179 | K32: =IFERROR((J32-I32)/I32,"") | L32: 22894.479 | N32: 26557.922 | O32: 25802.819 | P32: 25057.266 | Q32: 24205.265 | R32: 22698.917 | S32: 21693.862 | T32: =IFERROR((S32-R32)/R32,"")
A33: Loan-to-Value (LTV) | B33: % | C33: =IF(OR(C31="",C28="",N(C28)=0),"",C31/C28) | D33: =IF(OR(D31="",D28="",N(D28)=0),"",D31/D28) | E33: =IF(OR(E31="",E28="",N(E28)=0),"",E31/E28) | F33: =IF(OR(F31="",F28="",N(F28)=0),"",F31/F28) | G33: =IF(OR(G31="",G28="",N(G28)=0),"",G31/G28) | H33: =IF(OR(H31="",H28="",N(H28)=0),"",H31/H28) | I33: =IF(OR(I31="",I28="",N(I28)=0),"",I31/I28) | J33: =IF(OR(J31="",J28="",N(J28)=0),"",J31/J28) | L33: =IF(OR(L31="",L28="",N(L28)=0),"",L31/L28) | M33: =IF(OR(M31="",M28="",N(M28)=0),"",M31/M28) | N33: =IF(OR(N31="",N28="",N(N28)=0),"",N31/N28) | O33: =IF(OR(O31="",O28="",N(O28)=0),"",O31/O28) | P33: =IF(OR(P31="",P28="",N(P28)=0),"",P31/P28) | Q33: =IF(OR(Q31="",Q28="",N(Q28)=0),"",Q31/Q28) | R33: =IF(OR(R31="",R28="",N(R28)=0),"",R31/R28) | S33: =IF(OR(S31="",S28="",N(S28)=0),"",S31/S28)
A34: NAV per Unit | B34: INR/unit | C34: 362 | D34: 374.64 | E34: 387.54 | F34: 393.9 | G34: 394.88 | H34: 401.59 | I34: 423.22 | J34: 491.62 | K34: =IFERROR((J34-I34)/I34,"") | L34: n/a | M34: n/a | N34: n/a | O34: n/a | P34: n/a | Q34: n/a | R34: n/a | S34: n/a | T34: n/a
A35: MARKET DATA
A36: Units Outstanding | B36: mn units | C36: 771.67 | D36: 771.67 | E36: 947.89 | F36: 947.89 | G36: 947.89 | H36: 947.89 | I36: 947.89 | J36: 947.89 | K36: =IFERROR((J36-I36)/I36,"") | L36: n/a | M36: n/a | N36: n/a | O36: n/a | P36: n/a | Q36: n/a | R36: n/a | S36: n/a | T36: n/a
A37: Unit Price (period-end) | B37: INR/unit | E37: 325.45 | F37: 370.11 | G37: 312.6 | H37: 369.61 | I37: 365.49 | J37: 420.3 | K37: =IFERROR((J37-I37)/I37,"") | L37: n/a | M37: n/a | N37: n/a | O37: n/a | P37: n/a | Q37: n/a | R37: n/a | S37: n/a | T37: n/a
A38: Market Capitalisation | B38: INR cr | C38: =IF(OR(C36="",C37=""),"",C36*C37/10) | D38: =IF(OR(D36="",D37=""),"",D36*D37/10) | E38: =IF(OR(E36="",E37=""),"",E36*E37/10) | F38: =IF(OR(F36="",F37=""),"",F36*F37/10) | G38: =IF(OR(G36="",G37=""),"",G36*G37/10) | H38: =IF(OR(H36="",H37=""),"",H36*H37/10) | I38: =IF(OR(I36="",I37=""),"",I36*I37/10) | J38: =IF(OR(J36="",J37=""),"",J36*J37/10) | K38: =IFERROR((J38-I38)/I38,"") | L38: n/a | M38: n/a | N38: n/a | O38: n/a | P38: n/a | Q38: n/a | R38: n/a | S38: n/a | T38: n/a
A39: Annual Distribution Yield | B39: % | C39: =IF(OR(C25="",C37="",N(C37)=0),"",C25/C37) | D39: =IF(OR(D25="",D37="",N(D37)=0),"",D25/D37) | E39: =IF(OR(E25="",E37="",N(E37)=0),"",E25/E37) | F39: =IF(OR(F25="",F37="",N(F37)=0),"",F25/F37) | G39: =IF(OR(G25="",G37="",N(G37)=0),"",G25/G37) | H39: =IF(OR(H25="",H37="",N(H37)=0),"",H25/H37) | I39: =IF(OR(I25="",I37="",N(I37)=0),"",I25/I37) | J39: =IF(OR(J25="",J37="",N(J37)=0),"",J25/J37) | L39: n/a | M39: n/a | N39: n/a | O39: n/a | P39: n/a | Q39: n/a | R39: n/a | S39: n/a | T39: n/a
A40: Cost of Debt | B40: % | D40: 0.095 | E40: 0.0781 | F40: 0.067 | G40: 0.072 | H40: 0.078 | I40: 0.079 | J40: 0.0725 | L40: n/a | M40: n/a | N40: n/a | O40: n/a | P40: n/a | Q40: n/a | R40: n/a | S40: n/a | T40: n/a
A41: PORTFOLIO & OPERATING METRICS (consolidated)
A42: Total Leasable Area (GLA) | B42: Msf | C42: 32.7 | D42: 33.3 | E42: 42.4 | F42: 42.8 | G42: 45 | H42: 45.4 | I42: 51.1 | J42: 52.5 | K42: =IFERROR((J42-I42)/I42,"") | L42: n/a | M42: n/a | N42: n/a | O42: n/a | P42: n/a | Q42: n/a | R42: n/a | S42: n/a | T42: n/a
A43: Operational Area | B43: Msf | C43: 24.8 | D43: 26.2 | E43: 32.3 | F43: 33.8 | G43: 34.3 | H43: 36.5 | I43: 40.3 | J43: 43.4 | K43: =IFERROR((J43-I43)/I43,"") | L43: n/a | M43: n/a | N43: n/a | O43: n/a | P43: n/a | Q43: n/a | R43: n/a | S43: n/a | T43: n/a
A44: Under Construction + Future Development | B44: Msf | C44: 7.9 | D44: 7.1 | E44: 10.1 | F44: 9 | G44: 10.7 | H44: 8.9 | I44: 10.9 | J44: 9.1 | K44: =IFERROR((J44-I44)/I44,"") | L44: n/a | M44: n/a | N44: n/a | O44: n/a | P44: n/a | Q44: n/a | R44: n/a | S44: n/a | T44: n/a
A45: Committed Occupancy | B45: % | J45: 0.94 | L45: n/a | M45: n/a | N45: n/a | O45: n/a | P45: n/a | Q45: n/a | R45: n/a | S45: n/a | T45: n/a
A46: In-place / Physical Occupancy | B46: % | C46: 0.943 | D46: 0.928 | E46: 0.889 | F46: 0.871 | G46: 0.86 | H46: 0.85 | I46: 0.87 | J46: 0.9 | L46: n/a | M46: n/a | N46: n/a | O46: n/a | P46: n/a | Q46: n/a | R46: n/a | S46: n/a | T46: n/a
A47: WALE | B47: years | C47: 7 | D47: 7 | E47: 7 | F47: 7 | G47: 6.6 | H47: 6.8 | I47: 8.4 | J47: 8.5 | K47: =IFERROR((J47-I47)/I47,"") | L47: n/a | M47: n/a | N47: n/a | O47: n/a | P47: n/a | Q47: n/a | R47: n/a | S47: n/a | T47: n/a
A48: Number of Tenants | B48: count | C48: 160 | D48: 160 | E48: 190 | F48: 200 | G48: 230 | H48: 255 | I48: 272 | J48: 274 | K48: =IFERROR((J48-I48)/I48,"") | L48: n/a | M48: n/a | N48: n/a | O48: n/a | P48: n/a | Q48: n/a | R48: n/a | S48: n/a | T48: n/a
A49: In-place Rent | B49: INR psf/mo | C49: 63 | D49: 68 | E49: 71 | F49: 75 | G49: 80 | H49: 87 | I49: 92 | J49: 95 | K49: =IFERROR((J49-I49)/I49,"") | L49: n/a | M49: n/a | N49: n/a | O49: n/a | P49: n/a | Q49: n/a | R49: n/a | S49: n/a | T49: n/a
A52: DEBT & NDCF / DISTRIBUTION DETAIL (consolidated; INR cr unless noted)
A53: Metric | B53: Unit | C53: FY2019 | D53: FY2020 | E53: FY2021 | F53: FY2022 | G53: FY2023 | H53: FY2024 | I53: FY2025 | J53: FY2026
A54: Distribution composition (NDCF -> unitholders) | V54: Embassy REIT
A55: Net Distributable Cash Flow (NDCF) | B55: INR cr | C55: =IF(N(C23)=0,IF(C23="","",C23),C23) | D55: =IF(N(D23)=0,IF(D23="","",D23),D23) | E55: =IF(N(E23)=0,IF(E23="","",E23),E23) | F55: =IF(N(F23)=0,IF(F23="","",F23),F23) | G55: =IF(N(G23)=0,IF(G23="","",G23),G23) | H55: =IF(N(H23)=0,IF(H23="","",H23),H23) | I55: =IF(N(I23)=0,IF(I23="","",I23),I23) | J55: =IF(N(J23)=0,IF(J23="","",J23),J23)
A56: Total Distribution | B56: INR cr | C56: =IF(N(C24)=0,IF(C24="","",C24),C24) | D56: =IF(N(D24)=0,IF(D24="","",D24),D24) | E56: =IF(N(E24)=0,IF(E24="","",E24),E24) | F56: =IF(N(F24)=0,IF(F24="","",F24),F24) | G56: =IF(N(G24)=0,IF(G24="","",G24),G24) | H56: =IF(N(H24)=0,IF(H24="","",H24),H24) | I56: =IF(N(I24)=0,IF(I24="","",I24),I24) | J56: =IF(N(J24)=0,IF(J24="","",J24),J24) | S56: =A7 | T56: =B7 | U56: =C7 | V56: =D7 | W56: =E7 | X56: =F7 | Y56: =G7 | Z56: =H7 | ... AB56: =J7
A57: of which: Interest | B57: INR cr | S57: =A46 | T57: =B46 | U57: =C46*10 | V57: =D46*10 | W57: =E46*10 | X57: =F46*10 | Y57: =G46*10 | Z57: =H46*10 | AA57: =I46*10 | AB57: =J46*10
A58: of which: Dividend | B58: INR cr | S58: =A47 | T58: =B47 | U58: =C47 | V58: =D47 | W58: =E47 | X58: =F47 | Y58: =G47 | Z58: =H47 | ... AB58: =J47
A59: of which: Return of capital (SPV/shareholder-loan repayment) | B59: INR cr
A60: of which: Other | B60: INR cr
A61: Return-of-capital % of distribution | B61: % | C61: =IF(OR(C59="",C56="",N(C56)=0),"",C59/C56) | D61: =IF(OR(D59="",D56="",N(D56)=0),"",D59/D56) | E61: =IF(OR(E59="",E56="",N(E56)=0),"",E59/E56) | F61: =IF(OR(F59="",F56="",N(F56)=0),"",F59/F56) | G61: =IF(OR(G59="",G56="",N(G56)=0),"",G59/G56) | H61: =IF(OR(H59="",H56="",N(H56)=0),"",H59/H56) | I61: =IF(OR(I59="",I56="",N(I56)=0),"",I59/I56) | J61: =IF(OR(J59="",J56="",N(J56)=0),"",J59/J56)
A62: Distribution per Unit (DPU) | B62: INR/unit | C62: =IF(N(C25)=0,IF(C25="","",C25),C25) | D62: =IF(N(D25)=0,IF(D25="","",D25),D25) | E62: =IF(N(E25)=0,IF(E25="","",E25),E25) | F62: =IF(N(F25)=0,IF(F25="","",F25),F25) | G62: =IF(N(G25)=0,IF(G25="","",G25),G25) | H62: =IF(N(H25)=0,IF(H25="","",H25),H25) | I62: =IF(N(I25)=0,IF(I25="","",I25),I25) | J62: =IF(N(J25)=0,IF(J25="","",J25),J25)
A63: DPU: Interest | B63: INR/unit | J63: 0.14
A64: DPU: Dividend | B64: INR/unit | J64: 1.39
A65: DPU: Return of capital | B65: INR/unit | J65: 4.97
A66: DPU: Other | B66: INR/unit
A67: Debt & leverage profile
A68: Gross Debt - external (banks/NCDs/LRD) | B68: INR cr | C68: =IF(C29="","",C29) | D68: =IF(D29="","",D29) | E68: =IF(E29="","",E29) | F68: =IF(F29="","",F29) | G68: =IF(G29="","",G29) | H68: 16807.953 | I68: 19807.304 | J68: 22384.789
A69: Shareholder / unitholder loans (Trust -> SPVs) | B69: INR cr | G69: 9386.084 | H69: 8288.92 | I69: 6450.427 | J69: 8797.061
A70: Cash & Cash Equivalents | B70: INR cr | C70: =IF(N(C30)=0,IF(C30="","",C30),C30) | D70: =IF(N(D30)=0,IF(D30="","",D30),D30) | E70: =IF(N(E30)=0,IF(E30="","",E30),E30) | F70: =IF(N(F30)=0,IF(F30="","",F30),F30) | G70: =IF(N(G30)=0,IF(G30="","",G30),G30) | H70: =IF(N(H30)=0,IF(H30="","",H30),H30) | I70: =IF(N(I30)=0,IF(I30="","",I30),I30) | J70: =IF(N(J30)=0,IF(J30="","",J30),J30)
A71: Net Debt | B71: INR cr | C71: =IF(N(C31)=0,IF(C31="","",C31),C31) | D71: =IF(N(D31)=0,IF(D31="","",D31),D31) | E71: =IF(N(E31)=0,IF(E31="","",E31),E31) | F71: =IF(N(F31)=0,IF(F31="","",F31),F31) | G71: =IF(N(G31)=0,IF(G31="","",G31),G31) | H71: =IF(N(H31)=0,IF(H31="","",H31),H31) | I71: =IF(N(I31)=0,IF(I31="","",I31),I31) | J71: =IF(N(J31)=0,IF(J31="","",J31),J31)
A72: Gross Asset Value (GAV) | B72: INR cr | C72: =IF(N(C28)=0,IF(C28="","",C28),C28) | D72: =IF(N(D28)=0,IF(D28="","",D28),D28) | E72: =IF(N(E28)=0,IF(E28="","",E28),E28) | F72: =IF(N(F28)=0,IF(F28="","",F28),F28) | G72: =IF(N(G28)=0,IF(G28="","",G28),G28) | H72: =IF(N(H28)=0,IF(H28="","",H28),H28) | I72: =IF(N(I28)=0,IF(I28="","",I28),I28) | J72: =IF(N(J28)=0,IF(J28="","",J28),J28)
A73: Loan-to-Value (LTV) | B73: % | C73: =IF(N(C33)=0,IF(C33="","",C33),C33) | D73: =IF(N(D33)=0,IF(D33="","",D33),D33) | E73: =IF(N(E33)=0,IF(E33="","",E33),E33) | F73: =IF(N(F33)=0,IF(F33="","",F33),F33) | G73: =IF(N(G33)=0,IF(G33="","",G33),G33) | H73: =IF(N(H33)=0,IF(H33="","",H33),H33) | I73: =IF(N(I33)=0,IF(I33="","",I33),I33) | J73: =IF(N(J33)=0,IF(J33="","",J33),J33)
A74: Cost of Debt (wtd avg) | B74: % | C74: =IF(N(C40)=0,IF(C40="","",C40),C40) | D74: =IF(N(D40)=0,IF(D40="","",D40),D40) | E74: =IF(N(E40)=0,IF(E40="","",E40),E40) | F74: =IF(N(F40)=0,IF(F40="","",F40),F40) | G74: =IF(N(G40)=0,IF(G40="","",G40),G40) | H74: =IF(N(H40)=0,IF(H40="","",H40),H40) | I74: =IF(N(I40)=0,IF(I40="","",I40),I40) | J74: =IF(N(J40)=0,IF(J40="","",J40),J40)
A75: % Floating rate | B75: % | H75: 0.4 | I75: 0.49
A76: Wtd-avg debt maturity | B76: years | H76: 4 | I76: 4
A77: Undrawn debt headroom | B77: INR cr | H77: 900 | I77: 10000
A78: Interest cover (NOI / Finance cost) | B78: x | C78: =IF(OR(C13="",N(C17)=0),"",C13/C17) | D78: =IF(OR(D13="",N(D17)=0),"",D13/D17) | E78: =IF(OR(E13="",N(E17)=0),"",E13/E17) | F78: =IF(OR(F13="",N(F17)=0),"",F13/F17) | G78: =IF(OR(G13="",N(G17)=0),"",G13/G17) | H78: =IF(OR(H13="",N(H17)=0),"",H13/H17) | I78: =IF(OR(I13="",N(I17)=0),"",I13/I17) | J78: =IF(OR(J13="",N(J17)=0),"",J13/J17)
A80: Distribution-component split is shown where the issuer disclosed it (often per-unit for Q4 only in older years); blanks = not separately disclosed.

Sheet Mindspace
A1: Mindspace REIT - Key Financials & Operating Metrics
A2: Sponsor: K Raheja Corp. All INR figures in INR crore (cr) unless stated. 1 crore = 10 million. FY ends 31 March.
A3: Hover a cell for its Source (report + page + original figure). Grey italic = auto-calculated. YoY% = FY2026 vs FY2025.
C6: CONSOLIDATED | L6: STANDALONE
A7: Metric | B7: Unit | C7: FY2019 | D7: FY2020 | E7: FY2021 | F7: FY2022 | G7: FY2023 | H7: FY2024 | I7: FY2025 | J7: FY2026 | K7: YoY% | L7: FY2019 | M7: FY2020 | N7: FY2021 | O7: FY2022 | P7: FY2023 | Q7: FY2024 | R7: FY2025 | S7: FY2026 | T7: YoY%
A8: INCOME STATEMENT
A9: Revenue from Operations | B9: INR cr | E9: 1138.1 | F9: 1750.1 | H9: 2429.2 | I9: 2596.109 | J9: 3216.346 | K9: =IFERROR((J9-I9)/I9,"") | T9: =IFERROR((S9-R9)/R9,"")
A10: Other Income | B10: INR cr | E10: 5.1 | F10: 8.8 | H10: 14.501 | I10: 15.158 | J10: 76.741 | K10: =IFERROR((J10-I10)/I10,"") | N10: 1.2 | O10: 1.1 | Q10: 0.69 | R10: 0.464 | S10: 5.335 | T10: =IFERROR((S10-R10)/R10,"")
A11: Total Income | B11: INR cr | C11: =IF(AND(C9="",C10=""),"",N(C9)+N(C10)) | D11: =IF(AND(D9="",D10=""),"",N(D9)+N(D10)) | E11: =IF(AND(E9="",E10=""),"",N(E9)+N(E10)) | F11: =IF(AND(F9="",F10=""),"",N(F9)+N(F10)) | G11: =IF(AND(G9="",G10=""),"",N(G9)+N(G10)) | H11: =IF(AND(H9="",H10=""),"",N(H9)+N(H10)) | I11: =IF(AND(I9="",I10=""),"",N(I9)+N(I10)) | J11: =IF(AND(J9="",J10=""),"",N(J9)+N(J10)) | K11: =IFERROR((J11-I11)/I11,"") | L11: =IF(AND(L9="",L10=""),"",N(L9)+N(L10)) | M11: =IF(AND(M9="",M10=""),"",N(M9)+N(M10)) | N11: =IF(AND(N9="",N10=""),"",N(N9)+N(N10)) | O11: =IF(AND(O9="",O10=""),"",N(O9)+N(O10)) | P11: =IF(AND(P9="",P10=""),"",N(P9)+N(P10)) | Q11: =IF(AND(Q9="",Q10=""),"",N(Q9)+N(Q10)) | R11: =IF(AND(R9="",R10=""),"",N(R9)+N(R10)) | S11: =IF(AND(S9="",S10=""),"",N(S9)+N(S10)) | T11: =IFERROR((S11-R11)/R11,"")
A12: Property / Operating Expenses | B12: INR cr | K12: =IFERROR((J12-I12)/I12,"") | T12: =IFERROR((S12-R12)/R12,"")
A13: Net Operating Income (NOI) | B13: INR cr | E13: 1374.1 | F13: 1486.4 | H13: 1895.9 | I13: 2061.6 | J13: 2663.6 | K13: =IFERROR((J13-I13)/I13,"") | T13: =IFERROR((S13-R13)/R13,"")
A14: NOI Margin | B14: % | C14: =IF(OR(C13="",C9="",N(C9)=0),"",C13/C9) | D14: =IF(OR(D13="",D9="",N(D9)=0),"",D13/D9) | E14: =IF(OR(E13="",E9="",N(E9)=0),"",E13/E9) | F14: =IF(OR(F13="",F9="",N(F9)=0),"",F13/F9) | G14: =IF(OR(G13="",G9="",N(G9)=0),"",G13/G9) | H14: =IF(OR(H13="",H9="",N(H9)=0),"",H13/H9) | I14: =IF(OR(I13="",I9="",N(I9)=0),"",I13/I9) | J14: =IF(OR(J13="",J9="",N(J9)=0),"",J13/J9) | L14: =IF(OR(L13="",L9="",N(L9)=0),"",L13/L9) | M14: =IF(OR(M13="",M9="",N(M9)=0),"",M13/M9) | N14: =IF(OR(N13="",N9="",N(N9)=0),"",N13/N9) | O14: =IF(OR(O13="",O9="",N(O9)=0),"",O13/O9) | P14: =IF(OR(P13="",P9="",N(P9)=0),"",P13/P9) | Q14: =IF(OR(Q13="",Q9="",N(Q9)=0),"",Q13/Q9) | R14: =IF(OR(R13="",R9="",N(R9)=0),"",R13/R9) | S14: =IF(OR(S13="",S9="",N(S9)=0),"",S13/S9)
A15: EBITDA | B15: INR cr | E15: 846.6 | F15: 1384.3 | H15: 1798.821 | I15: 1968.161 | J15: 2514.56 | K15: =IFERROR((J15-I15)/I15,"") | N15: 606.9 | O15: 1190.3 | T15: =IFERROR((S15-R15)/R15,"")
A16: EBITDA Margin | B16: % | C16: =IF(OR(C15="",C9="",N(C9)=0),"",C15/C9) | D16: =IF(OR(D15="",D9="",N(D9)=0),"",D15/D9) | E16: =IF(OR(E15="",E9="",N(E9)=0),"",E15/E9) | F16: =IF(OR(F15="",F9="",N(F9)=0),"",F15/F9) | G16: =IF(OR(G15="",G9="",N(G9)=0),"",G15/G9) | H16: =IF(OR(H15="",H9="",N(H9)=0),"",H15/H9) | I16: =IF(OR(I15="",I9="",N(I9)=0),"",I15/I9) | J16: =IF(OR(J15="",J9="",N(J9)=0),"",J15/J9) | L16: =IF(OR(L15="",L9="",N(L9)=0),"",L15/L9) | M16: =IF(OR(M15="",M9="",N(M9)=0),"",M15/M9) | N16: =IF(OR(N15="",N9="",N(N9)=0),"",N15/N9) | O16: =IF(OR(O15="",O9="",N(O9)=0),"",O15/O9) | P16: =IF(OR(P15="",P9="",N(P9)=0),"",P15/P9) | Q16: =IF(OR(Q15="",Q9="",N(Q9)=0),"",Q15/Q9) | R16: =IF(OR(R15="",R9="",N(R9)=0),"",R15/R9) | S16: =IF(OR(S15="",S9="",N(S9)=0),"",S15/S9)
A17: Finance Costs | B17: INR cr | E17: 170.7 | F17: 264.4 | H17: 456.632 | I17: 557.273 | J17: 836.401 | K17: =IFERROR((J17-I17)/I17,"") | N17: 23 | O17: 86.7 | Q17: 222.151 | R17: 348.033 | S17: 529.302 | T17: =IFERROR((S17-R17)/R17,"")
A18: Depreciation & Amortisation | B18: INR cr | E18: 196.4 | F18: 328.9 | H18: 382.654 | I18: 405.984 | J18: 478.98 | K18: =IFERROR((J18-I18)/I18,"") | N18: 0 | O18: 0 | T18: =IFERROR((S18-R18)/R18,"")
A19: Profit Before Tax (PBT) | B19: INR cr | E19: 479.4 | F19: 714.3 | H19: 910.611 | I19: 968.153 | J19: 1172.334 | K19: =IFERROR((J19-I19)/I19,"") | N19: 583.9 | O19: 1103.6 | Q19: 1162.037 | R19: 596.847 | S19: 729.319 | T19: =IFERROR((S19-R19)/R19,"")
A20: Profit After Tax (PAT) | B20: INR cr | E20: 334.9 | F20: 447.3 | H20: 561.238 | I20: 513.746 | J20: 694.258 | K20: =IFERROR((J20-I20)/I20,"") | N20: 583.4 | O20: 1103 | Q20: 1161.198 | R20: 591.586 | S20: 724.6 | T20: =IFERROR((S20-R20)/R20,"")
A21: PAT Margin | B21: % | C21: =IF(OR(C20="",C9="",N(C9)=0),"",C20/C9) | D21: =IF(OR(D20="",D9="",N(D9)=0),"",D20/D9) | E21: =IF(OR(E20="",E9="",N(E9)=0),"",E20/E9) | F21: =IF(OR(F20="",F9="",N(F9)=0),"",F20/F9) | G21: =IF(OR(G20="",G9="",N(G9)=0),"",G20/G9) | H21: =IF(OR(H20="",H9="",N(H9)=0),"",H20/H9) | I21: =IF(OR(I20="",I9="",N(I9)=0),"",I20/I9) | J21: =IF(OR(J20="",J9="",N(J9)=0),"",J20/J9) | L21: =IF(OR(L20="",L9="",N(L9)=0),"",L20/L9) | M21: =IF(OR(M20="",M9="",N(M9)=0),"",M20/M9) | N21: =IF(OR(N20="",N9="",N(N9)=0),"",N20/N9) | O21: =IF(OR(O20="",O9="",N(O9)=0),"",O20/O9) | P21: =IF(OR(P20="",P9="",N(P9)=0),"",P20/P9) | Q21: =IF(OR(Q20="",Q9="",N(Q9)=0),"",Q20/Q9) | R21: =IF(OR(R20="",R9="",N(R9)=0),"",R20/R9) | S21: =IF(OR(S20="",S9="",N(S9)=0),"",S20/S9)
A22: DISTRIBUTIONS & CASH FLOW
A23: Net Distributable Cash Flow (NDCF) | B23: INR cr | E23: 570.6 | F23: 1098.4 | H23: 1143 | I23: 1321.435 | J23: 1528.778 | K23: =IFERROR((J23-I23)/I23,"") | L23: n/a | M23: n/a | N23: n/a | O23: n/a | P23: n/a | Q23: n/a | R23: n/a | S23: n/a | T23: n/a
A24: Total Distribution | B24: INR cr | E24: 568.7 | F24: 1094.1 | H24: 1136.2 | I24: 1312.1 | J24: 1516.356 | K24: =IFERROR((J24-I24)/I24,"") | L24: n/a | M24: n/a | N24: n/a | O24: n/a | P24: n/a | Q24: n/a | R24: n/a | S24: n/a | T24: n/a
A25: Distribution per Unit (DPU) | B25: INR/unit | E25: 9.59 | F25: 18.45 | H25: 19.16 | I25: 21.95 | J25: 24.09 | K25: =IFERROR((J25-I25)/I25,"") | L25: n/a | M25: n/a | N25: n/a | O25: n/a | P25: n/a | Q25: n/a | R25: n/a | S25: n/a | T25: n/a
A26: NDCF Payout Ratio | B26: % | C26: =IF(OR(C24="",C23="",N(C23)=0),"",C24/C23) | D26: =IF(OR(D24="",D23="",N(D23)=0),"",D24/D23) | E26: =IF(OR(E24="",E23="",N(E23)=0),"",E24/E23) | F26: =IF(OR(F24="",F23="",N(F23)=0),"",F24/F23) | G26: =IF(OR(G24="",G23="",N(G23)=0),"",G24/G23) | H26: =IF(OR(H24="",H23="",N(H23)=0),"",H24/H23) | I26: =IF(OR(I24="",I23="",N(I23)=0),"",I24/I23) | J26: =IF(OR(J24="",J23="",N(J23)=0),"",J24/J23) | L26: n/a | M26: n/a | N26: n/a | O26: n/a | P26: n/a | Q26: n/a | R26: n/a | S26: n/a | T26: n/a
A27: BALANCE SHEET & LEVERAGE
A28: Gross Asset Value (GAV) / AUM | B28: INR cr | E28: 24616.7 | F28: 26399.6 | G28: 28026.5 | H28: 29900 | I28: 36600 | J28: 49711.61 | K28: =IFERROR((J28-I28)/I28,"") | L28: n/a | M28: n/a | N28: n/a | O28: n/a | P28: n/a | Q28: n/a | R28: n/a | S28: n/a | T28: n/a
A29: Gross Debt | B29: INR cr | E29: 3606.3 | F29: 4448 | G29: 5453.5 | H29: 6972.811 | I29: 10109.782 | J29: 12976.165 | K29: =IFERROR((J29-I29)/I29,"") | N29: 1142.5 | O29: 1641.9 | Q29: 3473.601 | R29: 4615.561 | S29: 8753.529 | T29: =IFERROR((S29-R29)/R29,"")
A30: Cash & Cash Equivalents | B30: INR cr | E30: 353.9 | F30: 347.8 | G30: 406.2 | H30: 324.996 | I30: 637.931 | J30: 1217.59 | K30: =IFERROR((J30-I30)/I30,"") | N30: 293.8 | O30: 281.4 | Q30: 303.781 | R30: 28.175 | S30: 122.489 | T30: =IFERROR((S30-R30)/R30,"")
A31: Net Debt | B31: INR cr | C31: =IF(C29="","",C29-N(C30)) | D31: =IF(D29="","",D29-N(D30)) | E31: =IF(E29="","",E29-N(E30)) | F31: =IF(F29="","",F29-N(F30)) | G31: =IF(G29="","",G29-N(G30)) | H31: =IF(H29="","",H29-N(H30)) | I31: =IF(I29="","",I29-N(I30)) | J31: =IF(J29="","",J29-N(J30)) | K31: =IFERROR((J31-I31)/I31,"") | L31: =IF(L29="","",L29-N(L30)) | M31: =IF(M29="","",M29-N(M30)) | N31: =IF(N29="","",N29-N(N30)) | O31: =IF(O29="","",O29-N(O30)) | P31: =IF(P29="","",P29-N(P30)) | Q31: =IF(Q29="","",Q29-N(Q30)) | R31: =IF(R29="","",R29-N(R30)) | S31: =IF(S29="","",S29-N(S30)) | T31: =IFERROR((S31-R31)/R31,"")
A32: Net Worth / Unitholders Equity | B32: INR cr | E32: 16303 | F32: 15620.5 | H32: 14928.541 | I32: 14810.55 | J32: 15796.831 | K32: =IFERROR((J32-I32)/I32,"") | N32: 16578.9 | O32: 16575.8 | Q32: 16626.754 | R32: 16628.221 | S32: 17693.675 | T32: =IFERROR((S32-R32)/R32,"")
A33: Loan-to-Value (LTV) | B33: % | C33: =IF(OR(C31="",C28="",N(C28)=0),"",C31/C28) | D33: =IF(OR(D31="",D28="",N(D28)=0),"",D31/D28) | E33: =IF(OR(E31="",E28="",N(E28)=0),"",E31/E28) | F33: =IF(OR(F31="",F28="",N(F28)=0),"",F31/F28) | G33: =IF(OR(G31="",G28="",N(G28)=0),"",G31/G28) | H33: =IF(OR(H31="",H28="",N(H28)=0),"",H31/H28) | I33: =IF(OR(I31="",I28="",N(I28)=0),"",I31/I28) | J33: =IF(OR(J31="",J28="",N(J28)=0),"",J31/J28) | L33: =IF(OR(L31="",L28="",N(L28)=0),"",L31/L28) | M33: =IF(OR(M31="",M28="",N(M28)=0),"",M31/M28) | N33: =IF(OR(N31="",N28="",N(N28)=0),"",N31/N28) | O33: =IF(OR(O31="",O28="",N(O28)=0),"",O31/O28) | P33: =IF(OR(P31="",P28="",N(P28)=0),"",P31/P28) | Q33: =IF(OR(Q31="",Q28="",N(Q28)=0),"",Q31/Q28) | R33: =IF(OR(R31="",R28="",N(R28)=0),"",R31/R28) | S33: =IF(OR(S31="",S28="",N(S28)=0),"",S31/S28)
A34: NAV per Unit | B34: INR/unit | E34: 345.2 | F34: 364.9 | H34: 380.5 | I34: 431.7 | J34: 527.01 | K34: =IFERROR((J34-I34)/I34,"") | L34: n/a | M34: n/a | N34: n/a | O34: n/a | P34: n/a | Q34: n/a | R34: n/a | S34: n/a | T34: n/a
A35: MARKET DATA
A36: Units Outstanding | B36: mn units | E36: 593.02 | F36: 593.02 | H36: 593.02 | I36: 609.18 | J36: 648.34 | K36: =IFERROR((J36-I36)/I36,"") | L36: n/a | M36: n/a | N36: n/a | O36: n/a | P36: n/a | Q36: n/a | R36: n/a | S36: n/a | T36: n/a
A37: Unit Price (period-end) | B37: INR/unit | F37: 346.02 | G37: 325.1 | H37: 344.99 | I37: 376.99 | J37: 449 | K37: =IFERROR((J37-I37)/I37,"") | L37: n/a | M37: n/a | N37: n/a | O37: n/a | P37: n/a | Q37: n/a | R37: n/a | S37: n/a | T37: n/a
A38: Market Capitalisation | B38: INR cr | C38: =IF(OR(C36="",C37=""),"",C36*C37/10) | D38: =IF(OR(D36="",D37=""),"",D36*D37/10) | E38: =IF(OR(E36="",E37=""),"",E36*E37/10) | F38: =IF(OR(F36="",F37=""),"",F36*F37/10) | G38: =IF(OR(G36="",G37=""),"",G36*G37/10) | H38: =IF(OR(H36="",H37=""),"",H36*H37/10) | I38: =IF(OR(I36="",I37=""),"",I36*I37/10) | J38: =IF(OR(J36="",J37=""),"",J36*J37/10) | K38: =IFERROR((J38-I38)/I38,"") | L38: n/a | M38: n/a | N38: n/a | O38: n/a | P38: n/a | Q38: n/a | R38: n/a | S38: n/a | T38: n/a
A39: Annual Distribution Yield | B39: % | C39: =IF(OR(C25="",C37="",N(C37)=0),"",C25/C37) | D39: =IF(OR(D25="",D37="",N(D37)=0),"",D25/D37) | E39: =IF(OR(E25="",E37="",N(E37)=0),"",E25/E37) | F39: =IF(OR(F25="",F37="",N(F37)=0),"",F25/F37) | G39: =IF(OR(G25="",G37="",N(G37)=0),"",G25/G37) | H39: =IF(OR(H25="",H37="",N(H37)=0),"",H25/H37) | I39: =IF(OR(I25="",I37="",N(I37)=0),"",I25/I37) | J39: =IF(OR(J25="",J37="",N(J37)=0),"",J25/J37) | L39: n/a | M39: n/a | N39: n/a | O39: n/a | P39: n/a | Q39: n/a | R39: n/a | S39: n/a | T39: n/a
A40: Cost of Debt | B40: % | E40: 0.071 | F40: 0.066 | G40: 0.076 | H40: 0.078 | I40: 0.0815 | J40: 0.0741 | L40: n/a | M40: n/a | N40: n/a | O40: n/a | P40: n/a | Q40: n/a | R40: n/a | S40: n/a | T40: n/a
A41: PORTFOLIO & OPERATING METRICS (consolidated)
A42: Total Leasable Area (GLA) | B42: Msf | E42: 30.2 | F42: 31.8 | G42: 32 | H42: 33.2 | I42: 37.1 | J42: 38.2 | K42: =IFERROR((J42-I42)/I42,"") | L42: n/a | M42: n/a | N42: n/a | O42: n/a | P42: n/a | Q42: n/a | R42: n/a | S42: n/a | T42: n/a
A43: Operational Area | B43: Msf | E43: 23.9 | F43: 24.2 | G43: 25.8 | H43: 26.3 | I43: 30 | J43: 31 | K43: =IFERROR((J43-I43)/I43,"") | L43: n/a | M43: n/a | N43: n/a | O43: n/a | P43: n/a | Q43: n/a | R43: n/a | S43: n/a | T43: n/a
A44: Under Construction + Future Development | B44: Msf | E44: 6.4 | F44: 7.6 | G44: 6.2 | H44: 7 | I44: 7.1 | J44: 7.2 | K44: =IFERROR((J44-I44)/I44,"") | L44: n/a | M44: n/a | N44: n/a | O44: n/a | P44: n/a | Q44: n/a | R44: n/a | S44: n/a | T44: n/a
A45: Committed Occupancy | B45: % | E45: 0.84 | F45: 0.84 | H45: 0.906 | I45: 0.93 | J45: 0.94 | L45: n/a | M45: n/a | N45: n/a | O45: n/a | P45: n/a | Q45: n/a | R45: n/a | S45: n/a | T45: n/a
A46: In-place / Physical Occupancy | B46: % | H46: 0.838 | I46: 0.84 | J46: 0.91 | L46: n/a | M46: n/a | N46: n/a | O46: n/a | P46: n/a | Q46: n/a | R46: n/a | S46: n/a | T46: n/a
A47: WALE | B47: years | E47: 6 | F47: 6.9 | H47: 6.8 | I47: 7.4 | J47: 7.1 | K47: =IFERROR((J47-I47)/I47,"") | L47: n/a | M47: n/a | N47: n/a | O47: n/a | P47: n/a | Q47: n/a | R47: n/a | S47: n/a | T47: n/a
A48: Number of Tenants | B48: count | E48: 160 | F48: 716 | H48: 220 | I48: 225 | J48: 270 | K48: =IFERROR((J48-I48)/I48,"") | L48: n/a | M48: n/a | N48: n/a | O48: n/a | P48: n/a | Q48: n/a | R48: n/a | S48: n/a | T48: n/a
A49: In-place Rent | B49: INR psf/mo | E49: 55.9 | F49: 61.7 | H49: 69 | I49: 71 | J49: 80.4 | K49: =IFERROR((J49-I49)/I49,"") | L49: n/a | M49: n/a | N49: n/a | O49: n/a | P49: n/a | Q49: n/a | R49: n/a | S49: n/a | T49: n/a
A52: DEBT & NDCF / DISTRIBUTION DETAIL (consolidated; INR cr unless noted)
A53: Metric | B53: Unit | C53: FY2019 | D53: FY2020 | E53: FY2021 | F53: FY2022 | G53: FY2023 | H53: FY2024 | I53: FY2025 | J53: FY2026
A54: Distribution composition (NDCF -> unitholders)
A55: Net Distributable Cash Flow (NDCF) | B55: INR cr | C55: =IF(N(C23)=0,IF(C23="","",C23),C23) | D55: =IF(N(D23)=0,IF(D23="","",D23),D23) | E55: =IF(N(E23)=0,IF(E23="","",E23),E23) | F55: =IF(N(F23)=0,IF(F23="","",F23),F23) | G55: =IF(N(G23)=0,IF(G23="","",G23),G23) | H55: =IF(N(H23)=0,IF(H23="","",H23),H23) | I55: =IF(N(I23)=0,IF(I23="","",I23),I23) | J55: =IF(N(J23)=0,IF(J23="","",J23),J23)
A56: Total Distribution | B56: INR cr | C56: =IF(N(C24)=0,IF(C24="","",C24),C24) | D56: =IF(N(D24)=0,IF(D24="","",D24),D24) | E56: =IF(N(E24)=0,IF(E24="","",E24),E24) | F56: =IF(N(F24)=0,IF(F24="","",F24),F24) | G56: =IF(N(G24)=0,IF(G24="","",G24),G24) | H56: =IF(N(H24)=0,IF(H24="","",H24),H24) | I56: =IF(N(I24)=0,IF(I24="","",I24),I24) | J56: =IF(N(J24)=0,IF(J24="","",J24),J24) | S56: =A7 | T56: =B7 | U56: =E7 | V56: =F7 | W56: =G7 | X56: =H7 | Y56: =I7 | Z56: =J7
A57: of which: Interest | B57: INR cr | H57: 113.2 | S57: =A46 | T57: =B46 | U57: 8.4 | V57: 8.22 | W57: =904.833% | X57: =H46*10 | Y57: =I46*10 | Z57: =J46*10
A58: of which: Dividend | B58: INR cr | H58: 1021.8 | S58: =A47 | T58: =B47 | U58: =E47 | V58: =F47 | W58: 6.7 | X58: =H47 | Y58: =I47 | Z58: =J47
A59: of which: Return of capital (SPV/shareholder-loan repayment) | B59: INR cr | H59: 0
A60: of which: Other | B60: INR cr | H60: 1.2
A61: Return-of-capital % of distribution | B61: % | C61: =IF(OR(C59="",C56="",N(C56)=0),"",C59/C56) | D61: =IF(OR(D59="",D56="",N(D56)=0),"",D59/D56) | E61: =IF(OR(E59="",E56="",N(E56)=0),"",E59/E56) | F61: =IF(OR(F59="",F56="",N(F56)=0),"",F59/F56) | G61: =IF(OR(G59="",G56="",N(G56)=0),"",G59/G56) | H61: =IF(OR(H59="",H56="",N(H56)=0),"",H59/H56) | I61: =IF(OR(I59="",I56="",N(I56)=0),"",I59/I56) | J61: =IF(OR(J59="",J56="",N(J56)=0),"",J59/J56)
A62: Distribution per Unit (DPU) | B62: INR/unit | C62: =IF(N(C25)=0,IF(C25="","",C25),C25) | D62: =IF(N(D25)=0,IF(D25="","",D25),D25) | E62: =IF(N(E25)=0,IF(E25="","",E25),E25) | F62: =IF(N(F25)=0,IF(F25="","",F25),F25) | G62: =IF(N(G25)=0,IF(G25="","",G25),G25) | H62: =IF(N(H25)=0,IF(H25="","",H25),H25) | I62: =IF(N(I25)=0,IF(I25="","",I25),I25) | J62: =IF(N(J25)=0,IF(J25="","",J25),J25)
A63: DPU: Interest | B63: INR/unit | I63: 0.97 | J63: 0.2
A64: DPU: Dividend | B64: INR/unit | I64: 12.1 | J64: 12.68 | S64: Occupancy (%)
A65: DPU: Return of capital | B65: INR/unit | I65: 8.78 | J65: 11.16 | S65: Committed Occupancy (%) 88.3% 70.7% 97.9% 100.0% 100.0% 100.0%
A66: DPU: Other | B66: INR/unit | I66: 0.1 | J66: 0.05
A67: Debt & leverage profile
A68: Gross Debt - external (banks/NCDs/LRD) | B68: INR cr | C68: =IF(C29="","",C29) | D68: =IF(D29="","",D29) | E68: =IF(E29="","",E29) | F68: =IF(F29="","",F29) | G68: =IF(G29="","",G29) | H68: 6972.811 | I68: 10109.782 | J68: 12976.165 | S68: =(4.6+9.7+3.2+8.7+9.4+4.6)/6
A69: Shareholder / unitholder loans (Trust -> SPVs) | B69: INR cr | I69: 4915.657 | J69: 8279.404
A70: Cash & Cash Equivalents | B70: INR cr | C70: =IF(N(C30)=0,IF(C30="","",C30),C30) | D70: =IF(N(D30)=0,IF(D30="","",D30),D30) | E70: =IF(N(E30)=0,IF(E30="","",E30),E30) | F70: =IF(N(F30)=0,IF(F30="","",F30),F30) | G70: =IF(N(G30)=0,IF(G30="","",G30),G30) | H70: =IF(N(H30)=0,IF(H30="","",H30),H30) | I70: =IF(N(I30)=0,IF(I30="","",I30),I30) | J70: =IF(N(J30)=0,IF(J30="","",J30),J30)
A71: Net Debt | B71: INR cr | C71: =IF(N(C31)=0,IF(C31="","",C31),C31) | D71: =IF(N(D31)=0,IF(D31="","",D31),D31) | E71: =IF(N(E31)=0,IF(E31="","",E31),E31) | F71: =IF(N(F31)=0,IF(F31="","",F31),F31) | G71: =IF(N(G31)=0,IF(G31="","",G31),G31) | H71: =IF(N(H31)=0,IF(H31="","",H31),H31) | I71: =IF(N(I31)=0,IF(I31="","",I31),I31) | J71: =IF(N(J31)=0,IF(J31="","",J31),J31) | W71: =88.3%+70%+97.9%+100%+86.7%+100% | X71: =W71/6
A72: Gross Asset Value (GAV) | B72: INR cr | C72: =IF(N(C28)=0,IF(C28="","",C28),C28) | D72: =IF(N(D28)=0,IF(D28="","",D28),D28) | E72: =IF(N(E28)=0,IF(E28="","",E28),E28) | F72: =IF(N(F28)=0,IF(F28="","",F28),F28) | G72: =IF(N(G28)=0,IF(G28="","",G28),G28) | H72: =IF(N(H28)=0,IF(H28="","",H28),H28) | I72: =IF(N(I28)=0,IF(I28="","",I28),I28) | J72: =IF(N(J28)=0,IF(J28="","",J28),J28)
A73: Loan-to-Value (LTV) | B73: % | C73: =IF(N(C33)=0,IF(C33="","",C33),C33) | D73: =IF(N(D33)=0,IF(D33="","",D33),D33) | E73: =IF(N(E33)=0,IF(E33="","",E33),E33) | F73: =IF(N(F33)=0,IF(F33="","",F33),F33) | G73: =IF(N(G33)=0,IF(G33="","",G33),G33) | H73: =IF(N(H33)=0,IF(H33="","",H33),H33) | I73: =IF(N(I33)=0,IF(I33="","",I33),I33) | J73: =IF(N(J33)=0,IF(J33="","",J33),J33)
A74: Cost of Debt (wtd avg) | B74: % | C74: =IF(N(C40)=0,IF(C40="","",C40),C40) | D74: =IF(N(D40)=0,IF(D40="","",D40),D40) | E74: =IF(N(E40)=0,IF(E40="","",E40),E40) | F74: =IF(N(F40)=0,IF(F40="","",F40),F40) | G74: =IF(N(G40)=0,IF(G40="","",G40),G40) | H74: =IF(N(H40)=0,IF(H40="","",H40),H40) | I74: =IF(N(I40)=0,IF(I40="","",I40),I40) | J74: =IF(N(J40)=0,IF(J40="","",J40),J40)
A75: % Floating rate | B75: % | H75: 0.444 | I75: 0.54 | J75: 0.325
A76: Wtd-avg debt maturity | B76: years | H76: 5.2 | I76: 7 | J76: 5.2
A77: Undrawn debt headroom | B77: INR cr | H77: 915.5 | I77: 487 | J77: 595.2
A78: Interest cover (NOI / Finance cost) | B78: x | C78: =IF(OR(C13="",N(C17)=0),"",C13/C17) | D78: =IF(OR(D13="",N(D17)=0),"",D13/D17) | E78: =IF(OR(E13="",N(E17)=0),"",E13/E17) | F78: =IF(OR(F13="",N(F17)=0),"",F13/F17) | G78: =IF(OR(G13="",N(G17)=0),"",G13/G17) | H78: =IF(OR(H13="",N(H17)=0),"",H13/H17) | I78: =IF(OR(I13="",N(I17)=0),"",I13/I17) | J78: =IF(OR(J13="",N(J17)=0),"",J13/J17)
A80: Distribution-component split is shown where the issuer disclosed it (often per-unit for Q4 only in older years); blanks = not separately disclosed.

Sheet Brookfield
A1: Brookfield REIT - Key Financials & Operating Metrics
A2: Sponsor: Brookfield. All INR figures in INR crore (cr) unless stated. 1 crore = 10 million. FY ends 31 March.
A3: Hover a cell for its Source (report + page + original figure). Grey italic = auto-calculated. YoY% = FY2026 vs FY2025.
C6: CONSOLIDATED | L6: STANDALONE
A7: Metric | B7: Unit | C7: FY2019 | D7: FY2020 | E7: FY2021 | F7: FY2022 | G7: FY2023 | H7: FY2024 | I7: FY2025 | J7: FY2026 | K7: YoY% | L7: FY2019 | M7: FY2020 | N7: FY2021 | O7: FY2022 | P7: FY2023 | Q7: FY2024 | R7: FY2025 | S7: FY2026 | T7: YoY%
A8: INCOME STATEMENT
A9: Revenue from Operations | B9: INR cr | E9: 130.942 | F9: 876.791 | G9: 1196.999 | H9: 1787.068 | I9: 2389.998 | J9: 2971.144 | K9: =IFERROR((J9-I9)/I9,"") | T9: =IFERROR((S9-R9)/R9,"")
A10: Other Income | B10: INR cr | E10: 5.165 | F10: 22.423 | G10: 32.48 | H10: 11.606 | I10: 81.815 | J10: 100.189 | K10: =IFERROR((J10-I10)/I10,"") | N10: 0 | O10: 12.678 | P10: 39.794 | Q10: 0.059 | R10: 219.174 | S10: 118.167 | T10: =IFERROR((S10-R10)/R10,"")
A11: Total Income | B11: INR cr | C11: =IF(AND(C9="",C10=""),"",N(C9)+N(C10)) | D11: =IF(AND(D9="",D10=""),"",N(D9)+N(D10)) | E11: =IF(AND(E9="",E10=""),"",N(E9)+N(E10)) | F11: =IF(AND(F9="",F10=""),"",N(F9)+N(F10)) | G11: =IF(AND(G9="",G10=""),"",N(G9)+N(G10)) | H11: =IF(AND(H9="",H10=""),"",N(H9)+N(H10)) | I11: =IF(AND(I9="",I10=""),"",N(I9)+N(I10)) | J11: =IF(AND(J9="",J10=""),"",N(J9)+N(J10)) | K11: =IFERROR((J11-I11)/I11,"") | L11: =IF(AND(L9="",L10=""),"",N(L9)+N(L10)) | M11: =IF(AND(M9="",M10=""),"",N(M9)+N(M10)) | N11: =IF(AND(N9="",N10=""),"",N(N9)+N(N10)) | O11: =IF(AND(O9="",O10=""),"",N(O9)+N(O10)) | P11: =IF(AND(P9="",P10=""),"",N(P9)+N(P10)) | Q11: =IF(AND(Q9="",Q10=""),"",N(Q9)+N(Q10)) | R11: =IF(AND(R9="",R10=""),"",N(R9)+N(R10)) | S11: =IF(AND(S9="",S10=""),"",N(S9)+N(S10)) | T11: =IFERROR((S11-R11)/R11,"")
A12: Property / Operating Expenses | B12: INR cr | K12: =IFERROR((J12-I12)/I12,"") | T12: =IFERROR((S12-R12)/R12,"")
A13: Net Operating Income (NOI) | B13: INR cr | E13: 660 | F13: 673 | G13: 888.5 | H13: 1350 | I13: 1854.004 | J13: 2291.299 | K13: =IFERROR((J13-I13)/I13,"") | T13: =IFERROR((S13-R13)/R13,"")
A14: NOI Margin | B14: % | C14: =IF(OR(C13="",C9="",N(C9)=0),"",C13/C9) | D14: =IF(OR(D13="",D9="",N(D9)=0),"",D13/D9) | E14: =IF(OR(E13="",E9="",N(E9)=0),"",E13/E9) | F14: =IF(OR(F13="",F9="",N(F9)=0),"",F13/F9) | G14: =IF(OR(G13="",G9="",N(G9)=0),"",G13/G9) | H14: =IF(OR(H13="",H9="",N(H9)=0),"",H13/H9) | I14: =IF(OR(I13="",I9="",N(I9)=0),"",I13/I9) | J14: =IF(OR(J13="",J9="",N(J9)=0),"",J13/J9) | L14: =IF(OR(L13="",L9="",N(L9)=0),"",L13/L9) | M14: =IF(OR(M13="",M9="",N(M9)=0),"",M13/M9) | N14: =IF(OR(N13="",N9="",N(N9)=0),"",N13/N9) | O14: =IF(OR(O13="",O9="",N(O9)=0),"",O13/O9) | P14: =IF(OR(P13="",P9="",N(P9)=0),"",P13/P9) | Q14: =IF(OR(Q13="",Q9="",N(Q9)=0),"",Q13/Q9) | R14: =IF(OR(R13="",R9="",N(R9)=0),"",R13/R9) | S14: =IF(OR(S13="",S9="",N(S9)=0),"",S13/S9)
A15: EBITDA | B15: INR cr | E15: 87.695 | F15: 640.745 | G15: 848.049 | H15: 1487.6 | I15: 1910.7 | J15: 2241.8 | K15: =IFERROR((J15-I15)/I15,"") | T15: =IFERROR((S15-R15)/R15,"")
A16: EBITDA Margin | B16: % | C16: =IF(OR(C15="",C9="",N(C9)=0),"",C15/C9) | D16: =IF(OR(D15="",D9="",N(D9)=0),"",D15/D9) | E16: =IF(OR(E15="",E9="",N(E9)=0),"",E15/E9) | F16: =IF(OR(F15="",F9="",N(F9)=0),"",F15/F9) | G16: =IF(OR(G15="",G9="",N(G9)=0),"",G15/G9) | H16: =IF(OR(H15="",H9="",N(H9)=0),"",H15/H9) | I16: =IF(OR(I15="",I9="",N(I9)=0),"",I15/I9) | J16: =IF(OR(J15="",J9="",N(J9)=0),"",J15/J9) | L16: =IF(OR(L15="",L9="",N(L9)=0),"",L15/L9) | M16: =IF(OR(M15="",M9="",N(M9)=0),"",M15/M9) | N16: =IF(OR(N15="",N9="",N(N9)=0),"",N15/N9) | O16: =IF(OR(O15="",O9="",N(O9)=0),"",O15/O9) | P16: =IF(OR(P15="",P9="",N(P9)=0),"",P15/P9) | Q16: =IF(OR(Q15="",Q9="",N(Q9)=0),"",Q15/Q9) | R16: =IF(OR(R15="",R9="",N(R9)=0),"",R15/R9) | S16: =IF(OR(S15="",S9="",N(S9)=0),"",S15/S9)
A17: Finance Costs | B17: INR cr | E17: 41.077 | F17: 208.069 | G17: 432.457 | H17: 852.245 | I17: 1078.177 | J17: 974.781 | K17: =IFERROR((J17-I17)/I17,"") | Q17: 34.479 | R17: 71.252 | S17: 110.657 | T17: =IFERROR((S17-R17)/R17,"")
A18: Depreciation & Amortisation | B18: INR cr | E18: 31.675 | F18: 208.477 | G18: 275.202 | H18: 411.209 | I18: 429.89 | J18: 469.402 | K18: =IFERROR((J18-I18)/I18,"") | T18: =IFERROR((S18-R18)/R18,"")
A19: Profit Before Tax (PBT) | B19: INR cr | E19: 14.943 | F19: 224.199 | G19: 140.39 | H19: 54.211 | I19: 249.502 | J19: 758.419 | K19: =IFERROR((J19-I19)/I19,"") | N19: 62.623 | O19: 453.702 | P19: 351.859 | Q19: 296.912 | R19: 751.498 | S19: 846.437 | T19: =IFERROR((S19-R19)/R19,"")
A20: Profit After Tax (PAT) | B20: INR cr | E20: 25.303 | F20: 246.285 | G20: 131.232 | H20: -15.35 | I20: 159.953 | J20: 536.751 | K20: =IFERROR((J20-I20)/I20,"") | N20: 62.623 | O20: 452.475 | P20: 338.808 | Q20: 298.394 | R20: 714.454 | S20: 814.876 | T20: =IFERROR((S20-R20)/R20,"")
A21: PAT Margin | B21: % | C21: =IF(OR(C20="",C9="",N(C9)=0),"",C20/C9) | D21: =IF(OR(D20="",D9="",N(D9)=0),"",D20/D9) | E21: =IF(OR(E20="",E9="",N(E9)=0),"",E20/E9) | F21: =IF(OR(F20="",F9="",N(F9)=0),"",F20/F9) | G21: =IF(OR(G20="",G9="",N(G9)=0),"",G20/G9) | H21: =IF(OR(H20="",H9="",N(H9)=0),"",H20/H9) | I21: =IF(OR(I20="",I9="",N(I9)=0),"",I20/I9) | J21: =IF(OR(J20="",J9="",N(J9)=0),"",J20/J9) | L21: =IF(OR(L20="",L9="",N(L9)=0),"",L20/L9) | M21: =IF(OR(M20="",M9="",N(M9)=0),"",M20/M9) | N21: =IF(OR(N20="",N9="",N(N9)=0),"",N20/N9) | O21: =IF(OR(O20="",O9="",N(O9)=0),"",O20/O9) | P21: =IF(OR(P20="",P9="",N(P9)=0),"",P20/P9) | Q21: =IF(OR(Q20="",Q9="",N(Q9)=0),"",Q20/Q9) | R21: =IF(OR(R20="",R9="",N(R9)=0),"",R20/R9) | S21: =IF(OR(S20="",S9="",N(S9)=0),"",S20/S9)
A22: DISTRIBUTIONS & CASH FLOW
A23: Net Distributable Cash Flow (NDCF) | B23: INR cr | F23: 688.458 | G23: 678.611 | H23: 770.52 | I23: 1055.18 | J23: 1506.695 | K23: =IFERROR((J23-I23)/I23,"") | L23: n/a | M23: n/a | N23: n/a | O23: n/a | P23: n/a | Q23: n/a | R23: n/a | S23: n/a | T23: n/a
A24: Total Distribution | B24: INR cr | F24: 740.478 | G24: 676.875 | H24: 779.4 | I24: 1053.682 | J24: 1516.178 | K24: =IFERROR((J24-I24)/I24,"") | L24: n/a | M24: n/a | N24: n/a | O24: n/a | P24: n/a | Q24: n/a | R24: n/a | S24: n/a | T24: n/a
A25: Distribution per Unit (DPU) | B25: INR/unit | F25: 22.1 | G25: 20.2 | H25: 17.75 | I25: 19.25 | J25: 21.4 | K25: =IFERROR((J25-I25)/I25,"") | L25: n/a | M25: n/a | N25: n/a | O25: n/a | P25: n/a | Q25: n/a | R25: n/a | S25: n/a | T25: n/a
A26: NDCF Payout Ratio | B26: % | C26: =IF(OR(C24="",C23="",N(C23)=0),"",C24/C23) | D26: =IF(OR(D24="",D23="",N(D23)=0),"",D24/D23) | E26: =IF(OR(E24="",E23="",N(E23)=0),"",E24/E23) | F26: =IF(OR(F24="",F23="",N(F23)=0),"",F24/F23) | G26: =IF(OR(G24="",G23="",N(G23)=0),"",G24/G23) | H26: =IF(OR(H24="",H23="",N(H23)=0),"",H24/H23) | I26: =IF(OR(I24="",I23="",N(I23)=0),"",I24/I23) | J26: =IF(OR(J24="",J23="",N(J23)=0),"",J24/J23) | L26: n/a | M26: n/a | N26: n/a | O26: n/a | P26: n/a | Q26: n/a | R26: n/a | S26: n/a | T26: n/a
A27: BALANCE SHEET & LEVERAGE
A28: Gross Asset Value (GAV) / AUM | B28: INR cr | E28: 11500 | F28: 16000 | G28: 16400 | H28: 30719.831 | I28: 34031.306 | J28: 56528.1 | K28: =IFERROR((J28-I28)/I28,"") | L28: n/a | M28: n/a | N28: n/a | O28: n/a | P28: n/a | Q28: n/a | R28: n/a | S28: n/a | T28: n/a
A29: Gross Debt | B29: INR cr | E29: 2101.517 | F29: 5165.534 | G29: 5452.038 | H29: 12112.636 | I29: 10690.03 | J29: 18130.165 | K29: =IFERROR((J29-I29)/I29,"") | N29: 0 | O29: 0 | P29: 0 | Q29: 728.487 | R29: 669.321 | S29: 2711.894 | T29: =IFERROR((S29-R29)/R29,"")
A30: Cash & Cash Equivalents | B30: INR cr | H30: 378.407 | I30: 574.649 | J30: 674.218 | K30: =IFERROR((J30-I30)/I30,"") | Q30: 239.289 | R30: 209.45 | S30: 239.311 | T30: =IFERROR((S30-R30)/R30,"")
A31: Net Debt | B31: INR cr | C31: =IF(C29="","",C29-N(C30)) | D31: =IF(D29="","",D29-N(D30)) | E31: =IF(E29="","",E29-N(E30)) | F31: =IF(F29="","",F29-N(F30)) | G31: =IF(G29="","",G29-N(G30)) | H31: =IF(H29="","",H29-N(H30)) | I31: =IF(I29="","",I29-N(I30)) | J31: =IF(J29="","",J29-N(J30)) | K31: =IFERROR((J31-I31)/I31,"") | L31: =IF(L29="","",L29-N(L30)) | M31: =IF(M29="","",M29-N(M30)) | N31: =IF(N29="","",N29-N(N30)) | O31: =IF(O29="","",O29-N(O30)) | P31: =IF(P29="","",P29-N(P30)) | Q31: =IF(Q29="","",Q29-N(Q30)) | R31: =IF(R29="","",R29-N(R30)) | S31: =IF(S29="","",S29-N(S30)) | T31: =IFERROR((S31-R31)/R31,"")
A32: Net Worth / Unitholders Equity | B32: INR cr | E32: 8202.753 | F32: 8882.093 | G32: 8333.738 | H32: 12129.66 | I32: 16010.615 | J32: 19562.123 | K32: =IFERROR((J32-I32)/I32,"") | N32: 8240.101 | O32: 9125.477 | P32: 8784.058 | Q32: 10981.584 | R32: 15414.414 | S32: 19243.162 | T32: =IFERROR((S32-R32)/R32,"")
A33: Loan-to-Value (LTV) | B33: % | C33: =IF(OR(C31="",C28="",N(C28)=0),"",C31/C28) | D33: =IF(OR(D31="",D28="",N(D28)=0),"",D31/D28) | E33: =IF(OR(E31="",E28="",N(E28)=0),"",E31/E28) | F33: =IF(OR(F31="",F28="",N(F28)=0),"",F31/F28) | G33: =IF(OR(G31="",G28="",N(G28)=0),"",G31/G28) | H33: =IF(OR(H31="",H28="",N(H28)=0),"",H31/H28) | I33: =IF(OR(I31="",I28="",N(I28)=0),"",I31/I28) | J33: =IF(OR(J31="",J28="",N(J28)=0),"",J31/J28) | L33: =IF(OR(L31="",L28="",N(L28)=0),"",L31/L28) | M33: =IF(OR(M31="",M28="",N(M28)=0),"",M31/M28) | N33: =IF(OR(N31="",N28="",N(N28)=0),"",N31/N28) | O33: =IF(OR(O31="",O28="",N(O28)=0),"",O31/O28) | P33: =IF(OR(P31="",P28="",N(P28)=0),"",P31/P28) | Q33: =IF(OR(Q31="",Q28="",N(Q28)=0),"",Q31/Q28) | R33: =IF(OR(R31="",R28="",N(R28)=0),"",R31/R28) | S33: =IF(OR(S31="",S28="",N(S28)=0),"",S31/S28)
A34: NAV per Unit | B34: INR/unit | E34: 316.59 | F34: 333.81 | G34: 332.08 | H34: 233.57 | I34: 230.85 | J34: 233.87 | K34: =IFERROR((J34-I34)/I34,"") | L34: n/a | M34: n/a | N34: n/a | O34: n/a | P34: n/a | Q34: n/a | R34: n/a | S34: n/a | T34: n/a
A35: MARKET DATA
A36: Units Outstanding | B36: mn units | E36: 302801601 | F36: 335087073 | G36: 335087073 | H36: 439.09 | I36: 607.75 | J36: 749.39 | K36: =IFERROR((J36-I36)/I36,"") | L36: n/a | M36: n/a | N36: n/a | O36: n/a | P36: n/a | Q36: n/a | R36: n/a | S36: n/a | T36: n/a
A37: Unit Price (period-end) | B37: INR/unit | F37: 310.21 | G37: 279.9 | H37: 253.25 | I37: 290 | J37: 320.31 | K37: =IFERROR((J37-I37)/I37,"") | L37: n/a | M37: n/a | N37: n/a | O37: n/a | P37: n/a | Q37: n/a | R37: n/a | S37: n/a | T37: n/a
A38: Market Capitalisation | B38: INR cr | C38: =IF(OR(C36="",C37=""),"",C36*C37/10) | D38: =IF(OR(D36="",D37=""),"",D36*D37/10) | E38: =IF(OR(E36="",E37=""),"",E36*E37/10) | F38: =IF(OR(F36="",F37=""),"",F36*F37/10) | G38: =IF(OR(G36="",G37=""),"",G36*G37/10) | H38: =IF(OR(H36="",H37=""),"",H36*H37/10) | I38: =IF(OR(I36="",I37=""),"",I36*I37/10) | J38: =IF(OR(J36="",J37=""),"",J36*J37/10) | K38: =IFERROR((J38-I38)/I38,"") | L38: n/a | M38: n/a | N38: n/a | O38: n/a | P38: n/a | Q38: n/a | R38: n/a | S38: n/a | T38: n/a
A39: Annual Distribution Yield | B39: % | C39: =IF(OR(C25="",C37="",N(C37)=0),"",C25/C37) | D39: =IF(OR(D25="",D37="",N(D37)=0),"",D25/D37) | E39: =IF(OR(E25="",E37="",N(E37)=0),"",E25/E37) | F39: =IF(OR(F25="",F37="",N(F37)=0),"",F25/F37) | G39: =IF(OR(G25="",G37="",N(G37)=0),"",G25/G37) | H39: =IF(OR(H25="",H37="",N(H37)=0),"",H25/H37) | I39: =IF(OR(I25="",I37="",N(I37)=0),"",I25/I37) | J39: =IF(OR(J25="",J37="",N(J37)=0),"",J25/J37) | L39: n/a | M39: n/a | N39: n/a | O39: n/a | P39: n/a | Q39: n/a | R39: n/a | S39: n/a | T39: n/a
A40: Cost of Debt | B40: % | E40: 0.0715 | F40: 0.0676 | G40: 0.082 | H40: 0.083 | I40: 0.082 | J40: 0.0805 | L40: n/a | M40: n/a | N40: n/a | O40: n/a | P40: n/a | Q40: n/a | R40: n/a | S40: n/a | T40: n/a
A41: PORTFOLIO & OPERATING METRICS (consolidated)
A42: Total Leasable Area (GLA) | B42: Msf | E42: 14 | F42: 18.6 | G42: 18.7 | H42: 25.5 | I42: 29 | J42: 32.43 | K42: =IFERROR((J42-I42)/I42,"") | L42: n/a | M42: n/a | N42: n/a | O42: n/a | P42: n/a | Q42: n/a | R42: n/a | S42: n/a | T42: n/a
A43: Operational Area | B43: Msf | E43: 10.3 | F43: 14.1 | G43: 14.3 | H43: 20.9 | I43: 24.5 | J43: 32.43 | K43: =IFERROR((J43-I43)/I43,"") | L43: n/a | M43: n/a | N43: n/a | O43: n/a | P43: n/a | Q43: n/a | R43: n/a | S43: n/a | T43: n/a
A44: Under Construction + Future Development | B44: Msf | E44: 3.7 | F44: 4.6 | G44: 4.4 | H44: 4.6 | I44: 4.5 | J44: 4.6 | K44: =IFERROR((J44-I44)/I44,"") | L44: n/a | M44: n/a | N44: n/a | O44: n/a | P44: n/a | Q44: n/a | R44: n/a | S44: n/a | T44: n/a
A45: Committed Occupancy | B45: % | F45: 0.83 | G45: 0.84 | H45: 0.82 | I45: 0.88 | J45: 0.9292 | L45: n/a | M45: n/a | N45: n/a | O45: n/a | P45: n/a | Q45: n/a | R45: n/a | S45: n/a | T45: n/a
A46: In-place / Physical Occupancy | B46: % | F46: 0.87 | G46: 0.89 | H46: 0.87 | L46: n/a | M46: n/a | N46: n/a | O46: n/a | P46: n/a | Q46: n/a | R46: n/a | S46: n/a | T46: n/a
A47: WALE | B47: years | F47: 7.1 | G47: 7.9 | H47: 7.6 | I47: 7 | J47: 6.7 | K47: =IFERROR((J47-I47)/I47,"") | L47: n/a | M47: n/a | N47: n/a | O47: n/a | P47: n/a | Q47: n/a | R47: n/a | S47: n/a | T47: n/a
A48: Number of Tenants | B48: count | F48: 70 | G48: 75 | H48: 141 | K48: =IFERROR((J48-I48)/I48,"") | L48: n/a | M48: n/a | N48: n/a | O48: n/a | P48: n/a | Q48: n/a | R48: n/a | S48: n/a | T48: n/a
A49: In-place Rent | B49: INR psf/mo | F49: 63 | G49: 65 | H49: 84 | I49: 97 | J49: 100.1 | K49: =IFERROR((J49-I49)/I49,"") | L49: n/a | M49: n/a | N49: n/a | O49: n/a | P49: n/a | Q49: n/a | R49: n/a | S49: n/a | T49: n/a
A52: DEBT & NDCF / DISTRIBUTION DETAIL (consolidated; INR cr unless noted)
A53: Metric | B53: Unit | C53: FY2019 | D53: FY2020 | E53: FY2021 | F53: FY2022 | G53: FY2023 | H53: FY2024 | I53: FY2025 | J53: FY2026
A54: Distribution composition (NDCF -> unitholders)
A55: Net Distributable Cash Flow (NDCF) | B55: INR cr | C55: =IF(N(C23)=0,IF(C23="","",C23),C23) | D55: =IF(N(D23)=0,IF(D23="","",D23),D23) | E55: =IF(N(E23)=0,IF(E23="","",E23),E23) | F55: =IF(N(F23)=0,IF(F23="","",F23),F23) | G55: =IF(N(G23)=0,IF(G23="","",G23),G23) | H55: =IF(N(H23)=0,IF(H23="","",H23),H23) | I55: =IF(N(I23)=0,IF(I23="","",I23),I23) | J55: =IF(N(J23)=0,IF(J23="","",J23),J23)
A56: Total Distribution | B56: INR cr | C56: =IF(N(C24)=0,IF(C24="","",C24),C24) | D56: =IF(N(D24)=0,IF(D24="","",D24),D24) | E56: =IF(N(E24)=0,IF(E24="","",E24),E24) | F56: =IF(N(F24)=0,IF(F24="","",F24),F24) | G56: =IF(N(G24)=0,IF(G24="","",G24),G24) | H56: =IF(N(H24)=0,IF(H24="","",H24),H24) | I56: =IF(N(I24)=0,IF(I24="","",I24),I24) | J56: =IF(N(J24)=0,IF(J24="","",J24),J24) | S56: =A7 | T56: =B7 | U56: =F7 | V56: =G7 | W56: =H7 | X56: =I7 | Y56: =J7
A57: of which: Interest | B57: INR cr | H57: 382.6 | S57: =A46 | T57: =B46 | U57: =F46*10 | V57: =G46*10 | W57: =H46*10 | X57: 8.8 | Y57: 9.29
A58: of which: Dividend | B58: INR cr | S58: =A47 | T58: =B47 | U58: =F47 | V58: =G47 | W58: =H47 | X58: =I47 | Y58: =J47
A59: of which: Return of capital (SPV/shareholder-loan repayment) | B59: INR cr | H59: 560
A60: of which: Other | B60: INR cr
A61: Return-of-capital % of distribution | B61: % | C61: =IF(OR(C59="",C56="",N(C56)=0),"",C59/C56) | D61: =IF(OR(D59="",D56="",N(D56)=0),"",D59/D56) | E61: =IF(OR(E59="",E56="",N(E56)=0),"",E59/E56) | F61: =IF(OR(F59="",F56="",N(F56)=0),"",F59/F56) | G61: =IF(OR(G59="",G56="",N(G56)=0),"",G59/G56) | H61: =IF(OR(H59="",H56="",N(H56)=0),"",H59/H56) | I61: =IF(OR(I59="",I56="",N(I56)=0),"",I59/I56) | J61: =IF(OR(J59="",J56="",N(J56)=0),"",J59/J56)
A62: Distribution per Unit (DPU) | B62: INR/unit | C62: =IF(N(C25)=0,IF(C25="","",C25),C25) | D62: =IF(N(D25)=0,IF(D25="","",D25),D25) | E62: =IF(N(E25)=0,IF(E25="","",E25),E25) | F62: =IF(N(F25)=0,IF(F25="","",F25),F25) | G62: =IF(N(G25)=0,IF(G25="","",G25),G25) | H62: =IF(N(H25)=0,IF(H25="","",H25),H25) | I62: =IF(N(I25)=0,IF(I25="","",I25),I25) | J62: =IF(N(J25)=0,IF(J25="","",J25),J25)
A63: DPU: Interest | B63: INR/unit | I63: 2.01 | J63: 1.66
A64: DPU: Dividend | B64: INR/unit | I64: 0.54 | J64: 0.88
A65: DPU: Return of capital | B65: INR/unit | I65: 2.7 | J65: 2.96
A66: DPU: Other | B66: INR/unit
A67: Debt & leverage profile
A68: Gross Debt - external (banks/NCDs/LRD) | B68: INR cr | C68: =IF(C29="","",C29) | D68: =IF(D29="","",D29) | E68: =IF(E29="","",E29) | F68: =IF(F29="","",F29) | G68: =IF(G29="","",G29) | H68: 10790 | I68: 11180 | J68: 18840
A69: Shareholder / unitholder loans (Trust -> SPVs) | B69: INR cr | I69: 4542.464 | J69: 4407.554
A70: Cash & Cash Equivalents | B70: INR cr | C70: =IF(N(C30)=0,IF(C30="","",C30),C30) | D70: =IF(N(D30)=0,IF(D30="","",D30),D30) | E70: =IF(N(E30)=0,IF(E30="","",E30),E30) | F70: =IF(N(F30)=0,IF(F30="","",F30),F30) | G70: =IF(N(G30)=0,IF(G30="","",G30),G30) | H70: =IF(N(H30)=0,IF(H30="","",H30),H30) | I70: =IF(N(I30)=0,IF(I30="","",I30),I30) | J70: =IF(N(J30)=0,IF(J30="","",J30),J30)
A71: Net Debt | B71: INR cr | C71: =IF(N(C31)=0,IF(C31="","",C31),C31) | D71: =IF(N(D31)=0,IF(D31="","",D31),D31) | E71: =IF(N(E31)=0,IF(E31="","",E31),E31) | F71: =IF(N(F31)=0,IF(F31="","",F31),F31) | G71: =IF(N(G31)=0,IF(G31="","",G31),G31) | H71: =IF(N(H31)=0,IF(H31="","",H31),H31) | I71: =IF(N(I31)=0,IF(I31="","",I31),I31) | J71: =IF(N(J31)=0,IF(J31="","",J31),J31)
A72: Gross Asset Value (GAV) | B72: INR cr | C72: =IF(N(C28)=0,IF(C28="","",C28),C28) | D72: =IF(N(D28)=0,IF(D28="","",D28),D28) | E72: =IF(N(E28)=0,IF(E28="","",E28),E28) | F72: =IF(N(F28)=0,IF(F28="","",F28),F28) | G72: =IF(N(G28)=0,IF(G28="","",G28),G28) | H72: =IF(N(H28)=0,IF(H28="","",H28),H28) | I72: =IF(N(I28)=0,IF(I28="","",I28),I28) | J72: =IF(N(J28)=0,IF(J28="","",J28),J28)
A73: Loan-to-Value (LTV) | B73: % | C73: =IF(N(C33)=0,IF(C33="","",C33),C33) | D73: =IF(N(D33)=0,IF(D33="","",D33),D33) | E73: =IF(N(E33)=0,IF(E33="","",E33),E33) | F73: =IF(N(F33)=0,IF(F33="","",F33),F33) | G73: =IF(N(G33)=0,IF(G33="","",G33),G33) | H73: =IF(N(H33)=0,IF(H33="","",H33),H33) | I73: =IF(N(I33)=0,IF(I33="","",I33),I33) | J73: =IF(N(J33)=0,IF(J33="","",J33),J33)
A74: Cost of Debt (wtd avg) | B74: % | C74: =IF(N(C40)=0,IF(C40="","",C40),C40) | D74: =IF(N(D40)=0,IF(D40="","",D40),D40) | E74: =IF(N(E40)=0,IF(E40="","",E40),E40) | F74: =IF(N(F40)=0,IF(F40="","",F40),F40) | G74: =IF(N(G40)=0,IF(G40="","",G40),G40) | H74: =IF(N(H40)=0,IF(H40="","",H40),H40) | I74: =IF(N(I40)=0,IF(I40="","",I40),I40) | J74: =IF(N(J40)=0,IF(J40="","",J40),J40)
A75: % Floating rate | B75: % | H75: 0.87 | I75: 0.84 | J75: 0.1
A76: Wtd-avg debt maturity | B76: years | H76: 9 | I76: 10 | J76: 10
A77: Undrawn debt headroom | B77: INR cr | J77: 5000
A78: Interest cover (NOI / Finance cost) | B78: x | C78: =IF(OR(C13="",N(C17)=0),"",C13/C17) | D78: =IF(OR(D13="",N(D17)=0),"",D13/D17) | E78: =IF(OR(E13="",N(E17)=0),"",E13/E17) | F78: =IF(OR(F13="",N(F17)=0),"",F13/F17) | G78: =IF(OR(G13="",N(G17)=0),"",G13/G17) | H78: =IF(OR(H13="",N(H17)=0),"",H13/H17) | I78: =IF(OR(I13="",N(I17)=0),"",I13/I17) | J78: =IF(OR(J13="",N(J17)=0),"",J13/J17)
A80: Distribution-component split is shown where the issuer disclosed it (often per-unit for Q4 only in older years); blanks = not separately disclosed.

Sheet Nexus
A1: Nexus REIT - Key Financials & Operating Metrics
A2: Sponsor: Blackstone (Retail REIT). All INR figures in INR crore (cr) unless stated. 1 crore = 10 million. FY ends 31 March.
A3: Hover a cell for its Source (report + page + original figure). Grey italic = auto-calculated. YoY% = FY2026 vs FY2025.
C6: CONSOLIDATED | L6: STANDALONE
A7: Metric | B7: Unit | C7: FY2019 | D7: FY2020 | E7: FY2021 | F7: FY2022 | G7: FY2023 | H7: FY2024 | I7: FY2025 | J7: FY2026 | K7: YoY% | L7: FY2019 | M7: FY2020 | N7: FY2021 | O7: FY2022 | P7: FY2023 | Q7: FY2024 | R7: FY2025 | S7: FY2026 | T7: YoY%
A8: INCOME STATEMENT
A9: Revenue from Operations | B9: INR cr | H9: 1916.374 | I9: 2282.89 | J9: 2568 | K9: =IFERROR((J9-I9)/I9,"") | T9: =IFERROR((S9-R9)/R9,"")
A10: Other Income | B10: INR cr | H10: 80.737 | I10: 116.52 | J10: 87.3 | K10: =IFERROR((J10-I10)/I10,"") | Q10: 6.947 | R10: 14.87 | S10: 5.24 | T10: =IFERROR((S10-R10)/R10,"")
A11: Total Income | B11: INR cr | C11: =IF(AND(C9="",C10=""),"",N(C9)+N(C10)) | D11: =IF(AND(D9="",D10=""),"",N(D9)+N(D10)) | E11: =IF(AND(E9="",E10=""),"",N(E9)+N(E10)) | F11: =IF(AND(F9="",F10=""),"",N(F9)+N(F10)) | G11: =IF(AND(G9="",G10=""),"",N(G9)+N(G10)) | H11: =IF(AND(H9="",H10=""),"",N(H9)+N(H10)) | I11: =IF(AND(I9="",I10=""),"",N(I9)+N(I10)) | J11: =IF(AND(J9="",J10=""),"",N(J9)+N(J10)) | K11: =IFERROR((J11-I11)/I11,"") | L11: =IF(AND(L9="",L10=""),"",N(L9)+N(L10)) | M11: =IF(AND(M9="",M10=""),"",N(M9)+N(M10)) | N11: =IF(AND(N9="",N10=""),"",N(N9)+N(N10)) | O11: =IF(AND(O9="",O10=""),"",N(O9)+N(O10)) | P11: =IF(AND(P9="",P10=""),"",N(P9)+N(P10)) | Q11: =IF(AND(Q9="",Q10=""),"",N(Q9)+N(Q10)) | R11: =IF(AND(R9="",R10=""),"",N(R9)+N(R10)) | S11: =IF(AND(S9="",S10=""),"",N(S9)+N(S10)) | T11: =IFERROR((S11-R11)/R11,"")
A12: Property / Operating Expenses | B12: INR cr | H12: 166.227 | I12: 387.06 | J12: 428.43 | K12: =IFERROR((J12-I12)/I12,"") | R12: 12.62 | S12: 13.66 | T12: =IFERROR((S12-R12)/R12,"")
A13: Net Operating Income (NOI) | B13: INR cr | H13: 1434.788 | I13: 1711.03 | J13: 1929.64 | K13: =IFERROR((J13-I13)/I13,"") | T13: =IFERROR((S13-R13)/R13,"")
A14: NOI Margin | B14: % | C14: =IF(OR(C13="",C9="",N(C9)=0),"",C13/C9) | D14: =IF(OR(D13="",D9="",N(D9)=0),"",D13/D9) | E14: =IF(OR(E13="",E9="",N(E9)=0),"",E13/E9) | F14: =IF(OR(F13="",F9="",N(F9)=0),"",F13/F9) | G14: =IF(OR(G13="",G9="",N(G9)=0),"",G13/G9) | H14: =IF(OR(H13="",H9="",N(H9)=0),"",H13/H9) | I14: =IF(OR(I13="",I9="",N(I9)=0),"",I13/I9) | J14: =IF(OR(J13="",J9="",N(J9)=0),"",J13/J9) | L14: =IF(OR(L13="",L9="",N(L9)=0),"",L13/L9) | M14: =IF(OR(M13="",M9="",N(M9)=0),"",M13/M9) | N14: =IF(OR(N13="",N9="",N(N9)=0),"",N13/N9) | O14: =IF(OR(O13="",O9="",N(O9)=0),"",O13/O9) | P14: =IF(OR(P13="",P9="",N(P9)=0),"",P13/P9) | Q14: =IF(OR(Q13="",Q9="",N(Q9)=0),"",Q13/Q9) | R14: =IF(OR(R13="",R9="",N(R9)=0),"",R13/R9) | S14: =IF(OR(S13="",S9="",N(S9)=0),"",S13/S9)
A15: EBITDA | B15: INR cr | H15: 1365.778 | I15: 1660.76 | J15: 1820.73 | K15: =IFERROR((J15-I15)/I15,"") | Q15: 1046.081 | R15: 1307.16 | S15: 1485.44 | T15: =IFERROR((S15-R15)/R15,"")
A16: EBITDA Margin | B16: % | C16: =IF(OR(C15="",C9="",N(C9)=0),"",C15/C9) | D16: =IF(OR(D15="",D9="",N(D9)=0),"",D15/D9) | E16: =IF(OR(E15="",E9="",N(E9)=0),"",E15/E9) | F16: =IF(OR(F15="",F9="",N(F9)=0),"",F15/F9) | G16: =IF(OR(G15="",G9="",N(G9)=0),"",G15/G9) | H16: =IF(OR(H15="",H9="",N(H9)=0),"",H15/H9) | I16: =IF(OR(I15="",I9="",N(I9)=0),"",I15/I9) | J16: =IF(OR(J15="",J9="",N(J9)=0),"",J15/J9) | L16: =IF(OR(L15="",L9="",N(L9)=0),"",L15/L9) | M16: =IF(OR(M15="",M9="",N(M9)=0),"",M15/M9) | N16: =IF(OR(N15="",N9="",N(N9)=0),"",N15/N9) | O16: =IF(OR(O15="",O9="",N(O9)=0),"",O15/O9) | P16: =IF(OR(P15="",P9="",N(P9)=0),"",P15/P9) | Q16: =IF(OR(Q15="",Q9="",N(Q9)=0),"",Q15/Q9) | R16: =IF(OR(R15="",R9="",N(R9)=0),"",R15/R9) | S16: =IF(OR(S15="",S9="",N(S9)=0),"",S15/S9)
A17: Finance Costs | B17: INR cr | H17: 337.095 | I17: 394.34 | J17: 457.95 | K17: =IFERROR((J17-I17)/I17,"") | Q17: 150.091 | R17: 234.51 | S17: 316.22 | T17: =IFERROR((S17-R17)/R17,"")
A18: Depreciation & Amortisation | B18: INR cr | H18: 570.164 | I18: 586.12 | J18: 619.84 | K18: =IFERROR((J18-I18)/I18,"") | T18: =IFERROR((S18-R18)/R18,"")
A19: Profit Before Tax (PBT) | B19: INR cr | H19: 514.775 | I19: 697.85 | J19: 743.29 | K19: =IFERROR((J19-I19)/I19,"") | Q19: 895.99 | R19: 1072.65 | S19: 1169.22 | T19: =IFERROR((S19-R19)/R19,"")
A20: Profit After Tax (PAT) | B20: INR cr | H20: 597.846 | I20: 482.81 | J20: 403.47 | K20: =IFERROR((J20-I20)/I20,"") | Q20: 893.91 | R20: 1069.01 | S20: 1168.43 | T20: =IFERROR((S20-R20)/R20,"")
A21: PAT Margin | B21: % | C21: =IF(OR(C20="",C9="",N(C9)=0),"",C20/C9) | D21: =IF(OR(D20="",D9="",N(D9)=0),"",D20/D9) | E21: =IF(OR(E20="",E9="",N(E9)=0),"",E20/E9) | F21: =IF(OR(F20="",F9="",N(F9)=0),"",F20/F9) | G21: =IF(OR(G20="",G9="",N(G9)=0),"",G20/G9) | H21: =IF(OR(H20="",H9="",N(H9)=0),"",H20/H9) | I21: =IF(OR(I20="",I9="",N(I9)=0),"",I20/I9) | J21: =IF(OR(J20="",J9="",N(J9)=0),"",J20/J9) | L21: =IF(OR(L20="",L9="",N(L9)=0),"",L20/L9) | M21: =IF(OR(M20="",M9="",N(M9)=0),"",M20/M9) | N21: =IF(OR(N20="",N9="",N(N9)=0),"",N20/N9) | O21: =IF(OR(O20="",O9="",N(O9)=0),"",O20/O9) | P21: =IF(OR(P20="",P9="",N(P9)=0),"",P20/P9) | Q21: =IF(OR(Q20="",Q9="",N(Q9)=0),"",Q20/Q9) | R21: =IF(OR(R20="",R9="",N(R9)=0),"",R20/R9) | S21: =IF(OR(S20="",S9="",N(S9)=0),"",S20/S9)
A22: DISTRIBUTIONS & CASH FLOW
A23: Net Distributable Cash Flow (NDCF) | B23: INR cr | H23: 1071.863 | I23: 1190.48 | J23: 1279.32 | K23: =IFERROR((J23-I23)/I23,"") | L23: n/a | M23: n/a | N23: n/a | O23: n/a | P23: n/a | Q23: n/a | R23: n/a | S23: n/a | T23: n/a
A24: Total Distribution | B24: INR cr | H24: 755.076 | I24: 1234.725 | J24: 1375.77 | K24: =IFERROR((J24-I24)/I24,"") | L24: n/a | M24: n/a | N24: n/a | O24: n/a | P24: n/a | Q24: n/a | R24: n/a | S24: n/a | T24: n/a
A25: Distribution per Unit (DPU) | B25: INR/unit | H25: 4.99 | I25: 8.15 | J25: 9.08 | K25: =IFERROR((J25-I25)/I25,"") | L25: n/a | M25: n/a | N25: n/a | O25: n/a | P25: n/a | Q25: n/a | R25: n/a | S25: n/a | T25: n/a
A26: NDCF Payout Ratio | B26: % | C26: =IF(OR(C24="",C23="",N(C23)=0),"",C24/C23) | D26: =IF(OR(D24="",D23="",N(D23)=0),"",D24/D23) | E26: =IF(OR(E24="",E23="",N(E23)=0),"",E24/E23) | F26: =IF(OR(F24="",F23="",N(F23)=0),"",F24/F23) | G26: =IF(OR(G24="",G23="",N(G23)=0),"",G24/G23) | H26: =IF(OR(H24="",H23="",N(H23)=0),"",H24/H23) | I26: =IF(OR(I24="",I23="",N(I23)=0),"",I24/I23) | J26: =IF(OR(J24="",J23="",N(J23)=0),"",J24/J23) | L26: n/a | M26: n/a | N26: n/a | O26: n/a | P26: n/a | Q26: n/a | R26: n/a | S26: n/a | T26: n/a
A27: BALANCE SHEET & LEVERAGE
A28: Gross Asset Value (GAV) / AUM | B28: INR cr | H28: 27083.693 | I28: 29411.332 | J28: 30558.3 | K28: =IFERROR((J28-I28)/I28,"") | L28: n/a | M28: n/a | N28: n/a | O28: n/a | P28: n/a | Q28: n/a | R28: n/a | S28: n/a | T28: n/a
A29: Gross Debt | B29: INR cr | H29: 4263.531 | I29: 5328.55 | J29: 6197.23 | K29: =IFERROR((J29-I29)/I29,"") | Q29: 7224.537 | R29: 3521.13 | S29: 4384.91 | T29: =IFERROR((S29-R29)/R29,"")
A30: Cash & Cash Equivalents | B30: INR cr | H30: 39.404 | I30: 19.3 | J30: 36.03 | K30: =IFERROR((J30-I30)/I30,"") | Q30: 52.016 | R30: 7.72 | S30: 23.11 | T30: =IFERROR((S30-R30)/R30,"")
A31: Net Debt | B31: INR cr | C31: =IF(C29="","",C29-N(C30)) | D31: =IF(D29="","",D29-N(D30)) | E31: =IF(E29="","",E29-N(E30)) | F31: =IF(F29="","",F29-N(F30)) | G31: =IF(G29="","",G29-N(G30)) | H31: =IF(H29="","",H29-N(H30)) | I31: =IF(I29="","",I29-N(I30)) | J31: =IF(J29="","",J29-N(J30)) | K31: =IFERROR((J31-I31)/I31,"") | L31: =IF(L29="","",L29-N(L30)) | M31: =IF(M29="","",M29-N(M30)) | N31: =IF(N29="","",N29-N(N30)) | O31: =IF(O29="","",O29-N(O30)) | P31: =IF(P29="","",P29-N(P30)) | Q31: =IF(Q29="","",Q29-N(Q30)) | R31: =IF(R29="","",R29-N(R30)) | S31: =IF(S29="","",S29-N(S30)) | T31: =IFERROR((S31-R31)/R31,"")
A32: Net Worth / Unitholders Equity | B32: INR cr | H32: 14934.85 | I32: 14138.66 | J32: 13210.1 | K32: =IFERROR((J32-I32)/I32,"") | Q32: 15230.914 | R32: 15021.11 | S32: 14857.09 | T32: =IFERROR((S32-R32)/R32,"")
A33: Loan-to-Value (LTV) | B33: % | C33: =IF(OR(C31="",C28="",N(C28)=0),"",C31/C28) | D33: =IF(OR(D31="",D28="",N(D28)=0),"",D31/D28) | E33: =IF(OR(E31="",E28="",N(E28)=0),"",E31/E28) | F33: =IF(OR(F31="",F28="",N(F28)=0),"",F31/F28) | G33: =IF(OR(G31="",G28="",N(G28)=0),"",G31/G28) | H33: =IF(OR(H31="",H28="",N(H28)=0),"",H31/H28) | I33: =IF(OR(I31="",I28="",N(I28)=0),"",I31/I28) | J33: =IF(OR(J31="",J28="",N(J28)=0),"",J31/J28) | L33: =IF(OR(L31="",L28="",N(L28)=0),"",L31/L28) | M33: =IF(OR(M31="",M28="",N(M28)=0),"",M31/M28) | N33: =IF(OR(N31="",N28="",N(N28)=0),"",N31/N28) | O33: =IF(OR(O31="",O28="",N(O28)=0),"",O31/O28) | P33: =IF(OR(P31="",P28="",N(P28)=0),"",P31/P28) | Q33: =IF(OR(Q31="",Q28="",N(Q28)=0),"",Q31/Q28) | R33: =IF(OR(R31="",R28="",N(R28)=0),"",R31/R28) | S33: =IF(OR(S31="",S28="",N(S28)=0),"",S31/S28)
A34: NAV per Unit | B34: INR/unit | H34: 98.58 | I34: 93.32 | J34: 87.7 | K34: =IFERROR((J34-I34)/I34,"") | L34: n/a | M34: n/a | N34: n/a | O34: n/a | P34: n/a | Q34: n/a | R34: n/a | S34: n/a | T34: n/a
A35: MARKET DATA
A36: Units Outstanding | B36: mn units | H36: 1515 | I36: 1515 | J36: 1515 | K36: =IFERROR((J36-I36)/I36,"") | L36: n/a | M36: n/a | N36: n/a | O36: n/a | P36: n/a | Q36: n/a | R36: n/a | S36: n/a | T36: n/a
A37: Unit Price (period-end) | B37: INR/unit | H37: 128 | I37: 130.5 | J37: 151 | K37: =IFERROR((J37-I37)/I37,"") | L37: n/a | M37: n/a | N37: n/a | O37: n/a | P37: n/a | Q37: n/a | R37: n/a | S37: n/a | T37: n/a
A38: Market Capitalisation | B38: INR cr | C38: =IF(OR(C36="",C37=""),"",C36*C37/10) | D38: =IF(OR(D36="",D37=""),"",D36*D37/10) | E38: =IF(OR(E36="",E37=""),"",E36*E37/10) | F38: =IF(OR(F36="",F37=""),"",F36*F37/10) | G38: =IF(OR(G36="",G37=""),"",G36*G37/10) | H38: =IF(OR(H36="",H37=""),"",H36*H37/10) | I38: =IF(OR(I36="",I37=""),"",I36*I37/10) | J38: =IF(OR(J36="",J37=""),"",J36*J37/10) | K38: =IFERROR((J38-I38)/I38,"") | L38: n/a | M38: n/a | N38: n/a | O38: n/a | P38: n/a | Q38: n/a | R38: n/a | S38: n/a | T38: n/a
A39: Annual Distribution Yield | B39: % | C39: =IF(OR(C25="",C37="",N(C37)=0),"",C25/C37) | D39: =IF(OR(D25="",D37="",N(D37)=0),"",D25/D37) | E39: =IF(OR(E25="",E37="",N(E37)=0),"",E25/E37) | F39: =IF(OR(F25="",F37="",N(F37)=0),"",F25/F37) | G39: =IF(OR(G25="",G37="",N(G37)=0),"",G25/G37) | H39: =IF(OR(H25="",H37="",N(H37)=0),"",H25/H37) | I39: =IF(OR(I25="",I37="",N(I37)=0),"",I25/I37) | J39: =IF(OR(J25="",J37="",N(J37)=0),"",J25/J37) | L39: n/a | M39: n/a | N39: n/a | O39: n/a | P39: n/a | Q39: n/a | R39: n/a | S39: n/a | T39: n/a
A40: Cost of Debt | B40: % | H40: 0.08 | I40: 0.08 | J40: 0.075 | L40: n/a | M40: n/a | N40: n/a | O40: n/a | P40: n/a | Q40: n/a | R40: n/a | S40: n/a | T40: n/a
A41: PORTFOLIO & OPERATING METRICS (consolidated)
A42: Total Leasable Area (GLA) | B42: Msf | H42: 9.9 | I42: 10.4 | J42: 11.9 | K42: =IFERROR((J42-I42)/I42,"") | L42: n/a | M42: n/a | N42: n/a | O42: n/a | P42: n/a | Q42: n/a | R42: n/a | S42: n/a | T42: n/a
A43: Operational Area | B43: Msf | H43: 9.5 | I43: 10 | J43: 11.3 | K43: =IFERROR((J43-I43)/I43,"") | L43: n/a | M43: n/a | N43: n/a | O43: n/a | P43: n/a | Q43: n/a | R43: n/a | S43: n/a | T43: n/a
A44: Under Construction + Future Development | B44: Msf | K44: =IFERROR((J44-I44)/I44,"") | L44: n/a | M44: n/a | N44: n/a | O44: n/a | P44: n/a | Q44: n/a | R44: n/a | S44: n/a | T44: n/a
A45: Committed Occupancy | B45: % | H45: 0.98 | I45: 0.97 | J45: 0.97 | L45: n/a | M45: n/a | N45: n/a | O45: n/a | P45: n/a | Q45: n/a | R45: n/a | S45: n/a | T45: n/a
A46: In-place / Physical Occupancy | B46: % | H46: 0.96 | I46: 0.97 | J46: 0.95 | L46: n/a | M46: n/a | N46: n/a | O46: n/a | P46: n/a | Q46: n/a | R46: n/a | S46: n/a | T46: n/a
A47: WALE | B47: years | H47: 5.1 | I47: 4.9 | J47: 4.7 | K47: =IFERROR((J47-I47)/I47,"") | L47: n/a | M47: n/a | N47: n/a | O47: n/a | P47: n/a | Q47: n/a | R47: n/a | S47: n/a | T47: n/a
A48: Number of Tenants | B48: count | H48: 3000 | I48: 3000 | J48: 3200 | K48: =IFERROR((J48-I48)/I48,"") | L48: n/a | M48: n/a | N48: n/a | O48: n/a | P48: n/a | Q48: n/a | R48: n/a | S48: n/a | T48: n/a
A49: In-place Rent | B49: INR psf/mo | H49: 127 | I49: 134 | K49: =IFERROR((J49-I49)/I49,"") | L49: n/a | M49: n/a | N49: n/a | O49: n/a | P49: n/a | Q49: n/a | R49: n/a | S49: n/a | T49: n/a
A52: DEBT & NDCF / DISTRIBUTION DETAIL (consolidated; INR cr unless noted)
A53: Metric | B53: Unit | C53: FY2019 | D53: FY2020 | E53: FY2021 | F53: FY2022 | G53: FY2023 | H53: FY2024 | I53: FY2025 | J53: FY2026
A54: Distribution composition (NDCF -> unitholders)
A55: Net Distributable Cash Flow (NDCF) | B55: INR cr | C55: =IF(N(C23)=0,IF(C23="","",C23),C23) | D55: =IF(N(D23)=0,IF(D23="","",D23),D23) | E55: =IF(N(E23)=0,IF(E23="","",E23),E23) | F55: =IF(N(F23)=0,IF(F23="","",F23),F23) | G55: =IF(N(G23)=0,IF(G23="","",G23),G23) | H55: =IF(N(H23)=0,IF(H23="","",H23),H23) | I55: =IF(N(I23)=0,IF(I23="","",I23),I23) | J55: =IF(N(J23)=0,IF(J23="","",J23),J23)
A56: Total Distribution | B56: INR cr | C56: =IF(N(C24)=0,IF(C24="","",C24),C24) | D56: =IF(N(D24)=0,IF(D24="","",D24),D24) | E56: =IF(N(E24)=0,IF(E24="","",E24),E24) | F56: =IF(N(F24)=0,IF(F24="","",F24),F24) | G56: =IF(N(G24)=0,IF(G24="","",G24),G24) | H56: =IF(N(H24)=0,IF(H24="","",H24),H24) | I56: =IF(N(I24)=0,IF(I24="","",I24),I24) | J56: =IF(N(J24)=0,IF(J24="","",J24),J24) | S56: =A7 | T56: =B7 | U56: =H7 | V56: =I7 | W56: =J7
A57: of which: Interest | B57: INR cr | S57: =A46 | T57: =B46 | U57: =H46*10 | V57: 8.8 | W57: 9.29
A58: of which: Dividend | B58: INR cr | S58: =A47 | T58: =B47 | U58: =H47 | V58: =I47 | W58: =J47
A59: of which: Return of capital (SPV/shareholder-loan repayment) | B59: INR cr
A60: of which: Other | B60: INR cr
A61: Return-of-capital % of distribution | B61: % | C61: =IF(OR(C59="",C56="",N(C56)=0),"",C59/C56) | D61: =IF(OR(D59="",D56="",N(D56)=0),"",D59/D56) | E61: =IF(OR(E59="",E56="",N(E56)=0),"",E59/E56) | F61: =IF(OR(F59="",F56="",N(F56)=0),"",F59/F56) | G61: =IF(OR(G59="",G56="",N(G56)=0),"",G59/G56) | H61: =IF(OR(H59="",H56="",N(H56)=0),"",H59/H56) | I61: =IF(OR(I59="",I56="",N(I56)=0),"",I59/I56) | J61: =IF(OR(J59="",J56="",N(J56)=0),"",J59/J56)
A62: Distribution per Unit (DPU) | B62: INR/unit | C62: =IF(N(C25)=0,IF(C25="","",C25),C25) | D62: =IF(N(D25)=0,IF(D25="","",D25),D25) | E62: =IF(N(E25)=0,IF(E25="","",E25),E25) | F62: =IF(N(F25)=0,IF(F25="","",F25),F25) | G62: =IF(N(G25)=0,IF(G25="","",G25),G25) | H62: =IF(N(H25)=0,IF(H25="","",H25),H25) | I62: =IF(N(I25)=0,IF(I25="","",I25),I25) | J62: =IF(N(J25)=0,IF(J25="","",J25),J25)
A63: DPU: Interest | B63: INR/unit
A64: DPU: Dividend | B64: INR/unit
A65: DPU: Return of capital | B65: INR/unit
A66: DPU: Other | B66: INR/unit
A67: Debt & leverage profile
A68: Gross Debt - external (banks/NCDs/LRD) | B68: INR cr | C68: =IF(C29="","",C29) | D68: =IF(D29="","",D29) | E68: =IF(E29="","",E29) | F68: =IF(F29="","",F29) | G68: =IF(G29="","",G29) | H68: 4263.531 | I68: 5328.55 | J68: 6197.23
A69: Shareholder / unitholder loans (Trust -> SPVs) | B69: INR cr | H69: 3005.518 | I69: 4151.07 | J69: 4785.45
A70: Cash & Cash Equivalents | B70: INR cr | C70: =IF(N(C30)=0,IF(C30="","",C30),C30) | D70: =IF(N(D30)=0,IF(D30="","",D30),D30) | E70: =IF(N(E30)=0,IF(E30="","",E30),E30) | F70: =IF(N(F30)=0,IF(F30="","",F30),F30) | G70: =IF(N(G30)=0,IF(G30="","",G30),G30) | H70: =IF(N(H30)=0,IF(H30="","",H30),H30) | I70: =IF(N(I30)=0,IF(I30="","",I30),I30) | J70: =IF(N(J30)=0,IF(J30="","",J30),J30)
A71: Net Debt | B71: INR cr | C71: =IF(N(C31)=0,IF(C31="","",C31),C31) | D71: =IF(N(D31)=0,IF(D31="","",D31),D31) | E71: =IF(N(E31)=0,IF(E31="","",E31),E31) | F71: =IF(N(F31)=0,IF(F31="","",F31),F31) | G71: =IF(N(G31)=0,IF(G31="","",G31),G31) | H71: =IF(N(H31)=0,IF(H31="","",H31),H31) | I71: =IF(N(I31)=0,IF(I31="","",I31),I31) | J71: =IF(N(J31)=0,IF(J31="","",J31),J31)
A72: Gross Asset Value (GAV) | B72: INR cr | C72: =IF(N(C28)=0,IF(C28="","",C28),C28) | D72: =IF(N(D28)=0,IF(D28="","",D28),D28) | E72: =IF(N(E28)=0,IF(E28="","",E28),E28) | F72: =IF(N(F28)=0,IF(F28="","",F28),F28) | G72: =IF(N(G28)=0,IF(G28="","",G28),G28) | H72: =IF(N(H28)=0,IF(H28="","",H28),H28) | I72: =IF(N(I28)=0,IF(I28="","",I28),I28) | J72: =IF(N(J28)=0,IF(J28="","",J28),J28)
A73: Loan-to-Value (LTV) | B73: % | C73: =IF(N(C33)=0,IF(C33="","",C33),C33) | D73: =IF(N(D33)=0,IF(D33="","",D33),D33) | E73: =IF(N(E33)=0,IF(E33="","",E33),E33) | F73: =IF(N(F33)=0,IF(F33="","",F33),F33) | G73: =IF(N(G33)=0,IF(G33="","",G33),G33) | H73: =IF(N(H33)=0,IF(H33="","",H33),H33) | I73: =IF(N(I33)=0,IF(I33="","",I33),I33) | J73: =IF(N(J33)=0,IF(J33="","",J33),J33)
A74: Cost of Debt (wtd avg) | B74: % | C74: =IF(N(C40)=0,IF(C40="","",C40),C40) | D74: =IF(N(D40)=0,IF(D40="","",D40),D40) | E74: =IF(N(E40)=0,IF(E40="","",E40),E40) | F74: =IF(N(F40)=0,IF(F40="","",F40),F40) | G74: =IF(N(G40)=0,IF(G40="","",G40),G40) | H74: =IF(N(H40)=0,IF(H40="","",H40),H40) | I74: =IF(N(I40)=0,IF(I40="","",I40),I40) | J74: =IF(N(J40)=0,IF(J40="","",J40),J40)
A75: % Floating rate | B75: % | H75: 0.74 | I75: 0.56 | J75: 0.51
A76: Wtd-avg debt maturity | B76: years
A77: Undrawn debt headroom | B77: INR cr
A78: Interest cover (NOI / Finance cost) | B78: x | C78: =IF(OR(C13="",N(C17)=0),"",C13/C17) | D78: =IF(OR(D13="",N(D17)=0),"",D13/D17) | E78: =IF(OR(E13="",N(E17)=0),"",E13/E17) | F78: =IF(OR(F13="",N(F17)=0),"",F13/F17) | G78: =IF(OR(G13="",N(G17)=0),"",G13/G17) | H78: =IF(OR(H13="",N(H17)=0),"",H13/H17) | I78: =IF(OR(I13="",N(I17)=0),"",I13/I17) | J78: =IF(OR(J13="",N(J17)=0),"",J13/J17)
A80: Distribution-component split is shown where the issuer disclosed it (often per-unit for Q4 only in older years); blanks = not separately disclosed.

Sheet Knowledge (KRT)
A1: Knowledge Realty Trust (KRT) - Key Financials & Operating Metrics
A2: Sponsor: Sattva Group / Blackstone. All INR figures in INR crore (cr) unless stated. 1 crore = 10 million. FY ends 31 March.
A3: Hover a cell for its Source (report + page + original figure). Grey italic = auto-calculated. YoY% = FY2026 vs FY2025.
C6: CONSOLIDATED | L6: STANDALONE
A7: Metric | B7: Unit | C7: FY2019 | D7: FY2020 | E7: FY2021 | F7: FY2022 | G7: FY2023 | H7: FY2024 | I7: FY2025 | J7: FY2026 | K7: YoY% | L7: FY2019 | M7: FY2020 | N7: FY2021 | O7: FY2022 | P7: FY2023 | Q7: FY2024 | R7: FY2025 | S7: FY2026 | T7: YoY%
A8: INCOME STATEMENT
A9: Revenue from Operations | B9: INR cr | I9: 0 | J9: 3046.628 | K9: =IFERROR((J9-I9)/I9,"") | T9: =IFERROR((S9-R9)/R9,"")
A10: Other Income | B10: INR cr | J10: 43.982 | K10: =IFERROR((J10-I10)/I10,"") | S10: 7.2 | T10: =IFERROR((S10-R10)/R10,"")
A11: Total Income | B11: INR cr | C11: =IF(AND(C9="",C10=""),"",N(C9)+N(C10)) | D11: =IF(AND(D9="",D10=""),"",N(D9)+N(D10)) | E11: =IF(AND(E9="",E10=""),"",N(E9)+N(E10)) | F11: =IF(AND(F9="",F10=""),"",N(F9)+N(F10)) | G11: =IF(AND(G9="",G10=""),"",N(G9)+N(G10)) | H11: =IF(AND(H9="",H10=""),"",N(H9)+N(H10)) | I11: =IF(AND(I9="",I10=""),"",N(I9)+N(I10)) | J11: =IF(AND(J9="",J10=""),"",N(J9)+N(J10)) | K11: =IFERROR((J11-I11)/I11,"") | L11: =IF(AND(L9="",L10=""),"",N(L9)+N(L10)) | M11: =IF(AND(M9="",M10=""),"",N(M9)+N(M10)) | N11: =IF(AND(N9="",N10=""),"",N(N9)+N(N10)) | O11: =IF(AND(O9="",O10=""),"",N(O9)+N(O10)) | P11: =IF(AND(P9="",P10=""),"",N(P9)+N(P10)) | Q11: =IF(AND(Q9="",Q10=""),"",N(Q9)+N(Q10)) | R11: =IF(AND(R9="",R10=""),"",N(R9)+N(R10)) | S11: =IF(AND(S9="",S10=""),"",N(S9)+N(S10)) | T11: =IFERROR((S11-R11)/R11,"")
A12: Property / Operating Expenses | B12: INR cr | J12: 271.098 | K12: =IFERROR((J12-I12)/I12,"") | T12: =IFERROR((S12-R12)/R12,"")
A13: Net Operating Income (NOI) | B13: INR cr | J13: 2694.076 | K13: =IFERROR((J13-I13)/I13,"") | T13: =IFERROR((S13-R13)/R13,"")
A14: NOI Margin | B14: % | C14: =IF(OR(C13="",C9="",N(C9)=0),"",C13/C9) | D14: =IF(OR(D13="",D9="",N(D9)=0),"",D13/D9) | E14: =IF(OR(E13="",E9="",N(E9)=0),"",E13/E9) | F14: =IF(OR(F13="",F9="",N(F9)=0),"",F13/F9) | G14: =IF(OR(G13="",G9="",N(G9)=0),"",G13/G9) | H14: =IF(OR(H13="",H9="",N(H9)=0),"",H13/H9) | I14: =IF(OR(I13="",I9="",N(I9)=0),"",I13/I9) | J14: =IF(OR(J13="",J9="",N(J9)=0),"",J13/J9) | L14: =IF(OR(L13="",L9="",N(L9)=0),"",L13/L9) | M14: =IF(OR(M13="",M9="",N(M9)=0),"",M13/M9) | N14: =IF(OR(N13="",N9="",N(N9)=0),"",N13/N9) | O14: =IF(OR(O13="",O9="",N(O9)=0),"",O13/O9) | P14: =IF(OR(P13="",P9="",N(P9)=0),"",P13/P9) | Q14: =IF(OR(Q13="",Q9="",N(Q9)=0),"",Q13/Q9) | R14: =IF(OR(R13="",R9="",N(R9)=0),"",R13/R9) | S14: =IF(OR(S13="",S9="",N(S9)=0),"",S13/S9)
A15: EBITDA | B15: INR cr | J15: 2532.579 | K15: =IFERROR((J15-I15)/I15,"") | S15: 2519.71 | T15: =IFERROR((S15-R15)/R15,"")
A16: EBITDA Margin | B16: % | C16: =IF(OR(C15="",C9="",N(C9)=0),"",C15/C9) | D16: =IF(OR(D15="",D9="",N(D9)=0),"",D15/D9) | E16: =IF(OR(E15="",E9="",N(E9)=0),"",E15/E9) | F16: =IF(OR(F15="",F9="",N(F9)=0),"",F15/F9) | G16: =IF(OR(G15="",G9="",N(G9)=0),"",G15/G9) | H16: =IF(OR(H15="",H9="",N(H9)=0),"",H15/H9) | I16: =IF(OR(I15="",I9="",N(I9)=0),"",I15/I9) | J16: =IF(OR(J15="",J9="",N(J9)=0),"",J15/J9) | L16: =IF(OR(L15="",L9="",N(L9)=0),"",L15/L9) | M16: =IF(OR(M15="",M9="",N(M9)=0),"",M15/M9) | N16: =IF(OR(N15="",N9="",N(N9)=0),"",N15/N9) | O16: =IF(OR(O15="",O9="",N(O9)=0),"",O15/O9) | P16: =IF(OR(P15="",P9="",N(P9)=0),"",P15/P9) | Q16: =IF(OR(Q15="",Q9="",N(Q9)=0),"",Q15/Q9) | R16: =IF(OR(R15="",R9="",N(R9)=0),"",R15/R9) | S16: =IF(OR(S15="",S9="",N(S9)=0),"",S15/S9)
A17: Finance Costs | B17: INR cr | J17: 681.952 | K17: =IFERROR((J17-I17)/I17,"") | S17: 128.154 | T17: =IFERROR((S17-R17)/R17,"")
A18: Depreciation & Amortisation | B18: INR cr | J18: 1050.479 | K18: =IFERROR((J18-I18)/I18,"") | S18: 0 | T18: =IFERROR((S18-R18)/R18,"")
A19: Profit Before Tax (PBT) | B19: INR cr | J19: 800.148 | K19: =IFERROR((J19-I19)/I19,"") | S19: 2391.556 | T19: =IFERROR((S19-R19)/R19,"")
A20: Profit After Tax (PAT) | B20: INR cr | J20: 375.436 | K20: =IFERROR((J20-I20)/I20,"") | S20: 2390.63 | T20: =IFERROR((S20-R20)/R20,"")
A21: PAT Margin | B21: % | C21: =IF(OR(C20="",C9="",N(C9)=0),"",C20/C9) | D21: =IF(OR(D20="",D9="",N(D9)=0),"",D20/D9) | E21: =IF(OR(E20="",E9="",N(E9)=0),"",E20/E9) | F21: =IF(OR(F20="",F9="",N(F9)=0),"",F20/F9) | G21: =IF(OR(G20="",G9="",N(G9)=0),"",G20/G9) | H21: =IF(OR(H20="",H9="",N(H9)=0),"",H20/H9) | I21: =IF(OR(I20="",I9="",N(I9)=0),"",I20/I9) | J21: =IF(OR(J20="",J9="",N(J9)=0),"",J20/J9) | L21: =IF(OR(L20="",L9="",N(L9)=0),"",L20/L9) | M21: =IF(OR(M20="",M9="",N(M9)=0),"",M20/M9) | N21: =IF(OR(N20="",N9="",N(N9)=0),"",N20/N9) | O21: =IF(OR(O20="",O9="",N(O9)=0),"",O20/O9) | P21: =IF(OR(P20="",P9="",N(P9)=0),"",P20/P9) | Q21: =IF(OR(Q20="",Q9="",N(Q9)=0),"",Q20/Q9) | R21: =IF(OR(R20="",R9="",N(R9)=0),"",R20/R9) | S21: =IF(OR(S20="",S9="",N(S9)=0),"",S20/S9)
A22: DISTRIBUTIONS & CASH FLOW
A23: Net Distributable Cash Flow (NDCF) | B23: INR cr | J23: 2101.972 | K23: =IFERROR((J23-I23)/I23,"") | L23: n/a | M23: n/a | N23: n/a | O23: n/a | P23: n/a | Q23: n/a | R23: n/a | S23: n/a | T23: n/a
A24: Total Distribution | B24: INR cr | J24: 2101.919 | K24: =IFERROR((J24-I24)/I24,"") | L24: n/a | M24: n/a | N24: n/a | O24: n/a | P24: n/a | Q24: n/a | R24: n/a | S24: n/a | T24: n/a
A25: Distribution per Unit (DPU) | B25: INR/unit | J25: 4.74 | K25: =IFERROR((J25-I25)/I25,"") | L25: n/a | M25: n/a | N25: n/a | O25: n/a | P25: n/a | Q25: n/a | R25: n/a | S25: n/a | T25: n/a
A26: NDCF Payout Ratio | B26: % | C26: =IF(OR(C24="",C23="",N(C23)=0),"",C24/C23) | D26: =IF(OR(D24="",D23="",N(D23)=0),"",D24/D23) | E26: =IF(OR(E24="",E23="",N(E23)=0),"",E24/E23) | F26: =IF(OR(F24="",F23="",N(F23)=0),"",F24/F23) | G26: =IF(OR(G24="",G23="",N(G23)=0),"",G24/G23) | H26: =IF(OR(H24="",H23="",N(H23)=0),"",H24/H23) | I26: =IF(OR(I24="",I23="",N(I23)=0),"",I24/I23) | J26: =IF(OR(J24="",J23="",N(J23)=0),"",J24/J23) | L26: n/a | M26: n/a | N26: n/a | O26: n/a | P26: n/a | Q26: n/a | R26: n/a | S26: n/a | T26: n/a
A27: BALANCE SHEET & LEVERAGE
A28: Gross Asset Value (GAV) / AUM | B28: INR cr | J28: 67411.1 | K28: =IFERROR((J28-I28)/I28,"") | L28: n/a | M28: n/a | N28: n/a | O28: n/a | P28: n/a | Q28: n/a | R28: n/a | S28: n/a | T28: n/a
A29: Gross Debt | B29: INR cr | J29: 12358.644 | K29: =IFERROR((J29-I29)/I29,"") | S29: 4153.742 | T29: =IFERROR((S29-R29)/R29,"")
A30: Cash & Cash Equivalents | B30: INR cr | J30: 626.553 | K30: =IFERROR((J30-I30)/I30,"") | S30: 13.655 | T30: =IFERROR((S30-R30)/R30,"")
A31: Net Debt | B31: INR cr | C31: =IF(C29="","",C29-N(C30)) | D31: =IF(D29="","",D29-N(D30)) | E31: =IF(E29="","",E29-N(E30)) | F31: =IF(F29="","",F29-N(F30)) | G31: =IF(G29="","",G29-N(G30)) | H31: =IF(H29="","",H29-N(H30)) | I31: =IF(I29="","",I29-N(I30)) | J31: =IF(J29="","",J29-N(J30)) | K31: =IFERROR((J31-I31)/I31,"") | L31: =IF(L29="","",L29-N(L30)) | M31: =IF(M29="","",M29-N(M30)) | N31: =IF(N29="","",N29-N(N30)) | O31: =IF(O29="","",O29-N(O30)) | P31: =IF(P29="","",P29-N(P30)) | Q31: =IF(Q29="","",Q29-N(Q30)) | R31: =IF(R29="","",R29-N(R30)) | S31: =IF(S29="","",S29-N(S30)) | T31: =IFERROR((S31-R31)/R31,"")
A32: Net Worth / Unitholders Equity | B32: INR cr | J32: 43187.295 | K32: =IFERROR((J32-I32)/I32,"") | S32: 45202.077 | T32: =IFERROR((S32-R32)/R32,"")
A33: Loan-to-Value (LTV) | B33: % | C33: =IF(OR(C31="",C28="",N(C28)=0),"",C31/C28) | D33: =IF(OR(D31="",D28="",N(D28)=0),"",D31/D28) | E33: =IF(OR(E31="",E28="",N(E28)=0),"",E31/E28) | F33: =IF(OR(F31="",F28="",N(F28)=0),"",F31/F28) | G33: =IF(OR(G31="",G28="",N(G28)=0),"",G31/G28) | H33: =IF(OR(H31="",H28="",N(H28)=0),"",H31/H28) | I33: =IF(OR(I31="",I28="",N(I28)=0),"",I31/I28) | J33: =IF(OR(J31="",J28="",N(J28)=0),"",J31/J28) | L33: =IF(OR(L31="",L28="",N(L28)=0),"",L31/L28) | M33: =IF(OR(M31="",M28="",N(M28)=0),"",M31/M28) | N33: =IF(OR(N31="",N28="",N(N28)=0),"",N31/N28) | O33: =IF(OR(O31="",O28="",N(O28)=0),"",O31/O28) | P33: =IF(OR(P31="",P28="",N(P28)=0),"",P31/P28) | Q33: =IF(OR(Q31="",Q28="",N(Q28)=0),"",Q31/Q28) | R33: =IF(OR(R31="",R28="",N(R28)=0),"",R31/R28) | S33: =IF(OR(S31="",S28="",N(S28)=0),"",S31/S28)
A34: NAV per Unit | B34: INR/unit | J34: 123.61 | K34: =IFERROR((J34-I34)/I34,"") | L34: n/a | M34: n/a | N34: n/a | O34: n/a | P34: n/a | Q34: n/a | R34: n/a | S34: n/a | T34: n/a
A35: MARKET DATA
A36: Units Outstanding | B36: mn units | J36: 4434.4 | K36: =IFERROR((J36-I36)/I36,"") | L36: n/a | M36: n/a | N36: n/a | O36: n/a | P36: n/a | Q36: n/a | R36: n/a | S36: n/a | T36: n/a
A37: Unit Price (period-end) | B37: INR/unit | J37: 113.54 | K37: =IFERROR((J37-I37)/I37,"") | L37: n/a | M37: n/a | N37: n/a | O37: n/a | P37: n/a | Q37: n/a | R37: n/a | S37: n/a | T37: n/a
A38: Market Capitalisation | B38: INR cr | C38: =IF(OR(C36="",C37=""),"",C36*C37/10) | D38: =IF(OR(D36="",D37=""),"",D36*D37/10) | E38: =IF(OR(E36="",E37=""),"",E36*E37/10) | F38: =IF(OR(F36="",F37=""),"",F36*F37/10) | G38: =IF(OR(G36="",G37=""),"",G36*G37/10) | H38: =IF(OR(H36="",H37=""),"",H36*H37/10) | I38: =IF(OR(I36="",I37=""),"",I36*I37/10) | J38: =IF(OR(J36="",J37=""),"",J36*J37/10) | K38: =IFERROR((J38-I38)/I38,"") | L38: n/a | M38: n/a | N38: n/a | O38: n/a | P38: n/a | Q38: n/a | R38: n/a | S38: n/a | T38: n/a
A39: Annual Distribution Yield | B39: % | C39: =IF(OR(C25="",C37="",N(C37)=0),"",C25/C37) | D39: =IF(OR(D25="",D37="",N(D37)=0),"",D25/D37) | E39: =IF(OR(E25="",E37="",N(E37)=0),"",E25/E37) | F39: =IF(OR(F25="",F37="",N(F37)=0),"",F25/F37) | G39: =IF(OR(G25="",G37="",N(G37)=0),"",G25/G37) | H39: =IF(OR(H25="",H37="",N(H37)=0),"",H25/H37) | I39: =IF(OR(I25="",I37="",N(I37)=0),"",I25/I37) | J39: =IF(OR(J25="",J37="",N(J37)=0),"",J25/J37) | L39: n/a | M39: n/a | N39: n/a | O39: n/a | P39: n/a | Q39: n/a | R39: n/a | S39: n/a | T39: n/a
A40: Cost of Debt | B40: % | J40: 0.072 | L40: n/a | M40: n/a | N40: n/a | O40: n/a | P40: n/a | Q40: n/a | R40: n/a | S40: n/a | T40: n/a
A41: PORTFOLIO & OPERATING METRICS (consolidated)
A42: Total Leasable Area (GLA) | B42: Msf | J42: 46.5 | K42: =IFERROR((J42-I42)/I42,"") | L42: n/a | M42: n/a | N42: n/a | O42: n/a | P42: n/a | Q42: n/a | R42: n/a | S42: n/a | T42: n/a
A43: Operational Area | B43: Msf | J43: 37.2 | K43: =IFERROR((J43-I43)/I43,"") | L43: n/a | M43: n/a | N43: n/a | O43: n/a | P43: n/a | Q43: n/a | R43: n/a | S43: n/a | T43: n/a
A44: Under Construction + Future Development | B44: Msf | J44: 9.2 | K44: =IFERROR((J44-I44)/I44,"") | L44: n/a | M44: n/a | N44: n/a | O44: n/a | P44: n/a | Q44: n/a | R44: n/a | S44: n/a | T44: n/a
A45: Committed Occupancy | B45: % | J45: 0.92 | L45: n/a | M45: n/a | N45: n/a | O45: n/a | P45: n/a | Q45: n/a | R45: n/a | S45: n/a | T45: n/a
A46: In-place / Physical Occupancy | B46: % | L46: n/a | M46: n/a | N46: n/a | O46: n/a | P46: n/a | Q46: n/a | R46: n/a | S46: n/a | T46: n/a
A47: WALE | B47: years | J47: 8 | K47: =IFERROR((J47-I47)/I47,"") | L47: n/a | M47: n/a | N47: n/a | O47: n/a | P47: n/a | Q47: n/a | R47: n/a | S47: n/a | T47: n/a
A48: Number of Tenants | B48: count | J48: 475 | K48: =IFERROR((J48-I48)/I48,"") | L48: n/a | M48: n/a | N48: n/a | O48: n/a | P48: n/a | Q48: n/a | R48: n/a | S48: n/a | T48: n/a
A49: In-place Rent | B49: INR psf/mo | J49: 97 | K49: =IFERROR((J49-I49)/I49,"") | L49: n/a | M49: n/a | N49: n/a | O49: n/a | P49: n/a | Q49: n/a | R49: n/a | S49: n/a | T49: n/a
A52: DEBT & NDCF / DISTRIBUTION DETAIL (consolidated; INR cr unless noted)
A53: Metric | B53: Unit | C53: FY2019 | D53: FY2020 | E53: FY2021 | F53: FY2022 | G53: FY2023 | H53: FY2024 | I53: FY2025 | J53: FY2026
A54: Distribution composition (NDCF -> unitholders)
A55: Net Distributable Cash Flow (NDCF) | B55: INR cr | C55: =IF(N(C23)=0,IF(C23="","",C23),C23) | D55: =IF(N(D23)=0,IF(D23="","",D23),D23) | E55: =IF(N(E23)=0,IF(E23="","",E23),E23) | F55: =IF(N(F23)=0,IF(F23="","",F23),F23) | G55: =IF(N(G23)=0,IF(G23="","",G23),G23) | H55: =IF(N(H23)=0,IF(H23="","",H23),H23) | I55: =IF(N(I23)=0,IF(I23="","",I23),I23) | J55: =IF(N(J23)=0,IF(J23="","",J23),J23)
A56: Total Distribution | B56: INR cr | C56: =IF(N(C24)=0,IF(C24="","",C24),C24) | D56: =IF(N(D24)=0,IF(D24="","",D24),D24) | E56: =IF(N(E24)=0,IF(E24="","",E24),E24) | F56: =IF(N(F24)=0,IF(F24="","",F24),F24) | G56: =IF(N(G24)=0,IF(G24="","",G24),G24) | H56: =IF(N(H24)=0,IF(H24="","",H24),H24) | I56: =IF(N(I24)=0,IF(I24="","",I24),I24) | J56: =IF(N(J24)=0,IF(J24="","",J24),J24) | S56: =A7 | T56: =B7 | U56: =C7 | V56: =D7 | W56: =E7 | X56: =F7 | Y56: =G7 | Z56: =H7 | ... AB56: =J7
A57: of which: Interest | B57: INR cr | S57: =A46 | T57: =B46 | U57: =C46*10 | V57: =D46*10 | W57: =E46*10 | X57: =F46*10 | Y57: =G46*10 | Z57: =H46*10 | AA57: =I46*10 | AB57: =J46*10
A58: of which: Dividend | B58: INR cr | S58: =A47 | T58: =B47 | U58: =C47 | V58: =D47 | W58: =E47 | X58: =F47 | Y58: =G47 | Z58: =H47 | ... AB58: =J47
A59: of which: Return of capital (SPV/shareholder-loan repayment) | B59: INR cr
A60: of which: Other | B60: INR cr
A61: Return-of-capital % of distribution | B61: % | C61: =IF(OR(C59="",C56="",N(C56)=0),"",C59/C56) | D61: =IF(OR(D59="",D56="",N(D56)=0),"",D59/D56) | E61: =IF(OR(E59="",E56="",N(E56)=0),"",E59/E56) | F61: =IF(OR(F59="",F56="",N(F56)=0),"",F59/F56) | G61: =IF(OR(G59="",G56="",N(G56)=0),"",G59/G56) | H61: =IF(OR(H59="",H56="",N(H56)=0),"",H59/H56) | I61: =IF(OR(I59="",I56="",N(I56)=0),"",I59/I56) | J61: =IF(OR(J59="",J56="",N(J56)=0),"",J59/J56)
A62: Distribution per Unit (DPU) | B62: INR/unit | C62: =IF(N(C25)=0,IF(C25="","",C25),C25) | D62: =IF(N(D25)=0,IF(D25="","",D25),D25) | E62: =IF(N(E25)=0,IF(E25="","",E25),E25) | F62: =IF(N(F25)=0,IF(F25="","",F25),F25) | G62: =IF(N(G25)=0,IF(G25="","",G25),G25) | H62: =IF(N(H25)=0,IF(H25="","",H25),H25) | I62: =IF(N(I25)=0,IF(I25="","",I25),I25) | J62: =IF(N(J25)=0,IF(J25="","",J25),J25)
A63: DPU: Interest | B63: INR/unit
A64: DPU: Dividend | B64: INR/unit
A65: DPU: Return of capital | B65: INR/unit
A66: DPU: Other | B66: INR/unit
A67: Debt & leverage profile
A68: Gross Debt - external (banks/NCDs/LRD) | B68: INR cr | C68: =IF(C29="","",C29) | D68: =IF(D29="","",D29) | E68: =IF(E29="","",E29) | F68: =IF(F29="","",F29) | G68: =IF(G29="","",G29) | H68: =IF(H29="","",H29) | I68: =IF(I29="","",I29) | J68: 12365.4
A69: Shareholder / unitholder loans (Trust -> SPVs) | B69: INR cr | J69: 8982.555
A70: Cash & Cash Equivalents | B70: INR cr | C70: =IF(N(C30)=0,IF(C30="","",C30),C30) | D70: =IF(N(D30)=0,IF(D30="","",D30),D30) | E70: =IF(N(E30)=0,IF(E30="","",E30),E30) | F70: =IF(N(F30)=0,IF(F30="","",F30),F30) | G70: =IF(N(G30)=0,IF(G30="","",G30),G30) | H70: =IF(N(H30)=0,IF(H30="","",H30),H30) | I70: =IF(N(I30)=0,IF(I30="","",I30),I30) | J70: =IF(N(J30)=0,IF(J30="","",J30),J30)
A71: Net Debt | B71: INR cr | C71: =IF(N(C31)=0,IF(C31="","",C31),C31) | D71: =IF(N(D31)=0,IF(D31="","",D31),D31) | E71: =IF(N(E31)=0,IF(E31="","",E31),E31) | F71: =IF(N(F31)=0,IF(F31="","",F31),F31) | G71: =IF(N(G31)=0,IF(G31="","",G31),G31) | H71: =IF(N(H31)=0,IF(H31="","",H31),H31) | I71: =IF(N(I31)=0,IF(I31="","",I31),I31) | J71: =IF(N(J31)=0,IF(J31="","",J31),J31)
A72: Gross Asset Value (GAV) | B72: INR cr | C72: =IF(N(C28)=0,IF(C28="","",C28),C28) | D72: =IF(N(D28)=0,IF(D28="","",D28),D28) | E72: =IF(N(E28)=0,IF(E28="","",E28),E28) | F72: =IF(N(F28)=0,IF(F28="","",F28),F28) | G72: =IF(N(G28)=0,IF(G28="","",G28),G28) | H72: =IF(N(H28)=0,IF(H28="","",H28),H28) | I72: =IF(N(I28)=0,IF(I28="","",I28),I28) | J72: =IF(N(J28)=0,IF(J28="","",J28),J28)
A73: Loan-to-Value (LTV) | B73: % | C73: =IF(N(C33)=0,IF(C33="","",C33),C33) | D73: =IF(N(D33)=0,IF(D33="","",D33),D33) | E73: =IF(N(E33)=0,IF(E33="","",E33),E33) | F73: =IF(N(F33)=0,IF(F33="","",F33),F33) | G73: =IF(N(G33)=0,IF(G33="","",G33),G33) | H73: =IF(N(H33)=0,IF(H33="","",H33),H33) | I73: =IF(N(I33)=0,IF(I33="","",I33),I33) | J73: =IF(N(J33)=0,IF(J33="","",J33),J33)
A74: Cost of Debt (wtd avg) | B74: % | C74: =IF(N(C40)=0,IF(C40="","",C40),C40) | D74: =IF(N(D40)=0,IF(D40="","",D40),D40) | E74: =IF(N(E40)=0,IF(E40="","",E40),E40) | F74: =IF(N(F40)=0,IF(F40="","",F40),F40) | G74: =IF(N(G40)=0,IF(G40="","",G40),G40) | H74: =IF(N(H40)=0,IF(H40="","",H40),H40) | I74: =IF(N(I40)=0,IF(I40="","",I40),I40) | J74: =IF(N(J40)=0,IF(J40="","",J40),J40)
A75: % Floating rate | B75: % | J75: 0.79
A76: Wtd-avg debt maturity | B76: years
A77: Undrawn debt headroom | B77: INR cr | J77: 2277.2
A78: Interest cover (NOI / Finance cost) | B78: x | C78: =IF(OR(C13="",N(C17)=0),"",C13/C17) | D78: =IF(OR(D13="",N(D17)=0),"",D13/D17) | E78: =IF(OR(E13="",N(E17)=0),"",E13/E17) | F78: =IF(OR(F13="",N(F17)=0),"",F13/F17) | G78: =IF(OR(G13="",N(G17)=0),"",G13/G17) | H78: =IF(OR(H13="",N(H17)=0),"",H13/H17) | I78: =IF(OR(I13="",N(I17)=0),"",I13/I17) | J78: =IF(OR(J13="",N(J17)=0),"",J13/J17)
A80: Distribution-component split is shown where the issuer disclosed it (often per-unit for Q4 only in older years); blanks = not separately disclosed.

Sheet Bagmane
A1: Bagmane REIT - Key Financials & Operating Metrics
A2: Sponsor: Bagmane Developers. All INR figures in INR crore (cr) unless stated. 1 crore = 10 million. FY ends 31 March.
A3: Hover a cell for its Source (report + page + original figure). Grey italic = auto-calculated. YoY% = FY2026 vs FY2025.
C6: CONSOLIDATED | L6: STANDALONE
A7: Metric | B7: Unit | C7: FY2019 | D7: FY2020 | E7: FY2021 | F7: FY2022 | G7: FY2023 | H7: FY2024 | I7: FY2025 | J7: FY2026 | K7: YoY% | L7: FY2019 | M7: FY2020 | N7: FY2021 | O7: FY2022 | P7: FY2023 | Q7: FY2024 | R7: FY2025 | S7: FY2026 | T7: YoY%
A8: INCOME STATEMENT
A9: Revenue from Operations | B9: INR cr | H9: 2205.365 | I9: 2370.752 | J9: 1942.937 | K9: =IFERROR((J9-I9)/I9,"") | S9: 0 | T9: =IFERROR((S9-R9)/R9,"")
A10: Other Income | B10: INR cr | H10: 31.96 | I10: 20.125 | J10: 16.857 | K10: =IFERROR((J10-I10)/I10,"") | S10: 0 | T10: =IFERROR((S10-R10)/R10,"")
A11: Total Income | B11: INR cr | C11: =IF(AND(C9="",C10=""),"",N(C9)+N(C10)) | D11: =IF(AND(D9="",D10=""),"",N(D9)+N(D10)) | E11: =IF(AND(E9="",E10=""),"",N(E9)+N(E10)) | F11: =IF(AND(F9="",F10=""),"",N(F9)+N(F10)) | G11: =IF(AND(G9="",G10=""),"",N(G9)+N(G10)) | H11: =IF(AND(H9="",H10=""),"",N(H9)+N(H10)) | I11: =IF(AND(I9="",I10=""),"",N(I9)+N(I10)) | J11: =IF(AND(J9="",J10=""),"",N(J9)+N(J10)) | K11: =IFERROR((J11-I11)/I11,"") | L11: =IF(AND(L9="",L10=""),"",N(L9)+N(L10)) | M11: =IF(AND(M9="",M10=""),"",N(M9)+N(M10)) | N11: =IF(AND(N9="",N10=""),"",N(N9)+N(N10)) | O11: =IF(AND(O9="",O10=""),"",N(O9)+N(O10)) | P11: =IF(AND(P9="",P10=""),"",N(P9)+N(P10)) | Q11: =IF(AND(Q9="",Q10=""),"",N(Q9)+N(Q10)) | R11: =IF(AND(R9="",R10=""),"",N(R9)+N(R10)) | S11: =IF(AND(S9="",S10=""),"",N(S9)+N(S10)) | T11: =IFERROR((S11-R11)/R11,"")
A12: Property / Operating Expenses | B12: INR cr | K12: =IFERROR((J12-I12)/I12,"") | T12: =IFERROR((S12-R12)/R12,"")
A13: Net Operating Income (NOI) | B13: INR cr | H13: 1865.948 | I13: 2084.368 | J13: 1758.976 | K13: =IFERROR((J13-I13)/I13,"") | T13: =IFERROR((S13-R13)/R13,"")
A14: NOI Margin | B14: % | C14: =IF(OR(C13="",C9="",N(C9)=0),"",C13/C9) | D14: =IF(OR(D13="",D9="",N(D9)=0),"",D13/D9) | E14: =IF(OR(E13="",E9="",N(E9)=0),"",E13/E9) | F14: =IF(OR(F13="",F9="",N(F9)=0),"",F13/F9) | G14: =IF(OR(G13="",G9="",N(G9)=0),"",G13/G9) | H14: =IF(OR(H13="",H9="",N(H9)=0),"",H13/H9) | I14: =IF(OR(I13="",I9="",N(I9)=0),"",I13/I9) | J14: =IF(OR(J13="",J9="",N(J9)=0),"",J13/J9) | L14: =IF(OR(L13="",L9="",N(L9)=0),"",L13/L9) | M14: =IF(OR(M13="",M9="",N(M9)=0),"",M13/M9) | N14: =IF(OR(N13="",N9="",N(N9)=0),"",N13/N9) | O14: =IF(OR(O13="",O9="",N(O9)=0),"",O13/O9) | P14: =IF(OR(P13="",P9="",N(P9)=0),"",P13/P9) | Q14: =IF(OR(Q13="",Q9="",N(Q9)=0),"",Q13/Q9) | R14: =IF(OR(R13="",R9="",N(R9)=0),"",R13/R9) | S14: =IF(OR(S13="",S9="",N(S9)=0),"",S13/S9)
A15: EBITDA | B15: INR cr | H15: 1740.297 | I15: 1906.67 | J15: 1630.093 | K15: =IFERROR((J15-I15)/I15,"") | T15: =IFERROR((S15-R15)/R15,"")
A16: EBITDA Margin | B16: % | C16: =IF(OR(C15="",C9="",N(C9)=0),"",C15/C9) | D16: =IF(OR(D15="",D9="",N(D9)=0),"",D15/D9) | E16: =IF(OR(E15="",E9="",N(E9)=0),"",E15/E9) | F16: =IF(OR(F15="",F9="",N(F9)=0),"",F15/F9) | G16: =IF(OR(G15="",G9="",N(G9)=0),"",G15/G9) | H16: =IF(OR(H15="",H9="",N(H9)=0),"",H15/H9) | I16: =IF(OR(I15="",I9="",N(I9)=0),"",I15/I9) | J16: =IF(OR(J15="",J9="",N(J9)=0),"",J15/J9) | L16: =IF(OR(L15="",L9="",N(L9)=0),"",L15/L9) | M16: =IF(OR(M15="",M9="",N(M9)=0),"",M15/M9) | N16: =IF(OR(N15="",N9="",N(N9)=0),"",N15/N9) | O16: =IF(OR(O15="",O9="",N(O9)=0),"",O15/O9) | P16: =IF(OR(P15="",P9="",N(P9)=0),"",P15/P9) | Q16: =IF(OR(Q15="",Q9="",N(Q9)=0),"",Q15/Q9) | R16: =IF(OR(R15="",R9="",N(R9)=0),"",R15/R9) | S16: =IF(OR(S15="",S9="",N(S9)=0),"",S15/S9)
A17: Finance Costs | B17: INR cr | H17: 353.107 | I17: 394.026 | J17: 251.091 | K17: =IFERROR((J17-I17)/I17,"") | S17: 0 | T17: =IFERROR((S17-R17)/R17,"")
A18: Depreciation & Amortisation | B18: INR cr | H18: 161.663 | I18: 168.83 | J18: 136.415 | K18: =IFERROR((J18-I18)/I18,"") | S18: 0 | T18: =IFERROR((S18-R18)/R18,"")
A19: Profit Before Tax (PBT) | B19: INR cr | H19: 1225.527 | I19: 1343.814 | J19: 1242.587 | K19: =IFERROR((J19-I19)/I19,"") | S19: -0.257 | T19: =IFERROR((S19-R19)/R19,"")
A20: Profit After Tax (PAT) | B20: INR cr | H20: 809.357 | I20: 897.101 | J20: 829.018 | K20: =IFERROR((J20-I20)/I20,"") | S20: -0.257 | T20: =IFERROR((S20-R20)/R20,"")
A21: PAT Margin | B21: % | C21: =IF(OR(C20="",C9="",N(C9)=0),"",C20/C9) | D21: =IF(OR(D20="",D9="",N(D9)=0),"",D20/D9) | E21: =IF(OR(E20="",E9="",N(E9)=0),"",E20/E9) | F21: =IF(OR(F20="",F9="",N(F9)=0),"",F20/F9) | G21: =IF(OR(G20="",G9="",N(G9)=0),"",G20/G9) | H21: =IF(OR(H20="",H9="",N(H9)=0),"",H20/H9) | I21: =IF(OR(I20="",I9="",N(I9)=0),"",I20/I9) | J21: =IF(OR(J20="",J9="",N(J9)=0),"",J20/J9) | L21: =IF(OR(L20="",L9="",N(L9)=0),"",L20/L9) | M21: =IF(OR(M20="",M9="",N(M9)=0),"",M20/M9) | N21: =IF(OR(N20="",N9="",N(N9)=0),"",N20/N9) | O21: =IF(OR(O20="",O9="",N(O9)=0),"",O20/O9) | P21: =IF(OR(P20="",P9="",N(P9)=0),"",P20/P9) | Q21: =IF(OR(Q20="",Q9="",N(Q9)=0),"",Q20/Q9) | R21: =IF(OR(R20="",R9="",N(R9)=0),"",R20/R9) | S21: =IF(OR(S20="",S9="",N(S9)=0),"",S20/S9)
A22: DISTRIBUTIONS & CASH FLOW
A23: Net Distributable Cash Flow (NDCF) | B23: INR cr | K23: =IFERROR((J23-I23)/I23,"") | L23: n/a | M23: n/a | N23: n/a | O23: n/a | P23: n/a | Q23: n/a | R23: n/a | S23: n/a | T23: n/a
A24: Total Distribution | B24: INR cr | K24: =IFERROR((J24-I24)/I24,"") | L24: n/a | M24: n/a | N24: n/a | O24: n/a | P24: n/a | Q24: n/a | R24: n/a | S24: n/a | T24: n/a
A25: Distribution per Unit (DPU) | B25: INR/unit | K25: =IFERROR((J25-I25)/I25,"") | L25: n/a | M25: n/a | N25: n/a | O25: n/a | P25: n/a | Q25: n/a | R25: n/a | S25: n/a | T25: n/a
A26: NDCF Payout Ratio | B26: % | C26: =IF(OR(C24="",C23="",N(C23)=0),"",C24/C23) | D26: =IF(OR(D24="",D23="",N(D23)=0),"",D24/D23) | E26: =IF(OR(E24="",E23="",N(E23)=0),"",E24/E23) | F26: =IF(OR(F24="",F23="",N(F23)=0),"",F24/F23) | G26: =IF(OR(G24="",G23="",N(G23)=0),"",G24/G23) | H26: =IF(OR(H24="",H23="",N(H23)=0),"",H24/H23) | I26: =IF(OR(I24="",I23="",N(I23)=0),"",I24/I23) | J26: =IF(OR(J24="",J23="",N(J23)=0),"",J24/J23) | L26: n/a | M26: n/a | N26: n/a | O26: n/a | P26: n/a | Q26: n/a | R26: n/a | S26: n/a | T26: n/a
A27: BALANCE SHEET & LEVERAGE
A28: Gross Asset Value (GAV) / AUM | B28: INR cr | J28: 40263.49 | K28: =IFERROR((J28-I28)/I28,"") | L28: n/a | M28: n/a | N28: n/a | O28: n/a | P28: n/a | Q28: n/a | R28: n/a | S28: n/a | T28: n/a
A29: Gross Debt | B29: INR cr | H29: 3873.714 | I29: 3763.969 | J29: 3029.619 | K29: =IFERROR((J29-I29)/I29,"") | S29: 0 | T29: =IFERROR((S29-R29)/R29,"")
A30: Cash & Cash Equivalents | B30: INR cr | H30: 145.639 | I30: 243.148 | J30: 284.649 | K30: =IFERROR((J30-I30)/I30,"") | S30: 0 | T30: =IFERROR((S30-R30)/R30,"")
A31: Net Debt | B31: INR cr | C31: =IF(C29="","",C29-N(C30)) | D31: =IF(D29="","",D29-N(D30)) | E31: =IF(E29="","",E29-N(E30)) | F31: =IF(F29="","",F29-N(F30)) | G31: =IF(G29="","",G29-N(G30)) | H31: =IF(H29="","",H29-N(H30)) | I31: =IF(I29="","",I29-N(I30)) | J31: =IF(J29="","",J29-N(J30)) | K31: =IFERROR((J31-I31)/I31,"") | L31: =IF(L29="","",L29-N(L30)) | M31: =IF(M29="","",M29-N(M30)) | N31: =IF(N29="","",N29-N(N30)) | O31: =IF(O29="","",O29-N(O30)) | P31: =IF(P29="","",P29-N(P30)) | Q31: =IF(Q29="","",Q29-N(Q30)) | R31: =IF(R29="","",R29-N(R30)) | S31: =IF(S29="","",S29-N(S30)) | T31: =IFERROR((S31-R31)/R31,"")
A32: Net Worth / Unitholders Equity | B32: INR cr | H32: 1230.35 | I32: 1592.268 | J32: 2692.354 | K32: =IFERROR((J32-I32)/I32,"") | S32: -0.257 | T32: =IFERROR((S32-R32)/R32,"")
A33: Loan-to-Value (LTV) | B33: % | C33: =IF(OR(C31="",C28="",N(C28)=0),"",C31/C28) | D33: =IF(OR(D31="",D28="",N(D28)=0),"",D31/D28) | E33: =IF(OR(E31="",E28="",N(E28)=0),"",E31/E28) | F33: =IF(OR(F31="",F28="",N(F28)=0),"",F31/F28) | G33: =IF(OR(G31="",G28="",N(G28)=0),"",G31/G28) | H33: =IF(OR(H31="",H28="",N(H28)=0),"",H31/H28) | I33: =IF(OR(I31="",I28="",N(I28)=0),"",I31/I28) | J33: =IF(OR(J31="",J28="",N(J28)=0),"",J31/J28) | L33: =IF(OR(L31="",L28="",N(L28)=0),"",L31/L28) | M33: =IF(OR(M31="",M28="",N(M28)=0),"",M31/M28) | N33: =IF(OR(N31="",N28="",N(N28)=0),"",N31/N28) | O33: =IF(OR(O31="",O28="",N(O28)=0),"",O31/O28) | P33: =IF(OR(P31="",P28="",N(P28)=0),"",P31/P28) | Q33: =IF(OR(Q31="",Q28="",N(Q28)=0),"",Q31/Q28) | R33: =IF(OR(R31="",R28="",N(R28)=0),"",R31/R28) | S33: =IF(OR(S31="",S28="",N(S28)=0),"",S31/S28)
A34: NAV per Unit | B34: INR/unit | J34: 108.49 | K34: =IFERROR((J34-I34)/I34,"") | L34: n/a | M34: n/a | N34: n/a | O34: n/a | P34: n/a | Q34: n/a | R34: n/a | S34: n/a | T34: n/a
A35: MARKET DATA
A36: Units Outstanding | B36: mn units | J36: 3400 | K36: =IFERROR((J36-I36)/I36,"") | L36: n/a | M36: n/a | N36: n/a | O36: n/a | P36: n/a | Q36: n/a | R36: n/a | S36: n/a | T36: n/a
A37: Unit Price (period-end) | B37: INR/unit | J37: 100 | K37: =IFERROR((J37-I37)/I37,"") | L37: n/a | M37: n/a | N37: n/a | O37: n/a | P37: n/a | Q37: n/a | R37: n/a | S37: n/a | T37: n/a
A38: Market Capitalisation | B38: INR cr | C38: =IF(OR(C36="",C37=""),"",C36*C37/10) | D38: =IF(OR(D36="",D37=""),"",D36*D37/10) | E38: =IF(OR(E36="",E37=""),"",E36*E37/10) | F38: =IF(OR(F36="",F37=""),"",F36*F37/10) | G38: =IF(OR(G36="",G37=""),"",G36*G37/10) | H38: =IF(OR(H36="",H37=""),"",H36*H37/10) | I38: =IF(OR(I36="",I37=""),"",I36*I37/10) | J38: =IF(OR(J36="",J37=""),"",J36*J37/10) | K38: =IFERROR((J38-I38)/I38,"") | L38: n/a | M38: n/a | N38: n/a | O38: n/a | P38: n/a | Q38: n/a | R38: n/a | S38: n/a | T38: n/a
A39: Annual Distribution Yield | B39: % | C39: =IF(OR(C25="",C37="",N(C37)=0),"",C25/C37) | D39: =IF(OR(D25="",D37="",N(D37)=0),"",D25/D37) | E39: =IF(OR(E25="",E37="",N(E37)=0),"",E25/E37) | F39: =IF(OR(F25="",F37="",N(F37)=0),"",F25/F37) | G39: =IF(OR(G25="",G37="",N(G37)=0),"",G25/G37) | H39: =IF(OR(H25="",H37="",N(H37)=0),"",H25/H37) | I39: =IF(OR(I25="",I37="",N(I37)=0),"",I25/I37) | J39: =IF(OR(J25="",J37="",N(J37)=0),"",J25/J37) | L39: n/a | M39: n/a | N39: n/a | O39: n/a | P39: n/a | Q39: n/a | R39: n/a | S39: n/a | T39: n/a
A40: Cost of Debt | B40: % | L40: n/a | M40: n/a | N40: n/a | O40: n/a | P40: n/a | Q40: n/a | R40: n/a | S40: n/a | T40: n/a
A41: PORTFOLIO & OPERATING METRICS (consolidated)
A42: Total Leasable Area (GLA) | B42: Msf | J42: 19.6 | K42: =IFERROR((J42-I42)/I42,"") | L42: n/a | M42: n/a | N42: n/a | O42: n/a | P42: n/a | Q42: n/a | R42: n/a | S42: n/a | T42: n/a
A43: Operational Area | B43: Msf | J43: 16.6 | K43: =IFERROR((J43-I43)/I43,"") | L43: n/a | M43: n/a | N43: n/a | O43: n/a | P43: n/a | Q43: n/a | R43: n/a | S43: n/a | T43: n/a
A44: Under Construction + Future Development | B44: Msf | J44: 3 | K44: =IFERROR((J44-I44)/I44,"") | L44: n/a | M44: n/a | N44: n/a | O44: n/a | P44: n/a | Q44: n/a | R44: n/a | S44: n/a | T44: n/a
A45: Committed Occupancy | B45: % | J45: 0.99 | L45: n/a | M45: n/a | N45: n/a | O45: n/a | P45: n/a | Q45: n/a | R45: n/a | S45: n/a | T45: n/a
A46: In-place / Physical Occupancy | B46: % | L46: n/a | M46: n/a | N46: n/a | O46: n/a | P46: n/a | Q46: n/a | R46: n/a | S46: n/a | T46: n/a
A47: WALE | B47: years | J47: 7.4 | K47: =IFERROR((J47-I47)/I47,"") | L47: n/a | M47: n/a | N47: n/a | O47: n/a | P47: n/a | Q47: n/a | R47: n/a | S47: n/a | T47: n/a
A48: Number of Tenants | B48: count | J48: 60 | K48: =IFERROR((J48-I48)/I48,"") | L48: n/a | M48: n/a | N48: n/a | O48: n/a | P48: n/a | Q48: n/a | R48: n/a | S48: n/a | T48: n/a
A49: In-place Rent | B49: INR psf/mo | K49: =IFERROR((J49-I49)/I49,"") | L49: n/a | M49: n/a | N49: n/a | O49: n/a | P49: n/a | Q49: n/a | R49: n/a | S49: n/a | T49: n/a
A52: DEBT & NDCF / DISTRIBUTION DETAIL (consolidated; INR cr unless noted)
A53: Metric | B53: Unit | C53: FY2019 | D53: FY2020 | E53: FY2021 | F53: FY2022 | G53: FY2023 | H53: FY2024 | I53: FY2025 | J53: FY2026
A54: Distribution composition (NDCF -> unitholders)
A55: Net Distributable Cash Flow (NDCF) | B55: INR cr | C55: =IF(N(C23)=0,IF(C23="","",C23),C23) | D55: =IF(N(D23)=0,IF(D23="","",D23),D23) | E55: =IF(N(E23)=0,IF(E23="","",E23),E23) | F55: =IF(N(F23)=0,IF(F23="","",F23),F23) | G55: =IF(N(G23)=0,IF(G23="","",G23),G23) | H55: =IF(N(H23)=0,IF(H23="","",H23),H23) | I55: =IF(N(I23)=0,IF(I23="","",I23),I23) | J55: =IF(N(J23)=0,IF(J23="","",J23),J23)
A56: Total Distribution | B56: INR cr | C56: =IF(N(C24)=0,IF(C24="","",C24),C24) | D56: =IF(N(D24)=0,IF(D24="","",D24),D24) | E56: =IF(N(E24)=0,IF(E24="","",E24),E24) | F56: =IF(N(F24)=0,IF(F24="","",F24),F24) | G56: =IF(N(G24)=0,IF(G24="","",G24),G24) | H56: =IF(N(H24)=0,IF(H24="","",H24),H24) | I56: =IF(N(I24)=0,IF(I24="","",I24),I24) | J56: =IF(N(J24)=0,IF(J24="","",J24),J24)
A57: of which: Interest | B57: INR cr
A58: of which: Dividend | B58: INR cr
A59: of which: Return of capital (SPV/shareholder-loan repayment) | B59: INR cr
A60: of which: Other | B60: INR cr
A61: Return-of-capital % of distribution | B61: % | C61: =IF(OR(C59="",C56="",N(C56)=0),"",C59/C56) | D61: =IF(OR(D59="",D56="",N(D56)=0),"",D59/D56) | E61: =IF(OR(E59="",E56="",N(E56)=0),"",E59/E56) | F61: =IF(OR(F59="",F56="",N(F56)=0),"",F59/F56) | G61: =IF(OR(G59="",G56="",N(G56)=0),"",G59/G56) | H61: =IF(OR(H59="",H56="",N(H56)=0),"",H59/H56) | I61: =IF(OR(I59="",I56="",N(I56)=0),"",I59/I56) | J61: =IF(OR(J59="",J56="",N(J56)=0),"",J59/J56)
A62: Distribution per Unit (DPU) | B62: INR/unit | C62: =IF(N(C25)=0,IF(C25="","",C25),C25) | D62: =IF(N(D25)=0,IF(D25="","",D25),D25) | E62: =IF(N(E25)=0,IF(E25="","",E25),E25) | F62: =IF(N(F25)=0,IF(F25="","",F25),F25) | G62: =IF(N(G25)=0,IF(G25="","",G25),G25) | H62: =IF(N(H25)=0,IF(H25="","",H25),H25) | I62: =IF(N(I25)=0,IF(I25="","",I25),I25) | J62: =IF(N(J25)=0,IF(J25="","",J25),J25)
A63: DPU: Interest | B63: INR/unit
A64: DPU: Dividend | B64: INR/unit
A65: DPU: Return of capital | B65: INR/unit
A66: DPU: Other | B66: INR/unit
A67: Debt & leverage profile
A68: Gross Debt - external (banks/NCDs/LRD) | B68: INR cr | C68: =IF(C29="","",C29) | D68: =IF(D29="","",D29) | E68: =IF(E29="","",E29) | F68: =IF(F29="","",F29) | G68: 3456.348 | H68: 3873.714 | I68: 3763.969 | J68: 3016.823
A69: Shareholder / unitholder loans (Trust -> SPVs) | B69: INR cr | J69: 0
A70: Cash & Cash Equivalents | B70: INR cr | C70: =IF(N(C30)=0,IF(C30="","",C30),C30) | D70: =IF(N(D30)=0,IF(D30="","",D30),D30) | E70: =IF(N(E30)=0,IF(E30="","",E30),E30) | F70: =IF(N(F30)=0,IF(F30="","",F30),F30) | G70: =IF(N(G30)=0,IF(G30="","",G30),G30) | H70: =IF(N(H30)=0,IF(H30="","",H30),H30) | I70: =IF(N(I30)=0,IF(I30="","",I30),I30) | J70: =IF(N(J30)=0,IF(J30="","",J30),J30)
A71: Net Debt | B71: INR cr | C71: =IF(N(C31)=0,IF(C31="","",C31),C31) | D71: =IF(N(D31)=0,IF(D31="","",D31),D31) | E71: =IF(N(E31)=0,IF(E31="","",E31),E31) | F71: =IF(N(F31)=0,IF(F31="","",F31),F31) | G71: =IF(N(G31)=0,IF(G31="","",G31),G31) | H71: =IF(N(H31)=0,IF(H31="","",H31),H31) | I71: =IF(N(I31)=0,IF(I31="","",I31),I31) | J71: =IF(N(J31)=0,IF(J31="","",J31),J31)
A72: Gross Asset Value (GAV) | B72: INR cr | C72: =IF(N(C28)=0,IF(C28="","",C28),C28) | D72: =IF(N(D28)=0,IF(D28="","",D28),D28) | E72: =IF(N(E28)=0,IF(E28="","",E28),E28) | F72: =IF(N(F28)=0,IF(F28="","",F28),F28) | G72: =IF(N(G28)=0,IF(G28="","",G28),G28) | H72: =IF(N(H28)=0,IF(H28="","",H28),H28) | I72: =IF(N(I28)=0,IF(I28="","",I28),I28) | J72: =IF(N(J28)=0,IF(J28="","",J28),J28)
A73: Loan-to-Value (LTV) | B73: % | C73: =IF(N(C33)=0,IF(C33="","",C33),C33) | D73: =IF(N(D33)=0,IF(D33="","",D33),D33) | E73: =IF(N(E33)=0,IF(E33="","",E33),E33) | F73: =IF(N(F33)=0,IF(F33="","",F33),F33) | G73: =IF(N(G33)=0,IF(G33="","",G33),G33) | H73: =IF(N(H33)=0,IF(H33="","",H33),H33) | I73: =IF(N(I33)=0,IF(I33="","",I33),I33) | J73: =IF(N(J33)=0,IF(J33="","",J33),J33)
A74: Cost of Debt (wtd avg) | B74: % | C74: =IF(N(C40)=0,IF(C40="","",C40),C40) | D74: =IF(N(D40)=0,IF(D40="","",D40),D40) | E74: =IF(N(E40)=0,IF(E40="","",E40),E40) | F74: =IF(N(F40)=0,IF(F40="","",F40),F40) | G74: =IF(N(G40)=0,IF(G40="","",G40),G40) | H74: =IF(N(H40)=0,IF(H40="","",H40),H40) | I74: =IF(N(I40)=0,IF(I40="","",I40),I40) | J74: =IF(N(J40)=0,IF(J40="","",J40),J40)
A75: % Floating rate | B75: % | J75: 0.9501
A76: Wtd-avg debt maturity | B76: years
A77: Undrawn debt headroom | B77: INR cr | G77: 386.086 | H77: 730.086 | I77: 360 | J77: 50
A78: Interest cover (NOI / Finance cost) | B78: x | C78: =IF(OR(C13="",N(C17)=0),"",C13/C17) | D78: =IF(OR(D13="",N(D17)=0),"",D13/D17) | E78: =IF(OR(E13="",N(E17)=0),"",E13/E17) | F78: =IF(OR(F13="",N(F17)=0),"",F13/F17) | G78: =IF(OR(G13="",N(G17)=0),"",G13/G17) | H78: =IF(OR(H13="",N(H17)=0),"",H13/H17) | I78: =IF(OR(I13="",N(I17)=0),"",I13/I17) | J78: =IF(OR(J13="",N(J17)=0),"",J13/J17)
A80: Distribution-component split is shown where the issuer disclosed it (often per-unit for Q4 only in older years); blanks = not separately disclosed.

Sheet Notes & Definitions
A1: Indian Listed REITs - Coverage, Definitions & Sources
A2: REITs Covered
A3: REIT (sector) | B3: Sponsor | C3: Source report & period (fill in)
A4: Embassy Office Parks REIT (Office) | B4: Embassy Group / Blackstone
A5: Mindspace Business Parks REIT (Office) | B5: K Raheja Corp
A6: Brookfield India Real Estate Trust (Office) | B6: Brookfield
A7: Nexus Select Trust (Retail) | B7: Blackstone
A8: Knowledge Realty Trust (Office) | B8: Sattva Group / Blackstone
A9: Bagmane Developers REIT (Office) | B9: Bagmane Developers
A11: Metric Definitions
A12: Metric | B12: Definition | C12: Source / Page Reference
A13: Revenue from Operations | B13: Rental & related income from leasing the portfolio (consolidated); interest & dividend income from SPVs (standalone).
A14: Other Income | B14: Non-operating income - interest on deposits, fair-value gains, miscellaneous.
A15: Total Income | B15: Revenue from Operations + Other Income.
A16: Property / Operating Expenses | B16: Direct property operating, maintenance, utilities & related costs.
A17: Net Operating Income (NOI) | B17: Property revenue less direct property operating expenses; core REIT profitability measure.
A18: NOI Margin | B18: NOI / Revenue from Operations.
A19: EBITDA | B19: Earnings before interest, tax, depreciation & amortisation.
A20: EBITDA Margin | B20: EBITDA / Revenue from Operations.
A21: Finance Costs | B21: Interest and other borrowing costs.
A22: Depreciation & Amortisation | B22: Non-cash charge for property & intangible depreciation.
A23: Profit Before Tax (PBT) | B23: Profit before income tax.
A24: Profit After Tax (PAT) | B24: Net profit after tax.
... A49: In-place Rent | B49: Average in-place rent per square foot per month (office) / minimum guarantee + revenue share (retail).
