Workbook

Sheet Prices
A1: Date | B1: Security | C1: Value | D1: Indexed_100
A2: 46156 | B2: Bagmane REIT | C2: 103.54 | D2: 100
A3: 46157 | B3: Bagmane REIT | C3: 104.1 | D3: 100.54085
A4: 46160 | B4: Bagmane REIT | C4: 104.05 | D4: 100.49256
A5: 46161 | B5: Bagmane REIT | C5: 103.94 | D5: 100.38632
A6: 46162 | B6: Bagmane REIT | C6: 104 | D6: 100.44427
A7: 46163 | B7: Bagmane REIT | C7: 103.81 | D7: 100.26077
A8: 46164 | B8: Bagmane REIT | C8: 103.98 | D8: 100.42496
A9: 46167 | B9: Bagmane REIT | C9: 103.96 | D9: 100.40564
A10: 46168 | B10: Bagmane REIT | C10: 104 | D10: 100.44427
A11: 46169 | B11: Bagmane REIT | C11: 103.86 | D11: 100.30906
A12: 46171 | B12: Bagmane REIT | C12: 103.58 | D12: 100.03863
A13: 46174 | B13: Bagmane REIT | C13: 103.28 | D13: 99.748889
... A7197: 46197 | B7197: Nexus Select Trust | C7197: 160 | D7197: 153.40364

Sheet Security
A1: Security | B1: Ticker | C1: Security Type | D1: Source Sheet
A2: Knowledge Realty Trust | B2: KRTRRN | C2: REIT | D2: Knowledge Realty Trust
A3: Embassy REIT | B3: EMBASSYRRN | C3: REIT | D3: Embassy REIT
A4: Bagmane REIT | B4: BAGMANERRN | C4: REIT | D4: BAGMANE REIT
A5: Mindspace REIT | B5: MINDSPACERRN | C5: REIT | D5: MINDSPACE REIT
A6: Brookfield REIT | B6: BIRETRRN | C6: REIT | D6: Brookfield
A7: Nexus Select Trust | B7: NXSTRRN | C7: REIT | D7: NEXUS Select Trust
A8: NIFTY 50 | B8: NIFTY 50 | C8: Benchmark | D8: Nifty 50 Trading Price
A9: NIFTY REALTY | B9: NIFTY REALTY | C9: Benchmark | D9: NIFTY REALTY

Sheet REIT Overview
A1: Security | B1: REIT Name | C1: IPO Date | D1: Current Market Cap (INR Cr) | E1: Total Area (msf) | F1: Completed Area (msf^2) | G1: U/C and Future Development Area (msf^2) | H1: Sponsor | I1: Sponsor Stake (Mar '26) | J1: Total Return Since Listing (CAGR) | K1: Committed Ocupancy (%)
A2: Knowledge Realty Trust | B2: Knowledge Realty Trust | C2: 45870 | D2: 51470 | E2: 46.5 | F2: 37.2 | G2: 9.3 | H2: Sattva Group, Blackstone | I2: 32%/47% | J2: 0.21 | K2: 0.92
A3: Embassy REIT | B3: Embassy REIT | C3: 43556 | D3: 40744 | E3: 51.5 | F3: 41.1 | G3: 10.5 | H3: Blackstone, Embassy Group | I3: - / 8% | J3: 0.12 | K3: 0.9
A4: Bagmane REIT | B4: Bagmane REIT | C4: 46143 | D4: 34966 | E4: 19.6 | F4: 16.6 | G4: 3 | H4: Bagmane Group (backed by Blackstone) | I4: 0.83 | K4: 0.99
A5: Mindspace REIT | B5: MIND SPACE | C5: 44044 | D5: 30731 | E5: 44.2 | F5: 35.9 | G5: 8.3 | H5: K Raheja Corp Group (backed by Blackstone) | I5: 0.67 | J5: 0.15 | K5: 0.93
A6: Brookfield REIT | B6: Brookfield | C6: 44228 | D6: 26466 | E6: 37.1 | F6: 32.5 | G6: 4.6 | H6: Brookfield | I6: 0.19 | J6: 0.1 | K6: 0.93
A7: Nexus Select Trust | B7: Nexus select trust | C7: 45047 | D7: 23487 | E7: 10.7 | F7: 10.7 | G7: 0 | H7: Blackstone | I7: 0.22 | J7: 0.23 | K7: 0.97

Sheet REIT Metrics
A1: Security | B1: Unit Price | C1: Equity Value | D1: Valuer NAV | E1: Premium/(Disc.) to NAV | F1: Net Debt | G1: Security Deposits + Minority Interest | H1: Trading Enterprise Value (TEV) | I1: Trading Gearing Ratio | J1: FY27 - Adjusted NOI (Completed Office/Retail) | K1: Attributable TEV | L1: FY27 - Implied Cap Rate | M1: FY27 NDCF | N1: FY27 Pre Tax Yield | O1: FY28 NDCF | P1: Growth in Yield (FY28/FY27) | Q1: Total Return (Gross) | R1: Tax Efficient Portion of Distribution
A2: Knowledge Realty Trust | B2: 116 | C2: 51470 | D2: 124 | E2: -0.061 | F2: 12000 | G2: 1962 | H2: 65432 | I2: 0.183 | J2: 4505 | K2: 62978 | L2: 0.072 | M2: 3130 | N2: 0.061 | O2: 3395 | P2: 0.085 | Q2: 0.146 | R2: 0.76
A3: Embassy REIT | B3: 430 | C3: 40744 | D3: 492 | E3: -0.126 | F3: 21415 | G3: 1803 | H3: 63962 | I3: 0.335 | J3: 4040 | K3: 56572 | L3: 0.071 | M3: 2653 | N3: 0.065 | O3: 2917 | P3: 0.1 | Q3: 0.165 | R3: 0.93
A4: Bagmane REIT | B4: 103 | C4: 34966 | D4: 109 | E4: -0.058 | F4: 2013 | G4: 1120 | H4: 38099 | I4: 0.053 | J4: 2532 | K4: 32607 | L4: 0.078 | M4: 2096 | N4: 0.06 | O4: 2186 | P4: 0.043 | Q4: 0.103 | R4: 0.7
A5: Mindspace REIT | B5: 464 | C5: 30731 | D5: 527 | E5: -0.119 | F5: 15394 | G5: 4386 | H5: 50512 | I5: 0.305 | J5: 3271 | K5: 45345 | L5: 0.072 | M5: 1711 | N5: 0.056 | O5: 1912 | P5: 0.117 | Q5: 0.173 | R5: 0.99
A6: Brookfield REIT | B6: 319 | C6: 26466 | D6: 380 | E6: -0.161 | F6: 13811 | G6: 6952 | H6: 47229 | I6: 0.292 | J6: 3534 | K6: 45945 | L6: 0.077 | M6: 1894 | N6: 0.072 | O6: 2046 | P6: 0.08 | Q6: 0.151 | R6: 0.8
A7: Nexus Select Trust | B7: 155 | C7: 23487 | D7: 164 | E7: -0.055 | F7: 5748 | G7: 803 | H7: 30038 | I7: 0.191 | J7: 1879 | K7: 27308 | L7: 0.069 | M7: 1505 | N7: 0.064 | O7: 1632 | P7: 0.084 | Q7: 0.148 | R7: 0.7

Sheet Trading Volume
A1: Date | B1: Security | C1: Open | D1: High | E1: Low | F1: LTP | G1: Close | H1: VWAP | I1: Volume | J1: Turnover_INR | K1: No_of_Trades | L1: Volume_Type
A2: 45887 | B2: Knowledge Realty Trust | C2: 103 | D2: 108.94 | E2: 103 | F2: 106.24 | G2: 106.24 | H2: 104.66 | I2: 36304024 | J2: 3.7994523e+09 | K2: 99210 | L2: Equity Shares
A3: 45888 | B3: Knowledge Realty Trust | C3: 107.45 | D3: 108 | E3: 107.3 | F3: 107.35 | G3: 107.42 | H3: 107.71 | I3: 2392632 | J3: 2.5771704e+08 | K3: 7179 | L3: Equity Shares
A4: 45889 | B4: Knowledge Realty Trust | C4: 108.29 | D4: 108.38 | E4: 107 | F4: 107.25 | G4: 107.25 | H4: 107.3 | I4: 1460406 | J4: 1.5670383e+08 | K4: 7241 | L4: Equity Shares
A5: 45890 | B5: Knowledge Realty Trust | C5: 107.89 | D5: 107.89 | E5: 107 | F5: 107.1 | G5: 107.06 | H5: 107.24 | I5: 1233854 | J5: 1.3232287e+08 | K5: 2778 | L5: Equity Shares
A6: 45891 | B6: Knowledge Realty Trust | C6: 107.4 | D6: 107.4 | E6: 107 | F6: 107.05 | G6: 107.06 | H6: 107.17 | I6: 709231 | J6: 76009491 | K6: 1687 | L6: Equity Shares
A7: 45894 | B7: Knowledge Realty Trust | C7: 107.49 | D7: 107.49 | E7: 107.07 | F7: 107.12 | G7: 107.3 | H7: 107.29 | I7: 468885 | J7: 50306467 | K7: 1936 | L7: Equity Shares
A8: 45895 | B8: Knowledge Realty Trust | C8: 107.3 | D8: 107.45 | E8: 106.51 | F8: 107.1 | G8: 107.09 | H8: 107.06 | I8: 1366254 | J8: 1.4626769e+08 | K8: 3086 | L8: Equity Shares
A9: 45897 | B9: Knowledge Realty Trust | C9: 107.35 | D9: 107.5 | E9: 107.08 | F9: 107.11 | G9: 107.22 | H9: 107.25 | I9: 887534 | J9: 95183814 | K9: 1856 | L9: Equity Shares
A10: 45898 | B10: Knowledge Realty Trust | C10: 107.2 | D10: 107.34 | E10: 107.01 | F10: 107.09 | G10: 107.14 | H10: 107.15 | I10: 874217 | J10: 93670521 | K10: 1493 | L10: Equity Shares
A11: 45901 | B11: Knowledge Realty Trust | C11: 107.39 | D11: 107.39 | E11: 107.01 | F11: 107.16 | G11: 107.16 | H11: 107.15 | I11: 502243 | J11: 53814104 | K11: 1761 | L11: Equity Shares
A12: 45902 | B12: Knowledge Realty Trust | C12: 107.29 | D12: 109.4 | E12: 107.16 | F12: 107.17 | G12: 107.56 | H12: 107.88 | I12: 802267 | J12: 86546318 | K12: 2367 | L12: Equity Shares
A13: 45903 | B13: Knowledge Realty Trust | C13: 107.56 | D13: 108.18 | E13: 107.27 | F13: 107.8 | G13: 107.93 | H13: 107.85 | I13: 488157 | J13: 52648643 | K13: 1195 | L13: Equity Shares
... A1222: 46198 | B1222: Nexus Select Trust | C1222: 157.7 | D1222: 161.65 | E1222: 157.7 | F1222: 161.5 | G1222: 161.44 | H1222: 160.53 | I1222: 484997 | J1222: 77856684 | K1222: 8420 | L1222: Equity Shares
A1223: 45838 | B1223: NIFTY 50 | C1223: 25661.65 | D1223: 25669.35 | E1223: 25473.3 | G1223: 25517.05 | I1223: 270981274 | J1223: 246734800000 | L1223: Index (cash market)
A1224: 45839 | B1224: NIFTY 50 | C1224: 25551.35 | D1224: 25593.4 | E1224: 25501.8 | G1224: 25541.8 | I1224: 260669106 | J1224: 239210200000 | L1224: Index (cash market)
A1225: 45840 | B1225: NIFTY 50 | C1225: 25588.3 | D1225: 25608.1 | E1225: 25378.75 | G1225: 25453.4 | I1225: 309828013 | J1225: 266816600000 | L1225: Index (cash market)
A1226: 45841 | B1226: NIFTY 50 | C1226: 25505.1 | D1226: 25587.5 | E1226: 25384.35 | G1226: 25405.3 | I1226: 293428797 | J1226: 245317000000 | L1226: Index (cash market)
A1227: 45842 | B1227: NIFTY 50 | C1227: 25428.85 | D1227: 25470.25 | E1227: 25331.65 | G1227: 25461 | I1227: 193511595 | J1227: 191013300000 | L1227: Index (cash market)
A1228: 45845 | B1228: NIFTY 50 | C1228: 25450.45 | D1228: 25489.8 | E1228: 25407.25 | G1228: 25461.3 | I1228: 196051345 | J1228: 169232600000 | L1228: Index (cash market)
A1229: 45846 | B1229: NIFTY 50 | C1229: 25427.85 | D1229: 25548.05 | E1229: 25424.15 | G1229: 25522.5 | I1229: 210410530 | J1229: 219473200000 | L1229: Index (cash market)
A1230: 45847 | B1230: NIFTY 50 | C1230: 25514.6 | D1230: 25548.7 | E1230: 25424.35 | G1230: 25476.1 | I1230: 239081546 | J1230: 205495000000 | L1230: Index (cash market)
A1231: 45848 | B1231: NIFTY 50 | C1231: 25511.65 | D1231: 25524.05 | E1231: 25340.45 | G1231: 25355.25 | I1231: 219609322 | J1231: 214353600000 | L1231: Index (cash market)
A1232: 45849 | B1232: NIFTY 50 | C1232: 25255.5 | D1232: 25322.45 | E1232: 25129 | G1232: 25149.85 | I1232: 249987681 | J1232: 262516500000 | L1232: Index (cash market)
A1233: 45852 | B1233: NIFTY 50 | C1233: 25149.5 | D1233: 25151.1 | E1233: 25001.95 | G1233: 25082.3 | I1233: 259533624 | J1233: 233163300000 | L1233: Index (cash market)
A1234: 45853 | B1234: NIFTY 50 | C1234: 25089.5 | D1234: 25245.2 | E1234: 25088.45 | G1234: 25195.8 | I1234: 241340130 | J1234: 232827000000 | L1234: Index (cash market)
... A1712: 46198 | B1712: NIFTY REALTY | C1712: 829.4 | D1712: 839.05 | E1712: 824.15 | G1712: 826.25 | I1712: 14524050 | J1712: 14682000000 | L1712: Index (cash market)

Sheet Volume Summary
A1: Security | B1: Volume Type | C1: Trading Days | D1: Avg Daily Volume | E1: Total Volume | F1: Max Daily Volume | G1: Min Daily Volume | H1: Avg Daily Turnover (INR Cr) | I1: Total Turnover (INR Cr) | J1: Avg Trades / Day
A2: Knowledge Realty Trust | B2: Equity Shares | C2: =COUNTIFS('Trading Volume'!$B$2:$B$1712,$A2) -> 211 | D2: =IFERROR(AVERAGEIFS('Trading Volume'!$I$2:$I$1712,'Trading Volume'!$B$2:$B$1712,$A2),"-") -> 1143524.8 | E2: =IFERROR(SUMIFS('Trading Volume'!$I$2:$I$1712,'Trading Volume'!$B$2:$B$1712,$A2),"-") -> 241283733 | F2: {=MAX(IF('Trading Volume'!$B$2:$B$1712=$A2,'Trading Volume'!$I$2:$I$1712))} -> 36304024 | G2: {=MIN(IF('Trading Volume'!$B$2:$B$1712=$A2,'Trading Volume'!$I$2:$I$1712))} -> 53847 | H2: =IFERROR(AVERAGEIFS('Trading Volume'!$J$2:$J$1712,'Trading Volume'!$B$2:$B$1712,$A2)/10000000,"-") -> 13.228915 | I2: =IFERROR(SUMIFS('Trading Volume'!$J$2:$J$1712,'Trading Volume'!$B$2:$B$1712,$A2)/10000000,"-") -> 2791.3011 | J2: =IFERROR(AVERAGEIFS('Trading Volume'!$K$2:$K$1712,'Trading Volume'!$B$2:$B$1712,$A2),"-") -> 12310.791
A3: Embassy REIT | B3: Equity Shares | C3: =COUNTIFS('Trading Volume'!$B$2:$B$1712,$A3) -> 245 | D3: =IFERROR(AVERAGEIFS('Trading Volume'!$I$2:$I$1712,'Trading Volume'!$B$2:$B$1712,$A3),"-") -> 1034771 | E3: =IFERROR(SUMIFS('Trading Volume'!$I$2:$I$1712,'Trading Volume'!$B$2:$B$1712,$A3),"-") -> 253518888 | F3: {=MAX(IF('Trading Volume'!$B$2:$B$1712=$A3,'Trading Volume'!$I$2:$I$1712))} -> 58160702 | G3: {=MIN(IF('Trading Volume'!$B$2:$B$1712=$A3,'Trading Volume'!$I$2:$I$1712))} -> 26202 | H3: =IFERROR(AVERAGEIFS('Trading Volume'!$J$2:$J$1712,'Trading Volume'!$B$2:$B$1712,$A3)/10000000,"-") -> 43.536405 | I3: =IFERROR(SUMIFS('Trading Volume'!$J$2:$J$1712,'Trading Volume'!$B$2:$B$1712,$A3)/10000000,"-") -> 10666.419 | J3: =IFERROR(AVERAGEIFS('Trading Volume'!$K$2:$K$1712,'Trading Volume'!$B$2:$B$1712,$A3),"-") -> 19195.339
A4: Bagmane REIT | B4: Equity Shares | C4: =COUNTIFS('Trading Volume'!$B$2:$B$1712,$A4) -> 30 | D4: =IFERROR(AVERAGEIFS('Trading Volume'!$I$2:$I$1712,'Trading Volume'!$B$2:$B$1712,$A4),"-") -> 2630295.4 | E4: =IFERROR(SUMIFS('Trading Volume'!$I$2:$I$1712,'Trading Volume'!$B$2:$B$1712,$A4),"-") -> 78908863 | F4: {=MAX(IF('Trading Volume'!$B$2:$B$1712=$A4,'Trading Volume'!$I$2:$I$1712))} -> 38632214 | G4: {=MIN(IF('Trading Volume'!$B$2:$B$1712=$A4,'Trading Volume'!$I$2:$I$1712))} -> 218543 | H4: =IFERROR(AVERAGEIFS('Trading Volume'!$J$2:$J$1712,'Trading Volume'!$B$2:$B$1712,$A4)/10000000,"-") -> 27.252548 | I4: =IFERROR(SUMIFS('Trading Volume'!$J$2:$J$1712,'Trading Volume'!$B$2:$B$1712,$A4)/10000000,"-") -> 817.57643 | J4: =IFERROR(AVERAGEIFS('Trading Volume'!$K$2:$K$1712,'Trading Volume'!$B$2:$B$1712,$A4),"-") -> 14173.1
A5: Mindspace REIT | B5: Equity Shares | C5: =COUNTIFS('Trading Volume'!$B$2:$B$1712,$A5) -> 245 | D5: =IFERROR(AVERAGEIFS('Trading Volume'!$I$2:$I$1712,'Trading Volume'!$B$2:$B$1712,$A5),"-") -> 188435.53 | E5: =IFERROR(SUMIFS('Trading Volume'!$I$2:$I$1712,'Trading Volume'!$B$2:$B$1712,$A5),"-") -> 46166704 | F5: {=MAX(IF('Trading Volume'!$B$2:$B$1712=$A5,'Trading Volume'!$I$2:$I$1712))} -> 2139765 | G5: {=MIN(IF('Trading Volume'!$B$2:$B$1712=$A5,'Trading Volume'!$I$2:$I$1712))} -> 21011 | H5: =IFERROR(AVERAGEIFS('Trading Volume'!$J$2:$J$1712,'Trading Volume'!$B$2:$B$1712,$A5)/10000000,"-") -> 8.6358783 | I5: =IFERROR(SUMIFS('Trading Volume'!$J$2:$J$1712,'Trading Volume'!$B$2:$B$1712,$A5)/10000000,"-") -> 2115.7902 | J5: =IFERROR(AVERAGEIFS('Trading Volume'!$K$2:$K$1712,'Trading Volume'!$B$2:$B$1712,$A5),"-") -> 7414.0735
A6: Brookfield REIT | B6: Equity Shares | C6: =COUNTIFS('Trading Volume'!$B$2:$B$1712,$A6) -> 245 | D6: =IFERROR(AVERAGEIFS('Trading Volume'!$I$2:$I$1712,'Trading Volume'!$B$2:$B$1712,$A6),"-") -> 548757.77 | E6: =IFERROR(SUMIFS('Trading Volume'!$I$2:$I$1712,'Trading Volume'!$B$2:$B$1712,$A6),"-") -> 134445654 | F6: {=MAX(IF('Trading Volume'!$B$2:$B$1712=$A6,'Trading Volume'!$I$2:$I$1712))} -> 15085887 | G6: {=MIN(IF('Trading Volume'!$B$2:$B$1712=$A6,'Trading Volume'!$I$2:$I$1712))} -> 21299 | H6: =IFERROR(AVERAGEIFS('Trading Volume'!$J$2:$J$1712,'Trading Volume'!$B$2:$B$1712,$A6)/10000000,"-") -> 18.234138 | I6: =IFERROR(SUMIFS('Trading Volume'!$J$2:$J$1712,'Trading Volume'!$B$2:$B$1712,$A6)/10000000,"-") -> 4467.3638 | J6: =IFERROR(AVERAGEIFS('Trading Volume'!$K$2:$K$1712,'Trading Volume'!$B$2:$B$1712,$A6),"-") -> 11816.8
A7: Nexus Select Trust | B7: Equity Shares | C7: =COUNTIFS('Trading Volume'!$B$2:$B$1712,$A7) -> 245 | D7: =IFERROR(AVERAGEIFS('Trading Volume'!$I$2:$I$1712,'Trading Volume'!$B$2:$B$1712,$A7),"-") -> 631710.91 | E7: =IFERROR(SUMIFS('Trading Volume'!$I$2:$I$1712,'Trading Volume'!$B$2:$B$1712,$A7),"-") -> 154769174 | F7: {=MAX(IF('Trading Volume'!$B$2:$B$1712=$A7,'Trading Volume'!$I$2:$I$1712))} -> 31197748 | G7: {=MIN(IF('Trading Volume'!$B$2:$B$1712=$A7,'Trading Volume'!$I$2:$I$1712))} -> 32789 | H7: =IFERROR(AVERAGEIFS('Trading Volume'!$J$2:$J$1712,'Trading Volume'!$B$2:$B$1712,$A7)/10000000,"-") -> 9.686462 | I7: =IFERROR(SUMIFS('Trading Volume'!$J$2:$J$1712,'Trading Volume'!$B$2:$B$1712,$A7)/10000000,"-") -> 2373.1832 | J7: =IFERROR(AVERAGEIFS('Trading Volume'!$K$2:$K$1712,'Trading Volume'!$B$2:$B$1712,$A7),"-") -> 8319.1306
A8: NIFTY 50 | B8: Index (cash market) | C8: =COUNTIFS('Trading Volume'!$B$2:$B$1712,$A8) -> 245 | D8: =IFERROR(AVERAGEIFS('Trading Volume'!$I$2:$I$1712,'Trading Volume'!$B$2:$B$1712,$A8),"-") -> 3.5919192e+08 | E8: =IFERROR(SUMIFS('Trading Volume'!$I$2:$I$1712,'Trading Volume'!$B$2:$B$1712,$A8),"-") -> 88002019448 | F8: {=MAX(IF('Trading Volume'!$B$2:$B$1712=$A8,'Trading Volume'!$I$2:$I$1712))} -> 1198023438 | G8: {=MIN(IF('Trading Volume'!$B$2:$B$1712=$A8,'Trading Volume'!$I$2:$I$1712))} -> 42477128 | H8: =IFERROR(AVERAGEIFS('Trading Volume'!$J$2:$J$1712,'Trading Volume'!$B$2:$B$1712,$A8)/10000000,"-") -> 30527.706 | I8: =IFERROR(SUMIFS('Trading Volume'!$J$2:$J$1712,'Trading Volume'!$B$2:$B$1712,$A8)/10000000,"-") -> 7479287.9 | J8: =IFERROR(AVERAGEIFS('Trading Volume'!$K$2:$K$1712,'Trading Volume'!$B$2:$B$1712,$A8),"-") -> -
A9: NIFTY REALTY | B9: Index (cash market) | C9: =COUNTIFS('Trading Volume'!$B$2:$B$1712,$A9) -> 245 | D9: =IFERROR(AVERAGEIFS('Trading Volume'!$I$2:$I$1712,'Trading Volume'!$B$2:$B$1712,$A9),"-") -> 12898832 | E9: =IFERROR(SUMIFS('Trading Volume'!$I$2:$I$1712,'Trading Volume'!$B$2:$B$1712,$A9),"-") -> 3160213747 | F9: {=MAX(IF('Trading Volume'!$B$2:$B$1712=$A9,'Trading Volume'!$I$2:$I$1712))} -> 45485811 | G9: {=MIN(IF('Trading Volume'!$B$2:$B$1712=$A9,'Trading Volume'!$I$2:$I$1712))} -> 1815639 | H9: =IFERROR(AVERAGEIFS('Trading Volume'!$J$2:$J$1712,'Trading Volume'!$B$2:$B$1712,$A9)/10000000,"-") -> 1207.4385 | I9: =IFERROR(SUMIFS('Trading Volume'!$J$2:$J$1712,'Trading Volume'!$B$2:$B$1712,$A9)/10000000,"-") -> 295822.43 | J9: =IFERROR(AVERAGEIFS('Trading Volume'!$K$2:$K$1712,'Trading Volume'!$B$2:$B$1712,$A9),"-") -> -
A11: Notes: REIT Volume = shares traded (NSE "VALUE" for turnover). NIFTY 50 & NIFTY REALTY = NSE index files — "Shares Traded" and "Turnover" are the aggregate cash-market trading of the index constituents (same units as the REITs; turnover converted from ₹ Cr to ₹). Index files carry no per-name trade count, so Avg Trades/Day is blank for benchmarks. Compare a single REIT vs a multi-stock index on a per-name basis with care — turnover is the most comparable lens. Window: 30-Jun-2025 to 25-Jun-2026.
